Workbook
Name _Buy_America: #REF!
Name _Buy_America: 'CTX Price Book'!$C$68:$C$85
Name _CTX_Category_List: #REF!
Name _CTX_Category_List: 'CTX Price Book'!$I$3:$I$16
Name _CTX_category_List2: #REF!
Name _CTX_Service_Plans: #REF!
Name _CTX_Service_Plans: 'CTX Price Book'!$C$111:$C$131
Name _CTX_Warranty: #REF!
Name _CTX_Warranty: 'CTX Price Book'!$C$95:$C$110
Name _Distributed_System: #REF!
Name _Distributed_System: 'CTX Price Book'!$C$63:$C$67
Name _kW120: #REF!
Name _kW120: 'CTX Price Book'!$C$22:$C$30
Name _kW160: #REF!
Name _kW160: 'CTX Price Book'!$C$31:$C$41
Name _kW180: #REF!
Name _kW180: 'CTX Price Book'!$C$42:$C$46
Name _kW240: #REF!
Name _kW240: 'CTX Price Book'!$C$47:$C$54
Name _kW30: #REF!
Name _kW30: 'CTX Price Book'!$C$13:$C$14
Name _kW360: #REF!
Name _kW360: 'CTX Price Book'!$C$55:$C$62
Name _kW60: #REF!
Name _kW60: 'CTX Price Book'!$C$15:$C$21
Name _L2: #REF!
Name _L2: 'CTX Price Book'!$C$3:$C$12
Name _L2_Accessories: #REF!
Name _L2_Accessories: 'CTX Price Book'!$C$90:$C$94
Name _Pick_First: 'CTX Price Book'!$J$2
Name _V2G: #REF!
Name _V2G: 'CTX Price Book'!$C$86:$C$89
Name Beg_Bal: 'DLL Schedule'!$C$18:$C$497
Name ColumnTitle1: #REF!
Name ColumnTitleRegion1..B12.1: #REF!
Name ColumnTitleRegion2..E12.1: #REF!
Name Company_Name: #REF!
Name Cum_Int: 'DLL Schedule'!$J$18:$J$497
Name cumCashCats: OFFSET('Financial Worksheet'!$D$5,0,0,'Financial Worksheet'!$B$10+1,1)
Name cumCashVals: OFFSET('Financial Worksheet'!$F$5,0,0,'Financial Worksheet'!$B$10+1,1)
Name Data: 'DLL Schedule'!$A$18:$J$497
Name End_Bal: 'DLL Schedule'!$I$18:$I$497
Name Extra_Pay: 'DLL Schedule'!$E$18:$E$497
Name Full_Print: 'DLL Schedule'!$A$1:$J$497
Name Int: 'DLL Schedule'!$H$18:$H$497
Name Interest_Rate: 'DLL Schedule'!$D$6
Name Loan_Amount: 'DLL Schedule'!$D$5
Name Loan_Start: 'DLL Schedule'!$D$9
Name Loan_Years: 'DLL Schedule'!$D$7
Name Num_Pmt_Per_Year: 'DLL Schedule'!$D$8
Name Pay_Date: 'DLL Schedule'!$B$18:$B$497
Name Pay_Num: 'DLL Schedule'!$A$18:$A$497
Name Princ: 'DLL Schedule'!$G$18:$G$497
Name RowTitleRegion1..E5: #REF!
Name Sched_Pay: 'DLL Schedule'!$D$18:$D$497
Name Scheduled_Extra_Payments: 'DLL Schedule'!$D$10
Name Scheduled_Interest_Rate: 'DLL Schedule'!$D$6
Name Scheduled_Monthly_Payment: 'DLL Schedule'!$J$5
Name Total_Interest: 'DLL Schedule'!$J$9
Name Total_Pay: 'DLL Schedule'!$F$18:$F$497

Sheet INPUT SHEET
C2: Charger Input Calculator
B5: CTX Product Selection: | M5: Financial Worksheet Inputs
B6: Start by selecting Category dropdown → (blue cells = your inputs: Category, SKU, Discount %, Qty)
C7: Item # | D7: Category | E7: SKU | F7: Description | G7: MSRP | H7: Discount % | I7: Qty | J7: MSRP Total | K7: Line Total After Discount | N7: Level 2 | O7: L3 Type 1 (DCFC) | P7: L3 Type 2 (DCFC) | Q7: L3 Type 3 (DCFC) | R7: L3 Type 4 (DCFC) | S7: L3 Type 5 (DCFC) | T7: L3 Type 6 (DCFC)
C8: =IF($E8="","",ROW()-7) | D8: _kW120 | E8: TP5-120-480-1 | F8: =IF($E8="","",IFERROR(INDEX('CTX Price Book'!$D:$D,MATCH($E8,'CTX Price Book'!$C:$C,0)),"SKU not found")) | G8: =IF($E8="","",IFERROR(INDEX('CTX Price Book'!$F:$F,MATCH($E8,'CTX Price Book'!$C:$C,0)),"")) | H8: 0.07 | I8: 6 | J8: =IF(E8="","",I8*G8) | K8: =IF(OR($G8="",$I8=""),"",J8-(H8*J8)) | M8: # Chargers (auto from line items) | N8: =SUMIF($D$8:$D$37,"_L2",$I$8:$I$37) -> 0 | O8: =SUMIF($D$8:$D$37,"_kW"&O10,$I$8:$I$37) -> 0 | P8: =SUMIF($D$8:$D$37,"_kW"&P10,$I$8:$I$37) -> 0 | Q8: =SUMIF($D$8:$D$37,"_kW"&Q10,$I$8:$I$37) -> 0 | R8: =SUMIF($D$8:$D$37,"_kW"&R10,$I$8:$I$37) -> 0 | S8: =SUMIF($D$8:$D$37,"_kW"&S10,$I$8:$I$37) -> 0 | T8: =SUMIF($D$8:$D$37,"_kW"&T10,$I$8:$I$37) -> 0
C9: =IF($E9="","",ROW()-7) | F9: =IF($E9="","",IFERROR(INDEX('CTX Price Book'!$D:$D,MATCH($E9,'CTX Price Book'!$C:$C,0)),"SKU not found")) | G9: =IF($E9="","",IFERROR(INDEX('CTX Price Book'!$F:$F,MATCH($E9,'CTX Price Book'!$C:$C,0)),"")) | J9: =IF(E9="","",I9*G9) | K9: =IF(OR($G9="",$I9=""),"",J9-(H9*J9)) | M9: EV Stall Qty (# of ports) | N9: =SUMPRODUCT(($D$8:$D$37="_L2")*(1+ISNUMBER(SEARCH("dual",$F$8:$F$37&"")))*IF($I$8:$I$37="",0,$I$8:$I$37)) -> 0 | O9: =O8*2 -> 0 | P9: =P8*2 -> 0 | Q9: =Q8*2 -> 0 | R9: =R8*2 -> 0 | S9: =S8*2 -> 0 | T9: =T8*2 -> 0
C10: =IF($E10="","",ROW()-7) | F10: =IF($E10="","",IFERROR(INDEX('CTX Price Book'!$D:$D,MATCH($E10,'CTX Price Book'!$C:$C,0)),"SKU not found")) | G10: =IF($E10="","",IFERROR(INDEX('CTX Price Book'!$F:$F,MATCH($E10,'CTX Price Book'!$C:$C,0)),"")) | J10: =IF(E10="","",I10*G10) | K10: =IF(OR($G10="",$I10=""),"",J10-(H10*J10)) | M10: Charger Rating (kW) | N10: 7.2 | O10: 60 | P10: 120 | Q10: 160 | R10: 180 | S10: 240 | T10: 360
C11: =IF($E11="","",ROW()-7) | F11: =IF($E11="","",IFERROR(INDEX('CTX Price Book'!$D:$D,MATCH($E11,'CTX Price Book'!$C:$C,0)),"SKU not found")) | G11: =IF($E11="","",IFERROR(INDEX('CTX Price Book'!$F:$F,MATCH($E11,'CTX Price Book'!$C:$C,0)),"")) | J11: =IF(E11="","",I11*G11) | K11: =IF(OR($G11="",$I11=""),"",J11-(H11*J11)) | M11: Rating de-rate factor (x) | N11: 0.98 | O11: =N11 -> 0.98 | P11: =N11 -> 0.98 | Q11: =$N$11 -> 0.98 | R11: =$N$11 -> 0.98 | S11: =$N$11 -> 0.98 | T11: =$N$11 -> 0.98
C12: =IF($E12="","",ROW()-7) | F12: =IF($E12="","",IFERROR(INDEX('CTX Price Book'!$D:$D,MATCH($E12,'CTX Price Book'!$C:$C,0)),"SKU not found")) | G12: =IF($E12="","",IFERROR(INDEX('CTX Price Book'!$F:$F,MATCH($E12,'CTX Price Book'!$C:$C,0)),"")) | J12: =IF(E12="","",I12*G12) | K12: =IF(OR($G12="",$I12=""),"",J12-(H12*J12))
C13: =IF($E13="","",ROW()-7) | F13: =IF($E13="","",IFERROR(INDEX('CTX Price Book'!$D:$D,MATCH($E13,'CTX Price Book'!$C:$C,0)),"SKU not found")) | G13: =IF($E13="","",IFERROR(INDEX('CTX Price Book'!$F:$F,MATCH($E13,'CTX Price Book'!$C:$C,0)),"")) | J13: =IF(E13="","",I13*G13) | K13: =IF(OR($G13="",$I13=""),"",J13-(H13*J13)) | M13: Tip: # Chargers auto-fills from your line item categories (_L2 and _kW*).
C14: =IF($E14="","",ROW()-7) | F14: =IF($E14="","",IFERROR(INDEX('CTX Price Book'!$D:$D,MATCH($E14,'CTX Price Book'!$C:$C,0)),"SKU not found")) | G14: =IF($E14="","",IFERROR(INDEX('CTX Price Book'!$F:$F,MATCH($E14,'CTX Price Book'!$C:$C,0)),"")) | J14: =IF(E14="","",I14*G14) | K14: =IF(OR($G14="",$I14=""),"",J14-(H14*J14)) | M14: Set the ports and kW rating per level. Revenue uses rating x de-rate factor.
C15: =IF($E15="","",ROW()-7) | F15: =IF($E15="","",IFERROR(INDEX('CTX Price Book'!$D:$D,MATCH($E15,'CTX Price Book'!$C:$C,0)),"SKU not found")) | G15: =IF($E15="","",IFERROR(INDEX('CTX Price Book'!$F:$F,MATCH($E15,'CTX Price Book'!$C:$C,0)),"")) | J15: =IF(E15="","",I15*G15) | K15: =IF(OR($G15="",$I15=""),"",J15-(H15*J15))
C16: =IF($E16="","",ROW()-7) | F16: =IF($E16="","",IFERROR(INDEX('CTX Price Book'!$D:$D,MATCH($E16,'CTX Price Book'!$C:$C,0)),"SKU not found")) | G16: =IF($E16="","",IFERROR(INDEX('CTX Price Book'!$F:$F,MATCH($E16,'CTX Price Book'!$C:$C,0)),"")) | J16: =IF(E16="","",I16*G16) | K16: =IF(OR($G16="",$I16=""),"",J16-(H16*J16)) | M16: Fill this out for CPMS
C17: =IF($E17="","",ROW()-7) | F17: =IF($E17="","",IFERROR(INDEX('CTX Price Book'!$D:$D,MATCH($E17,'CTX Price Book'!$C:$C,0)),"SKU not found")) | G17: =IF($E17="","",IFERROR(INDEX('CTX Price Book'!$F:$F,MATCH($E17,'CTX Price Book'!$C:$C,0)),"")) | J17: =IF(E17="","",I17*G17) | K17: =IF(OR($G17="",$I17=""),"",J17-(H17*J17)) | M17: Address
C18: =IF($E18="","",ROW()-7) | F18: =IF($E18="","",IFERROR(INDEX('CTX Price Book'!$D:$D,MATCH($E18,'CTX Price Book'!$C:$C,0)),"SKU not found")) | G18: =IF($E18="","",IFERROR(INDEX('CTX Price Book'!$F:$F,MATCH($E18,'CTX Price Book'!$C:$C,0)),"")) | J18: =IF(E18="","",I18*G18) | K18: =IF(OR($G18="",$I18=""),"",J18-(H18*J18)) | M18: RSM: RSM: Paul Arms / Brian Rischmann / Dan Koven
C19: =IF($E19="","",ROW()-7) | F19: =IF($E19="","",IFERROR(INDEX('CTX Price Book'!$D:$D,MATCH($E19,'CTX Price Book'!$C:$C,0)),"SKU not found")) | G19: =IF($E19="","",IFERROR(INDEX('CTX Price Book'!$F:$F,MATCH($E19,'CTX Price Book'!$C:$C,0)),"")) | J19: =IF(E19="","",I19*G19) | K19: =IF(OR($G19="",$I19=""),"",J19-(H19*J19)) | M19: Client Info:
C20: =IF($E20="","",ROW()-7) | F20: =IF($E20="","",IFERROR(INDEX('CTX Price Book'!$D:$D,MATCH($E20,'CTX Price Book'!$C:$C,0)),"SKU not found")) | G20: =IF($E20="","",IFERROR(INDEX('CTX Price Book'!$F:$F,MATCH($E20,'CTX Price Book'!$C:$C,0)),"")) | J20: =IF(E20="","",I20*G20) | K20: =IF(OR($G20="",$I20=""),"",J20-(H20*J20)) | M20: Utility
C21: =IF($E21="","",ROW()-7) | F21: =IF($E21="","",IFERROR(INDEX('CTX Price Book'!$D:$D,MATCH($E21,'CTX Price Book'!$C:$C,0)),"SKU not found")) | G21: =IF($E21="","",IFERROR(INDEX('CTX Price Book'!$F:$F,MATCH($E21,'CTX Price Book'!$C:$C,0)),"")) | J21: =IF(E21="","",I21*G21) | K21: =IF(OR($G21="",$I21=""),"",J21-(H21*J21)) | M21: Scope of Work: ie: Client Requests, Amount of chargers, if chargers are dual… Is the client a city?
C22: =IF($E22="","",ROW()-7) | F22: =IF($E22="","",IFERROR(INDEX('CTX Price Book'!$D:$D,MATCH($E22,'CTX Price Book'!$C:$C,0)),"SKU not found")) | G22: =IF($E22="","",IFERROR(INDEX('CTX Price Book'!$F:$F,MATCH($E22,'CTX Price Book'!$C:$C,0)),"")) | J22: =IF(E22="","",I22*G22) | K22: =IF(OR($G22="",$I22=""),"",J22-(H22*J22))
C23: =IF($E23="","",ROW()-7) | F23: =IF($E23="","",IFERROR(INDEX('CTX Price Book'!$D:$D,MATCH($E23,'CTX Price Book'!$C:$C,0)),"SKU not found")) | G23: =IF($E23="","",IFERROR(INDEX('CTX Price Book'!$F:$F,MATCH($E23,'CTX Price Book'!$C:$C,0)),"")) | J23: =IF(E23="","",I23*G23) | K23: =IF(OR($G23="",$I23=""),"",J23-(H23*J23))
C24: =IF($E24="","",ROW()-7) | F24: =IF($E24="","",IFERROR(INDEX('CTX Price Book'!$D:$D,MATCH($E24,'CTX Price Book'!$C:$C,0)),"SKU not found")) | G24: =IF($E24="","",IFERROR(INDEX('CTX Price Book'!$F:$F,MATCH($E24,'CTX Price Book'!$C:$C,0)),"")) | J24: =IF(E24="","",I24*G24) | K24: =IF(OR($G24="",$I24=""),"",J24-(H24*J24))
C25: =IF($E25="","",ROW()-7) | F25: =IF($E25="","",IFERROR(INDEX('CTX Price Book'!$D:$D,MATCH($E25,'CTX Price Book'!$C:$C,0)),"SKU not found")) | G25: =IF($E25="","",IFERROR(INDEX('CTX Price Book'!$F:$F,MATCH($E25,'CTX Price Book'!$C:$C,0)),"")) | J25: =IF(E25="","",I25*G25) | K25: =IF(OR($G25="",$I25=""),"",J25-(H25*J25))
C26: =IF($E26="","",ROW()-7) | F26: =IF($E26="","",IFERROR(INDEX('CTX Price Book'!$D:$D,MATCH($E26,'CTX Price Book'!$C:$C,0)),"SKU not found")) | G26: =IF($E26="","",IFERROR(INDEX('CTX Price Book'!$F:$F,MATCH($E26,'CTX Price Book'!$C:$C,0)),"")) | J26: =IF(E26="","",I26*G26) | K26: =IF(OR($G26="",$I26=""),"",J26-(H26*J26))
C27: =IF($E27="","",ROW()-7) | F27: =IF($E27="","",IFERROR(INDEX('CTX Price Book'!$D:$D,MATCH($E27,'CTX Price Book'!$C:$C,0)),"SKU not found")) | G27: =IF($E27="","",IFERROR(INDEX('CTX Price Book'!$F:$F,MATCH($E27,'CTX Price Book'!$C:$C,0)),"")) | J27: =IF(E27="","",I27*G27) | K27: =IF(OR($G27="",$I27=""),"",J27-(H27*J27)) | M27: Pictures of Site (Max 3, circle the location of the chargers) Give 2 or 3 Possible options for Charger Locations..
C28: =IF($E28="","",ROW()-7) | F28: =IF($E28="","",IFERROR(INDEX('CTX Price Book'!$D:$D,MATCH($E28,'CTX Price Book'!$C:$C,0)),"SKU not found")) | G28: =IF($E28="","",IFERROR(INDEX('CTX Price Book'!$F:$F,MATCH($E28,'CTX Price Book'!$C:$C,0)),"")) | J28: =IF(E28="","",I28*G28) | K28: =IF(OR($G28="",$I28=""),"",J28-(H28*J28))
C29: =IF($E29="","",ROW()-7) | F29: =IF($E29="","",IFERROR(INDEX('CTX Price Book'!$D:$D,MATCH($E29,'CTX Price Book'!$C:$C,0)),"SKU not found")) | G29: =IF($E29="","",IFERROR(INDEX('CTX Price Book'!$F:$F,MATCH($E29,'CTX Price Book'!$C:$C,0)),"")) | J29: =IF(E29="","",I29*G29) | K29: =IF(OR($G29="",$I29=""),"",J29-(H29*J29))
C30: =IF($E30="","",ROW()-7) | F30: =IF($E30="","",IFERROR(INDEX('CTX Price Book'!$D:$D,MATCH($E30,'CTX Price Book'!$C:$C,0)),"SKU not found")) | G30: =IF($E30="","",IFERROR(INDEX('CTX Price Book'!$F:$F,MATCH($E30,'CTX Price Book'!$C:$C,0)),"")) | J30: =IF(E30="","",I30*G30) | K30: =IF(OR($G30="",$I30=""),"",J30-(H30*J30))
C31: =IF($E31="","",ROW()-7) | F31: =IF($E31="","",IFERROR(INDEX('CTX Price Book'!$D:$D,MATCH($E31,'CTX Price Book'!$C:$C,0)),"SKU not found")) | G31: =IF($E31="","",IFERROR(INDEX('CTX Price Book'!$F:$F,MATCH($E31,'CTX Price Book'!$C:$C,0)),"")) | J31: =IF(E31="","",I31*G31) | K31: =IF(OR($G31="",$I31=""),"",J31-(H31*J31))
C32: =IF($E32="","",ROW()-7) | F32: =IF($E32="","",IFERROR(INDEX('CTX Price Book'!$D:$D,MATCH($E32,'CTX Price Book'!$C:$C,0)),"SKU not found")) | G32: =IF($E32="","",IFERROR(INDEX('CTX Price Book'!$F:$F,MATCH($E32,'CTX Price Book'!$C:$C,0)),"")) | J32: =IF(E32="","",I32*G32) | K32: =IF(OR($G32="",$I32=""),"",J32-(H32*J32))
C33: =IF($E33="","",ROW()-7) | F33: =IF($E33="","",IFERROR(INDEX('CTX Price Book'!$D:$D,MATCH($E33,'CTX Price Book'!$C:$C,0)),"SKU not found")) | G33: =IF($E33="","",IFERROR(INDEX('CTX Price Book'!$F:$F,MATCH($E33,'CTX Price Book'!$C:$C,0)),"")) | J33: =IF(E33="","",I33*G33) | K33: =IF(OR($G33="",$I33=""),"",J33-(H33*J33))
C34: =IF($E34="","",ROW()-7) | F34: =IF($E34="","",IFERROR(INDEX('CTX Price Book'!$D:$D,MATCH($E34,'CTX Price Book'!$C:$C,0)),"SKU not found")) | G34: =IF($E34="","",IFERROR(INDEX('CTX Price Book'!$F:$F,MATCH($E34,'CTX Price Book'!$C:$C,0)),"")) | J34: =IF(E34="","",I34*G34) | K34: =IF(OR($G34="",$I34=""),"",J34-(H34*J34))
C35: =IF($E35="","",ROW()-7) | F35: =IF($E35="","",IFERROR(INDEX('CTX Price Book'!$D:$D,MATCH($E35,'CTX Price Book'!$C:$C,0)),"SKU not found")) | G35: =IF($E35="","",IFERROR(INDEX('CTX Price Book'!$F:$F,MATCH($E35,'CTX Price Book'!$C:$C,0)),"")) | J35: =IF(E35="","",I35*G35) | K35: =IF(OR($G35="",$I35=""),"",J35-(H35*J35))
C36: =IF($E36="","",ROW()-7) | F36: =IF($E36="","",IFERROR(INDEX('CTX Price Book'!$D:$D,MATCH($E36,'CTX Price Book'!$C:$C,0)),"SKU not found")) | G36: =IF($E36="","",IFERROR(INDEX('CTX Price Book'!$F:$F,MATCH($E36,'CTX Price Book'!$C:$C,0)),"")) | J36: =IF(E36="","",I36*G36) | K36: =IF(OR($G36="",$I36=""),"",J36-(H36*J36))
C37: =IF($E37="","",ROW()-7) | F37: =IF($E37="","",IFERROR(INDEX('CTX Price Book'!$D:$D,MATCH($E37,'CTX Price Book'!$C:$C,0)),"SKU not found")) | G37: =IF($E37="","",IFERROR(INDEX('CTX Price Book'!$F:$F,MATCH($E37,'CTX Price Book'!$C:$C,0)),"")) | J37: =IF(E37="","",I37*G37) | K37: =IF(OR($G37="",$I37=""),"",J37-(H37*J37))
B38: Grand Total | J38: =SUM(J8:J37) -> 0 | K38: =SUM(K8:K37) -> 0
B40: Instructions
B41: How to use: Pick a Category, then a SKU, using the dropdowns (tip: select the cell and press Alt + ↓ to open a dropdown without clicking the small arrow). Then type the Discount % and Qty in the blue cells. To REMOVE a row: right-click its row number on the left → Delete (rows below shift up automatically). To CLEAR a row in place: select the blue cells in that row and press Delete. To ADD more rows: right-click a row number inside the table → Insert. Fill out CPM INFO Table

Sheet Proposal
B1: ZERO IMPACT SOLUTIONS COSTS BREAKDOWN | G1: Charger cost factor (1.05 contingency x 1.10 markup): | H1: 1
B2: Charger (Parts Only Warranty included: 1 yr AC / 2 yrs DC) | C2: Quantity | D2: Final Cost | E2: Total
B3: =IF('INPUT SHEET'!E8="","",'INPUT SHEET'!F8) | C3: =IF('INPUT SHEET'!E8="","",'INPUT SHEET'!I8) | D3: =IF('INPUT SHEET'!E8="","",'INPUT SHEET'!K8*$H$1 /'INPUT SHEET'!I8*$H$1) | E3: =IF(B3="","",C3*D3)
B4: =IF('INPUT SHEET'!E9="","",'INPUT SHEET'!F9) | C4: =IF('INPUT SHEET'!E9="","",'INPUT SHEET'!I9) | D4: =IF('INPUT SHEET'!E9="","",'INPUT SHEET'!K9*$H$1 /'INPUT SHEET'!I9*$H$1) | E4: =IF(B4="","",C4*D4)
B5: =IF('INPUT SHEET'!E10="","",'INPUT SHEET'!F10) | C5: =IF('INPUT SHEET'!E10="","",'INPUT SHEET'!I10) | D5: =IF('INPUT SHEET'!E10="","",'INPUT SHEET'!K10*$H$1 /'INPUT SHEET'!I10*$H$1) | E5: =IF(B5="","",C5*D5)
B6: =IF('INPUT SHEET'!E11="","",'INPUT SHEET'!F11) | C6: =IF('INPUT SHEET'!E11="","",'INPUT SHEET'!I11) | D6: =IF('INPUT SHEET'!E11="","",'INPUT SHEET'!K11*$H$1 /'INPUT SHEET'!I11*$H$1) | E6: =IF(B6="","",C6*D6)
B7: =IF('INPUT SHEET'!E12="","",'INPUT SHEET'!F12) | C7: =IF('INPUT SHEET'!E12="","",'INPUT SHEET'!I12) | D7: =IF('INPUT SHEET'!E12="","",'INPUT SHEET'!K12*$H$1 /'INPUT SHEET'!I12*$H$1) | E7: =IF(B7="","",C7*D7)
B8: =IF('INPUT SHEET'!E13="","",'INPUT SHEET'!F13) | C8: =IF('INPUT SHEET'!E13="","",'INPUT SHEET'!I13) | D8: =IF('INPUT SHEET'!E13="","",'INPUT SHEET'!K13*$H$1 /'INPUT SHEET'!I13*$H$1) | E8: =IF(B8="","",C8*D8)
B9: =IF('INPUT SHEET'!E14="","",'INPUT SHEET'!F14) | C9: =IF('INPUT SHEET'!E14="","",'INPUT SHEET'!I14) | D9: =IF('INPUT SHEET'!E14="","",'INPUT SHEET'!K14*$H$1 /'INPUT SHEET'!I14*$H$1) | E9: =IF(B9="","",C9*D9)
B10: =IF('INPUT SHEET'!E15="","",'INPUT SHEET'!F15) | C10: =IF('INPUT SHEET'!E15="","",'INPUT SHEET'!I15) | D10: =IF('INPUT SHEET'!E15="","",'INPUT SHEET'!K15*$H$1 /'INPUT SHEET'!I15*$H$1) | E10: =IF(B10="","",C10*D10)
B11: =IF('INPUT SHEET'!E16="","",'INPUT SHEET'!F16) | C11: =IF('INPUT SHEET'!E16="","",'INPUT SHEET'!I16) | D11: =IF('INPUT SHEET'!E16="","",'INPUT SHEET'!K16*$H$1 /'INPUT SHEET'!I16*$H$1) | E11: =IF(B11="","",C11*D11)
B12: =IF('INPUT SHEET'!E17="","",'INPUT SHEET'!F17) | C12: =IF('INPUT SHEET'!E17="","",'INPUT SHEET'!I17) | D12: =IF('INPUT SHEET'!E17="","",'INPUT SHEET'!K17*$H$1 /'INPUT SHEET'!I17*$H$1) | E12: =IF(B12="","",C12*D12)
B13: Total Cost of EVSE | E13: ='Internal Summary'!D4 -> 0
B14: Electrical Supply & Construction Management Costs | C14: Quantity | D14: Final Cost | E14: Total after Discount
B15: Wires, Conduits and Peripherals | C15: =IF(N(D15)=0,0,1) -> 0 | D15: ='Internal Summary'!D14 -> 0 | E15: =C15*D15 -> 0
B16: Main Distribution Switchgear | C16: =IF(N(D16)=0,0,1) -> 0 | D16: ='Internal Summary'!D15 -> 0 | E16: =C16*D16 -> 0
B17: Electrical Sub-Panels, Transformers, Breakers | C17: =IF(N(D17)=0,0,1) -> 0 | D17: ='Internal Summary'!D16 -> 0 | E17: =C17*D17 -> 0
B18: Striping, Bollards, Signage | C18: =IF(N(D18)=0,0,1) -> 0 | D18: ='Internal Summary'!D17 -> 0 | E18: =C18*D18 -> 0
B19: Permits | C19: =IF(N(D19)=0,0,1) -> 0 | D19: ='Internal Summary'!D22 -> 0 | E19: =C19*D19 -> 0
B20: Designs and Engineering | C20: =IF(N(D20)=0,0,1) -> 0 | D20: ='Internal Summary'!D8 -> 0 | E20: =C20*D20 -> 0
B21: Construction Equipment | C21: =IF(N(D21)=0,0,1) -> 0 | D21: ='Internal Summary'!D24 -> 0 | E21: =C21*D21 -> 0
B22: Material Costs | C22: =IF(N(D22)=0,0,1) -> 0 | D22: ='Internal Summary'!D26 -> 0 | E22: =C22*D22 -> 0
B23: Miscellaneous | C23: =IF(N(D23)=0,0,1) -> 0 | D23: =SUM('Internal Summary'!D18:D21,'Internal Summary'!D23,'Internal Summary'!D25:D27) -'Internal Summary'!D26 -> 0 | E23: =C23*D23 -> 0
B24: Total Cost of Supply & Management | E24: =SUM(E15:E23) -> 0
B25: EVOLV platform costs (Calculated Yearly) | C25: Quantity | D25: Final Cost | E25: Total
B26: Monthly Network Cloud Services Fees (Per Port) | C26: ='INPUT SHEET'!N9 -> 0 | D26: 39.99 | E26: =C26*D26*12 -> 0
B27: # of years for duration of contract | C27: ='Internal Summary'!G4 -> 5 | E27: =C27*E26 -> 0
D28: Evolv Total Cost | E28: ='Internal Summary'!D6 -> 0
D29: Subtotal | E29: ='Internal Summary'!D6 +E24+E13 -> 0
D30: Tax | E30: ='Internal Summary'!D7 -> 0
D31: Rebate | E31: =0 -> 0
D32: Total | E32: =E29+E30 -> 0
B34: ZERO IMPACT BUILDERS COSTS BREAKDOWN
B35: Labor Days | C35: ='INPUT SHEET CPM'!P11 -> 30 | D35: 2772.5 | E35: =C35*D35 -> 83175
B36: Total Labor Costs | E36: =IF('Internal Summary'!D28<>"", 'Internal Summary'!D28, E35) -> 0
B37: Servicing Fees (Yearly calculation) | C37: Quantity | D37: Final Cost | E37: Total
B38: Service Plan - all chargers (every year) | C38: ='Internal Summary'!G11 -> 5 | D38: ='Internal Summary'!H11 -> 0 | E38: =C38*D38 -> 0
B39: Warranty - AC chargers (after free period) | C39: ='Internal Summary'!G12 -> 4 | D39: ='Internal Summary'!H12 -> 0 | E39: =C39*D39 -> 0
B40: Warranty - DC chargers (after free period) | C40: ='Internal Summary'!G13 -> 3 | D40: ='Internal Summary'!H13 -> 0 | E40: =C40*D40 -> 0
B41: Total | E41: ='Internal Summary'!D5+E36 -> 0
B42: Length Of Contract (years) | C42: ='Internal Summary'!$G$16 -> 5
B43: Total Charger | EVSE | Evolv | E43: =E32 -> 0
B44: Total ZIB Costs | E44: =E41 -> 0
B45: Grand Total | E45: =E43+E44 -> 0

Sheet Internal Summary
B2: Price | C2: Applied Discount | D2: Customer Price | F2: EVOLV platform costs (Calculated Yearly) | G2: Quantity | H2: Final Cost | I2: Total
A3: Equipment Purchase Invoice (Finance) | B3: =SUM(B4:B7) -> 0 | C3: =IF((B3)=0,0,1-D3/(B3)) -> 0 | D3: =SUM(D4:D7) -> 0 | F3: Monthly Network Cloud Services Fees (Per Port) | G3: =SUM('INPUT SHEET'!N9:T9) -> 0 | H3: 39.99 | I3: =H3*G3*12 -> 0
A4: Charger Hardware | B4: ='INPUT SHEET'!J38 -> 0 | C4: =IF(B4=0,0,(100 -('INPUT SHEET'!K38/'INPUT SHEET'!J38 *100)))*0.01 -> 0 | D4: =(B4)-((B4)*C4) -> 0 | F4: # of years for duration of contract | G4: 5
A5: 5 Year Service Agreement + Warranty | B5: =I14 -> 0 | C5: 0 | D5: =(B5)-((B5)*C5) -> 0 | H5: Subtotal | I5: =G4*I3 -> 0
A6: EVOLV & Commissioning Subtotal | B6: =I5 -> 0 | C6: 0 | D6: =(B6)-((B6)*C6) -> 0
A7: Sales Tax on Chargers | B7: =D4*7.25% -> 0 | C7: 0 | D7: =(B7)-((B7)*C7) -> 0
A8: Design Invoice (Finance) | B8: =SUM(B9:B12) -> 0 | C8: =IF((B8)=0,0,1-D8/(B8)) -> 0 | D8: =SUM(D9:D12) -> 0
A9: AutoCad Design Services | B9: 0 | C9: 0 | D9: =(B9)-((B9)*C9) -> 0 | G9: Servicing Fees
A10: Electrical Engineering Design | B10: 0 | C10: 0 | D10: =(B10)-((B10)*C10) -> 0 | G10: Quantity | H10: Cost | I10: Total
A11: Project Management | B11: 0 | C11: 0 | D11: =(B11)-((B11)*C11) -> 0 | F11: Service Plan - all chargers (every year) | G11: =$G$16 -> 5 | H11: =SUMPRODUCT('CTX Price Book'!$C$135:$C$144,'CTX Price Book'!$E$135:$E$144) -> 0 | I11: =G11*H11 -> 0
A12: Plan Check and Permit Fees | B12: 0 | C12: 0 | D12: =(B12)-((B12)*C12) -> 0 | F12: Warranty - AC chargers (after free period) | G12: =MAX(0,$G$16-'CTX Price Book'!$I$135) -> 4 | H12: =SUMPRODUCT('CTX Price Book'!$C$135:$C$138,'CTX Price Book'!$D$135:$D$138) -> 0 | I12: =G12*H12 -> 0
A13: Electrical Supply & Construction Management Costs | B13: =SUM(B14:B27) -> 0 | C13: =IF((B13)=0,0,1-D13/(B13)) -> 0 | D13: =SUM(D14:D27) -> 0 | F13: Warranty - DC chargers (after free period) | G13: =MAX(0,$G$16-'CTX Price Book'!$I$139) -> 3 | H13: =SUMPRODUCT('CTX Price Book'!$C$139:$C$144,'CTX Price Book'!$D$139:$D$144) -> 0 | I13: =G13*H13 -> 0
A14: Wires, Conduits and Peripherals | B14: =IF(ROUND('Costs Internal'!G15,2)=88919.7, 0, 'Costs Internal'!G3) -> 0 | C14: 0 | D14: =(B14)-((B14)*C14) -> 0 | F14: Total | I14: =SUM(I11:I13) -> 0
A15: Main Distribution Switchgear | B15: =IF(ROUND('Costs Internal'!G15,2)=88919.7, 0, 'Costs Internal'!G4) -> 0 | C15: 0 | D15: =(B15)-((B15)*C15) -> 0
A16: Electrical Sub-Panels, Transformers, Breakers | B16: =IF(ROUND('Costs Internal'!G15,2)=88919.7, 0, 'Costs Internal'!G5) -> 0 | C16: 0 | D16: =(B16)-((B16)*C16) -> 0 | F16: Length Of Contract (years) [INPUT] | G16: 5
A17: Striping, Bollards, Signage | B17: =IF(ROUND('Costs Internal'!G15,2)=88919.7, 0, 'Costs Internal'!G6) -> 0 | C17: 0 | D17: =(B17)-((B17)*C17) -> 0
A18: Asphalt and Paving | B18: =IF(ROUND('Costs Internal'!G15,2)=88919.7, 0, 'Costs Internal'!G7) -> 0 | C18: 0 | D18: =(B18)-((B18)*C18) -> 0
A19: Concrete Improvements | B19: =IF(ROUND('Costs Internal'!G15,2)=88919.7, 0, 'Costs Internal'!G8) -> 0 | C19: 0 | D19: =(B19)-((B19)*C19) -> 0
A20: ADA | B20: =IF(ROUND('Costs Internal'!G15,2)=88919.7, 0, 'Costs Internal'!G9) -> 0 | C20: 0 | D20: =(B20)-((B20)*C20) -> 0
A21: Environmental Cleanup Fee | B21: =IF(ROUND('Costs Internal'!G15,2)=88919.7, 0, 'Costs Internal'!G10) -> 0 | C21: 0 | D21: =(B21)-((B21)*C21) -> 0
A22: Permits | B22: =IF(ROUND('Costs Internal'!G15,2)=88919.7, 0, 'Costs Internal'!G11) -> 0 | C22: 0 | D22: =(B22)-((B22)*C22) -> 0
A23: Utility | B23: =IF(ROUND('Costs Internal'!G15,2)=88919.7, 0, 'Costs Internal'!G12) -> 0 | C23: 0 | D23: =(B23)-((B23)*C23) -> 0
A24: Construction Equipment | B24: =IF(ROUND('Costs Internal'!G15,2)=88919.7, 0, 'Costs Internal'!G13) -> 0 | C24: 0 | D24: =(B24)-((B24)*C24) -> 0 | N24: x
A25: Construction PM | B25: 0 | C25: 0 | D25: =(B25)-((B25)*C25) -> 0
A26: Materials | B26: 0 | C26: 0 | D26: =(B26)-((B26)*C26) -> 0
A27: Sales Tax on equipment | B27: 0 | C27: 0 | D27: =(B27)-((B27)*C27) -> 0
A28: Labor | B28: =IF(ROUND('Costs Internal'!G15,2)=88919.7, 0, 'Costs Internal'!G18) -> 0 | C28: 0 | D28: =(B28)-((B28)*C28) -> 0
A29: Grand Total | D29: =(B28+B13+B8+B3) -> 0
A30: Total After Discount | D30: =SUM(D3,D8,D13,D28) -> 0
A33: How to use: If you need extra costs Insert the extra costs into the Costs Row. The Values will be populated tot eh Cost Export and Financial Worksheet automatically

Sheet Financial Worksheet
L1: =B10&"-Year Cumulative Cashflow" -> 5-Year Cumulative Cashflow
A2: ="Projected Profits Over "&$B$10&" Years" -> Projected Profits Over 5 Years | D2: =$B$10&" Year Cashflow" -> 5 Year Cashflow | H2: =$B$10&" Year Charger Revenue" -> 5 Year Charger Revenue
A3: Total Costs Upfront | B3: =-B44 -> 0
A4: Carbon Credits | B4: =($B$10*SUMPRODUCT(E44:J44,E45:J45))+(G47*$B$10*12) -> 0 | D4: Year | E4: Annual Cashflow | F4: Cumulative | H4: Year | I4: Annual Charger Revenue | J4: Cumulative
A5: ITC | B5: 0 | D5: 0 | E5: =-B44 -> 0 | F5: =E5 -> 0 | H5: 0 | I5: =-B44 -> 0 | J5: =I5 -> 0
A6: EVSE Revenues | B6: =SUM(I6:I15) -> 0 | D6: =IF((ROW()-5)<=$B$10,ROW()-5,"") -> 1 | E6: =IF((ROW()-5)<=$B$10, I6+B5+(B4/$B$10), "") -> 0 | F6: =IF((ROW()-5)<=$B$10, F5+E6, "") -> 0 | H6: =IF((ROW()-5)<=$B$10,ROW()-5,"") -> 1 | I6: =IF((ROW()-5)<=$B$10,'Updated Chargers Revenue Calcul'!S95,"") -> 0 | J6: =IF((ROW()-5)<=$B$10, J5+I6, "") -> 0
A7: Net Revenues | B7: =B3+(B4+B6) -> 0 | D7: =IF((ROW()-5)<=$B$10,ROW()-5,"") -> 2 | E7: =IF((ROW()-5)<=$B$10, I7+(B4/$B$10), "") -> 0 | F7: =IF((ROW()-5)<=$B$10, F6+E7, "") -> 0 | H7: =IF((ROW()-5)<=$B$10,ROW()-5,"") -> 2 | I7: =IF((ROW()-5)<=$B$10,'Updated Chargers Revenue Calcul'!S96,"") -> 0 | J7: =IF((ROW()-5)<=$B$10, J6+I7, "") -> 0
D8: =IF((ROW()-5)<=$B$10,ROW()-5,"") -> 3 | E8: =IF((ROW()-5)<=$B$10, I8+(B4/$B$10), "") -> 0 | F8: =IF((ROW()-5)<=$B$10, F7+E8, "") -> 0 | H8: =IF((ROW()-5)<=$B$10,ROW()-5,"") -> 3 | I8: =IF((ROW()-5)<=$B$10,'Updated Chargers Revenue Calcul'!S97,"") -> 0 | J8: =IF((ROW()-5)<=$B$10, J7+I8, "") -> 0
A9: View Period | B9: 5 Year | D9: =IF((ROW()-5)<=$B$10,ROW()-5,"") -> 4 | E9: =IF((ROW()-5)<=$B$10, I9+(B4/$B$10), "") -> 0 | F9: =IF((ROW()-5)<=$B$10, F8+E9, "") -> 0 | H9: =IF((ROW()-5)<=$B$10,ROW()-5,"") -> 4 | I9: =IF((ROW()-5)<=$B$10,'Updated Chargers Revenue Calcul'!S98,"") -> 0 | J9: =IF((ROW()-5)<=$B$10, J8+I9, "") -> 0
A10: Years (auto) | B10: =IF(B9="10 Year",10,5) -> 5 | D10: =IF((ROW()-5)<=$B$10,ROW()-5,"") -> 5 | E10: =IF((ROW()-5)<=$B$10, I10+(B4/$B$10), "") -> 0 | F10: =IF((ROW()-5)<=$B$10, F9+E10, "") -> 0 | H10: =IF((ROW()-5)<=$B$10,ROW()-5,"") -> 5 | I10: =IF((ROW()-5)<=$B$10,'Updated Chargers Revenue Calcul'!S99,"") -> 0 | J10: =IF((ROW()-5)<=$B$10, J9+I10, "") -> 0
D11: =IF((ROW()-5)<=$B$10,ROW()-5,"") | E11: =IF((ROW()-5)<=$B$10, I11+(B4/$B$10), "") | F11: =IF((ROW()-5)<=$B$10, F10+E11, "") | H11: =IF((ROW()-5)<=$B$10,ROW()-5,"") | I11: =IF((ROW()-5)<=$B$10,'Updated Chargers Revenue Calcul'!S100,"") | J11: =IF((ROW()-5)<=$B$10, J10+I11, "")
D12: =IF((ROW()-5)<=$B$10,ROW()-5,"") | E12: =IF((ROW()-5)<=$B$10, I12+(B4/$B$10), "") | F12: =IF((ROW()-5)<=$B$10, F11+E12, "") | H12: =IF((ROW()-5)<=$B$10,ROW()-5,"") | I12: =IF((ROW()-5)<=$B$10,'Updated Chargers Revenue Calcul'!S101,"") | J12: =IF((ROW()-5)<=$B$10, J11+I12, "")
D13: =IF((ROW()-5)<=$B$10,ROW()-5,"") | E13: =IF((ROW()-5)<=$B$10, I13+(B4/$B$10), "") | F13: =IF((ROW()-5)<=$B$10, F12+E13, "") | H13: =IF((ROW()-5)<=$B$10,ROW()-5,"") | I13: =IF((ROW()-5)<=$B$10,'Updated Chargers Revenue Calcul'!S102,"") | J13: =IF((ROW()-5)<=$B$10, J12+I13, "")
D14: =IF((ROW()-5)<=$B$10,ROW()-5,"") | E14: =IF((ROW()-5)<=$B$10, I14+(B4/$B$10), "") | F14: =IF((ROW()-5)<=$B$10, F13+E14, "") | H14: =IF((ROW()-5)<=$B$10,ROW()-5,"") | I14: =IF((ROW()-5)<=$B$10,'Updated Chargers Revenue Calcul'!S103,"") | J14: =IF((ROW()-5)<=$B$10, J13+I14, "")
B15: Customer Total | D15: =IF((ROW()-5)<=$B$10,ROW()-5,"") | E15: =IF((ROW()-5)<=$B$10, I15+(B4/$B$10), "") | F15: =IF((ROW()-5)<=$B$10, F14+E15, "") | H15: =IF((ROW()-5)<=$B$10,ROW()-5,"") | I15: =IF((ROW()-5)<=$B$10,'Updated Chargers Revenue Calcul'!S104,"") | J15: =IF((ROW()-5)<=$B$10, J14+I15, "")
A16: Equipment Purchase Invoice | B16: ='Internal Summary'!D3 -> 0
A17: Charger Hardware | B17: ='Internal Summary'!D4 -> 0
A18: Parts Warranty | B18: ='Internal Summary'!D5 -> 0
A19: EVOLV & Commissioning Subtotal | B19: ='Internal Summary'!D6 -> 0
A20: 5 Year Service Agreement | B20: ='Internal Summary'!B5 -> 0
A21: Sales Tax on Chargers | B21: ='Internal Summary'!D7 -> 0
A22: Design Invoice | B22: ='Internal Summary'!D8 -> 0
A23: AutoCad Design Services | B23: ='Internal Summary'!D9 -> 0
A24: Electrical Engineering Design | B24: ='Internal Summary'!D10 -> 0
A25: Project Management (@$358/hour) | B25: ='Internal Summary'!D11 -> 0
A26: Plan Check and Permit Fees | B26: ='Internal Summary'!D12 -> 0
A27: Electrical Supply & Construction Management Costs | B27: ='Internal Summary'!D13 -> 0
A28: Wires, Conduits and Peripherals | B28: ='Internal Summary'!D14 -> 0
A29: Main Distribution Switchgear | B29: ='Internal Summary'!D15 -> 0
A30: Electrical Sub-Panels, Transformers, Breakers | B30: ='Internal Summary'!D16 -> 0
A31: Striping, Bollards, Signage | B31: ='Internal Summary'!D17 -> 0
A32: Asphalt and Paving | B32: ='Internal Summary'!D18 -> 0
... A41: Sales Tax on equipment | B41: ='Internal Summary'!D27 -> 0
A42: Labor | B42: ='Internal Summary'!D28 -> 0 | D42: CC Rate ($/kW/yr) | E42: 71.6667
A43: Grand Total | B43: ='Internal Summary'!D29 -> 0 | D43: L3 Rating (kW) | E43: ='INPUT SHEET'!O10 -> 60 | F43: ='INPUT SHEET'!P10 -> 120 | G43: ='INPUT SHEET'!Q10 -> 160 | H43: ='INPUT SHEET'!R10 -> 180 | I43: ='INPUT SHEET'!S10 -> 240 | J43: ='INPUT SHEET'!T10 -> 360
A44: Remaining Balance after Discount | B44: ='Internal Summary'!D30 -> 0 | D44: Qty | E44: ='INPUT SHEET'!O8 -> 0 | F44: ='INPUT SHEET'!P8 -> 0 | G44: ='INPUT SHEET'!Q8 -> 0 | H44: ='INPUT SHEET'!R8 -> 0 | I44: ='INPUT SHEET'!S8 -> 0 | J44: ='INPUT SHEET'!T8 -> 0
D45: Multiplier ($/yr) | E45: =E43*$E$42 -> 4300.002 | F45: =F43*$E$42 -> 8600.004 | G45: =G43*$E$42 -> 11466.672 | H45: =H43*$E$42 -> 12900.006 | I45: =I43*$E$42 -> 17200.008 | J45: =J43*$E$42 -> 25800.012
D46: L2 | E46: Usage | F46: Multiplier
D47: Consumption Credits/m | E47: ='Updated Chargers Revenue Calcul'!B16*30 -> 0 | F47: 0.0045 | G47: =E47*F47 -> 0

Sheet DLL Schedule
A1: Loan Amortization Schedule
B4: Enter values | H4: Loan summary
C5: Loan amount | D5: ='Financial Worksheet'!B44 -> 0 | I5: Scheduled payment | J5: =IF('DLL Schedule'!Values_Entered=1,-PMT('DLL Schedule'!Interest_Rate/'DLL Schedule'!Num_Pmt_Per_Year,'DLL Schedule'!Loan_Years*'DLL Schedule'!Num_Pmt_Per_Year,'DLL Schedule'!Loan_Amount),"")
C6: Annual interest rate | D6: 0.0839 | I6: Scheduled number of payments | J6: =IF('DLL Schedule'!Values_Entered=1,'DLL Schedule'!Loan_Years*'DLL Schedule'!Num_Pmt_Per_Year,"")
C7: Loan period in years | D7: 5 | I7: Actual number of payments | J7: =IF('DLL Schedule'!Values_Entered=1,MATCH(0.01,'DLL Schedule'!End_Bal,-1)+1,"")
C8: Number of payments per year | D8: 12 | I8: Total early payments | J8: =IF('DLL Schedule'!Values_Entered=1,SUMIF('DLL Schedule'!Beg_Bal,">0",'DLL Schedule'!Extra_Pay),"")
C9: Start date of loan | D9: 46235 | I9: Total interest | J9: =IF('DLL Schedule'!Values_Entered=1,SUMIF('DLL Schedule'!Beg_Bal,">0",'DLL Schedule'!Int),"")
C10: Optional extra payments | D10: 0
B12: Lender name:
A16: Pmt. No. | B16: Payment Date | C16: Beginning Balance | D16: Scheduled Payment | E16: Extra Payment | F16: Total Payment | G16: Principal | H16: Interest | I16: Ending Balance | J16: Cumulative Interest
A18: =IF('DLL Schedule'!Values_Entered=1,1,"") | B18: =IF('DLL Schedule'!Pay_Num<>"",DATE(YEAR('DLL Schedule'!Loan_Start),MONTH('DLL Schedule'!Loan_Start)+('DLL Schedule'!Pay_Num)*12/'DLL Schedule'!Num_Pmt_Per_Year,DAY('DLL Schedule'!Loan_Start)),"") | C18: =IF('DLL Schedule'!Values_Entered=1,'DLL Schedule'!Loan_Amount,"") | D18: =IF('DLL Schedule'!Pay_Num<>"",'DLL Schedule'!Scheduled_Monthly_Payment,"") | E18: =IF('DLL Schedule'!Pay_Num<>"",IF('DLL Schedule'!Sched_Pay+'DLL Schedule'!Scheduled_Extra_Payments<'DLL Schedule'!Beg_Bal,'DLL Schedule'!Scheduled_Extra_Payments,IF('DLL Schedule'!Beg_Bal-'DLL Schedule'!Sched_Pay>0,'DLL Schedule'!Beg_Bal-'DLL Schedule'!Sched_Pay,0)),"") | F18: =IF('DLL Schedule'!Pay_Num<>"",IF('DLL Schedule'!Sched_Pay+'DLL Schedule'!Extra_Pay<'DLL Schedule'!Beg_Bal,'DLL Schedule'!Sched_Pay+'DLL Schedule'!Extra_Pay,'DLL Schedule'!Beg_Bal),"") | G18: =IF('DLL Schedule'!Pay_Num<>"",'DLL Schedule'!Total_Pay-'DLL Schedule'!Int,"") | H18: =IF('DLL Schedule'!Pay_Num<>"",'DLL Schedule'!Beg_Bal*('DLL Schedule'!Interest_Rate/'DLL Schedule'!Num_Pmt_Per_Year),"") | I18: =IF('DLL Schedule'!Pay_Num<>"",IF('DLL Schedule'!Sched_Pay+'DLL Schedule'!Extra_Pay<'DLL Schedule'!Beg_Bal,'DLL Schedule'!Beg_Bal-'DLL Schedule'!Princ,0),"") | J18: =SUM($H$18:$H18) -> 0
A19: =IF(AND('DLL Schedule'!Values_Entered=1,A18<>"",I18>0),A18+1,"") | B19: =IF('DLL Schedule'!Pay_Num<>"",DATE(YEAR('DLL Schedule'!Loan_Start),MONTH('DLL Schedule'!Loan_Start)+('DLL Schedule'!Pay_Num)*12/'DLL Schedule'!Num_Pmt_Per_Year,DAY('DLL Schedule'!Loan_Start)),"") | C19: =IF('DLL Schedule'!Pay_Num<>"",I18,"") | D19: =IF('DLL Schedule'!Pay_Num<>"",'DLL Schedule'!Scheduled_Monthly_Payment,"") | E19: =IF('DLL Schedule'!Pay_Num<>"",IF('DLL Schedule'!Sched_Pay+'DLL Schedule'!Scheduled_Extra_Payments<'DLL Schedule'!Beg_Bal,'DLL Schedule'!Scheduled_Extra_Payments,IF('DLL Schedule'!Beg_Bal-'DLL Schedule'!Sched_Pay>0,'DLL Schedule'!Beg_Bal-'DLL Schedule'!Sched_Pay,0)),"") | F19: =IF('DLL Schedule'!Pay_Num<>"",IF('DLL Schedule'!Sched_Pay+'DLL Schedule'!Extra_Pay<'DLL Schedule'!Beg_Bal,'DLL Schedule'!Sched_Pay+'DLL Schedule'!Extra_Pay,'DLL Schedule'!Beg_Bal),"") | G19: =IF('DLL Schedule'!Pay_Num<>"",'DLL Schedule'!Total_Pay-'DLL Schedule'!Int,"") | H19: =IF('DLL Schedule'!Pay_Num<>"",'DLL Schedule'!Beg_Bal*'DLL Schedule'!Interest_Rate/'DLL Schedule'!Num_Pmt_Per_Year,"") | I19: =IF('DLL Schedule'!Pay_Num<>"",IF('DLL Schedule'!Sched_Pay+'DLL Schedule'!Extra_Pay<'DLL Schedule'!Beg_Bal,'DLL Schedule'!Beg_Bal-'DLL Schedule'!Princ,0),"") | J19: =SUM($H$18:$H19) -> 0
A20: =IF(AND('DLL Schedule'!Values_Entered=1,A19<>"",I19>0),A19+1,"") | B20: =IF('DLL Schedule'!Pay_Num<>"",DATE(YEAR('DLL Schedule'!Loan_Start),MONTH('DLL Schedule'!Loan_Start)+('DLL Schedule'!Pay_Num)*12/'DLL Schedule'!Num_Pmt_Per_Year,DAY('DLL Schedule'!Loan_Start)),"") | C20: =IF('DLL Schedule'!Pay_Num<>"",I19,"") | D20: =IF('DLL Schedule'!Pay_Num<>"",'DLL Schedule'!Scheduled_Monthly_Payment,"") | E20: =IF('DLL Schedule'!Pay_Num<>"",IF('DLL Schedule'!Sched_Pay+'DLL Schedule'!Scheduled_Extra_Payments<'DLL Schedule'!Beg_Bal,'DLL Schedule'!Scheduled_Extra_Payments,IF('DLL Schedule'!Beg_Bal-'DLL Schedule'!Sched_Pay>0,'DLL Schedule'!Beg_Bal-'DLL Schedule'!Sched_Pay,0)),"") | F20: =IF('DLL Schedule'!Pay_Num<>"",IF('DLL Schedule'!Sched_Pay+'DLL Schedule'!Extra_Pay<'DLL Schedule'!Beg_Bal,'DLL Schedule'!Sched_Pay+'DLL Schedule'!Extra_Pay,'DLL Schedule'!Beg_Bal),"") | G20: =IF('DLL Schedule'!Pay_Num<>"",'DLL Schedule'!Total_Pay-'DLL Schedule'!Int,"") | H20: =IF('DLL Schedule'!Pay_Num<>"",'DLL Schedule'!Beg_Bal*'DLL Schedule'!Interest_Rate/'DLL Schedule'!Num_Pmt_Per_Year,"") | I20: =IF('DLL Schedule'!Pay_Num<>"",IF('DLL Schedule'!Sched_Pay+'DLL Schedule'!Extra_Pay<'DLL Schedule'!Beg_Bal,'DLL Schedule'!Beg_Bal-'DLL Schedule'!Princ,0),"") | J20: =SUM($H$18:$H20) -> 0
A21: =IF(AND('DLL Schedule'!Values_Entered=1,A20<>"",I20>0),A20+1,"") | B21: =IF('DLL Schedule'!Pay_Num<>"",DATE(YEAR('DLL Schedule'!Loan_Start),MONTH('DLL Schedule'!Loan_Start)+('DLL Schedule'!Pay_Num)*12/'DLL Schedule'!Num_Pmt_Per_Year,DAY('DLL Schedule'!Loan_Start)),"") | C21: =IF('DLL Schedule'!Pay_Num<>"",I20,"") | D21: =IF('DLL Schedule'!Pay_Num<>"",'DLL Schedule'!Scheduled_Monthly_Payment,"") | E21: =IF('DLL Schedule'!Pay_Num<>"",IF('DLL Schedule'!Sched_Pay+'DLL Schedule'!Scheduled_Extra_Payments<'DLL Schedule'!Beg_Bal,'DLL Schedule'!Scheduled_Extra_Payments,IF('DLL Schedule'!Beg_Bal-'DLL Schedule'!Sched_Pay>0,'DLL Schedule'!Beg_Bal-'DLL Schedule'!Sched_Pay,0)),"") | F21: =IF('DLL Schedule'!Pay_Num<>"",IF('DLL Schedule'!Sched_Pay+'DLL Schedule'!Extra_Pay<'DLL Schedule'!Beg_Bal,'DLL Schedule'!Sched_Pay+'DLL Schedule'!Extra_Pay,'DLL Schedule'!Beg_Bal),"") | G21: =IF('DLL Schedule'!Pay_Num<>"",'DLL Schedule'!Total_Pay-'DLL Schedule'!Int,"") | H21: =IF('DLL Schedule'!Pay_Num<>"",'DLL Schedule'!Beg_Bal*'DLL Schedule'!Interest_Rate/'DLL Schedule'!Num_Pmt_Per_Year,"") | I21: =IF('DLL Schedule'!Pay_Num<>"",IF('DLL Schedule'!Sched_Pay+'DLL Schedule'!Extra_Pay<'DLL Schedule'!Beg_Bal,'DLL Schedule'!Beg_Bal-'DLL Schedule'!Princ,0),"") | J21: =SUM($H$18:$H21) -> 0
A22: =IF(AND('DLL Schedule'!Values_Entered=1,A21<>"",I21>0),A21+1,"") | B22: =IF('DLL Schedule'!Pay_Num<>"",DATE(YEAR('DLL Schedule'!Loan_Start),MONTH('DLL Schedule'!Loan_Start)+('DLL Schedule'!Pay_Num)*12/'DLL Schedule'!Num_Pmt_Per_Year,DAY('DLL Schedule'!Loan_Start)),"") | C22: =IF('DLL Schedule'!Pay_Num<>"",I21,"") | D22: =IF('DLL Schedule'!Pay_Num<>"",'DLL Schedule'!Scheduled_Monthly_Payment,"") | E22: =IF('DLL Schedule'!Pay_Num<>"",IF('DLL Schedule'!Sched_Pay+'DLL Schedule'!Scheduled_Extra_Payments<'DLL Schedule'!Beg_Bal,'DLL Schedule'!Scheduled_Extra_Payments,IF('DLL Schedule'!Beg_Bal-'DLL Schedule'!Sched_Pay>0,'DLL Schedule'!Beg_Bal-'DLL Schedule'!Sched_Pay,0)),"") | F22: =IF('DLL Schedule'!Pay_Num<>"",IF('DLL Schedule'!Sched_Pay+'DLL Schedule'!Extra_Pay<'DLL Schedule'!Beg_Bal,'DLL Schedule'!Sched_Pay+'DLL Schedule'!Extra_Pay,'DLL Schedule'!Beg_Bal),"") | G22: =IF('DLL Schedule'!Pay_Num<>"",'DLL Schedule'!Total_Pay-'DLL Schedule'!Int,"") | H22: =IF('DLL Schedule'!Pay_Num<>"",'DLL Schedule'!Beg_Bal*'DLL Schedule'!Interest_Rate/'DLL Schedule'!Num_Pmt_Per_Year,"") | I22: =IF('DLL Schedule'!Pay_Num<>"",IF('DLL Schedule'!Sched_Pay+'DLL Schedule'!Extra_Pay<'DLL Schedule'!Beg_Bal,'DLL Schedule'!Beg_Bal-'DLL Schedule'!Princ,0),"") | J22: =SUM($H$18:$H22) -> 0
A23: =IF(AND('DLL Schedule'!Values_Entered=1,A22<>"",I22>0),A22+1,"") | B23: =IF('DLL Schedule'!Pay_Num<>"",DATE(YEAR('DLL Schedule'!Loan_Start),MONTH('DLL Schedule'!Loan_Start)+('DLL Schedule'!Pay_Num)*12/'DLL Schedule'!Num_Pmt_Per_Year,DAY('DLL Schedule'!Loan_Start)),"") | C23: =IF('DLL Schedule'!Pay_Num<>"",I22,"") | D23: =IF('DLL Schedule'!Pay_Num<>"",'DLL Schedule'!Scheduled_Monthly_Payment,"") | E23: =IF('DLL Schedule'!Pay_Num<>"",IF('DLL Schedule'!Sched_Pay+'DLL Schedule'!Scheduled_Extra_Payments<'DLL Schedule'!Beg_Bal,'DLL Schedule'!Scheduled_Extra_Payments,IF('DLL Schedule'!Beg_Bal-'DLL Schedule'!Sched_Pay>0,'DLL Schedule'!Beg_Bal-'DLL Schedule'!Sched_Pay,0)),"") | F23: =IF('DLL Schedule'!Pay_Num<>"",IF('DLL Schedule'!Sched_Pay+'DLL Schedule'!Extra_Pay<'DLL Schedule'!Beg_Bal,'DLL Schedule'!Sched_Pay+'DLL Schedule'!Extra_Pay,'DLL Schedule'!Beg_Bal),"") | G23: =IF('DLL Schedule'!Pay_Num<>"",'DLL Schedule'!Total_Pay-'DLL Schedule'!Int,"") | H23: =IF('DLL Schedule'!Pay_Num<>"",'DLL Schedule'!Beg_Bal*'DLL Schedule'!Interest_Rate/'DLL Schedule'!Num_Pmt_Per_Year,"") | I23: =IF('DLL Schedule'!Pay_Num<>"",IF('DLL Schedule'!Sched_Pay+'DLL Schedule'!Extra_Pay<'DLL Schedule'!Beg_Bal,'DLL Schedule'!Beg_Bal-'DLL Schedule'!Princ,0),"") | J23: =SUM($H$18:$H23) -> 0
A24: =IF(AND('DLL Schedule'!Values_Entered=1,A23<>"",I23>0),A23+1,"") | B24: =IF('DLL Schedule'!Pay_Num<>"",DATE(YEAR('DLL Schedule'!Loan_Start),MONTH('DLL Schedule'!Loan_Start)+('DLL Schedule'!Pay_Num)*12/'DLL Schedule'!Num_Pmt_Per_Year,DAY('DLL Schedule'!Loan_Start)),"") | C24: =IF('DLL Schedule'!Pay_Num<>"",I23,"") | D24: =IF('DLL Schedule'!Pay_Num<>"",'DLL Schedule'!Scheduled_Monthly_Payment,"") | E24: =IF('DLL Schedule'!Pay_Num<>"",IF('DLL Schedule'!Sched_Pay+'DLL Schedule'!Scheduled_Extra_Payments<'DLL Schedule'!Beg_Bal,'DLL Schedule'!Scheduled_Extra_Payments,IF('DLL Schedule'!Beg_Bal-'DLL Schedule'!Sched_Pay>0,'DLL Schedule'!Beg_Bal-'DLL Schedule'!Sched_Pay,0)),"") | F24: =IF('DLL Schedule'!Pay_Num<>"",IF('DLL Schedule'!Sched_Pay+'DLL Schedule'!Extra_Pay<'DLL Schedule'!Beg_Bal,'DLL Schedule'!Sched_Pay+'DLL Schedule'!Extra_Pay,'DLL Schedule'!Beg_Bal),"") | G24: =IF('DLL Schedule'!Pay_Num<>"",'DLL Schedule'!Total_Pay-'DLL Schedule'!Int,"") | H24: =IF('DLL Schedule'!Pay_Num<>"",'DLL Schedule'!Beg_Bal*'DLL Schedule'!Interest_Rate/'DLL Schedule'!Num_Pmt_Per_Year,"") | I24: =IF('DLL Schedule'!Pay_Num<>"",IF('DLL Schedule'!Sched_Pay+'DLL Schedule'!Extra_Pay<'DLL Schedule'!Beg_Bal,'DLL Schedule'!Beg_Bal-'DLL Schedule'!Princ,0),"") | J24: =SUM($H$18:$H24) -> 0
A25: =IF(AND('DLL Schedule'!Values_Entered=1,A24<>"",I24>0),A24+1,"") | B25: =IF('DLL Schedule'!Pay_Num<>"",DATE(YEAR('DLL Schedule'!Loan_Start),MONTH('DLL Schedule'!Loan_Start)+('DLL Schedule'!Pay_Num)*12/'DLL Schedule'!Num_Pmt_Per_Year,DAY('DLL Schedule'!Loan_Start)),"") | C25: =IF('DLL Schedule'!Pay_Num<>"",I24,"") | D25: =IF('DLL Schedule'!Pay_Num<>"",'DLL Schedule'!Scheduled_Monthly_Payment,"") | E25: =IF('DLL Schedule'!Pay_Num<>"",IF('DLL Schedule'!Sched_Pay+'DLL Schedule'!Scheduled_Extra_Payments<'DLL Schedule'!Beg_Bal,'DLL Schedule'!Scheduled_Extra_Payments,IF('DLL Schedule'!Beg_Bal-'DLL Schedule'!Sched_Pay>0,'DLL Schedule'!Beg_Bal-'DLL Schedule'!Sched_Pay,0)),"") | F25: =IF('DLL Schedule'!Pay_Num<>"",IF('DLL Schedule'!Sched_Pay+'DLL Schedule'!Extra_Pay<'DLL Schedule'!Beg_Bal,'DLL Schedule'!Sched_Pay+'DLL Schedule'!Extra_Pay,'DLL Schedule'!Beg_Bal),"") | G25: =IF('DLL Schedule'!Pay_Num<>"",'DLL Schedule'!Total_Pay-'DLL Schedule'!Int,"") | H25: =IF('DLL Schedule'!Pay_Num<>"",'DLL Schedule'!Beg_Bal*'DLL Schedule'!Interest_Rate/'DLL Schedule'!Num_Pmt_Per_Year,"") | I25: =IF('DLL Schedule'!Pay_Num<>"",IF('DLL Schedule'!Sched_Pay+'DLL Schedule'!Extra_Pay<'DLL Schedule'!Beg_Bal,'DLL Schedule'!Beg_Bal-'DLL Schedule'!Princ,0),"") | J25: =SUM($H$18:$H25) -> 0
A26: =IF(AND('DLL Schedule'!Values_Entered=1,A25<>"",I25>0),A25+1,"") | B26: =IF('DLL Schedule'!Pay_Num<>"",DATE(YEAR('DLL Schedule'!Loan_Start),MONTH('DLL Schedule'!Loan_Start)+('DLL Schedule'!Pay_Num)*12/'DLL Schedule'!Num_Pmt_Per_Year,DAY('DLL Schedule'!Loan_Start)),"") | C26: =IF('DLL Schedule'!Pay_Num<>"",I25,"") | D26: =IF('DLL Schedule'!Pay_Num<>"",'DLL Schedule'!Scheduled_Monthly_Payment,"") | E26: =IF('DLL Schedule'!Pay_Num<>"",IF('DLL Schedule'!Sched_Pay+'DLL Schedule'!Scheduled_Extra_Payments<'DLL Schedule'!Beg_Bal,'DLL Schedule'!Scheduled_Extra_Payments,IF('DLL Schedule'!Beg_Bal-'DLL Schedule'!Sched_Pay>0,'DLL Schedule'!Beg_Bal-'DLL Schedule'!Sched_Pay,0)),"") | F26: =IF('DLL Schedule'!Pay_Num<>"",IF('DLL Schedule'!Sched_Pay+'DLL Schedule'!Extra_Pay<'DLL Schedule'!Beg_Bal,'DLL Schedule'!Sched_Pay+'DLL Schedule'!Extra_Pay,'DLL Schedule'!Beg_Bal),"") | G26: =IF('DLL Schedule'!Pay_Num<>"",'DLL Schedule'!Total_Pay-'DLL Schedule'!Int,"") | H26: =IF('DLL Schedule'!Pay_Num<>"",'DLL Schedule'!Beg_Bal*'DLL Schedule'!Interest_Rate/'DLL Schedule'!Num_Pmt_Per_Year,"") | I26: =IF('DLL Schedule'!Pay_Num<>"",IF('DLL Schedule'!Sched_Pay+'DLL Schedule'!Extra_Pay<'DLL Schedule'!Beg_Bal,'DLL Schedule'!Beg_Bal-'DLL Schedule'!Princ,0),"") | J26: =SUM($H$18:$H26) -> 0
A27: =IF(AND('DLL Schedule'!Values_Entered=1,A26<>"",I26>0),A26+1,"") | B27: =IF('DLL Schedule'!Pay_Num<>"",DATE(YEAR('DLL Schedule'!Loan_Start),MONTH('DLL Schedule'!Loan_Start)+('DLL Schedule'!Pay_Num)*12/'DLL Schedule'!Num_Pmt_Per_Year,DAY('DLL Schedule'!Loan_Start)),"") | C27: =IF('DLL Schedule'!Pay_Num<>"",I26,"") | D27: =IF('DLL Schedule'!Pay_Num<>"",'DLL Schedule'!Scheduled_Monthly_Payment,"") | E27: =IF('DLL Schedule'!Pay_Num<>"",IF('DLL Schedule'!Sched_Pay+'DLL Schedule'!Scheduled_Extra_Payments<'DLL Schedule'!Beg_Bal,'DLL Schedule'!Scheduled_Extra_Payments,IF('DLL Schedule'!Beg_Bal-'DLL Schedule'!Sched_Pay>0,'DLL Schedule'!Beg_Bal-'DLL Schedule'!Sched_Pay,0)),"") | F27: =IF('DLL Schedule'!Pay_Num<>"",IF('DLL Schedule'!Sched_Pay+'DLL Schedule'!Extra_Pay<'DLL Schedule'!Beg_Bal,'DLL Schedule'!Sched_Pay+'DLL Schedule'!Extra_Pay,'DLL Schedule'!Beg_Bal),"") | G27: =IF('DLL Schedule'!Pay_Num<>"",'DLL Schedule'!Total_Pay-'DLL Schedule'!Int,"") | H27: =IF('DLL Schedule'!Pay_Num<>"",'DLL Schedule'!Beg_Bal*'DLL Schedule'!Interest_Rate/'DLL Schedule'!Num_Pmt_Per_Year,"") | I27: =IF('DLL Schedule'!Pay_Num<>"",IF('DLL Schedule'!Sched_Pay+'DLL Schedule'!Extra_Pay<'DLL Schedule'!Beg_Bal,'DLL Schedule'!Beg_Bal-'DLL Schedule'!Princ,0),"") | J27: =SUM($H$18:$H27) -> 0
A28: =IF(AND('DLL Schedule'!Values_Entered=1,A27<>"",I27>0),A27+1,"") | B28: =IF('DLL Schedule'!Pay_Num<>"",DATE(YEAR('DLL Schedule'!Loan_Start),MONTH('DLL Schedule'!Loan_Start)+('DLL Schedule'!Pay_Num)*12/'DLL Schedule'!Num_Pmt_Per_Year,DAY('DLL Schedule'!Loan_Start)),"") | C28: =IF('DLL Schedule'!Pay_Num<>"",I27,"") | D28: =IF('DLL Schedule'!Pay_Num<>"",'DLL Schedule'!Scheduled_Monthly_Payment,"") | E28: =IF('DLL Schedule'!Pay_Num<>"",IF('DLL Schedule'!Sched_Pay+'DLL Schedule'!Scheduled_Extra_Payments<'DLL Schedule'!Beg_Bal,'DLL Schedule'!Scheduled_Extra_Payments,IF('DLL Schedule'!Beg_Bal-'DLL Schedule'!Sched_Pay>0,'DLL Schedule'!Beg_Bal-'DLL Schedule'!Sched_Pay,0)),"") | F28: =IF('DLL Schedule'!Pay_Num<>"",IF('DLL Schedule'!Sched_Pay+'DLL Schedule'!Extra_Pay<'DLL Schedule'!Beg_Bal,'DLL Schedule'!Sched_Pay+'DLL Schedule'!Extra_Pay,'DLL Schedule'!Beg_Bal),"") | G28: =IF('DLL Schedule'!Pay_Num<>"",'DLL Schedule'!Total_Pay-'DLL Schedule'!Int,"") | H28: =IF('DLL Schedule'!Pay_Num<>"",'DLL Schedule'!Beg_Bal*'DLL Schedule'!Interest_Rate/'DLL Schedule'!Num_Pmt_Per_Year,"") | I28: =IF('DLL Schedule'!Pay_Num<>"",IF('DLL Schedule'!Sched_Pay+'DLL Schedule'!Extra_Pay<'DLL Schedule'!Beg_Bal,'DLL Schedule'!Beg_Bal-'DLL Schedule'!Princ,0),"") | J28: =SUM($H$18:$H28) -> 0
A29: =IF(AND('DLL Schedule'!Values_Entered=1,A28<>"",I28>0),A28+1,"") | B29: =IF('DLL Schedule'!Pay_Num<>"",DATE(YEAR('DLL Schedule'!Loan_Start),MONTH('DLL Schedule'!Loan_Start)+('DLL Schedule'!Pay_Num)*12/'DLL Schedule'!Num_Pmt_Per_Year,DAY('DLL Schedule'!Loan_Start)),"") | C29: =IF('DLL Schedule'!Pay_Num<>"",I28,"") | D29: =IF('DLL Schedule'!Pay_Num<>"",'DLL Schedule'!Scheduled_Monthly_Payment,"") | E29: =IF('DLL Schedule'!Pay_Num<>"",IF('DLL Schedule'!Sched_Pay+'DLL Schedule'!Scheduled_Extra_Payments<'DLL Schedule'!Beg_Bal,'DLL Schedule'!Scheduled_Extra_Payments,IF('DLL Schedule'!Beg_Bal-'DLL Schedule'!Sched_Pay>0,'DLL Schedule'!Beg_Bal-'DLL Schedule'!Sched_Pay,0)),"") | F29: =IF('DLL Schedule'!Pay_Num<>"",IF('DLL Schedule'!Sched_Pay+'DLL Schedule'!Extra_Pay<'DLL Schedule'!Beg_Bal,'DLL Schedule'!Sched_Pay+'DLL Schedule'!Extra_Pay,'DLL Schedule'!Beg_Bal),"") | G29: =IF('DLL Schedule'!Pay_Num<>"",'DLL Schedule'!Total_Pay-'DLL Schedule'!Int,"") | H29: =IF('DLL Schedule'!Pay_Num<>"",'DLL Schedule'!Beg_Bal*'DLL Schedule'!Interest_Rate/'DLL Schedule'!Num_Pmt_Per_Year,"") | I29: =IF('DLL Schedule'!Pay_Num<>"",IF('DLL Schedule'!Sched_Pay+'DLL Schedule'!Extra_Pay<'DLL Schedule'!Beg_Bal,'DLL Schedule'!Beg_Bal-'DLL Schedule'!Princ,0),"") | J29: =SUM($H$18:$H29) -> 0
A30: =IF(AND('DLL Schedule'!Values_Entered=1,A29<>"",I29>0),A29+1,"") | B30: =IF('DLL Schedule'!Pay_Num<>"",DATE(YEAR('DLL Schedule'!Loan_Start),MONTH('DLL Schedule'!Loan_Start)+('DLL Schedule'!Pay_Num)*12/'DLL Schedule'!Num_Pmt_Per_Year,DAY('DLL Schedule'!Loan_Start)),"") | C30: =IF('DLL Schedule'!Pay_Num<>"",I29,"") | D30: =IF('DLL Schedule'!Pay_Num<>"",'DLL Schedule'!Scheduled_Monthly_Payment,"") | E30: =IF('DLL Schedule'!Pay_Num<>"",IF('DLL Schedule'!Sched_Pay+'DLL Schedule'!Scheduled_Extra_Payments<'DLL Schedule'!Beg_Bal,'DLL Schedule'!Scheduled_Extra_Payments,IF('DLL Schedule'!Beg_Bal-'DLL Schedule'!Sched_Pay>0,'DLL Schedule'!Beg_Bal-'DLL Schedule'!Sched_Pay,0)),"") | F30: =IF('DLL Schedule'!Pay_Num<>"",IF('DLL Schedule'!Sched_Pay+'DLL Schedule'!Extra_Pay<'DLL Schedule'!Beg_Bal,'DLL Schedule'!Sched_Pay+'DLL Schedule'!Extra_Pay,'DLL Schedule'!Beg_Bal),"") | G30: =IF('DLL Schedule'!Pay_Num<>"",'DLL Schedule'!Total_Pay-'DLL Schedule'!Int,"") | H30: =IF('DLL Schedule'!Pay_Num<>"",'DLL Schedule'!Beg_Bal*'DLL Schedule'!Interest_Rate/'DLL Schedule'!Num_Pmt_Per_Year,"") | I30: =IF('DLL Schedule'!Pay_Num<>"",IF('DLL Schedule'!Sched_Pay+'DLL Schedule'!Extra_Pay<'DLL Schedule'!Beg_Bal,'DLL Schedule'!Beg_Bal-'DLL Schedule'!Princ,0),"") | J30: =SUM($H$18:$H30) -> 0
... A497: =IF(AND('DLL Schedule'!Values_Entered=1,A496<>"",I496>0),A496+1,"") | B497: =IF('DLL Schedule'!Pay_Num<>"",DATE(YEAR('DLL Schedule'!Loan_Start),MONTH('DLL Schedule'!Loan_Start)+('DLL Schedule'!Pay_Num)*12/'DLL Schedule'!Num_Pmt_Per_Year,DAY('DLL Schedule'!Loan_Start)),"") | C497: =IF('DLL Schedule'!Pay_Num<>"",I496,"") | D497: =IF('DLL Schedule'!Pay_Num<>"",'DLL Schedule'!Scheduled_Monthly_Payment,"") | E497: =IF('DLL Schedule'!Pay_Num<>"",IF('DLL Schedule'!Sched_Pay+'DLL Schedule'!Scheduled_Extra_Payments<'DLL Schedule'!Beg_Bal,'DLL Schedule'!Scheduled_Extra_Payments,IF('DLL Schedule'!Beg_Bal-'DLL Schedule'!Sched_Pay>0,'DLL Schedule'!Beg_Bal-'DLL Schedule'!Sched_Pay,0)),"") | F497: =IF('DLL Schedule'!Pay_Num<>"",IF('DLL Schedule'!Sched_Pay+'DLL Schedule'!Extra_Pay<'DLL Schedule'!Beg_Bal,'DLL Schedule'!Sched_Pay+'DLL Schedule'!Extra_Pay,'DLL Schedule'!Beg_Bal),"") | G497: =IF('DLL Schedule'!Pay_Num<>"",'DLL Schedule'!Total_Pay-'DLL Schedule'!Int,"") | H497: =IF('DLL Schedule'!Pay_Num<>"",'DLL Schedule'!Beg_Bal*'DLL Schedule'!Interest_Rate/'DLL Schedule'!Num_Pmt_Per_Year,"") | I497: =IF('DLL Schedule'!Pay_Num<>"",IF('DLL Schedule'!Sched_Pay+'DLL Schedule'!Extra_Pay<'DLL Schedule'!Beg_Bal,'DLL Schedule'!Beg_Bal-'DLL Schedule'!Princ,0),"") | J497: =SUM($H$18:$H497) -> 0

Sheet Cashflow
F1: =SUM(F3:F62) -> 0 | G1: =SUM(G3:G62) -> 0 | H1: =SUM(H3:H62) -> 0
F2: Loan Payment | G2: Carbon Credits | H2: EVSE Profit | I2: Total
E3: 1 | F3: ='DLL Schedule'!J5 | G3: ='Financial Worksheet'!$B$4/('Financial Worksheet'!$B$10*12) -> 0 | H3: =('Updated Chargers Revenue Calcul'!$J$24/12)*1.125^INT((E3-1)/12) -> 0 | I3: =(G3+H3)-F3 -> #VALUE!
E4: 2 | F4: =F3 | G4: ='Financial Worksheet'!$B$4/('Financial Worksheet'!$B$10*12) -> 0 | H4: =('Updated Chargers Revenue Calcul'!$J$24/12)*1.125^INT((E4-1)/12) -> 0 | I4: =(G4+H4)-F4 -> #VALUE!
E5: 3 | F5: =F4 | G5: ='Financial Worksheet'!$B$4/('Financial Worksheet'!$B$10*12) -> 0 | H5: =('Updated Chargers Revenue Calcul'!$J$24/12)*1.125^INT((E5-1)/12) -> 0 | I5: =(G5+H5)-F5 -> #VALUE!
E6: =E5+1 -> 4 | F6: =F5 | G6: ='Financial Worksheet'!$B$4/('Financial Worksheet'!$B$10*12) -> 0 | H6: =('Updated Chargers Revenue Calcul'!$J$24/12)*1.125^INT((E6-1)/12) -> 0 | I6: =(G6+H6)-F6 -> #VALUE!
E7: =E6+1 -> 5 | F7: =F6 | G7: ='Financial Worksheet'!$B$4/('Financial Worksheet'!$B$10*12) -> 0 | H7: =('Updated Chargers Revenue Calcul'!$J$24/12)*1.125^INT((E7-1)/12) -> 0 | I7: =(G7+H7)-F7 -> #VALUE!
E8: =E7+1 -> 6 | F8: =F7 | G8: ='Financial Worksheet'!$B$4/('Financial Worksheet'!$B$10*12) -> 0 | H8: =('Updated Chargers Revenue Calcul'!$J$24/12)*1.125^INT((E8-1)/12) -> 0 | I8: =(G8+H8)-F8 -> #VALUE!
E9: =E8+1 -> 7 | F9: =F8 | G9: ='Financial Worksheet'!$B$4/('Financial Worksheet'!$B$10*12) -> 0 | H9: =('Updated Chargers Revenue Calcul'!$J$24/12)*1.125^INT((E9-1)/12) -> 0 | I9: =(G9+H9)-F9 -> #VALUE!
E10: =E9+1 -> 8 | F10: =F9 | G10: ='Financial Worksheet'!$B$4/('Financial Worksheet'!$B$10*12) -> 0 | H10: =('Updated Chargers Revenue Calcul'!$J$24/12)*1.125^INT((E10-1)/12) -> 0 | I10: =(G10+H10)-F10 -> #VALUE!
E11: =E10+1 -> 9 | F11: =F10 | G11: ='Financial Worksheet'!$B$4/('Financial Worksheet'!$B$10*12) -> 0 | H11: =('Updated Chargers Revenue Calcul'!$J$24/12)*1.125^INT((E11-1)/12) -> 0 | I11: =(G11+H11)-F11 -> #VALUE!
E12: =E11+1 -> 10 | F12: =F11 | G12: ='Financial Worksheet'!$B$4/('Financial Worksheet'!$B$10*12) -> 0 | H12: =('Updated Chargers Revenue Calcul'!$J$24/12)*1.125^INT((E12-1)/12) -> 0 | I12: =(G12+H12)-F12 -> #VALUE!
E13: =E12+1 -> 11 | F13: =F12 | G13: ='Financial Worksheet'!$B$4/('Financial Worksheet'!$B$10*12) -> 0 | H13: =('Updated Chargers Revenue Calcul'!$J$24/12)*1.125^INT((E13-1)/12) -> 0 | I13: =(G13+H13)-F13 -> #VALUE!
E14: =E13+1 -> 12 | F14: =F13 | G14: ='Financial Worksheet'!$B$4/('Financial Worksheet'!$B$10*12) -> 0 | H14: =('Updated Chargers Revenue Calcul'!$J$24/12)*1.125^INT((E14-1)/12) -> 0 | I14: =(G14+H14)-F14 -> #VALUE!
E15: =E14+1 -> 13 | F15: =F14 | G15: ='Financial Worksheet'!$B$4/('Financial Worksheet'!$B$10*12) -> 0 | H15: =('Updated Chargers Revenue Calcul'!$J$24/12)*1.125^INT((E15-1)/12) -> 0 | I15: =(G15+H15)-F15 -> #VALUE!
E16: =E15+1 -> 14 | F16: =F15 | G16: ='Financial Worksheet'!$B$4/('Financial Worksheet'!$B$10*12) -> 0 | H16: =('Updated Chargers Revenue Calcul'!$J$24/12)*1.125^INT((E16-1)/12) -> 0 | I16: =(G16+H16)-F16 -> #VALUE!
E17: =E16+1 -> 15 | F17: =F16 | G17: ='Financial Worksheet'!$B$4/('Financial Worksheet'!$B$10*12) -> 0 | H17: =('Updated Chargers Revenue Calcul'!$J$24/12)*1.125^INT((E17-1)/12) -> 0 | I17: =(G17+H17)-F17 -> #VALUE!
... E62: =E61+1 -> 60 | F62: =F61 | G62: ='Financial Worksheet'!$B$4/('Financial Worksheet'!$B$10*12) -> 0 | H62: =('Updated Chargers Revenue Calcul'!$J$24/12)*1.125^INT((E62-1)/12) -> 0 | I62: =(G62+H62)-F62 -> #VALUE!

Sheet Updated Chargers Revenue Calcul
B1: STANDARD-DAY | X1: FLEET-NIGHT
A3: Revenues | B3: Standard-Low | I3: Standard-Med | P3: Standard-High | X3: Fleet-Low | Y3: Fleet-Med | Z3: Fleet-High
B4: Level 2 | C4: ="L3 ("&'INPUT SHEET'!O10&" kW)" -> L3 (60 kW) | D4: ="L3 ("&'INPUT SHEET'!P10&" kW)" -> L3 (120 kW) | E4: ="L3 ("&'INPUT SHEET'!Q10&" kW)" -> L3 (160 kW) | F4: ="L3 ("&'INPUT SHEET'!R10&" kW)" -> L3 (180 kW) | G4: ="L3 ("&'INPUT SHEET'!S10&" kW)" -> L3 (240 kW) | H4: ="L3 ("&'INPUT SHEET'!T10&" kW)" -> L3 (360 kW) | I4: Level 2 | J4: ="L3 ("&'INPUT SHEET'!O10&" kW)" -> L3 (60 kW) | K4: ="L3 ("&'INPUT SHEET'!P10&" kW)" -> L3 (120 kW) | L4: ="L3 ("&'INPUT SHEET'!Q10&" kW)" -> L3 (160 kW) | M4: ="L3 ("&'INPUT SHEET'!R10&" kW)" -> L3 (180 kW) | N4: ="L3 ("&'INPUT SHEET'!S10&" kW)" -> L3 (240 kW) | O4: ="L3 ("&'INPUT SHEET'!T10&" kW)" -> L3 (360 kW) | P4: Level 2 | Q4: ="L3 ("&'INPUT SHEET'!O10&" kW)" -> L3 (60 kW) | R4: ="L3 ("&'INPUT SHEET'!P10&" kW)" -> L3 (120 kW) | S4: ="L3 ("&'INPUT SHEET'!Q10&" kW)" -> L3 (160 kW) | T4: ="L3 ("&'INPUT SHEET'!R10&" kW)" -> L3 (180 kW) | U4: ="L3 ("&'INPUT SHEET'!S10&" kW)" -> L3 (240 kW) | V4: ="L3 ("&'INPUT SHEET'!T10&" kW)" -> L3 (360 kW) | X4: Level 2 | Y4: Level 2 | Z4: Level 2
A5: Chargers | B5: ='INPUT SHEET'!N8 -> 0 | C5: ='INPUT SHEET'!O8 -> 0 | D5: ='INPUT SHEET'!P8 -> 0 | E5: ='INPUT SHEET'!Q8 -> 0 | F5: ='INPUT SHEET'!R8 -> 0 | G5: ='INPUT SHEET'!S8 -> 0 | H5: ='INPUT SHEET'!T8 -> 0 | I5: =B5 -> 0 | J5: =C5 -> 0 | K5: =D5 -> 0 | L5: =E5 -> 0 | M5: =F5 -> 0 | N5: =G5 -> 0 | O5: =H5 -> 0 | P5: =B5 -> 0 | Q5: =C5 -> 0 | R5: =D5 -> 0 | S5: =E5 -> 0 | T5: =F5 -> 0 | U5: =G5 -> 0 | V5: =H5 -> 0 | X5: =B5 -> 0 | Y5: =B5 -> 0 | Z5: =B5 -> 0
A6: EV Stall Quantity (Based on # of ports) | B6: ='INPUT SHEET'!N9 -> 0 | C6: ='INPUT SHEET'!O9 -> 0 | D6: ='INPUT SHEET'!P9 -> 0 | E6: ='INPUT SHEET'!Q9 -> 0 | F6: ='INPUT SHEET'!R9 -> 0 | G6: ='INPUT SHEET'!S9 -> 0 | H6: ='INPUT SHEET'!T9 -> 0 | I6: =B6 -> 0 | J6: =C6 -> 0 | K6: =D6 -> 0 | L6: =E6 -> 0 | M6: =F6 -> 0 | N6: =G6 -> 0 | O6: =H6 -> 0 | P6: =B6 -> 0 | Q6: =C6 -> 0 | R6: =D6 -> 0 | S6: =E6 -> 0 | T6: =F6 -> 0 | U6: =G6 -> 0 | V6: =H6 -> 0 | X6: =B6 -> 0 | Y6: =B6 -> 0 | Z6: =B6 -> 0
A7: Max hours of operation of parking | B7: 24 | C7: 24 | D7: 24 | E7: 24 | F7: 24 | G7: 24 | H7: 24 | I7: 12 | J7: 12 | K7: 12 | L7: 12 | M7: 12 | N7: 12 | O7: 12 | P7: 12 | Q7: 12 | R7: 12 | S7: 12 | T7: 12 | U7: 12 | V7: 12 | X7: 12 | Y7: 12 | Z7: 12
A8: Assumed Stall Occupancy % | B8: 0.2 | C8: 0.2 | D8: 0.2 | E8: 0.2 | F8: 0.2 | G8: 0.2 | H8: 0.2 | I8: =I20 -> 0.45 | J8: =J20 -> 0.5 | K8: =K20 -> 0.5 | L8: =L20 -> 0.5 | M8: =M20 -> 0.5 | N8: =N20 -> 0.5 | O8: =O20 -> 0.5 | P8: =P20 -> 0.6 | ... Z8: =Z20 -> 0.6
A9: Number of stalls used per day | B9: =B6*B8 -> 0 | C9: =C6*C8 -> 0 | D9: =D6*D8 -> 0 | E9: =E6*E8 -> 0 | F9: =F6*F8 -> 0 | G9: =G6*G8 -> 0 | H9: =H6*H8 -> 0 | I9: =I6*I8 -> 0 | ... V9: =V6*V8 -> 0 | X9: =X6*X8 -> 0 | Y9: =Y6*Y8 -> 0 | Z9: =Z6*Z8 -> 0
A10: Assumed Charging Hourly % per stall per day | B10: =B21 -> 0.5 | C10: =C21 -> 0.5 | D10: =D21 -> 0.5 | E10: =E21 -> 0.5 | F10: =F21 -> 0.5 | G10: =G21 -> 0.5 | H10: =H21 -> 0.5 | I10: =I21 -> 0.75 | ... Z10: =Z21 -> 0.85
A11: Number of hours usage per stall per day | B11: =B10*B7 -> 6 | C11: =C10*C7 -> 6 | D11: =D10*D7 -> 6 | E11: =E10*E7 -> 6 | F11: =F10*F7 -> 6 | G11: =G10*G7 -> 6 | H11: =H10*H7 -> 6 | I11: =I10*I7 -> 9 | ... V11: =V10*V7 -> 10.2 | X11: =X10*X7 -> 6 | Y11: =Y10*Y7 -> 9 | Z11: =Z10*Z7 -> 10.2
A12: Actual Charger Rating | B12: ='INPUT SHEET'!N10*'INPUT SHEET'!$N$11 -> 7.056 | C12: =30*0.98 -> 29.4 | D12: =60*0.98 -> 58.8 | E12: =80*0.98 -> 78.4 | F12: =90*0.98 -> 88.2 | G12: =120*0.98 -> 117.6 | H12: =180*0.98 -> 176.4 | I12: =B12 -> 7.056 | J12: =C12 -> 29.4 | K12: =D12 -> 58.8 | L12: =E12 -> 78.4 | M12: =F12 -> 88.2 | N12: =G12 -> 117.6 | O12: =H12 -> 176.4 | P12: =B12 -> 7.056 | Q12: =C12 -> 29.4 | R12: =D12 -> 58.8 | S12: =E12 -> 78.4 | T12: =F12 -> 88.2 | U12: =G12 -> 117.6 | V12: =H12 -> 176.4 | X12: =B12 -> 7.056 | Y12: =B12 -> 7.056 | Z12: =B12 -> 7.056
A13: Retail Revenue per kWHr | B13: 0.65 | C13: =B13 -> 0.65 | D13: =C13 -> 0.65 | E13: =D13 -> 0.65 | F13: =E13 -> 0.65 | G13: =F13 -> 0.65 | H13: =G13 -> 0.65 | I13: =B13 -> 0.65 | J13: =B13 -> 0.65 | K13: =C13 -> 0.65 | L13: =D13 -> 0.65 | M13: =E13 -> 0.65 | N13: =F13 -> 0.65 | O13: =G13 -> 0.65 | P13: =B13 -> 0.65 | Q13: =B13 -> 0.65 | R13: =C13 -> 0.65 | S13: =D13 -> 0.65 | T13: =E13 -> 0.65 | U13: =F13 -> 0.65 | V13: =G13 -> 0.65 | X13: 0.65 | Y13: =X13 -> 0.65 | Z13: =X13 -> 0.65
A14: Total Revenue per day | B14: =B13*B16 -> 0 | C14: =C13*C16 -> 0 | D14: =D13*D16 -> 0 | E14: =E13*E16 -> 0 | F14: =F13*F16 -> 0 | G14: =G13*G16 -> 0 | H14: =H13*H16 -> 0 | I14: =I13*I16 -> 0 | ... V14: =V13*V16 -> 0 | X14: =X13*X16 -> 0 | Y14: =Y13*Y16 -> 0 | Z14: =Z13*Z16 -> 0
A15: Per month (days per year ÷ 12) | B15: =B14*B36/12 -> 0 | C15: =C14*C36/12 -> 0 | D15: =D14*D36/12 -> 0 | E15: =E14*E36/12 -> 0 | F15: =F14*F36/12 -> 0 | G15: =G14*G36/12 -> 0 | H15: =H14*H36/12 -> 0 | I15: =I14*I36/12 -> 0 | ... V15: =V14*V36/12 -> 0 | X15: =X14*X36/12 -> 0 | Y15: =Y14*Y36/12 -> 0 | Z15: =Z14*Z36/12 -> 0
A16: Total kWhr dispensed per day | B16: =B9*B11*B35 -> 0 | C16: =C9*C11*C35 -> 0 | D16: =D9*D11*D35 -> 0 | E16: =E9*E11*E35 -> 0 | F16: =F9*F11*F35 -> 0 | G16: =G9*G11*G35 -> 0 | H16: =H9*H11*H35 -> 0 | I16: =I9*I11*I35 -> 0 | ... V16: =V9*V11*V35 -> 0 | X16: =X9*X11*X35 -> 0 | Y16: =Y9*Y11*Y35 -> 0 | Z16: =Z9*Z11*Z35 -> 0
A17: EV Utility Rate average per kWHr | B17: =B46 -> 0 | C17: =C46 -> 0 | D17: =D46 -> 0 | E17: =E46 -> 0 | F17: =F46 -> 0 | G17: =G46 -> 0 | H17: =H46 -> 0 | I17: =I46 -> 0 | ... V17: =V46 -> 0 | X17: =X46 -> 0.25 | Y17: =Y46 -> 0.25 | Z17: =Z46 -> 0.25
A18: Net Profit per Month | B18: =B15-(B16*B17*B36/12) -> 0 | C18: =C15-(C16*C17*C36/12) -> 0 | D18: =D15-(D16*D17*D36/12) -> 0 | E18: =E15-(E16*E17*E36/12) -> 0 | F18: =F15-(F16*F17*F36/12) -> 0 | G18: =G15-(G16*G17*G36/12) -> 0 | H18: =H15-(H16*H17*H36/12) -> 0 | I18: =I15-(I16*I17*I36/12) -> 0 | ... V18: =V15-(V16*V17*V36/12) -> 0 | X18: =X15-(X16*X17*X36/12) -> 0 | Y18: =Y15-(Y16*Y17*Y36/12) -> 0 | Z18: =Z15-(Z16*Z17*Z36/12) -> 0
A19: Total Profit per Year | B19: =B18*12 -> 0 | C19: =C18*12 -> 0 | D19: =D18*12 -> 0 | E19: =E18*12 -> 0 | F19: =F18*12 -> 0 | G19: =G18*12 -> 0 | H19: =H18*12 -> 0 | I19: =I18*12 -> 0 | ... V19: =V18*12 -> 0 | X19: =X18*12 -> 0 | Y19: =Y18*12 -> 0 | Z19: =Z18*12 -> 0
A20: Modify Stall Occupancy % here | B20: 0.2 | C20: 0.2 | D20: 0.2 | E20: 0.2 | F20: 0.2 | G20: 0.2 | H20: 0.2 | I20: 0.45 | J20: 0.5 | K20: 0.5 | L20: 0.5 | M20: 0.5 | N20: 0.5 | O20: 0.5 | P20: 0.6 | Q20: 0.7 | R20: 0.7 | S20: 0.7 | T20: 0.7 | U20: 0.7 | V20: 0.7 | X20: 0.2 | Y20: 0.45 | Z20: 0.6
A21: Modify Charging Hourly percentage per stall per day | B21: 0.25 | C21: 0.25 | D21: 0.25 | E21: 0.25 | F21: 0.25 | G21: 0.25 | H21: 0.25 | I21: 0.75 | J21: 0.75 | K21: 0.75 | L21: 0.75 | M21: 0.75 | N21: 0.75 | O21: 0.75 | P21: 0.85 | Q21: 0.85 | R21: 0.85 | S21: 0.85 | T21: 0.85 | U21: 0.85 | V21: 0.85 | X21: 0.5 | Y21: 0.75 | Z21: 0.85
A22: Rows 4-21 above: single-year view. The app-faithful ten-year model starts at row 33.
B23: Total (Standard ) | J23: Low | P23: Medium | Q23: High
B24: Yearly | J24: =SUM(B19:H19) -> 0 | P24: =SUM(I19:O19) -> 0 | Q24: =SUM(P19:V19) -> 0
B25: 3 Years | J25: =J24*3 -> 0 | P25: =P24*3 -> 0 | Q25: =Q24*3 -> 0
B26: 5 Years | J26: =J24*5 -> 0 | P26: =P24*5 -> 0 | Q26: =Q24*5 -> 0
B28: Total (Standard & Fleet Night) | J28: Low | P28: Medium | Q28: High
B29: Yearly | J29: =J24+X19 -> 0 | P29: =P24+Y19 -> 0 | Q29: =Q24+Z19 -> 0
B30: 3 Years | J30: =J29*3 -> 0 | P30: =P29*3 -> 0 | Q30: =Q29*3 -> 0
B31: 5 Years | J31: =J29*5 -> 0 | P31: =P29*5 -> 0 | Q31: =Q29*5 -> 0
A33: APP-ALIGNED INPUTS — mirrors the RFC Estimator Revenue tab (lib/proposal/model.ts) | B33: =B4 -> Level 2 | C33: =C4 -> L3 (60 kW) | D33: =D4 -> L3 (120 kW) | E33: =E4 -> L3 (160 kW) | F33: =F4 -> L3 (180 kW) | G33: =G4 -> L3 (240 kW) | H33: =H4 -> L3 (360 kW) | I33: =I4 -> Level 2 | ... V33: =V4 -> L3 (360 kW) | X33: =X4 -> Level 2 | Y33: =Y4 -> Level 2 | Z33: =Z4 -> Level 2
A34: Charging-curve taper (avg delivered power ÷ port rating) | B34: 0.7 | C34: 0.7 | D34: 0.7 | E34: 0.7 | F34: 0.7 | G34: 0.7 | H34: 0.7 | I34: 0.7 | J34: 0.7 | K34: 0.7 | L34: 0.7 | M34: 0.7 | N34: 0.7 | O34: 0.7 | P34: 0.7 | Q34: 0.7 | R34: 0.7 | S34: 0.7 | T34: 0.7 | U34: 0.7 | V34: 0.7 | X34: 0.7 | Y34: 0.7 | Z34: 0.7
A35: Average delivered kW per port (de-rated, then tapered) | B35: =B12*B34 -> 4.9392 | C35: =C12*C34 -> 20.58 | D35: =D12*D34 -> 41.16 | E35: =E12*E34 -> 54.88 | F35: =F12*F34 -> 61.74 | G35: =G12*G34 -> 82.32 | H35: =H12*H34 -> 123.48 | I35: =I12*I34 -> 4.9392 | ... V35: =V12*V34 -> 123.48 | X35: =X12*X34 -> 4.9392 | Y35: =Y12*Y34 -> 4.9392 | Z35: =Z12*Z34 -> 4.9392
A36: Days per year the site is open | B36: 365 | C36: 365 | D36: 365 | E36: 365 | F36: 365 | G36: 365 | H36: 365 | I36: 365 | J36: 365 | K36: 365 | L36: 365 | M36: 365 | N36: 365 | O36: 365 | P36: 365 | Q36: 365 | R36: 365 | S36: 365 | T36: 365 | U36: 365 | V36: 365 | X36: 365 | Y36: 365 | Z36: 365
A37: kWh per day, steady state | B37: =B16 -> 0 | C37: =C16 -> 0 | D37: =D16 -> 0 | E37: =E16 -> 0 | F37: =F16 -> 0 | G37: =G16 -> 0 | H37: =H16 -> 0 | I37: =I16 -> 0 | ... V37: =V16 -> 0 | X37: =X16 -> 0 | Y37: =Y16 -> 0 | Z37: =Z16 -> 0
A38: kWh per year, steady state | B38: =B37*B36 -> 0 | C38: =C37*C36 -> 0 | D38: =D37*D36 -> 0 | E38: =E37*E36 -> 0 | F38: =F37*F36 -> 0 | G38: =G37*G36 -> 0 | H38: =H37*H36 -> 0 | I38: =I37*I36 -> 0 | ... V38: =V37*V36 -> 0 | X38: =X37*X36 -> 0 | Y38: =Y37*Y36 -> 0 | Z38: =Z37*Z36 -> 0
A39: Card processing fee (share of gross) | B39: 0.03 | C39: 0.03 | D39: 0.03 | E39: 0.03 | F39: 0.03 | G39: 0.03 | H39: 0.03 | I39: 0.03 | J39: 0.03 | K39: 0.03 | L39: 0.03 | M39: 0.03 | N39: 0.03 | O39: 0.03 | P39: 0.03 | Q39: 0.03 | R39: 0.03 | S39: 0.03 | T39: 0.03 | U39: 0.03 | V39: 0.03 | X39: 0.03 | Y39: 0.03 | Z39: 0.03
A40: Peak $/kWh | B40: =$B$206 -> 0 | C40: =$B$206 -> 0 | D40: =$B$206 -> 0 | E40: =$B$206 -> 0 | F40: =$B$206 -> 0 | G40: =$B$206 -> 0 | H40: =$B$206 -> 0 | I40: =$B$206 -> 0 | ... V40: =$B$206 -> 0 | X40: 0.25 | Y40: 0.25 | Z40: 0.25
A41: Off-peak $/kWh | B41: =$B$207 -> 0 | C41: =$B$207 -> 0 | D41: =$B$207 -> 0 | E41: =$B$207 -> 0 | F41: =$B$207 -> 0 | G41: =$B$207 -> 0 | H41: =$B$207 -> 0 | I41: =$B$207 -> 0 | ... V41: =$B$207 -> 0 | X41: 0.25 | Y41: 0.25 | Z41: 0.25
A42: Super off-peak $/kWh | B42: =$B$208 -> 0 | C42: =$B$208 -> 0 | D42: =$B$208 -> 0 | E42: =$B$208 -> 0 | F42: =$B$208 -> 0 | G42: =$B$208 -> 0 | H42: =$B$208 -> 0 | I42: =$B$208 -> 0 | ... V42: =$B$208 -> 0 | X42: 0.25 | Y42: 0.25 | Z42: 0.25
A43: Peak share of energy dispensed | B43: 0.3 | C43: 0.3 | D43: 0.3 | E43: 0.3 | F43: 0.3 | G43: 0.3 | H43: 0.3 | I43: 0.3 | J43: 0.3 | K43: 0.3 | L43: 0.3 | M43: 0.3 | N43: 0.3 | O43: 0.3 | P43: 0.3 | Q43: 0.3 | R43: 0.3 | S43: 0.3 | T43: 0.3 | U43: 0.3 | V43: 0.3 | X43: 0.3 | Y43: 0.3 | Z43: 0.3
A44: Off-peak share | B44: 0.55 | C44: 0.55 | D44: 0.55 | E44: 0.55 | F44: 0.55 | G44: 0.55 | H44: 0.55 | I44: 0.55 | J44: 0.55 | K44: 0.55 | L44: 0.55 | M44: 0.55 | N44: 0.55 | O44: 0.55 | P44: 0.55 | Q44: 0.55 | R44: 0.55 | S44: 0.55 | T44: 0.55 | U44: 0.55 | V44: 0.55 | X44: 0.55 | Y44: 0.55 | Z44: 0.55
A45: Super off-peak share | B45: 0.15 | C45: 0.15 | D45: 0.15 | E45: 0.15 | F45: 0.15 | G45: 0.15 | H45: 0.15 | I45: 0.15 | J45: 0.15 | K45: 0.15 | L45: 0.15 | M45: 0.15 | N45: 0.15 | O45: 0.15 | P45: 0.15 | Q45: 0.15 | R45: 0.15 | S45: 0.15 | T45: 0.15 | U45: 0.15 | V45: 0.15 | X45: 0.15 | Y45: 0.15 | Z45: 0.15
A46: Blended volumetric $/kWh | B46: =B40*B43+B41*B44+B42*B45 -> 0 | C46: =C40*C43+C41*C44+C42*C45 -> 0 | D46: =D40*D43+D41*D44+D42*D45 -> 0 | E46: =E40*E43+E41*E44+E42*E45 -> 0 | F46: =F40*F43+F41*F44+F42*F45 -> 0 | G46: =G40*G43+G41*G44+G42*G45 -> 0 | H46: =H40*H43+H41*H44+H42*H45 -> 0 | I46: =I40*I43+I41*I44+I42*I45 -> 0 | ... V46: =V40*V43+V41*V44+V42*V45 -> 0 | X46: =X40*X43+X41*X44+X42*X45 -> 0.25 | Y46: =Y40*Y43+Y41*Y44+Y42*Y45 -> 0.25 | Z46: =Z40*Z43+Z41*Z44+Z42*Z45 -> 0.25
A47: Customer charge ($/month) | B47: =$B$209 -> 0 | C47: =$B$209 -> 0 | D47: =$B$209 -> 0 | E47: =$B$209 -> 0 | F47: =$B$209 -> 0 | G47: =$B$209 -> 0 | H47: =$B$209 -> 0 | I47: =$B$209 -> 0 | ... V47: =$B$209 -> 0 | X47: 0 | Y47: 0 | Z47: 0
A48: Demand charge ($/kW-month) | B48: =$B$210 -> 0 | C48: =$B$210 -> 0 | D48: =$B$210 -> 0 | E48: =$B$210 -> 0 | F48: =$B$210 -> 0 | G48: =$B$210 -> 0 | H48: =$B$210 -> 0 | I48: =$B$210 -> 0 | ... V48: =$B$210 -> 0 | X48: 0 | Y48: 0 | Z48: 0
A49: Subscription block size (kW) — 0 means no blocks sold | B49: =$B$211 -> 0 | C49: =$B$211 -> 0 | D49: =$B$211 -> 0 | E49: =$B$211 -> 0 | F49: =$B$211 -> 0 | G49: =$B$211 -> 0 | H49: =$B$211 -> 0 | I49: =$B$211 -> 0 | ... V49: =$B$211 -> 0 | X49: 0 | Y49: 0 | Z49: 0
A50: Subscription block price ($/block/month) | B50: =$B$212 -> 0 | C50: =$B$212 -> 0 | D50: =$B$212 -> 0 | E50: =$B$212 -> 0 | F50: =$B$212 -> 0 | G50: =$B$212 -> 0 | H50: =$B$212 -> 0 | I50: =$B$212 -> 0 | ... V50: =$B$212 -> 0 | X50: 0 | Y50: 0 | Z50: 0
A51: Peak-to-average concurrency factor | B51: 4 | C51: 4 | D51: 4 | E51: 4 | F51: 4 | G51: 4 | H51: 4 | I51: 4 | J51: 4 | K51: 4 | L51: 4 | M51: 4 | N51: 4 | O51: 4 | P51: 4 | Q51: 4 | R51: 4 | S51: 4 | T51: 4 | U51: 4 | V51: 4 | X51: 4 | Y51: 4 | Z51: 4
A52: Safety margin on subscribed kW | B52: 0.2 | C52: 0.2 | D52: 0.2 | E52: 0.2 | F52: 0.2 | G52: 0.2 | H52: 0.2 | I52: 0.2 | J52: 0.2 | K52: 0.2 | L52: 0.2 | M52: 0.2 | N52: 0.2 | O52: 0.2 | P52: 0.2 | Q52: 0.2 | R52: 0.2 | S52: 0.2 | T52: 0.2 | U52: 0.2 | V52: 0.2 | X52: 0.2 | Y52: 0.2 | Z52: 0.2
A53: Size demand on the full port rating? (Yes / No) | B53: Yes | C53: Yes | D53: Yes | E53: Yes | F53: Yes | G53: Yes | H53: Yes | I53: Yes | J53: Yes | K53: Yes | L53: Yes | M53: Yes | N53: Yes | O53: Yes | P53: Yes | Q53: Yes | R53: Yes | S53: Yes | T53: Yes | U53: Yes | V53: Yes | X53: Yes | Y53: Yes | Z53: Yes
A54: Demand charge bills from year | B54: 1 | C54: 1 | D54: 1 | E54: 1 | F54: 1 | G54: 1 | H54: 1 | I54: 1 | J54: 1 | K54: 1 | L54: 1 | M54: 1 | N54: 1 | O54: 1 | P54: 1 | Q54: 1 | R54: 1 | S54: 1 | T54: 1 | U54: 1 | V54: 1 | X54: 1 | Y54: 1 | Z54: 1
A55: Year 1 share of steady state | B55: 0.5 | C55: 0.5 | D55: 0.5 | E55: 0.5 | F55: 0.5 | G55: 0.5 | H55: 0.5 | I55: 0.5 | J55: 0.5 | K55: 0.5 | L55: 0.5 | M55: 0.5 | N55: 0.5 | O55: 0.5 | P55: 0.5 | Q55: 0.5 | R55: 0.5 | S55: 0.5 | T55: 0.5 | U55: 0.5 | V55: 0.5 | X55: 0.5 | Y55: 0.5 | Z55: 0.5
A56: Year 2 share of steady state | B56: 0.75 | C56: 0.75 | D56: 0.75 | E56: 0.75 | F56: 0.75 | G56: 0.75 | H56: 0.75 | I56: 0.75 | J56: 0.75 | K56: 0.75 | L56: 0.75 | M56: 0.75 | N56: 0.75 | O56: 0.75 | P56: 0.75 | Q56: 0.75 | R56: 0.75 | S56: 0.75 | T56: 0.75 | U56: 0.75 | V56: 0.75 | X56: 0.75 | Y56: 0.75 | Z56: 0.75
A57: Year 3 share of steady state | B57: 1 | C57: 1 | D57: 1 | E57: 1 | F57: 1 | G57: 1 | H57: 1 | I57: 1 | J57: 1 | K57: 1 | L57: 1 | M57: 1 | N57: 1 | O57: 1 | P57: 1 | Q57: 1 | R57: 1 | S57: 1 | T57: 1 | U57: 1 | V57: 1 | X57: 1 | Y57: 1 | Z57: 1
A58: Annual growth after the ramp | B58: 0.06 | C58: 0.06 | D58: 0.06 | E58: 0.06 | F58: 0.06 | G58: 0.06 | H58: 0.06 | I58: 0.06 | J58: 0.06 | K58: 0.06 | L58: 0.06 | M58: 0.06 | N58: 0.06 | O58: 0.06 | P58: 0.06 | Q58: 0.06 | R58: 0.06 | S58: 0.06 | T58: 0.06 | U58: 0.06 | V58: 0.06 | X58: 0.06 | Y58: 0.06 | Z58: 0.06
A59: Service contract length (years) | B59: 5 | C59: 5 | D59: 5 | E59: 5 | F59: 5 | G59: 5 | H59: 5 | I59: 5 | J59: 5 | K59: 5 | L59: 5 | M59: 5 | N59: 5 | O59: 5 | P59: 5 | Q59: 5 | R59: 5 | S59: 5 | T59: 5 | U59: 5 | V59: 5 | X59: 5 | Y59: 5 | Z59: 5
A60: Warranty + service after the contract ($/yr) — from the CTX Price Book | B60: =SUMPRODUCT('CTX Price Book'!$C$135:$C$138,'CTX Price Book'!$F$135:$F$138) -> 0 | C60: ='CTX Price Book'!$C$139*'CTX Price Book'!$F$139 -> 0 | D60: ='CTX Price Book'!$C$140*'CTX Price Book'!$F$140 -> 0 | E60: ='CTX Price Book'!$C$141*'CTX Price Book'!$F$141 -> 0 | F60: ='CTX Price Book'!$C$142*'CTX Price Book'!$F$142 -> 0 | G60: ='CTX Price Book'!$C$143*'CTX Price Book'!$F$143 -> 0 | H60: ='CTX Price Book'!$C$144*'CTX Price Book'!$F$144 -> 0 | I60: =SUMPRODUCT('CTX Price Book'!$C$135:$C$138,'CTX Price Book'!$F$135:$F$138) -> 0 | J60: ='CTX Price Book'!$C$139*'CTX Price Book'!$F$139 -> 0 | K60: ='CTX Price Book'!$C$140*'CTX Price Book'!$F$140 -> 0 | L60: ='CTX Price Book'!$C$141*'CTX Price Book'!$F$141 -> 0 | M60: ='CTX Price Book'!$C$142*'CTX Price Book'!$F$142 -> 0 | N60: ='CTX Price Book'!$C$143*'CTX Price Book'!$F$143 -> 0 | O60: ='CTX Price Book'!$C$144*'CTX Price Book'!$F$144 -> 0 | P60: =SUMPRODUCT('CTX Price Book'!$C$135:$C$138,'CTX Price Book'!$F$135:$F$138) -> 0 | Q60: ='CTX Price Book'!$C$139*'CTX Price Book'!$F$139 -> 0 | R60: ='CTX Price Book'!$C$140*'CTX Price Book'!$F$140 -> 0 | S60: ='CTX Price Book'!$C$141*'CTX Price Book'!$F$141 -> 0 | T60: ='CTX Price Book'!$C$142*'CTX Price Book'!$F$142 -> 0 | U60: ='CTX Price Book'!$C$143*'CTX Price Book'!$F$143 -> 0 | V60: ='CTX Price Book'!$C$144*'CTX Price Book'!$F$144 -> 0 | X60: =SUMPRODUCT('CTX Price Book'!$C$135:$C$138,'CTX Price Book'!$F$135:$F$138) -> 0 | Y60: =SUMPRODUCT('CTX Price Book'!$C$135:$C$138,'CTX Price Book'!$F$135:$F$138) -> 0 | Z60: =SUMPRODUCT('CTX Price Book'!$C$135:$C$138,'CTX Price Book'!$F$135:$F$138) -> 0
A61: Network fee after the contract ($/yr) | B61: =B6*39.99*12 -> 0 | C61: =C6*39.99*12 -> 0 | D61: =D6*39.99*12 -> 0 | E61: =E6*39.99*12 -> 0 | F61: =F6*39.99*12 -> 0 | G61: =G6*39.99*12 -> 0 | H61: =H6*39.99*12 -> 0 | I61: =I6*39.99*12 -> 0 | ... V61: =V6*39.99*12 -> 0 | X61: =X6*39.99*12 -> 0 | Y61: =Y6*39.99*12 -> 0 | Z61: =Z6*39.99*12 -> 0
A64: SCENARIO ROLL-UP — site level, as the app's ModelContext sees it | C64: Standard-Low | D64: Standard-Med | E64: Standard-High | F64: Fleet-Low | G64: Fleet-Med | H64: Fleet-High
A65: DC charging positions | C65: =SUM(C6:H6) -> 0 | D65: =SUM(J6:O6) -> 0 | E65: =SUM(Q6:V6) -> 0 | F65: 0 | G65: 0 | H65: 0
A66: DC nameplate (kW) | C66: =IF(SUM(C6:H6)=0,0,SUMPRODUCT(C6:H6,C12:H12)/'INPUT SHEET'!$N$11) -> 0 | D66: =IF(SUM(J6:O6)=0,0,SUMPRODUCT(J6:O6,J12:O12)/'INPUT SHEET'!$N$11) -> 0 | E66: =IF(SUM(Q6:V6)=0,0,SUMPRODUCT(Q6:V6,Q12:V12)/'INPUT SHEET'!$N$11) -> 0 | F66: 0 | G66: 0 | H66: 0
A67: Level 2 positions | C67: =B6 -> 0 | D67: =I6 -> 0 | E67: =P6 -> 0 | F67: =X6 -> 0 | G67: =Y6 -> 0 | H67: =Z6 -> 0
A68: Nameplate kW per Level 2 position | C68: =IF('INPUT SHEET'!$N$11=0,0,B12/'INPUT SHEET'!$N$11) -> 7.2 | D68: =IF('INPUT SHEET'!$N$11=0,0,I12/'INPUT SHEET'!$N$11) -> 7.2 | E68: =IF('INPUT SHEET'!$N$11=0,0,P12/'INPUT SHEET'!$N$11) -> 7.2 | F68: =IF('INPUT SHEET'!$N$11=0,0,X12/'INPUT SHEET'!$N$11) -> 7.2 | G68: =IF('INPUT SHEET'!$N$11=0,0,Y12/'INPUT SHEET'!$N$11) -> 7.2 | H68: =IF('INPUT SHEET'!$N$11=0,0,Z12/'INPUT SHEET'!$N$11) -> 7.2
A69: Power per DC position (kW, de-rated) | C69: =IF(SUM(C6:H6)=0,0,SUMPRODUCT(C6:H6,C12:H12)/SUM(C6:H6)) -> 0 | D69: =IF(SUM(J6:O6)=0,0,SUMPRODUCT(J6:O6,J12:O12)/SUM(J6:O6)) -> 0 | E69: =IF(SUM(Q6:V6)=0,0,SUMPRODUCT(Q6:V6,Q12:V12)/SUM(Q6:V6)) -> 0 | F69: 0 | G69: 0 | H69: 0
A70: Average delivered power (kW, tapered) | C70: =IF(SUM(C6:H6)=0,0,SUMPRODUCT(C6:H6,C35:H35)/SUM(C6:H6)) -> 0 | D70: =IF(SUM(J6:O6)=0,0,SUMPRODUCT(J6:O6,J35:O35)/SUM(J6:O6)) -> 0 | E70: =IF(SUM(Q6:V6)=0,0,SUMPRODUCT(Q6:V6,Q35:V35)/SUM(Q6:V6)) -> 0 | F70: 0 | G70: 0 | H70: 0
A71: Site kWh per day, both streams | C71: =SUM(B37:H37) -> 0 | D71: =SUM(I37:O37) -> 0 | E71: =SUM(P37:V37) -> 0 | F71: =SUM(X37:X37) -> 0 | G71: =SUM(Y37:Y37) -> 0 | H71: =SUM(Z37:Z37) -> 0
A72: Site kWh per year, steady state | C72: =SUM(B38:H38) -> 0 | D72: =SUM(I38:O38) -> 0 | E72: =SUM(P38:V38) -> 0 | F72: =SUM(X38:X38) -> 0 | G72: =SUM(Y38:Y38) -> 0 | H72: =SUM(Z38:Z38) -> 0
A73: Days per year | C73: =B36 -> 365 | D73: =I36 -> 365 | E73: =P36 -> 365 | F73: =X36 -> 365 | G73: =Y36 -> 365 | H73: =Z36 -> 365
A74: Retail $/kWh (kWh-weighted) | C74: =IF(SUM(B38:H38)=0,0,SUMPRODUCT(B38:H38,B13:H13)/SUM(B38:H38)) -> 0 | D74: =IF(SUM(I38:O38)=0,0,SUMPRODUCT(I38:O38,I13:O13)/SUM(I38:O38)) -> 0 | E74: =IF(SUM(P38:V38)=0,0,SUMPRODUCT(P38:V38,P13:V13)/SUM(P38:V38)) -> 0 | F74: =IF(SUM(X38:X38)=0,0,SUMPRODUCT(X38:X38,X13:X13)/SUM(X38:X38)) -> 0 | G74: =IF(SUM(Y38:Y38)=0,0,SUMPRODUCT(Y38:Y38,Y13:Y13)/SUM(Y38:Y38)) -> 0 | H74: =IF(SUM(Z38:Z38)=0,0,SUMPRODUCT(Z38:Z38,Z13:Z13)/SUM(Z38:Z38)) -> 0
A75: Blended utility $/kWh (kWh-weighted) | C75: =IF(SUM(B38:H38)=0,0,SUMPRODUCT(B38:H38,B46:H46)/SUM(B38:H38)) -> 0 | D75: =IF(SUM(I38:O38)=0,0,SUMPRODUCT(I38:O38,I46:O46)/SUM(I38:O38)) -> 0 | E75: =IF(SUM(P38:V38)=0,0,SUMPRODUCT(P38:V38,P46:V46)/SUM(P38:V38)) -> 0 | F75: =IF(SUM(X38:X38)=0,0,SUMPRODUCT(X38:X38,X46:X46)/SUM(X38:X38)) -> 0 | G75: =IF(SUM(Y38:Y38)=0,0,SUMPRODUCT(Y38:Y38,Y46:Y46)/SUM(Y38:Y38)) -> 0 | H75: =IF(SUM(Z38:Z38)=0,0,SUMPRODUCT(Z38:Z38,Z46:Z46)/SUM(Z38:Z38)) -> 0
A76: Card processing fee | C76: =MAX(B39:H39) -> 0.03 | D76: =MAX(I39:O39) -> 0.03 | E76: =MAX(P39:V39) -> 0.03 | F76: =MAX(X39:X39) -> 0.03 | G76: =MAX(Y39:Y39) -> 0.03 | H76: =MAX(Z39:Z39) -> 0.03
A77: Subscription block size (kW) | C77: =MAX(B49:H49) -> 0 | D77: =MAX(I49:O49) -> 0 | E77: =MAX(P49:V49) -> 0 | F77: =MAX(X49:X49) -> 0 | G77: =MAX(Y49:Y49) -> 0 | H77: =MAX(Z49:Z49) -> 0
A78: Subscription block price ($/month) | C78: =MAX(B50:H50) -> 0 | D78: =MAX(I50:O50) -> 0 | E78: =MAX(P50:V50) -> 0 | F78: =MAX(X50:X50) -> 0 | G78: =MAX(Y50:Y50) -> 0 | H78: =MAX(Z50:Z50) -> 0
A79: Demand charge ($/kW-month) | C79: =MAX(B48:H48) -> 0 | D79: =MAX(I48:O48) -> 0 | E79: =MAX(P48:V48) -> 0 | F79: =MAX(X48:X48) -> 0 | G79: =MAX(Y48:Y48) -> 0 | H79: =MAX(Z48:Z48) -> 0
A80: Customer charge ($/month) | C80: =MAX(B47:H47) -> 0 | D80: =MAX(I47:O47) -> 0 | E80: =MAX(P47:V47) -> 0 | F80: =MAX(X47:X47) -> 0 | G80: =MAX(Y47:Y47) -> 0 | H80: =MAX(Z47:Z47) -> 0
A81: Peak-to-average concurrency factor | C81: =MAX(B51:H51) -> 4 | D81: =MAX(I51:O51) -> 4 | E81: =MAX(P51:V51) -> 4 | F81: =MAX(X51:X51) -> 4 | G81: =MAX(Y51:Y51) -> 4 | H81: =MAX(Z51:Z51) -> 4
A82: Safety margin on subscribed kW | C82: =MAX(B52:H52) -> 0.2 | D82: =MAX(I52:O52) -> 0.2 | E82: =MAX(P52:V52) -> 0.2 | F82: =MAX(X52:X52) -> 0.2 | G82: =MAX(Y52:Y52) -> 0.2 | H82: =MAX(Z52:Z52) -> 0.2
A83: Size demand on the full port rating? | C83: =B53 -> Yes | D83: =I53 -> Yes | E83: =P53 -> Yes | F83: =X53 -> Yes | G83: =Y53 -> Yes | H83: =Z53 -> Yes
A84: Demand charge bills from year | C84: =MAX(B54:H54) -> 1 | D84: =MAX(I54:O54) -> 1 | E84: =MAX(P54:V54) -> 1 | F84: =MAX(X54:X54) -> 1 | G84: =MAX(Y54:Y54) -> 1 | H84: =MAX(Z54:Z54) -> 1
A85: Year 1 share of steady state | C85: =MAX(B55:H55) -> 0.5 | D85: =MAX(I55:O55) -> 0.5 | E85: =MAX(P55:V55) -> 0.5 | F85: =MAX(X55:X55) -> 0.5 | G85: =MAX(Y55:Y55) -> 0.5 | H85: =MAX(Z55:Z55) -> 0.5
A86: Year 2 share of steady state | C86: =MAX(B56:H56) -> 0.75 | D86: =MAX(I56:O56) -> 0.75 | E86: =MAX(P56:V56) -> 0.75 | F86: =MAX(X56:X56) -> 0.75 | G86: =MAX(Y56:Y56) -> 0.75 | H86: =MAX(Z56:Z56) -> 0.75
A87: Year 3 share of steady state | C87: =MAX(B57:H57) -> 1 | D87: =MAX(I57:O57) -> 1 | E87: =MAX(P57:V57) -> 1 | F87: =MAX(X57:X57) -> 1 | G87: =MAX(Y57:Y57) -> 1 | H87: =MAX(Z57:Z57) -> 1
A88: Annual growth after the ramp | C88: =MAX(B58:H58) -> 0.06 | D88: =MAX(I58:O58) -> 0.06 | E88: =MAX(P58:V58) -> 0.06 | F88: =MAX(X58:X58) -> 0.06 | G88: =MAX(Y58:Y58) -> 0.06 | H88: =MAX(Z58:Z58) -> 0.06
A89: Service contract length (years) | C89: =MAX(B59:H59) -> 5 | D89: =MAX(I59:O59) -> 5 | E89: =MAX(P59:V59) -> 5 | F89: =MAX(X59:X59) -> 5 | G89: =MAX(Y59:Y59) -> 5 | H89: =MAX(Z59:Z59) -> 5
A90: Warranty + service after the contract ($/yr) | C90: =SUM(B60:H60) -> 0 | D90: =SUM(I60:O60) -> 0 | E90: =SUM(P60:V60) -> 0 | F90: =SUM(X60:X60) -> 0 | G90: =SUM(Y60:Y60) -> 0 | H90: =SUM(Z60:Z60) -> 0
A91: Network fee after the contract ($/yr) | C91: =SUM(B61:H61) -> 0 | D91: =SUM(I61:O61) -> 0 | E91: =SUM(P61:V61) -> 0 | F91: =SUM(X61:X61) -> 0 | G91: =SUM(Y61:Y61) -> 0 | H91: =SUM(Z61:Z61) -> 0
A93: TEN-YEAR PROJECTION — Standard-Low
A94: Year | B94: Ramp | C94: kWh | D94: kWh/day | E94: Avg concurrent ports | F94: Peak concurrent ports | G94: Peak demand kW | H94: Subscribed kW | I94: Blocks | J94: Subscription $/yr | K94: Demand charge $/yr | L94: Customer charge $/yr | M94: Fixed & demand $/yr | N94: Energy $/yr | O94: Utility cost $/yr | P94: Gross revenue | Q94: Card fees | R94: Service & network | S94: Charging profit
A95: 1 | B95: =$C$85 -> 0.5 | C95: =$C$72*B95 -> 0 | D95: =IF($C$73=0,0,C95/$C$73) -> 0 | E95: =IF($C$70=0,0,D95/($C$70*24)) -> 0 | F95: =IF($C$65=0,0,MIN($C$65,MAX(1,ROUNDUP(E95*$C$81,0)))) -> 0 | G95: =F95*IF($C$83="Yes",$C$69,$C$70) -> 0 | H95: =G95*(1+$C$82) -> 0 | I95: =IF($C$77=0,0,ROUNDUP(H95/$C$77,0)) -> 0 | J95: =I95*$C$78*12 -> 0 | K95: =IF(A95>=$C$84,12*$C$79*G95,0) -> 0 | L95: =12*$C$80 -> 0 | M95: =J95+K95+L95 -> 0 | N95: =C95*$C$75 -> 0 | O95: =M95+N95 -> 0 | P95: =C95*$C$74 -> 0 | Q95: =P95*$C$76 -> 0 | R95: =IF(A95>$C$89,$C$90+$C$91,0) -> 0 | S95: =P95-O95-Q95-R95 -> 0
A96: 2 | B96: =$C$86 -> 0.75 | C96: =$C$72*B96 -> 0 | D96: =IF($C$73=0,0,C96/$C$73) -> 0 | E96: =IF($C$70=0,0,D96/($C$70*24)) -> 0 | F96: =IF($C$65=0,0,MIN($C$65,MAX(1,ROUNDUP(E96*$C$81,0)))) -> 0 | G96: =F96*IF($C$83="Yes",$C$69,$C$70) -> 0 | H96: =G96*(1+$C$82) -> 0 | I96: =IF($C$77=0,0,ROUNDUP(H96/$C$77,0)) -> 0 | J96: =I96*$C$78*12 -> 0 | K96: =IF(A96>=$C$84,12*$C$79*G96,0) -> 0 | L96: =12*$C$80 -> 0 | M96: =J96+K96+L96 -> 0 | N96: =C96*$C$75 -> 0 | O96: =M96+N96 -> 0 | P96: =C96*$C$74 -> 0 | Q96: =P96*$C$76 -> 0 | R96: =IF(A96>$C$89,$C$90+$C$91,0) -> 0 | S96: =P96-O96-Q96-R96 -> 0
A97: 3 | B97: =$C$87 -> 1 | C97: =$C$72*B97 -> 0 | D97: =IF($C$73=0,0,C97/$C$73) -> 0 | E97: =IF($C$70=0,0,D97/($C$70*24)) -> 0 | F97: =IF($C$65=0,0,MIN($C$65,MAX(1,ROUNDUP(E97*$C$81,0)))) -> 0 | G97: =F97*IF($C$83="Yes",$C$69,$C$70) -> 0 | H97: =G97*(1+$C$82) -> 0 | I97: =IF($C$77=0,0,ROUNDUP(H97/$C$77,0)) -> 0 | J97: =I97*$C$78*12 -> 0 | K97: =IF(A97>=$C$84,12*$C$79*G97,0) -> 0 | L97: =12*$C$80 -> 0 | M97: =J97+K97+L97 -> 0 | N97: =C97*$C$75 -> 0 | O97: =M97+N97 -> 0 | P97: =C97*$C$74 -> 0 | Q97: =P97*$C$76 -> 0 | R97: =IF(A97>$C$89,$C$90+$C$91,0) -> 0 | S97: =P97-O97-Q97-R97 -> 0
A98: 4 | B98: =$C$87*(1+$C$88)^1 -> 1.06 | C98: =$C$72*B98 -> 0 | D98: =IF($C$73=0,0,C98/$C$73) -> 0 | E98: =IF($C$70=0,0,D98/($C$70*24)) -> 0 | F98: =IF($C$65=0,0,MIN($C$65,MAX(1,ROUNDUP(E98*$C$81,0)))) -> 0 | G98: =F98*IF($C$83="Yes",$C$69,$C$70) -> 0 | H98: =G98*(1+$C$82) -> 0 | I98: =IF($C$77=0,0,ROUNDUP(H98/$C$77,0)) -> 0 | J98: =I98*$C$78*12 -> 0 | K98: =IF(A98>=$C$84,12*$C$79*G98,0) -> 0 | L98: =12*$C$80 -> 0 | M98: =J98+K98+L98 -> 0 | N98: =C98*$C$75 -> 0 | O98: =M98+N98 -> 0 | P98: =C98*$C$74 -> 0 | Q98: =P98*$C$76 -> 0 | R98: =IF(A98>$C$89,$C$90+$C$91,0) -> 0 | S98: =P98-O98-Q98-R98 -> 0
A99: 5 | B99: =$C$87*(1+$C$88)^2 -> 1.1236 | C99: =$C$72*B99 -> 0 | D99: =IF($C$73=0,0,C99/$C$73) -> 0 | E99: =IF($C$70=0,0,D99/($C$70*24)) -> 0 | F99: =IF($C$65=0,0,MIN($C$65,MAX(1,ROUNDUP(E99*$C$81,0)))) -> 0 | G99: =F99*IF($C$83="Yes",$C$69,$C$70) -> 0 | H99: =G99*(1+$C$82) -> 0 | I99: =IF($C$77=0,0,ROUNDUP(H99/$C$77,0)) -> 0 | J99: =I99*$C$78*12 -> 0 | K99: =IF(A99>=$C$84,12*$C$79*G99,0) -> 0 | L99: =12*$C$80 -> 0 | M99: =J99+K99+L99 -> 0 | N99: =C99*$C$75 -> 0 | O99: =M99+N99 -> 0 | P99: =C99*$C$74 -> 0 | Q99: =P99*$C$76 -> 0 | R99: =IF(A99>$C$89,$C$90+$C$91,0) -> 0 | S99: =P99-O99-Q99-R99 -> 0
A100: 6 | B100: =$C$87*(1+$C$88)^3 -> 1.191016 | C100: =$C$72*B100 -> 0 | D100: =IF($C$73=0,0,C100/$C$73) -> 0 | E100: =IF($C$70=0,0,D100/($C$70*24)) -> 0 | F100: =IF($C$65=0,0,MIN($C$65,MAX(1,ROUNDUP(E100*$C$81,0)))) -> 0 | G100: =F100*IF($C$83="Yes",$C$69,$C$70) -> 0 | H100: =G100*(1+$C$82) -> 0 | I100: =IF($C$77=0,0,ROUNDUP(H100/$C$77,0)) -> 0 | J100: =I100*$C$78*12 -> 0 | K100: =IF(A100>=$C$84,12*$C$79*G100,0) -> 0 | L100: =12*$C$80 -> 0 | M100: =J100+K100+L100 -> 0 | N100: =C100*$C$75 -> 0 | O100: =M100+N100 -> 0 | P100: =C100*$C$74 -> 0 | Q100: =P100*$C$76 -> 0 | R100: =IF(A100>$C$89,$C$90+$C$91,0) -> 0 | S100: =P100-O100-Q100-R100 -> 0
A101: 7 | B101: =$C$87*(1+$C$88)^4 -> 1.262477 | C101: =$C$72*B101 -> 0 | D101: =IF($C$73=0,0,C101/$C$73) -> 0 | E101: =IF($C$70=0,0,D101/($C$70*24)) -> 0 | F101: =IF($C$65=0,0,MIN($C$65,MAX(1,ROUNDUP(E101*$C$81,0)))) -> 0 | G101: =F101*IF($C$83="Yes",$C$69,$C$70) -> 0 | H101: =G101*(1+$C$82) -> 0 | I101: =IF($C$77=0,0,ROUNDUP(H101/$C$77,0)) -> 0 | J101: =I101*$C$78*12 -> 0 | K101: =IF(A101>=$C$84,12*$C$79*G101,0) -> 0 | L101: =12*$C$80 -> 0 | M101: =J101+K101+L101 -> 0 | N101: =C101*$C$75 -> 0 | O101: =M101+N101 -> 0 | P101: =C101*$C$74 -> 0 | Q101: =P101*$C$76 -> 0 | R101: =IF(A101>$C$89,$C$90+$C$91,0) -> 0 | S101: =P101-O101-Q101-R101 -> 0
A102: 8 | B102: =$C$87*(1+$C$88)^5 -> 1.3382256 | C102: =$C$72*B102 -> 0 | D102: =IF($C$73=0,0,C102/$C$73) -> 0 | E102: =IF($C$70=0,0,D102/($C$70*24)) -> 0 | F102: =IF($C$65=0,0,MIN($C$65,MAX(1,ROUNDUP(E102*$C$81,0)))) -> 0 | G102: =F102*IF($C$83="Yes",$C$69,$C$70) -> 0 | H102: =G102*(1+$C$82) -> 0 | I102: =IF($C$77=0,0,ROUNDUP(H102/$C$77,0)) -> 0 | J102: =I102*$C$78*12 -> 0 | K102: =IF(A102>=$C$84,12*$C$79*G102,0) -> 0 | L102: =12*$C$80 -> 0 | M102: =J102+K102+L102 -> 0 | N102: =C102*$C$75 -> 0 | O102: =M102+N102 -> 0 | P102: =C102*$C$74 -> 0 | Q102: =P102*$C$76 -> 0 | R102: =IF(A102>$C$89,$C$90+$C$91,0) -> 0 | S102: =P102-O102-Q102-R102 -> 0
A103: 9 | B103: =$C$87*(1+$C$88)^6 -> 1.4185191 | C103: =$C$72*B103 -> 0 | D103: =IF($C$73=0,0,C103/$C$73) -> 0 | E103: =IF($C$70=0,0,D103/($C$70*24)) -> 0 | F103: =IF($C$65=0,0,MIN($C$65,MAX(1,ROUNDUP(E103*$C$81,0)))) -> 0 | G103: =F103*IF($C$83="Yes",$C$69,$C$70) -> 0 | H103: =G103*(1+$C$82) -> 0 | I103: =IF($C$77=0,0,ROUNDUP(H103/$C$77,0)) -> 0 | J103: =I103*$C$78*12 -> 0 | K103: =IF(A103>=$C$84,12*$C$79*G103,0) -> 0 | L103: =12*$C$80 -> 0 | M103: =J103+K103+L103 -> 0 | N103: =C103*$C$75 -> 0 | O103: =M103+N103 -> 0 | P103: =C103*$C$74 -> 0 | Q103: =P103*$C$76 -> 0 | R103: =IF(A103>$C$89,$C$90+$C$91,0) -> 0 | S103: =P103-O103-Q103-R103 -> 0
A104: 10 | B104: =$C$87*(1+$C$88)^7 -> 1.5036303 | C104: =$C$72*B104 -> 0 | D104: =IF($C$73=0,0,C104/$C$73) -> 0 | E104: =IF($C$70=0,0,D104/($C$70*24)) -> 0 | F104: =IF($C$65=0,0,MIN($C$65,MAX(1,ROUNDUP(E104*$C$81,0)))) -> 0 | G104: =F104*IF($C$83="Yes",$C$69,$C$70) -> 0 | H104: =G104*(1+$C$82) -> 0 | I104: =IF($C$77=0,0,ROUNDUP(H104/$C$77,0)) -> 0 | J104: =I104*$C$78*12 -> 0 | K104: =IF(A104>=$C$84,12*$C$79*G104,0) -> 0 | L104: =12*$C$80 -> 0 | M104: =J104+K104+L104 -> 0 | N104: =C104*$C$75 -> 0 | O104: =M104+N104 -> 0 | P104: =C104*$C$74 -> 0 | Q104: =P104*$C$76 -> 0 | R104: =IF(A104>$C$89,$C$90+$C$91,0) -> 0 | S104: =P104-O104-Q104-R104 -> 0
A105: 10-year total | C105: =SUM(C95:C104) -> 0 | J105: =SUM(J95:J104) -> 0 | K105: =SUM(K95:K104) -> 0 | L105: =SUM(L95:L104) -> 0 | M105: =SUM(M95:M104) -> 0 | N105: =SUM(N95:N104) -> 0 | O105: =SUM(O95:O104) -> 0 | P105: =SUM(P95:P104) -> 0 | Q105: =SUM(Q95:Q104) -> 0 | ... S105: =SUM(S95:S104) -> 0
A106: All-in $/kWh (energy + fixed and demand) | N106: =$C$75+IF(C105=0,0,M105/C105) -> 0
...

Sheet CTX Price Book
B1: CTX Price Book
B2: Category | C2: SKU | D2: Description | E2: Our Cost | F2: MSRP | I2: Category List | J2: ← Pick a Category first
B3: _L2 | C3: CTX-R40-240-1 | D3: 40A Single Home Charger | E3: 273.8 | F3: 605 | I3: _L2
C4: CTX-R48-240-1 | D4: 48A Single Home Charger | E4: 235 | F4: 605 | I4: _kW30
C5: CTX-C32-240-1 | D5: 32A Single Commercial L2 Charger | E5: 510.3 | F5: 1402.5 | I5: _kW60
C6: CTX-C48-240-1 | D6: 48A Single Commercial L2 Charger (18' Cable with Modem) | E6: 510.3 | F6: 1402.5 | I6: _kW120
C7: CTX-C80-240-1 | D7: 80A Single Commercial L2 Charger (18' Cable with Modem) | E7: 640 | F7: 1650 | I7: _kW160
C8: CTX-C40-240-2 | D8: 40A Dual Commercial L2 Charger (18' Cable with Modem) | E8: 760.78 | F8: 1952.5 | I8: _kW180
C9: CTX-C80-240-2 | D9: 80A Dual Commercial L2 Charger (18' Cable with Modem) | E9: 828.95 | F9: 2194.5 | I9: _kW240
C10: CTX-C80-240-1-ISO | D10: 80A Single Commercial L2 Charger (18' Cable with Modem) | E10: 595.35 | F10: 2255 | I10: _kW360
C11: CTX-C40-240-2-ISO | D11: 40A Dual Commercial L2 Charger (18' Cable with Modem) | E11: 828.12 | F11: 2530 | I11: _Distributed_System
C12: CTX-C80-240-2-ISO | D12: 80A Dual Commercial L2 Charger (18' Cable with Modem) | E12: 1043.95 | F12: 2805 | I12: _Buy_America
B13: _kW30 | C13: TP5-30-480-1 | D13: Gen2 30kW DCFC Wall Mount - 100 Amps / 1000VDC with CCS1 (~16ft) | E13: 3600 | F13: 13750 | I13: _V2G
C14: TP5-30-480-3 | D14: Gen 2Gen 30kW DCFC Wall Mount - 200 Amps / 1000VDC with NACS (~16ft) | E14: 3600 | F14: 13750 | I14: _L2_Accessories
B15: _kW60 | C15: TP5-60-480-1 | D15: 60kW DCFC - 200 Amps / 1000VDC with CCS1 & CHAdeMO(~16ft) ; 4G Modem | E15: 8100 | F15: 28500 | I15: _CTX_Warranty
C16: TP5-60-480-2 | D16: 60kW DCFC - 200 Amps / 1000VDC with CCS1 & CCS1(~16ft) ; 4G Modem | E16: 8100 | F16: 28500 | I16: _CTX_Service_Plans
C17: TP5-60-480-3 | D17: 60kW DCFC - 200 Amps / 1000VDC with CCS1 & NACS(~16ft) ; 4G Modem | E17: 8100 | F17: 28500
C18: TP5-60-480-4 | D18: 60kW DCFC - 200 Amps / 1000VDC with NACS & NACS(~16ft) ; 4G Modem | E18: 8100 | F18: 28500
C19: CTX-AiO-60-2-200 | D19: Gen 2 60kW DCFC - 200 Amps / 1000VDC with CCS1 & CCS1(~16ft) ; 4G Modem | E19: 14145 | F19: 31350
C20: CTX-AiO-60-3-200 | D20: Gen 2 60kW DCFC - 200 Amps / 1000VDC with CCS1 & NACS(~16ft) ; 4G Modem | E20: 14145 | F20: 31350
C21: CTX-AiO-60-4-200 | D21: Gen 2 60kW DCFC - 200 Amps / 1000VDC with NACS & NACS(~16ft) ; 4G Modem | E21: 14145 | F21: 31350
B22: _kW120 | C22: TP5-120-480-1 | D22: 120kW DCFC All In One Charger - 200 Amps / 1000VDC with CCS1 & CHAdeMO(~16ft) ; Can charge 2 cars simultaneously with 60kW each ; 4G Modem | E22: 12588 | F22: 54000
C23: TP5-120-480-2 | D23: 120kW DCFC All In One Charger - 200 Amps / 1000VDC with CCS1 & CCS1(~16ft); Can charge 2 cars simultaneously with 60kW each ; 4G Modem | E23: 12588 | F23: 54000
C24: TP5-120-480-2-300 | D24: 120kW DCFC All In One Charger - 350A Cable / 1000VDC with CCS1 & CCS1(~16ft); Can charge 2 cars simultaneously with 60kW each ; 4G Modem | E24: 12588 | F24: 54000
C25: TP5-120-480-3-300 | D25: 120kW DCFC All In One Charger - 1000VDC, Cables: 350A CCS1 & 400A NACS (~16ft); Can charge 2 cars simultaneously with 60kW each ; 4G Modem | E25: 12588 | F25: 54000
C26: CTX-AiO-120-2-350 | D26: Gen3 120kW CCS1 350A + CCS1 350A ; Cable Management + CC | E26: 15950 | F26: 59400
C27: CTX-AiO-120-3-350 | D27: Gen3 120kW CCS1 350A + NACS 350A ; Cable Management + CC | E27: 15950 | F27: 59400
C28: CTX-AiO-120-4-350 | D28: Gen3 120kW NACS 350A + NACS 350A ; Cable Management + CC | E28: 15950 | F28: 59400
C29: CTX-AiO-120-5-350 | D29: Gen3 120kW Single CCS1 350A ; Cable Management + CC | E29: 15950 | F29: 59400
C30: CTX-AiO-120-6-350 | D30: Gen3 120kW Single NACS 350A ; Cable Management + CC | E30: 15950 | F30: 59400
B31: _kW160 | C31: TP5-160-480-1 | D31: 160kW DCFC All In One Charger - 200 Amps / 1000VDC with CCS1 & CHAdeMO(~16ft); It can dispense 200A on single connector and can charge 2 cars simultaneously with 80kW each or 100kW CCS1 and 60kW CHAdeMO ; 4G Modem | F31: 57000
C32: TP5-160-480-2 | D32: 160kW DCFC All In One Charger - 200 Amps / 1000VDC with CCS1 & CCS1(~16ft); It can dispense 200A on single connector and can charge 2 cars simultaneously with 80kW each ; 4G Modem | F32: 57000
C33: TP5-160-480-3 | D33: 160kW DCFC All In One Charger - 200 Amps / 1000VDC with CCS1 & NACS (~16ft); It can dispense 200A on single connector and can charge 2 cars simultaneously with 80kW each ; 4G Modem | F33: 57000
C34: TP5-160-480-2-300 | D34: 160kW DCFC All In One Charger - 350A Cable / 1000VDC with CCS1 & CCS1(~16ft); Can charge 2 cars simultaneously with 80kW each ; 4G Modem | F34: 57000
C35: HPC-160-480-1 | D35: 160kW HPC All In One Charger - 400 Amps / 1000VDC with Liquid Cooled Connector for CCS1(~14ft) & CHAdeMO(~16ft) ; It can deliver 400A on the CCS coonnector. Can charge 2 cars simultaneously with 80kW each or 100kW CCS1 and 60kW CHAdeMO ; 4G Modem | F35: 68000
C36: HPC-160-480-2 | D36: 160kW HPC All In One Charger - 400 Amps / 1000VDC with Liquid Cooled Connector for CCS1(~14ft) & CHAdeMO(~16ft) ; It can deliver 400A on the CCS coonnector. Also can charge 2 cars with 200Amps each; 4G Modem | F36: 70000
C37: CTX-AiO-160-2-350 | D37: Gen3 160kW CCS1 350A + CCS1 350A ; Cable Management + CC | E37: 17595 | F37: 68200
C38: CTX-AiO-160-3-350 | D38: Gen3 160kW CCS1 350A + NACS 350A ; Cable Management + CC | E38: 17595 | F38: 68200
C39: CTX-AiO-160-4-350 | D39: Gen3 160kW NACS 350A + NACS 350A ; Cable Management + CC | E39: 17595 | F39: 68200
C40: CTX-AiO-160-5-350 | D40: Gen3 160kW Single CCS1 350A ; Cable Management + CC | F40: 68200
C41: CTX-AiO-160-6-350 | D41: Gen3 160kW Single NACS 350A ; Cable Management + CC | F41: 68200
B42: _kW180 | C42: TP5-180-480-1 | D42: 180kW DCFC All In One Charger - 200 Amps / 1000VDC with CCS1 & CHAdeMO(~16ft); Can charge 2 cars simultaneously with 90kW each or 120kW on CCS1 and 60kW on CHAdeMO; 4G Modem | E42: 19500 | F42: 62000
C43: TP5-180-480-2 | D43: 180kW DCFC All In One Charger - 200 Amps / 1000VDC with CCS1 & CCS1(~16ft); Can charge 2 cars simultaneously with 90kW each ; 4G Modem | E43: 19500 | F43: 62000
C44: TP5-180-480-2-300 | D44: 180kW DCFC All In One Charger - 350A Cable / 1000VDC with CCS1 & CCS1(~16ft); Can charge 2 cars simultaneously with 90kW each ; 4G Modem | E44: 19500 | F44: 62000
C45: TP5-180-480-3-300 | D45: 180kW DCFC All In One Charger - 1000VDC, Cables: 350A CCS1 & 400A NACS (~16ft); Can charge 2 cars simultaneously with 90kW each ; 4G Modem | E45: 19500 | F45: 62000
C46: TP5-180-480-2-300-CL20 | D46: 180kW DCFC All In One Charger - 350A Cable / 1000VDC with CCS1 & CCS1(~20ft); Can charge 2 cars simultaneously with 90kW each ; 4G Modem | F46: 62000
B47: _kW240 | C47: TP5-240-480-2-300 | D47: 240kW DCFC All In One Charger - 350A Cable / 1000VDC Dual CCS1 ; Can charge 2 cars simultaneously with 120kW each ; 4G Modem | E47: 25000 | F47: 80000
C48: TP5-240-480-2-400 | D48: 240kW DCFC All In One Charger - 1000VDC, Cables: 350A CCS1 & 400A NACS; Can charge 2 cars simultaneously with 120kW each ; 4G Modem | E48: 25000 | F48: 80000
C49: HPC-240-480-1 | D49: 240kW HPC All In One Charger - 500 Amps / 1000VDC with Liquid Cooled Connector for CCS1 & CHAdeMO(~14ft) ; Can deliver 500A on CCS coonnector. Can charge 2 cars simultaneously; 4G Modem | F49: 98000
C50: HPC-240-480-2 | D50: 240kW HPC All In One Charger - 500 Amps / 1000VDC with Liquid Cooled Connector for Dual CCS1 ; Can deliver 450A on one CCS coonnector and 250A on each connector if used simultaneously ; 4G Modem | F50: 98000
C51: CTX-AiO-240-2-300 | D51: Gen3 240kW CCS1 350A + CCS1 350A; Cable Management + CC | E51: 24725 | F51: 88000
C52: CTX-AiO-240-3-300 | D52: Gen3 240kW CCS1 350A + NACS 350A; Cable Management + CC | E52: 24725 | F52: 88000
C53: CTX-AiO-240-4-300 | D53: Gen3 240kW NACS 350A + NACS 350A; Cable Management + CC | E53: 24725 | F53: 88000
C54: CTX-AiO-240-5-300 | D54: Gen3 240kW Single CCS1 350A; Cable Management + CC | E54: 24725 | F54: 88000
B55: _kW360 | C55: TP5-360-480-1-300 | D55: 360kW DCFC All In One Charger - 1000VDC, Cables: 350A CCS1 & CHAdeMO ; Can charge 2 cars simultaneously with 180kW each ; 4G Modem | E55: 29000 | F55: 99000
C56: TP5-360-480-2-300 | D56: 360kW DCFC All In One Charger - 350A Cable / 1000VDC Dual CCS1 ; Can charge 2 cars simultaneously with 180kW each ; 4G Modem | E56: 29000 | F56: 99000
C57: TP5-360-480-3-300 | D57: 360kW DCFC All In One Charger - 1000VDC, Cables: 350A CCS1 & 400A NACS ; Can charge 2 cars simultaneously with 180kW each ; 4G Modem | E57: 29000 | F57: 99000
C58: TP5-360-480-4-300 | D58: 360kW DCFC All In One Charger - 1000VDC, Cables: 400A NACS / 400A NACS ; Can charge 2 cars simultaneously with 180kW each ; 4G Modem | E58: 29000 | F58: 99000
C59: HPC-360-480-1 | D59: 360kW HPC All In One Charger - 500 Amps / 1000VDC with Liquid Cooled Connector for CCS1 & CHAdeMO(~14ft) ; Can deliver 500A on CCS coonnector. Can charge 2 cars simultaneously; 4G Modem | E59: 65520 | F59: 110000
C60: HPC-360-480-2 | D60: 360kW HPC All In One Charger - 500 Amps / 1000VDC with Liquid Cooled Connector for Dual CCS1 ; Can deliver 500A on one CCS coonnector and 400A on each connector if used simultaneously ; 4G Modem | E60: 65520 | F60: 110000
C61: HPC-360-480-3 | D61: 360kW HPC All In One Charger - 500 Amps / 1000VDC with Liquid Cooled Connector for CCS1 & NACS ; Can deliver 500A on CCS coonnector. Can charge 2 cars simultaneously; 4G Modem | E61: 65520 | F61: 110000
C62: HPC-360-480-4 | D62: 360kW HPC All In One Charger - 500 Amps / 1000VDC with Liquid Cooled Connector for NACS / NACS ; Can deliver 500A on CCS coonnector. Can charge 2 cars simultaneously; 4G Modem | E62: 65520 | F62: 110000
B63: _Distributed_System | C63: CTX-DSPB-360 | D63: 360kW Tower | E63: 28750 | F63: 81400
C64: CTX-DSPB-480 | D64: 480kW Tower | E64: 31000 | F64: 90200
C65: CTX-DSPB-1280 | D65: 1,280kW Tower | E65: 0 | F65: 225000
C66: CTX-DST-2-300 | D66: Dispenser 300/300 | E66: 13100 | F66: 35200
C67: CTX-DST-HPC-2-500/300 | D67: Dispenser 500/300 | E67: 24725 | F67: 49500
B68: _Buy_America | C68: TP5-60-480-2-BAA | D68: Buy America NEVI Compliant, Assembled in CA, USA 60kW DCFC - 140 Amps / 1000VDC with CCS1 & CCS1(~16ft) ; 4G Modem | E68: 17500 | F68: 68200
C69: TP5-60-480-3-BAA | D69: Buy America NEVI Compliant, Assembled in CA, USA 60kW DCFC - 140 Amps / 1000VDC with CCS1 & NACS ; 4G Modem | E69: 17500 | F69: 68200
C70: TP5-60-480-4-BAA | D70: Buy America NEVI Compliant, Assembled in CA, USA 60kW DCFC - 140 Amps / 1000VDC with NACS & NACS ; 4G Modem | E70: 0 | F70: 68200
C71: TP5-120-480-2-300-BAA | D71: Buy America NEVI Compliant, Assembled in CA, USA 120kW DCFC All In One Charger - 350A Cable / 1000VDC with CCS1 & CCS1(~16ft); Can charge 2 cars simultaneously with 60kW each ; 4G Modem | E71: 14480 | F71: 75900
C72: TP5-120-480-3-300-BAA | D72: Buy America NEVI Compliant, Assembled in CA, USA 120kW DCFC All In One Charger - 350A Cable / 1000VDC with CCS1 & NACS; Can charge 2 cars simultaneously with 60kW each ; 4G Modem | E72: 14480 | F72: 75900
C73: TP5-120-480-4-300-BAA | D73: Buy America NEVI Compliant, Assembled in CA, USA 120kW DCFC All In One Charger - 350A Cable / 1000VDC with NACS & NACS(~16ft); Can charge 2 cars simultaneously with 60kW each ; 4G Modem | E73: 14480 | F73: 75900
C74: TP5-180-480-2-BAA | D74: Buy America NEVI Compliant, Assembled in CA, USA 180kW Air Cooled 350A Cable (BAA) CCS1 / CCS1 1000VDC Connector for Dual CCS1; Can deliver 350A on one CCS conector. Set to Sequential Mode Only. | E74: 35500 | F74: 82500
C75: TP5-180-480-3-BAA | D75: Buy America NEVI Compliant, Assembled in CA, USA 180kW Air Cooled 350A Cable (BAA) CCS1 / NACS 1000VDC Connector for Dual CCS1; Can deliver 350A on one CCS conector. Set to Sequential Mode Only. | E75: 35500 | F75: 82500
C76: TP5-180-480-4-BAA | D76: Buy America NEVI Compliant, Assembled in CA, USA 180kW Air Cooled 350A Cable (BAA) NACS / NACS 1000VDC Connector for Dual CCS1; Can deliver 350A on one CCS conector. Set to Sequential Mode Only. | E76: 35500 | F76: 82500
C77: HPC-180-480-2-BAA | D77: Buy America NEVI Compliant, Assembled in CA, USA 180kW Liquid Cooled (BAA) Dual CCS1 500 Amps / 1000VDC with Liquid Cooled Connector for Dual CCS1 ; Can deliver 450A on one CCS connector. Set to Sequential Mode Only | E77: 43500 | F77: 82500
C78: HPC-180-480-3-BAA | D78: Buy America NEVI Compliant, Assembled in CA, USA 180kW Liquid Cooled (BAA) CCS1 / NACS 1000VDC with Liquid Cooled Connector for Dual CCS1 ; Can deliver 450A on one CCS connector. Set to Sequential Mode Only | E78: 43500 | F78: 82500
C79: HPC-180-480-4-BAA | D79: Buy America NEVI Compliant, Assembled in CA, USA 180kW Liquid Cooled (BAA) NACS /NACS 1000VDC with Liquid Cooled Connector for Dual CCS1 ; Can deliver 450A on one CCS connector. Set to Sequential Mode Only | E79: 43500 | F79: 82500
C80: TP5-360-480-2-BAA | D80: Buy America NEVI Compliant 360kW Air Cooled 350A Cable (BAA) Dual CCS1 / 1000VDC Connector for Dual CCS1 ; Can deliver 350A on one CCS connector and 350A on each connector if used simultaneously ; 4G Modem | E80: 0 | F80: 138600
... C85: HPC-360-480-4-BAA | D85: Buy America NEVI Compliant 360kW Liquid Cooled (BAA) 500 Amps / 1000VDC with Liquid Cooled Connector for NACS/NACS ; Can deliver 500A on one CCS connector and 400A on each connector if used simultaneously ; 4G Modem | E85: 0 | F85: 137500
B86: _V2G | C86: CTX-V2G-20-480-1 | D86: 20kW V2G Charger | E86: 5800 | F86: 16700
C87: CTX-V2G-30-480-1 | D87: 30kW V2G Charger | E87: 8250 | F87: 23800
C88: CTX-V2G-40-480-1 | D88: 40kW V2G Charger | E88: 12500 | F88: 35900
C89: CTX-V2G-60-480-1 | D89: 60kW V2G Charger | E89: 17500 | F89: 50000
B90: _L2_Accessories | C90: CTX-FLUXPED | D90: Single Post (no Retraction) | E90: 142.47 | F90: 412.5
C91: CTX-FLUXWAL-CMS-1 | D91: Single Retractor (Wall) | E91: 92.71 | F91: 275
C92: CTX-FLUXPED-CMS-1 | D92: Single Retractor post | E92: 142.15 | F92: 412.5
C93: CTX-FLUXPED-CMS-2 | D93: Dual Retractor (Post) | E93: 224.6 | F93: 632.5
C94: CTX-FLUXPED-SBS | D94: Side By Side Bracket | E94: 44.18 | F94: 137.5
B95: _CTX_Warranty | C95: CTX-W-AC-3 | D95: 3 year | F95: 884.52
C96: CTX-W-AC-5 | D96: 5 year | F96: 1474.2
C97: CTX-W-30-3 | D97: 3 year | F97: 1436.29
C98: CTX-W-30-5 | D98: 5 year | F98: 4308.88 | G98: =F98/5 -> 861.776
C99: CTX-W-60-3 | D99: 3 year | F99: 2888.52
C100: CTX-W-60-5 | D100: 5 year | F100: 4814.2 | G100: =F100/5 -> 962.84
C101: CTX-W-120-3 | D101: 3 year | F101: 3590.73
C102: CTX-W-120-5 | D102: 5 year | F102: 5984.55 | G102: =F102/5 -> 1196.91
C103: CTX-W-160-3 | D103: 3 year | F103: 4285.71
C104: CTX-W-160-5 | D104: 5 year | F104: 7142.85
...

Sheet INPUT SHEET CPM
C1: Level 2 | G1: Level 3 | M1: 480
B2: Type of Charger per Rating | C2: L2 Single P | D2: L2 Dual P | E2: L2 Single W | F2: L2 Dual W | G2: 30 | H2: 100 | I2: 120 | J2: 160 | K2: 240 | L2: 360 | M2: TOTAL | O2: CONTRACT LENGTH | P2: 5 | S2: Charger | T2: QTY
B3: Quantity | C3: =IF(P30>0,IFERROR(P30*INDEX(#REF!,MATCH(F30,#REF!,0))*#REF!,0),0) -> 0 | D3: 0 | E3: =IF(R30>0,IFERROR(R30*INDEX(#REF!,MATCH(H30,#REF!,0))*#REF!,0),0) -> 0 | F3: =IF(S30>0,IFERROR(S30*INDEX(#REF!,MATCH(I30,#REF!,0))*#REF!,0),0) -> 0 | G3: 0 | H3: 0 | I3: =IF(V30>0,IFERROR(V30*INDEX(#REF!,MATCH(L30,#REF!,0))*#REF!,0),0) -> 0 | J3: =IF(W30>0,IFERROR(W30*INDEX(#REF!,MATCH(M30,#REF!,0))*#REF!,0),0) -> 0 | K3: =IF(X30>0,IFERROR(X30*INDEX(#REF!,MATCH(N30,#REF!,0))*#REF!,0),0) -> 0 | L3: =IF(Y30>0,IFERROR(Y30*INDEX(#REF!,MATCH(O30,#REF!,0))*#REF!,0),0) -> 0 | S3: =IF('INPUT SHEET'!E8="","",'INPUT SHEET'!F8) | T3: =IF('INPUT SHEET'!E8="","",'INPUT SHEET'!I8)
B4: KVA per Phase | G4: =IF(G3=0,"",_xlfn.IFS(G2=30,40,G2=50,72,G2=60,80,G2=100,130,G2=120,160,G2=160,215,G2=180,240,G2=200,265,G2=240,320,G2=275,385,G2=300,400,G2=360,480)*M1*SQRT(3)/3) | H4: =IF(H3=0,"",_xlfn.IFS(H2=30,40,H2=50,72,H2=60,80,H2=100,130,H2=120,160,H2=160,215,H2=180,240,H2=200,265,H2=240,320,H2=275,385,H2=300,400,H2=360,480)*M1*SQRT(3)/3) | I4: =IF(I3=0,"",_xlfn.IFS(I2=30,40,I2=50,72,I2=60,80,I2=100,130,I2=120,160,I2=160,215,I2=180,240,I2=200,265,I2=240,320,I2=275,385,I2=300,400,I2=360,480)*M1*SQRT(3)/3) | J4: =IF(J3=0,"",_xlfn.IFS(J2=30,40,J2=50,72,J2=60,80,J2=100,130,J2=120,160,J2=160,215,J2=180,240,J2=200,265,J2=240,320,J2=275,385,J2=300,400,J2=360,480)*M1*SQRT(3)/3) | K4: =IF(K3=0,"",_xlfn.IFS(K2=30,40,K2=50,72,K2=60,80,K2=100,130,K2=120,160,K2=160,215,K2=180,240,K2=200,265,K2=240,320,K2=275,385,K2=300,400,K2=360,480)*M1*SQRT(3)/3) | L4: =IF(L3=0,"",_xlfn.IFS(L2=30,40,L2=50,72,L2=60,80,L2=100,130,L2=120,160,L2=160,215,L2=180,240,L2=200,265,L2=240,320,L2=275,385,L2=300,400,L2=360,480)*M1*SQRT(3)/3) | S4: =IF('INPUT SHEET'!E9="","",'INPUT SHEET'!F9) | T4: =IF('INPUT SHEET'!E9="","",'INPUT SHEET'!I9)
B5: Breaker size per port (in A) | G5: =IF(G3=0,"",_xlfn.IFS(G2=30,50,G2=50,100,G2=60,100,G2=100,200,G2=120,200,G2=160,300,G2=180,300,G2=200,335,G2=240,400,G2=275,500,G2=300,500,G2=360,600)) | H5: =IF(H3=0,"",_xlfn.IFS(H2=30,50,H2=50,100,H2=60,100,H2=100,200,H2=120,200,H2=160,300,H2=180,300,H2=200,335,H2=240,400,H2=275,500,H2=300,500,H2=360,600)) | I5: =IF(I3=0,"",_xlfn.IFS(I2=30,50,I2=50,100,I2=60,100,I2=100,200,I2=120,200,I2=160,300,I2=180,300,I2=200,335,I2=240,400,I2=275,500,I2=300,500,I2=360,600)) | J5: =IF(J3=0,"",_xlfn.IFS(J2=30,50,J2=50,100,J2=60,100,J2=100,200,J2=120,200,J2=160,300,J2=180,300,J2=200,335,J2=240,400,J2=275,500,J2=300,500,J2=360,600)) | K5: =IF(K3=0,"",_xlfn.IFS(K2=30,50,K2=50,100,K2=60,100,K2=100,200,K2=120,200,K2=160,300,K2=180,300,K2=200,335,K2=240,400,K2=275,500,K2=300,500,K2=360,600)) | L5: =IF(L3=0,"",_xlfn.IFS(L2=30,50,L2=50,100,L2=60,100,L2=100,200,L2=120,200,L2=160,300,L2=180,300,L2=200,335,L2=240,400,L2=275,500,L2=300,500,L2=360,600)) | S5: =IF('INPUT SHEET'!E10="","",'INPUT SHEET'!F10) | T5: =IF('INPUT SHEET'!E10="","",'INPUT SHEET'!I10)
B6: Quantity of Ports | C6: =C3*1 -> 0 | D6: =D3*2 -> 0 | E6: =E3*1 -> 0 | F6: =F3*2 -> 0 | G6: =G3*1 -> 0 | H6: =H3*1 -> 0 | I6: =I3*1 -> 0 | J6: =J3*1 -> 0 | K6: =K3*1 -> 0 | L6: =L3*1 -> 0 | M6: =SUM(C6:L6) -> 0 | S6: =IF('INPUT SHEET'!E11="","",'INPUT SHEET'!F11) | T6: =IF('INPUT SHEET'!E11="","",'INPUT SHEET'!I11)
B7: Rating per Port for L2 (in KW) | C7: 7.7 | D7: 19.2 | E7: 7.7 | F7: 19.2 | G7: 60 | H7: 120 | I7: 160 | J7: 180 | K7: 300 | L7: 360 | S7: =IF('INPUT SHEET'!E12="","",'INPUT SHEET'!F12) | T7: =IF('INPUT SHEET'!E12="","",'INPUT SHEET'!I12)
B8: CALCULATIONS | S8: =IF('INPUT SHEET'!E13="","",'INPUT SHEET'!F13) | T8: =IF('INPUT SHEET'!E13="","",'INPUT SHEET'!I13)
B9: Breaker size per port (in A) | C9: 30 | D9: 30 | E9: 30 | F9: 30 | G9: 100 | H9: 200 | I9: 300 | J9: 400 | K9: 500 | L9: 600 | S9: =IF('INPUT SHEET'!E14="","",'INPUT SHEET'!F14) | T9: =IF('INPUT SHEET'!E14="","",'INPUT SHEET'!I14)
B10: Quantity of Charger Breakers | C10: =C3*1 -> 0 | D10: =D3*2 -> 0 | E10: =E3*1 -> 0 | F10: =F3*2 -> 0 | G10: =G3*1 -> 0 | H10: =H3*1 -> 0 | I10: =I3*1 -> 0 | J10: =J3*1 -> 0 | K10: =K3*1 -> 0 | L10: =L3*1 -> 0 | S10: =IF('INPUT SHEET'!E15="","",'INPUT SHEET'!F15) | T10: =IF('INPUT SHEET'!E15="","",'INPUT SHEET'!I15)
B11: Total Load Size | C11: 0 | G11: 0 | O11: Labor In Days | P11: 30 | S11: =IF('INPUT SHEET'!E16="","",'INPUT SHEET'!F16) | T11: =IF('INPUT SHEET'!E16="","",'INPUT SHEET'!I16)
B12: Total Kva | C12: =(C6*C7)+(D6*D7)+(E6*E7)+(F6*F7) -> 0 | G12: =(G3*G7)+(H3*H7)+(I3*I7)+(J3*J7)+(K7*K3)+(L3*L7) -> 0 | S12: =IF('INPUT SHEET'!E17="","",'INPUT SHEET'!F17) | T12: =IF('INPUT SHEET'!E17="","",'INPUT SHEET'!I17)
B13: Quantity of Sub-panels | C13: ='CPM Calcs'!S69 -> 0 | G13: 0 | O13: Rebate Amount | P13: 0 | S13: =IF('INPUT SHEET'!E18="","",'INPUT SHEET'!F18) | T13: =IF('INPUT SHEET'!E18="","",'INPUT SHEET'!I18)
B14: Sub-panel Size | C14: ='CPM Calcs'!S71 -> 600 | G14: 0 | S14: =IF('INPUT SHEET'!E19="","",'INPUT SHEET'!F19) | T14: =IF('INPUT SHEET'!E19="","",'INPUT SHEET'!I19)
B15: Main Breaker Size | C15: =C14 -> 600 | G15: 0 | S15: =IF('INPUT SHEET'!E20="","",'INPUT SHEET'!F20) | T15: =IF('INPUT SHEET'!E20="","",'INPUT SHEET'!I20)
B16: Total Gear Size @208V (AMPERAGE) | C16: =C13*C14 -> 0 | S16: =IF('INPUT SHEET'!E21="","",'INPUT SHEET'!F21) | T16: =IF('INPUT SHEET'!E21="","",'INPUT SHEET'!I21)
B17: Total Gear Size @ 480 V (AMPERAGE) | G17: ='CPM Calcs'!R71 -> 100 | S17: =IF('INPUT SHEET'!E22="","",'INPUT SHEET'!F22) | T17: =IF('INPUT SHEET'!E22="","",'INPUT SHEET'!I22)
S18: =IF('INPUT SHEET'!E23="","",'INPUT SHEET'!F23) | T18: =IF('INPUT SHEET'!E23="","",'INPUT SHEET'!I23)
B19: STANDARD RFC | S19: =IF('INPUT SHEET'!E24="","",'INPUT SHEET'!F24) | T19: =IF('INPUT SHEET'!E24="","",'INPUT SHEET'!I24)
S29: Address | T29: ='INPUT SHEET'!N17 -> 0
C30: =IF(D30="","",ROW()-27) | S30: RSM: | T30: ='INPUT SHEET'!N18 -> 0
C31: =IF(D31="","",ROW()-27) | O31: =IF(F31="","",INDEX(#REF!,MATCH(F31,#REF!,0))) | Q31: =IF(P31="","",O31*P31) | S31: Client Info: | T31: ='INPUT SHEET'!N19 -> 0
C32: =IF(D32="","",ROW()-27) | O32: =IF(F32="","",INDEX(#REF!,MATCH(F32,#REF!,0))) | Q32: =IF(P32="","",O32*P32) | S32: CPM:
C33: =IF(D33="","",ROW()-27) | O33: =IF(F33="","",INDEX(#REF!,MATCH(F33,#REF!,0))) | Q33: =IF(P33="","",O33*P33) | S33: Utility: | T33: ='INPUT SHEET'!N20 -> 0
C34: =IF(D34="","",ROW()-27) | O34: =IF(F34="","",INDEX(#REF!,MATCH(F34,#REF!,0))) | Q34: =IF(P34="","",O34*P34) | S34: Scope of Work : Pictures Attatched on INPUT SHEET | T34: ='INPUT SHEET'!N21 -> 0
C35: =IF(D35="","",ROW()-27) | O35: =IF(F35="","",INDEX(#REF!,MATCH(F35,#REF!,0))) | Q35: =IF(P35="","",O35*P35)
O36: =IF(F36="","",INDEX(#REF!,MATCH(F36,#REF!,0)))

Sheet Costs Internal
B2: Electrical Supply & Construction Management Costs | C2: Quantity | D2: Individual Cost | E2: Contingency | F2: Final Cost | G2: Total
B3: Wires, Conduits and Peripherals | C3: 1 | D3: 18686.255 | E3: 0.1 | F3: =(D3*E3)+D3 -> 8623.7355 | G3: =F3*C3 -> 8623.7355 | J3: Labor
B4: Main Distribution Switchgear | C4: 1 | D4: 43292.68 | E4: 0.1 | F4: =(D4*E4)+D4 -> 44543.73 | G4: =F4*C4 -> 44543.73 | J4: Daily Cost | K4: 2750
B5: Electrical Sub-Panels, Transformers, Breakers | C5: 1 | D5: 3900 | E5: 0.1 | F5: =(D5*E5)+D5 -> 0 | G5: =F5*C5 -> 0 | J5: Total Business Days | K5: 28
B6: Bollards, Signage | C6: 1 | D6: 3068.3 | E6: 0.1 | F6: =(D6*E6)+D6 -> 0 | G6: =F6*C6 -> 0 | J6: Total Months | K6: =K5/30 -> 1
B7: Asphalt, Paving, and Striping | C7: 1 | D7: 12001.75 | E7: 0.1 | F7: =(D7*E7)+D7 -> 1728.3035 | G7: =F7*C7 -> 1728.3035 | J7: Total Labor | K7: =K5*K4 -> 67500
B8: Concrete Improvements | C8: 1 | D8: 7716.48 | E8: 0.1 | F8: =(D8*E8)+D8 -> 4748.4272 | G8: =F8*C8 -> 4748.4272
B9: ADA | C9: 1 | D9: 16600 | E9: 0.1 | F9: =(D9*E9)+D9 -> 11858 | G9: =F9*C9 -> 11858
B10: Dump/ Waste | C10: 1 | D10: 875 | E10: 0.1 | F10: =(D10*E10)+D10 -> 2420 | G10: =F10*C10 -> 2420
B11: Permits | C11: 1 | D11: 560 | E11: 0.1 | F11: =(D11*E11)+D11 -> 1210 | G11: =F11*C11 -> 1210
B12: Utility | C12: 1 | D12: 7500 | E12: 0.1 | F12: =(D12*E12)+D12 -> 0 | G12: =F12*C12 -> 0
B13: Construction Equipment | C13: 1 | D13: 12521 | E13: 0.1 | F13: =(D13*E13)+D13 -> 13787.502 | G13: =F13*C13 -> 13787.502
B14: Construction PM | C14: 1 | D14: 28505 | E14: 0
G15: =SUM(G3:G13) -> 88919.698
B17: ZERO IMPACT BUILDERS COSTS
B18: Labor | C18: =K5 -> 30 | D18: =K4 -> 2250 | E18: 0.1 | F18: =(D18*E18)+D18 -> 2475 | G18: =F18*C18 -> 74250
G19: =SUM(G18) -> 74250
C20: Total | G20: =G15+G19 -> 163169.7

Sheet EV_SUB 2P  208V
I4: PANEL SCHEDULE
C6: NAME | D6: EV_Main | F6: LOCATION | H6: OUTDOOR | J6: VOLTAGE | K6: =IF(L6=480,277,120) -> 277 | L6: 480 | M6: 3PH 4W | O6: MAIN | P6: =O36 -> 400 | Q6: =IF(O36<=1200,""&O36&"A 3P",""&O36&"A 3P") -> 400A 3P
F7: FED BY | H7: UTILITY | J7: ENCLOSURE | L7: NEMA3R | O7: BUS BAR | P7: =O36 -> 400 | Q7: A
F8: MOUNTING | H8: SURFACE | J8: PANEL TYPE | L8: NF | O8: MAIN AIC | P8: 65000
B11: CKT | C11: DESCRIPTION | E11: BREAKER | F11: POLES | G11: A | I11: B | K11: C | M11: POLES | N11: BREAKER | O11: DESCRIPTION | Q11: CKT
A12: A | B12: 1 | C12: =IF(MAX('INPUT SHEET CPM'!G3:L3)>=1,"EV CHARGER L3 #1","") | E12: =IF(MAX('INPUT SHEET CPM'!G3:L3)>=1,MAX('INPUT SHEET CPM'!G5:L5),"") | F12: =IF(MAX('INPUT SHEET CPM'!G3:L3)>=1,3,"") | G12: =IF(MAX('INPUT SHEET CPM'!G3:L3)>=1,MAX('INPUT SHEET CPM'!G4:L4),"") | H12: =IF(MAX('INPUT SHEET CPM'!G3:L3)>=2,MAX('INPUT SHEET CPM'!G4:L4),"") | M12: 3 | N12: 200 | O12: =IF(MAX('INPUT SHEET CPM'!G3:L3)>=2,"EV CHARGER L3 #2","") | Q12: 2 | R12: A
A13: B | B13: =B12+2 -> 3 | C13: --- | I13: =IF(MAX('INPUT SHEET CPM'!G3:L3)>=1,MAX('INPUT SHEET CPM'!G4:L4),"") | J13: =IF(MAX('INPUT SHEET CPM'!G3:L3)>=2,MAX('INPUT SHEET CPM'!G4:L4),"") | Q13: =Q12+2 -> 4 | R13: B
A14: C | B14: =B13+2 -> 5 | C14: --- | K14: =IF(MAX('INPUT SHEET CPM'!G3:L3)>=1,MAX('INPUT SHEET CPM'!G4:L4),"") | L14: =IF(MAX('INPUT SHEET CPM'!G3:L3)>=2,MAX('INPUT SHEET CPM'!G4:L4),"") | O14: --- | Q14: =Q13+2 -> 6 | R14: C
A15: A | B15: =B14+2 -> 7 | C15: =IF(MAX('INPUT SHEET CPM'!G3:L3)>=3,"EV CHARGER L3 #3","") | E15: =IF(MAX('INPUT SHEET CPM'!G3:L3)>=3,MAX('INPUT SHEET CPM'!G5:L5),"") | F15: =IF(MAX('INPUT SHEET CPM'!G3:L3)>=3,3,"") | G15: =IF(MAX('INPUT SHEET CPM'!G3:L3)>=3,MAX('INPUT SHEET CPM'!G4:L4),"") | H15: =IF(MAX('INPUT SHEET CPM'!G3:L3)>=4,MAX('INPUT SHEET CPM'!G4:L4),"") | M15: =IF(MAX('INPUT SHEET CPM'!G3:L3)>=4,3,"") | N15: =IF(MAX('INPUT SHEET CPM'!G3:L3)>=4,MAX('INPUT SHEET CPM'!G5:L5),"") | O15: =IF(MAX('INPUT SHEET CPM'!G3:L3)>=4,"EV CHARGER L3 #4","") | Q15: =Q14+2 -> 8 | R15: A
A16: B | B16: =B15+2 -> 9 | C16: --- | I16: =IF(MAX('INPUT SHEET CPM'!G3:L3)>=3,MAX('INPUT SHEET CPM'!G4:L4),"") | J16: =IF(MAX('INPUT SHEET CPM'!G3:L3)>=4,MAX('INPUT SHEET CPM'!G4:L4),"") | O16: --- | Q16: =Q15+2 -> 10 | R16: B
A17: C | B17: =B16+2 -> 11 | C17: --- | K17: =IF(MAX('INPUT SHEET CPM'!G3:L3)>=3,MAX('INPUT SHEET CPM'!G4:L4),"") | L17: =IF(MAX('INPUT SHEET CPM'!G3:L3)>=4,MAX('INPUT SHEET CPM'!G4:L4),"") | O17: --- | Q17: =Q16+2 -> 12 | R17: C
A18: A | B18: =B17+2 -> 13 | C18: =IF(MAX('INPUT SHEET CPM'!G3:L3)>=5,"EV CHARGER L3 #5","") | E18: =IF(MAX('INPUT SHEET CPM'!G3:L3)>=5,MAX('INPUT SHEET CPM'!G5:L5),"") | F18: =IF(MAX('INPUT SHEET CPM'!G3:L3)>=5,3,"") | G18: =IF(MAX('INPUT SHEET CPM'!G3:L3)>=5,MAX('INPUT SHEET CPM'!G4:L4),"") | H18: =IF(MAX('INPUT SHEET CPM'!G3:L3)>=6,MAX('INPUT SHEET CPM'!G4:L4),"") | M18: =IF(MAX('INPUT SHEET CPM'!G3:L3)>=6,3,"") | N18: =IF(MAX('INPUT SHEET CPM'!G3:L3)>=6,MAX('INPUT SHEET CPM'!G5:L5),"") | O18: =IF(MAX('INPUT SHEET CPM'!G3:L3)>=6,"EV CHARGER L3 #6","") | Q18: =Q17+2 -> 14 | R18: A
A19: B | B19: =B18+2 -> 15 | C19: --- | I19: =IF(MAX('INPUT SHEET CPM'!G3:L3)>=5,MAX('INPUT SHEET CPM'!G4:L4),"") | J19: =IF(MAX('INPUT SHEET CPM'!G3:L3)>=6,MAX('INPUT SHEET CPM'!G4:L4),"") | O19: --- | Q19: =Q18+2 -> 16 | R19: B
A20: C | B20: =B19+2 -> 17 | C20: --- | K20: =IF(MAX('INPUT SHEET CPM'!G3:L3)>=5,MAX('INPUT SHEET CPM'!G4:L4),"") | L20: =IF(MAX('INPUT SHEET CPM'!G3:L3)>=6,MAX('INPUT SHEET CPM'!G4:L4),"") | O20: --- | Q20: =Q19+2 -> 18 | R20: C
A21: A | B21: =B20+2 -> 19 | C21: =IF(MAX('INPUT SHEET CPM'!G3:L3)>=7,"EV CHARGER L3 #7","") | E21: =IF(MAX('INPUT SHEET CPM'!G3:L3)>=7,MAX('INPUT SHEET CPM'!G5:L5),"") | F21: =IF(MAX('INPUT SHEET CPM'!G3:L3)>=7,3,"") | G21: =IF(MAX('INPUT SHEET CPM'!G3:L3)>=7,MAX('INPUT SHEET CPM'!G4:L4),"") | H21: =IF(MAX('INPUT SHEET CPM'!G3:L3)>=8,MAX('INPUT SHEET CPM'!G4:L4),"") | M21: =IF(MAX('INPUT SHEET CPM'!G3:L3)>=8,3,"") | N21: =IF(MAX('INPUT SHEET CPM'!G3:L3)>=8,MAX('INPUT SHEET CPM'!G5:L5),"") | O21: =IF(MAX('INPUT SHEET CPM'!C3:L3)>=8,"EV CHARGER L3 #8","") | Q21: =Q20+2 -> 20 | R21: A
A22: B | B22: =B21+2 -> 21 | C22: --- | I22: =IF(MAX('INPUT SHEET CPM'!G3:L3)>=7,MAX('INPUT SHEET CPM'!G4:L4),"") | J22: =IF(MAX('INPUT SHEET CPM'!G3:L3)>=8,MAX('INPUT SHEET CPM'!G4:L4),"") | O22: --- | Q22: =Q21+2 -> 22 | R22: B
A23: C | B23: =B22+2 -> 23 | C23: --- | K23: =IF(MAX('INPUT SHEET CPM'!G3:L3)>=7,MAX('INPUT SHEET CPM'!G4:L4),"") | L23: =IF(MAX('INPUT SHEET CPM'!G3:L3)>=8,MAX('INPUT SHEET CPM'!G4:L4),"") | O23: --- | Q23: =Q22+2 -> 24 | R23: C
A24: A | B24: =B23+2 -> 25 | C24: =IF(MAX('INPUT SHEET CPM'!G3:L3)>=9,"EV CHARGER L3 #9","") | E24: =IF(MAX('INPUT SHEET CPM'!G3:L3)>=9,MAX('INPUT SHEET CPM'!G5:L5),"") | F24: =IF(MAX('INPUT SHEET CPM'!G3:L3)>=9,3,"") | G24: =IF(MAX('INPUT SHEET CPM'!G3:L3)>=9,MAX('INPUT SHEET CPM'!G4:L4),"") | H24: =IF(MAX('INPUT SHEET CPM'!G3:L3)>=10,MAX('INPUT SHEET CPM'!G4:L4),"") | M24: =IF(MAX('INPUT SHEET CPM'!G3:L3)>=10,3,"") | N24: =IF(MAX('INPUT SHEET CPM'!G3:L3)>=10,MAX('INPUT SHEET CPM'!G5:L5),"") | O24: =IF(MAX('INPUT SHEET CPM'!G3:L3)>=10,"EV CHARGER L3 #10","") | Q24: =Q23+2 -> 26 | R24: A
A25: B | B25: =B24+2 -> 27 | C25: --- | I25: =IF(MAX('INPUT SHEET CPM'!G3:L3)>=9,MAX('INPUT SHEET CPM'!G4:L4),"") | J25: =IF(MAX('INPUT SHEET CPM'!G3:L3)>=10,MAX('INPUT SHEET CPM'!G4:L4),"") | O25: --- | Q25: =Q24+2 -> 28 | R25: B
A26: C | B26: =B25+2 -> 29 | C26: --- | K26: =IF(MAX('INPUT SHEET CPM'!G3:L3)>=9,MAX('INPUT SHEET CPM'!G4:L4),"") | L26: =IF(MAX('INPUT SHEET CPM'!G3:L3)>=10,MAX('INPUT SHEET CPM'!G4:L4),"") | O26: --- | Q26: =Q25+2 -> 30 | R26: C
A27: A | B27: =B26+2 -> 31 | C27: =IF(MAX('INPUT SHEET CPM'!G3:L3)>=11,"EV CHARGER L3 #11","") | E27: =IF(MAX('INPUT SHEET CPM'!G3:L3)>=11,MAX('INPUT SHEET CPM'!G5:L5),"") | F27: =IF(MAX('INPUT SHEET CPM'!G3:L3)>=11,3,"") | G27: =IF(MAX('INPUT SHEET CPM'!G3:L3)>=11,MAX('INPUT SHEET CPM'!G4:L4),"") | H27: =IF(MAX('INPUT SHEET CPM'!G3:L3)>=12,MAX('INPUT SHEET CPM'!G4:L4),"") | M27: =IF(MAX('INPUT SHEET CPM'!G3:L3)>=12,3,"") | N27: =IF(MAX('INPUT SHEET CPM'!G3:L3)>=12,MAX('INPUT SHEET CPM'!G5:L5),"") | O27: =IF(MAX('INPUT SHEET CPM'!G3:L3)>=12,"EV CHARGER L3 #12","") | Q27: =Q26+2 -> 32 | R27: A
A28: B | B28: =B27+2 -> 33 | C28: --- | I28: =IF(MAX('INPUT SHEET CPM'!G3:L3)>=11,MAX('INPUT SHEET CPM'!G4:L4),"") | J28: =IF(MAX('INPUT SHEET CPM'!G3:L3)>=12,MAX('INPUT SHEET CPM'!G4:L4),"") | O28: --- | Q28: =Q27+2 -> 34 | R28: B
A29: C | B29: =B28+2 -> 35 | C29: --- | K29: =IF(MAX('INPUT SHEET CPM'!G3:L3)>=11,MAX('INPUT SHEET CPM'!G4:L4),"") | L29: =IF(MAX('INPUT SHEET CPM'!G3:L3)>=12,MAX('INPUT SHEET CPM'!G4:L4),"") | O29: --- | Q29: =Q28+2 -> 36 | R29: C
A30: A | B30: =B29+2 -> 37 | C30: =IF(MAX('INPUT SHEET CPM'!G3:L3)>=13,"EV CHARGER L3 #13","") | E30: =IF(MAX('INPUT SHEET CPM'!G3:L3)>=13,MAX('INPUT SHEET CPM'!G5:L5),"") | F30: =IF(MAX('INPUT SHEET CPM'!G3:L3)>=13,3,"") | G30: =IF(MAX('INPUT SHEET CPM'!G3:L3)>=14,MAX('INPUT SHEET CPM'!G4:L4),"") | H30: =IF(MAX('INPUT SHEET CPM'!G3:L3)>=14,MAX('INPUT SHEET CPM'!G4:L4),"") | M30: =IF(MAX('INPUT SHEET CPM'!G3:L3)>=14,3,"") | N30: =IF(MAX('INPUT SHEET CPM'!G3:L3)>=14,MAX('INPUT SHEET CPM'!G5:L5),"") | O30: =IF(MAX('INPUT SHEET CPM'!G3:L3)>=14,"EV CHARGER L3 #14","") | Q30: =Q29+2 -> 38 | R30: A
A31: B | B31: =B30+2 -> 39 | I31: =IF(MAX('INPUT SHEET CPM'!G3:L3)>=13,MAX('INPUT SHEET CPM'!G4:L4),"") | J31: =IF(MAX('INPUT SHEET CPM'!G3:L3)>=14,MAX('INPUT SHEET CPM'!G4:L4),"") | Q31: =Q30+2 -> 40 | R31: B
A32: C | B32: =B31+2 -> 41 | K32: =IF(MAX('INPUT SHEET CPM'!G3:L3)>=13,MAX('INPUT SHEET CPM'!G4:L4),"") | L32: =IF(MAX('INPUT SHEET CPM'!G3:L3)>=14,MAX('INPUT SHEET CPM'!G4:L4),"") | Q32: =Q31+2 -> 42 | R32: C
E33: TOTAL VA | G33: =SUM(G12:H32) -> 0 | I33: =SUM(I12:J32) -> 0 | K33: =SUM(K12:L32) -> 0 | M33: TOTAL 3PH VA | O33: =G33+I33+K33 -> 0
E34: DEMAND VA | G34: =G33*1.25 -> 0 | I34: =I33*1.25 -> 0 | K34: =K33*1.25 -> 0 | M34: TOTAL DEMAND VA | O34: =O33*1.25 -> 0
E35: HIGH PH VA | G35: =IF(MAX(G34,I34,K34)=G34,G34,0) -> 0 | I35: =IF(MAX(G34,I34,K34)=I34,I34,0) -> 0 | K35: =IF(MAX(G34,I34,K34)=K34,K34,0) -> 0 | M35: TOTAL AMP | O35: =ROUND(O34/(L6*SQRT(3)),1) -> 0
E36: HIGH PH AMP | G36: =IF(G35>0,ROUND(G35/277,1),"") | I36: =IF(I35>0,ROUND(I35/277,1),"") | K36: =IF(K35>0,ROUND(K35/277,1),"") | M36: MAIN BREAKER | O36: =_xlfn.IFS(O35<=400,400,O35<=600,600,O35<=800,800,O35<=1000,1000,O35<=1200,1200,O35<=1600,1600,O35<=2000,2000,O35<=3200,3200,O35<=4000,4000,O35<=5000,5000,O35<=10000,10000,TRUE,"EXCEEDS 10,000A") -> 400
I41: PANEL SCHEDULE
C43: NAME | D43: SB 2 | F43: LOCATION | H43: OUTDOOR | J43: VOLTAGE | K43: 120 | L43: 208 | M43: 3PH 4W | O43: MAIN | P43: 300 | Q43: A 3P
F44: FED BY | H44: UTILITY | J44: ENCLOSURE | L44: NEMA3R | O44: BUS BAR | P44: 300 | Q44: A
F45: MOUNTING | H45: SURFACE | J45: PANEL TYPE | L45: NF | O45: MAIN AIC | P45: 22000
B48: CKT | C48: DESCRIPTION | E48: BREAKER | F48: POLES | G48: A | I48: B | K48: C | M48: POLES | N48: BREAKER | O48: DESCRIPTION | Q48: CKT
A49: A | B49: 1 | C49: EV CHARGER L2 #1A | E49: 40 | F49: 2 | G49: =IF(MAX('INPUT SHEET CPM'!G3:L3)>=1,MAX('INPUT SHEET CPM'!G4:L4),"") | M49: 2 | N49: 40 | O49: EV CHARGER L2 #2A | Q49: 2 | R49: A
A50: B | B50: =B49+2 -> 3 | C50: --- | O50: --- | Q50: =Q49+2 -> 4 | R50: B
A51: C | B51: =B50+2 -> 5 | C51: EV CHARGER L2 #1B | E51: 40 | F51: 2 | M51: 2 | N51: 40 | O51: EV CHARGER L2 #2B | Q51: =Q50+2 -> 6 | R51: C
A52: A | B52: =B51+2 -> 7 | C52: --- | O52: --- | Q52: =Q51+2 -> 8 | R52: A
A53: B | B53: =B52+2 -> 9 | C53: EV CHARGER L2 #3A | E53: 40 | F53: 2 | M53: 2 | N53: 40 | O53: EV CHARGER L2 #4A | Q53: =Q52+2 -> 10 | R53: B
A54: C | B54: =B53+2 -> 11 | C54: --- | O54: --- | Q54: =Q53+2 -> 12 | R54: C
A55: A | B55: =B54+2 -> 13 | C55: EV CHARGER L2 #3B | E55: 40 | F55: 2 | M55: 2 | N55: 40 | O55: EV CHARGER L2 #4B | Q55: =Q54+2 -> 14 | R55: A
A56: B | B56: =B55+2 -> 15 | C56: --- | O56: --- | Q56: =Q55+2 -> 16 | R56: B
A57: C | B57: =B56+2 -> 17 | C57: EV CHARGER L2 #5A | E57: 40 | F57: 2 | M57: 2 | N57: 40 | O57: EV CHARGER L2 #6A | Q57: =Q56+2 -> 18 | R57: C
A58: A | B58: =B57+2 -> 19 | C58: --- | O58: --- | Q58: =Q57+2 -> 20 | R58: A
A59: B | B59: =B58+2 -> 21 | C59: EV CHARGER L2 #5B | E59: 40 | F59: 2 | M59: 2 | N59: 40 | O59: EV CHARGER L2 #6B | Q59: =Q58+2 -> 22 | R59: B
A60: C | B60: =B59+2 -> 23 | C60: --- | O60: --- | Q60: =Q59+2 -> 24 | R60: C
A61: A | B61: =B60+2 -> 25 | C61: --- | O61: --- | Q61: =Q60+2 -> 26 | R61: A
A62: B | B62: =B61+2 -> 27 | Q62: =Q61+2 -> 28 | R62: B
A63: C | B63: =B62+2 -> 29 | Q63: =Q62+2 -> 30 | R63: C
A64: A | B64: =B63+2 -> 31 | Q64: =Q63+2 -> 32 | R64: A
A65: B | B65: =B64+2 -> 33 | Q65: =Q64+2 -> 34 | R65: B
A66: C | B66: =B65+2 -> 35 | Q66: =Q65+2 -> 36 | R66: C
A67: A | B67: =B66+2 -> 37 | Q67: =Q66+2 -> 38 | R67: A
A68: B | B68: =B67+2 -> 39 | Q68: =Q67+2 -> 40 | R68: B
A69: C | B69: =B68+2 -> 41 | R69: C
A70: A | B70: =B69+2 -> 43 | R70: A
A71: B | B71: =B70+2 -> 45 | R71: B
A72: C | B72: =B71+2 -> 47 | R72: C
E74: TOTAL VA | G74: =SUM(G49:H73) -> 0 | I74: =SUM(I49:J73) -> 0 | K74: =SUM(K49:L73) -> 0 | M74: TOTAL 3PH VA | O74: =SUM(G49:L73) -> 0
E75: DEMAND VA | G75: =G74*1.25 -> 0 | I75: =I74*1.25 -> 0 | K75: =K74*1.25 -> 0 | M75: TOTAL DEMAND VA | O75: =O74 -> 0
E76: HIGH PH VA | G76: =IF(MAX(G75:L75)=G75,G75,0) -> 0 | I76: =IF(MAX(G75:L75)=I75,I75,0) -> 0 | K76: =IF(MAX(G75:L75)=K75,K75,0) -> 0 | M76: TOTAL AMP | O76: =O75/L43/1.732 -> 0
E77: HIGH PH AMP | G77: =G76/277 -> 0 | I77: =I76/277 -> 0 | K77: =K76/277 -> 0 | M77: MAIN BREAKER | O77: =_xlfn.IFS(O76<201,200,O76<401,400,O76<601,600,O76<801,800,O76<1001,1000,O76<1201,1200,O76<1601,1600,O76<2001,2000,O76<3001,3000,O76<4001,4000,O76<5001,5000,O76<6001,6000) -> 200

Sheet CPM Calcs
C2: CHARGER PLACEMENT AND DISTANCE FROM DISTRIBUTION | S2: DATE | W2: DATE | AC2: Rexel 3/20/26
Q3: Cu | S3: 46101 | U3: PVC | W3: 46101 | AC3: CU WIRE* | AG3: AL WIRE* | AK3: COND | AM3: PVC
B4: Material | C4: L2 | D4: Charger | E4: Distance | F4: Wire Length | G4: Wire Size | H4: Conduit Length | I4: Conduit Size | J4: Grounding | K4: Grounding Wire Size | L4: CAT 5 Cable | M4: Conduit Length | N4: Conduit Size | Q4: Wire | R4: Quantity | S4: Unit Cost | T4: Total | U4: Conduit | V4: Quantity | W4: Unit Cost | X4: Total | Y4: Grand Total | AC4: SIZE | AD4: TYPE | AE4: PRICE | AG4: SIZE | AH4: TYPE | AI4: PRICE | AK4: SIZE | AL4: EMT | AM4: SCH-40
C5: Dual | D5: 0 | E5: 0 | F5: =IF(C5="Dual",(E5*2)*2,(E5*2)) -> 0 | G5: =_xlfn.IFS($Q$3="Cu",_xlfn.IFS(E5<150,"8 AWG",E5<200,"6 AWG",E5<262,"4 AWG",E5<324,"2 AWG",E5>=325,"error"),$Q$3="Al",_xlfn.IFS(E5<150,"6 AWG",E5<200,"4 AWG",E5<262,"2 AWG",E5<324,"1 AWG",E5>=325,"error")) -> 8 AWG | H5: =E5 -> 0 | I5: =_xlfn.IFS(G5=$Q$6,$U$7,G5=$Q$8,$U$7,G5=$Q$9,$U$8,G5=$Q$7,$U$7,G5=$Q$10,$U$8,G5=$Q$11,$U$9,G5=$Q$12,$U$10,G5=$Q$13,$U$10,G5=$Q$14,$U$10,G5=$Q$15,$U$11,G5=$Q$16,$U$11,G5=$Q$17,$U$11,G5=$Q$18,$U$11,G5=$Q$20,$U$12) -> (1") | J5: =H5 -> 0 | K5: 10 AWG | L5: =J5 -> 0 | M5: =L5 -> 0 | N5: (3/4") | Q5: 10 AWG | R5: =SUMIF($G$5:$G$27,Q5,$F$5:$F$27)+SUMIF($G$33:$G$38,Q5,$F$33:$F$38)+SUMIF($G$44:$G$64,Q5,$F$44:$F$64)+SUMIF($K$5:$K$27,Q5,$J$5:$J$27)+SUMIF($K$44:$K$64,Q5,$J$44:$J$64)+SUMIF($K$33:$K$38,Q5,$J$33:$J$38) -> 0 | S5: =_xlfn.IFS($Q$3="Cu",IF( AE6="","",AE6/1000),$Q$3="Al",IF(AI5="","",AI5/1000)) -> 0.30329 | T5: =IF(S5="",0,R5*S5) -> 0 | U5: (1/2") | V5: =SUMIF($N$5:$N$27,U5,$M$5:$M$27)+SUMIF($I$33:I$38,U5,H$33:H$38)+SUMIF(I$5:I$27,U5,H$5:H$27)+SUMIF(I$44:I$64,U5,H$44:H$64)+SUMIF(N$44:N$64,U5,M$44:M$64) -> 0 | W5: =IF($U$3="PVC",AM6,AL6)/100 -> 0.2445 | X5: =V5*W5 -> 0 | Y5: =T5+X5 -> 0 | AC5: 10 SOL | AD5: THHN | AE5: 289.6 | AG5: 10 | AH5: XHHW | AI5: 280 | AK5: 3/8
Q6: 8 AWG | R6: =SUMIF($G$5:$G$27,Q6,$F$5:$F$27)+SUMIF($G$33:$G$38,Q6,$F$33:$F$38)+SUMIF($G$44:$G$91,Q6,$F$44:$F$91)+SUMIF($K$5:$K$27,Q6,$J$5:$J$27)+SUMIF($K$44:$K$91,Q6,$J$44:$J$91)+SUMIF($K$33:$K$38,Q6,$J$33:$J$38) -> 0 | S6: =_xlfn.IFS($Q$3="Cu",IF( AE7="","",AE7/1000),$Q$3="Al",IF(AI6="","",AI6/1000)) -> 0.56613 | T6: =IF(S6="",0,R6*S6) -> 0 | U6: (3/4") | V6: =SUMIF($N$5:$N$27,U6,$M$5:$M$27)+SUMIF($I$33:I$38,U6,H$33:H$38)+SUMIF(I$5:I$27,U6,H$5:H$27)+SUMIF(I$44:I$64,U6,H$44:H$64)+SUMIF(N$44:N$64,U6,M$44:M$64) -> 15 | W6: =IF($U$3="PVC",AM7,AL7)/100 -> 0.2912 | X6: =V6*W6 -> 4.368 | Y6: =T6+X6 -> 4.368 | AC6: 10 STR | AD6: THHN | AE6: 303.29 | AG6: 8 | AH6: XHHW | AK6: 1/2 | AL6: 46.62 | AM6: 24.45
Q7: 6 AWG | R7: =SUMIF($G$5:$G$27,Q7,$F$5:$F$27)+SUMIF($G$33:$G$38,Q7,$F$33:$F$38)+SUMIF($G$44:$G$91,Q7,$F$44:$F$91)+SUMIF($K$5:$K$27,Q7,$J$5:$J$27)+SUMIF($K$44:$K$91,Q7,$J$44:$J$91)+SUMIF($K$33:$K$38,Q7,$J$33:$J$38) -> 15 | S7: =_xlfn.IFS($Q$3="Cu",IF( AE8="","",AE8/1000),$Q$3="Al",IF(AI7="","",AI7/1000)) -> 0.87104 | T7: =IF(S7="",0,R7*S7) -> 13.0656 | U7: (1") | V7: =SUMIF($N$5:$N$27,U7,$M$5:$M$27)+SUMIF($I$33:I$38,U7,H$33:H$38)+SUMIF(I$5:I$27,U7,H$5:H$27)+SUMIF(I$44:I$64,U7,H$44:H$64)+SUMIF(N$44:N$64,U7,M$44:M$64) -> 0 | W7: =IF($U$3="PVC",AM8,AL8)/100 -> 0.4698 | X7: =V7*W7 -> 0 | Y7: =T7+X7 -> 13.0656 | AC7: 8 | AD7: THHN | AE7: 566.13 | AG7: 6 | AH7: XHHW | AI7: 306.36 | AK7: 3/4 | AL7: 79.72 | AM7: 29.12
Q8: 4 AWG | R8: =SUMIF($G$5:$G$27,Q8,$F$5:$F$27)+SUMIF($G$33:$G$38,Q8,$F$33:$F$38)+SUMIF($G$44:$G$91,Q8,$F$44:$F$91)+SUMIF($K$5:$K$27,Q8,$J$5:$J$27)+SUMIF($K$44:$K$91,Q8,$J$44:$J$91)+SUMIF($K$33:$K$38,Q8,$J$33:$J$38) -> 0 | S8: =_xlfn.IFS($Q$3="Cu",IF( AE9="","",AE9/1000),$Q$3="Al",IF(AI8="","",AI8/1000)) -> 1.33293 | T8: =IF(S8="",0,R8*S8) -> 0 | U8: (1 1/4") | V8: =SUMIF($N$5:$N$27,U8,$M$5:$M$27)+SUMIF($I$33:I$38,U8,H$33:H$38)+SUMIF(I$5:I$27,U8,H$5:H$27)+SUMIF(I$44:I$64,U8,H$44:H$64)+SUMIF(N$44:N$64,U8,M$44:M$64) -> 0 | W8: =IF($U$3="PVC",AM9,AL9)/100 -> 0.6155 | X8: =V8*W8 -> 0 | Y8: =T8+X8 -> 0 | AC8: 6 | AD8: THHN | AE8: 871.04 | AG8: 4 | AH8: XHHW | AI8: 379.98 | AK8: 1 | AL8: 139.78 | AM8: 46.98
Q9: 2 AWG | R9: =SUMIF($G$5:$G$27,Q9,$F$5:$F$27)+SUMIF($G$33:$G$38,Q9,$F$33:$F$38)+SUMIF($G$44:$G$91,Q9,$F$44:$F$91)+SUMIF($K$5:$K$27,Q9,$J$5:$J$27)+SUMIF($K$44:$K$91,Q9,$J$44:$J$91)+SUMIF($K$33:$K$38,Q9,$J$33:$J$38) -> 0 | S9: =_xlfn.IFS($Q$3="Cu",IF( AE11="","",AE11/1000),$Q$3="Al",IF(AI10="","",AI10/1000)) -> 2.1044 | T9: =IF(S9="",0,R9*S9) -> 0 | U9: (1 1/2") | V9: =SUMIF($N$5:$N$27,U9,$M$5:$M$27)+SUMIF($I$33:I$38,U9,H$33:H$38)+SUMIF(I$5:I$27,U9,H$5:H$27)+SUMIF(I$44:I$64,U9,H$44:H$64)+SUMIF(N$44:N$64,U9,M$44:M$64) -> 0 | W9: =IF($U$3="PVC",AM10,AL10)/100 -> 0.7129 | X9: =V9*W9 -> 0 | Y9: =T9+X9 -> 0 | AC9: 4 | AD9: THHN | AE9: 1332.93 | AG9: 3 | AH9: XHHW | AI9: 366.81 | AK9: 1-1/4 | AL9: 226.49 | AM9: 61.55
Q10: 1 AWG | R10: =SUMIF($G$5:$G$27,Q10,$F$5:$F$27)+SUMIF($G$33:$G$38,Q10,$F$33:$F$38)+SUMIF($G$44:$G$91,Q10,$F$44:$F$91)+SUMIF($K$5:$K$27,Q10,$J$5:$J$27)+SUMIF($K$44:$K$91,Q10,$J$44:$J$91)+SUMIF($K$33:$K$38,Q10,$J$33:$J$38) -> 0 | S10: =_xlfn.IFS($Q$3="Cu",IF( AE12="","",AE12/1000),$Q$3="Al",IF(AI11="","",AI11/1000)) -> 2.39833 | T10: =IF(S10="",0,R10*S10) -> 0 | U10: (2") | V10: =SUMIF($N$5:$N$27,U10,$M$5:$M$27)+SUMIF($I$33:I$38,U10,H$33:H$38)+SUMIF(I$5:I$27,U10,H$5:H$27)+SUMIF(I$44:I$64,U10,H$44:H$64)+SUMIF(N$44:N$64,U10,M$44:M$64) -> 15 | W10: =IF($U$3="PVC",AM11,AL11)/100 -> 0.8897 | X10: =V10*W10 -> 13.3455 | Y10: =T10+X10 -> 13.3455 | AC10: 3 | AD10: THHN | AE10: 1681.26 | AG10: 2 | AH10: XHHW | AI10: 482.1 | AK10: 1-1/2 | AL10: 276.41 | AM10: 71.29
Q11: 1 /0 | R11: =SUMIF($G$5:$G$27,Q11,$F$5:$F$27)+SUMIF($G$33:$G$38,Q11,$F$33:$F$38)+SUMIF($G$44:$G$91,Q11,$F$44:$F$91)+SUMIF($K$5:$K$27,Q11,$J$5:$J$27)+SUMIF($K$44:$K$91,Q11,$J$44:$J$91)+SUMIF($K$33:$K$38,Q11,$J$33:$J$38) -> 0 | S11: =_xlfn.IFS($Q$3="Cu",IF( AE13="","",AE13/1000),$Q$3="Al",IF(AI12="","",AI12/1000)) -> 2.95304 | T11: =IF(S11="",0,R11*S11) -> 0 | U11: (2 1/2") | V11: =SUMIF($N$5:$N$27,U11,$M$5:$M$27)+SUMIF($I$33:I$38,U11,H$33:H$38)+SUMIF(I$5:I$27,U11,H$5:H$27)+SUMIF(I$44:I$64,U11,H$44:H$64)+SUMIF(N$44:N$64,U11,M$44:M$64) -> 0 | W11: =IF($U$3="PVC",AM12,AL12)/100 -> 1.396 | X11: =V11*W11 -> 0 | Y11: =T11+X11 -> 0 | AC11: 2 | AD11: THHN | AE11: 2104.4 | AG11: 1 | AH11: XHHW | AI11: 667.33 | AK11: 2 | AL11: 315.97 | AM11: 88.97
Q12: 2 /0 | R12: =SUMIF($G$5:$G$27,Q12,$F$5:$F$27)+SUMIF($G$33:$G$38,Q12,$F$33:$F$38)+SUMIF($G$44:$G$91,Q12,$F$44:$F$91)+SUMIF($K$5:$K$27,Q12,$J$5:$J$27)+SUMIF($K$44:$K$91,Q12,$J$44:$J$91)+SUMIF($K$33:$K$38,Q12,$J$33:$J$38) -> 0 | S12: =_xlfn.IFS($Q$3="Cu",IF( AE14="","",AE14/1000),$Q$3="Al",IF(AI13="","",AI13/1000)) -> 3.63758 | T12: =IF(S12="",0,R12*S12) -> 0 | U12: (3") | V12: =SUMIF($N$5:$N$27,U12,$M$5:$M$27)+SUMIF($I$33:I$38,U12,H$33:H$38)+SUMIF(I$5:I$27,U12,H$5:H$27)+SUMIF(I$44:I$64,U12,H$44:H$64)+SUMIF(N$44:N$64,U12,M$44:M$64) -> 0 | W12: =IF($U$3="PVC",AM13,AL13)/100 -> 1.7033 | X12: =V12*W12 -> 0 | Y12: =T12+X12 -> 0 | AC12: 1 | AD12: THHN | AE12: 2398.33 | AG12: 1/0 | AH12: XHHW | AI12: 750.45 | AK12: 2-1/2 | AL12: 491.85 | AM12: 139.6
Q13: 3 /0 | R13: =SUMIF($G$5:$G$27,Q13,$F$5:$F$27)+SUMIF($G$33:$G$38,Q13,$F$33:$F$38)+SUMIF($G$44:$G$64,Q13,$F$44:$F$64)+SUMIF($K$5:$K$27,Q13,$J$5:$J$27)+SUMIF($K$44:$K$64,Q13,$J$44:$J$64)+SUMIF($K$33:$K$38,Q13,$J$33:$J$38) -> 45 | S13: =_xlfn.IFS($Q$3="Cu",IF( AE15="","",AE15/1000),$Q$3="Al",IF(AI14="","",AI14/1000)) -> 4.5658 | T13: =IF(S13="",0,R13*S13) -> 205.461 | U13: (3 1/2") | V13: =SUMIF($N$5:$N$27,U13,$M$5:$M$27)+SUMIF($I$33:I$38,U13,H$33:H$38)+SUMIF(I$5:I$27,U13,H$5:H$27)+SUMIF(I$44:I$64,U13,H$44:H$64)+SUMIF(N$44:N$64,U13,M$44:M$64) -> 0 | W13: =IF($U$3="PVC",AM14,AL14)/100 -> 2.25 | X13: =V13*W13 -> 0 | Y13: =T13+X13 -> 205.461 | AC13: 1/0 | AD13: THHN | AE13: 2953.04 | AG13: 2/0 | AH13: XHHW | AI13: 887.01 | AK13: 3 | AL13: 622.69 | AM13: 170.33
Q14: 4 /0 | R14: =SUMIF($G$5:$G$27,Q14,$F$5:$F$27)+SUMIF($G$33:$G$38,Q14,$F$33:$F$38)+SUMIF($G$44:$G$91,Q14,$F$44:$F$91)+SUMIF($K$5:$K$27,Q14,$J$5:$J$27)+SUMIF($K$44:$K$91,Q14,$J$44:$J$91)+SUMIF($K$33:$K$38,Q14,$J$33:$J$38) -> 0 | S14: =_xlfn.IFS($Q$3="Cu",IF( AE16="","",AE16/1000),$Q$3="Al",IF(AI15="","",AI15/1000)) -> 5.73045 | T14: =IF(S14="",0,R14*S14) -> 0 | U14: (4") | V14: =SUMIF($N$5:$N$27,U14,$M$5:$M$27)+SUMIF($I$33:I$38,U14,H$33:H$38)+SUMIF(I$5:I$27,U14,H$5:H$27)+SUMIF(I$44:I$64,U14,H$44:H$64)+SUMIF(N$44:N$64,U14,M$44:M$64) -> 0 | W14: =IF($U$3="PVC",AM15,AL15)/100 -> 2.3164 | X14: =V14*W14 -> 0 | Y14: =T14+X14 -> 0 | AC14: 2/0 | AD14: THHN | AE14: 3637.58 | AG14: 3/0 | AH14: XHHW | AI14: 1099.56 | AK14: 3-1/2 | AL14: 822.39 | AM14: 225
Q15: 250 KCMIL | R15: =SUMIF($G$5:$G$27,Q15,$F$5:$F$27)+SUMIF($G$33:$G$38,Q15,$F$33:$F$38)+SUMIF($G$44:$G$91,Q15,$F$44:$F$91)+SUMIF($K$5:$K$27,Q15,$J$5:$J$27)+SUMIF($K$44:$K$91,Q15,$J$44:$J$91)+SUMIF($K$33:$K$38,Q15,$J$33:$J$38) -> 0 | S15: =_xlfn.IFS($Q$3="Cu",IF( AE17="","",AE17/1000),$Q$3="Al",IF(AI16="","",AI16/1000)) -> 6.64016 | T15: =IF(S15="",0,R15*S15) -> 0 | U15: (5") | V15: =SUMIF($N$5:$N$27,U15,$M$5:$M$27)+SUMIF($I$33:I$38,U15,H$33:H$38)+SUMIF(I$5:I$27,U15,H$5:H$27)+SUMIF(I$44:I$64,U15,H$44:H$64)+SUMIF(N$44:N$64,U15,M$44:M$64) -> 0 | W15: =IF($U$3="PVC",AM16,AL16)/100 -> 3.3106 | X15: =V15*W15 -> 0 | Y15: =T15+X15 -> 0 | AC15: 3/0 | AD15: THHN | AE15: 4565.8 | AG15: 4/0 | AH15: XHHW | AI15: 1227.8 | AK15: 4 | AL15: 827.46 | AM15: 231.64
Q16: 300 KCMIL | R16: =SUMIF($G$5:$G$27,Q16,$F$5:$F$27)+SUMIF($G$33:$G$38,Q16,$F$33:$F$38)+SUMIF($G$44:$G$91,Q16,$F$44:$F$91)+SUMIF($K$5:$K$27,Q16,$J$5:$J$27)+SUMIF($K$44:$K$91,Q16,$J$44:$J$91)+SUMIF($K$33:$K$38,Q16,$J$33:$J$38) -> 0 | S16: =_xlfn.IFS($Q$3="Cu",IF( AE18="","",AE18/1000),$Q$3="Al",IF(AI17="","",AI17/1000)) -> 7.9632 | T16: =IF(S16="",0,R16*S16) -> 0 | Y16: =T16+X16 -> 0 | AC16: 4/0 | AD16: THHN | AE16: 5730.45 | AG16: 250 | AH16: XHHW | AI16: 1496.16 | AK16: 5 | AM16: 331.06
Q17: 350 KCMIL | R17: =SUMIF($G$5:$G$27,Q17,$F$5:$F$27)+SUMIF($G$33:$G$38,Q17,$F$33:$F$38)+SUMIF($G$44:$G$91,Q17,$F$44:$F$91)+SUMIF($K$5:$K$27,Q17,$J$5:$J$27)+SUMIF($K$44:$K$91,Q17,$J$44:$J$91)+SUMIF($K$33:$K$38,Q17,$J$33:$J$38) -> 0 | S17: =_xlfn.IFS($Q$3="Cu",IF( AE19="","",AE19/1000),$Q$3="Al",IF(AI18="","",AI18/1000)) -> 9.32416 | T17: =IF(S17="",0,R17*S17) -> 0 | Y17: =T17+X17 -> 0 | AC17: 250 | AD17: THHN | AE17: 6640.16 | AG17: 300 | AH17: XHHW | AI17: 2061.37 | AK17: 6
Q18: 400 KCMIL | R18: =SUMIF($G$5:$G$27,Q18,$F$5:$F$27)+SUMIF($G$33:$G$38,Q18,$F$33:$F$38)+SUMIF($G$44:$G$91,Q18,$F$44:$F$91)+SUMIF($K$5:$K$27,Q18,$J$5:$J$27)+SUMIF($K$44:$K$91,Q18,$J$44:$J$91)+SUMIF($K$33:$K$38,Q18,$J$33:$J$38) -> 0 | S18: =_xlfn.IFS($Q$3="Cu",IF( AE20="","",AE20/1000),$Q$3="Al",IF(AI19="","",AI19/1000)) -> 10.60671 | T18: =IF(S18="",0,R18*S18) -> 0 | Y18: =T18+X18 -> 0 | AC18: 300 | AD18: THHN | AE18: 7963.2 | AG18: 350 | AH18: XHHW | AI18: 2104.12
Q19: 450 KCMIL | R19: =SUMIF($G$5:$G$27,Q19,$F$5:$F$27)+SUMIF($G$33:$G$38,Q19,$F$33:$F$38)+SUMIF($G$44:$G$91,Q19,$F$44:$F$91)+SUMIF($K$5:$K$27,Q19,$J$5:$J$27)+SUMIF($K$44:$K$91,Q19,$J$44:$J$91)+SUMIF($K$33:$K$38,Q19,$J$33:$J$38) -> 0 | S19: =_xlfn.IFS($Q$3="Cu",IF( AE21="","",AE21/1000),$Q$3="Al",IF(AI20="","",AI20/1000)) -> 11.334 | T19: =IF(S19="",0,R19*S19) -> 0 | Y19: =T19+X19 -> 0 | AC19: 350 | AD19: THHN | AE19: 9324.16 | AG19: 400 | AH19: XHHW | AI19: 2457.97
Q20: 500 KCMIL | R20: =SUMIF($G$5:$G$27,Q20,$F$5:$F$27)+SUMIF($G$33:$G$38,Q20,$F$33:$F$38)+SUMIF($G$44:$G$91,Q20,$F$44:$F$91)+SUMIF($K$5:$K$27,Q20,$J$5:$J$27)+SUMIF($K$44:$K$91,Q20,$J$44:$J$91)+SUMIF($K$33:$K$38,Q20,$J$33:$J$38) -> 0 | S20: =_xlfn.IFS($Q$3="Cu",IF( AE22="","",AE22/1000),$Q$3="Al",IF(AI21="","",AI21/1000)) -> 13.30059 | T20: =IF(S20="",0,R20*S20) -> 0 | Y20: =T20+X20 -> 0 | AC20: 400 | AD20: THHN | AE20: 10606.71 | AG20: 450 | AH20: XHHW
Q21: 600 KCMIL | R21: =SUMIF($G$5:$G$27,Q21,$F$5:$F$27)+SUMIF($G$33:$G$38,Q21,$F$33:$F$38)+SUMIF($G$44:$G$91,Q21,$F$44:$F$91)+SUMIF($K$5:$K$27,Q21,$J$5:$J$27)+SUMIF($K$44:$K$91,Q21,$J$44:$J$91)+SUMIF($K$33:$K$38,Q21,$J$33:$J$38) -> 0 | S21: =_xlfn.IFS($Q$3="Cu",IF( AE23="","",AE23/1000),$Q$3="Al",IF(AI22="","",AI22/1000)) -> 16.57382 | T21: =IF(S21="",0,R21*S21) -> 0 | Y21: =T21+X21 -> 0 | AC21: 450 | AD21: THHN | AE21: 11334 | AG21: 500 | AH21: XHHW | AI21: 2720.4
Q22: 700 KCMIL | R22: =SUMIF($G$5:$G$27,Q22,$F$5:$F$27)+SUMIF($G$33:$G$38,Q22,$F$33:$F$38)+SUMIF($G$44:$G$91,Q22,$F$44:$F$91)+SUMIF($K$5:$K$27,Q22,$J$5:$J$27)+SUMIF($K$44:$K$91,Q22,$J$44:$J$91)+SUMIF($K$33:$K$38,Q22,$J$33:$J$38) -> 0 | S22: =_xlfn.IFS($Q$3="Cu",IF( AE24="","",AE24/1000),$Q$3="Al",IF(AI23="","",AI23/1000)) | T22: =IF(S22="",0,R22*S22) -> 0 | Y22: =T22+X22 -> 0 | AC22: 500 | AD22: THHN | AE22: 13300.59 | AG22: 600 | AH22: XHHW | AI22: 3443.54
Q23: 750 KCMIL | R23: =SUMIF($G$5:$G$27,Q23,$F$5:$F$27)+SUMIF($G$33:$G$38,Q23,$F$33:$F$38)+SUMIF($G$44:$G$91,Q23,$F$44:$F$91)+SUMIF($K$5:$K$27,Q23,$J$5:$J$27)+SUMIF($K$44:$K$91,Q23,$J$44:$J$91)+SUMIF($K$33:$K$38,Q23,$J$33:$J$38) -> 0 | S23: =_xlfn.IFS($Q$3="Cu",IF( AE25="","",AE25/1000),$Q$3="Al",IF(AI24="","",AI24/1000)) -> 25.921 | T23: =IF(S23="",0,R23*S23) -> 0 | Y23: =T23+X23 -> 0 | AC23: 600 | AD23: THHN | AE23: 16573.82 | AG23: 700 | AH23: XHHW | AI23: 4809
Q24: 800 KCMIL | R24: =SUMIF($G$5:$G$27,Q24,$F$5:$F$27)+SUMIF($G$33:$G$38,Q24,$F$33:$F$38)+SUMIF($G$44:$G$91,Q24,$F$44:$F$91)+SUMIF($K$5:$K$27,Q24,$J$5:$J$27)+SUMIF($K$44:$K$91,Q24,$J$44:$J$91)+SUMIF($K$33:$K$38,Q24,$J$33:$J$38) -> 0 | S24: =_xlfn.IFS($Q$3="Cu",IF( AE26="","",AE26/1000),$Q$3="Al",IF(AI25="","",AI25/1000)) | T24: =IF(S24="",0,R24*S24) -> 0 | Y24: =T24+X24 -> 0 | AC24: 700 | AD24: THHN | AG24: 750 | AH24: XHHW | AI24: 4859
Q25: 900 KCMIL | R25: =SUMIF($G$5:$G$27,Q25,$F$5:$F$27)+SUMIF($G$33:$G$38,Q25,$F$33:$F$38)+SUMIF($G$44:$G$91,Q25,$F$44:$F$91)+SUMIF($K$5:$K$27,Q25,$J$5:$J$27)+SUMIF($K$44:$K$91,Q25,$J$44:$J$91)+SUMIF($K$33:$K$38,Q25,$J$33:$J$38) -> 0 | S25: =_xlfn.IFS($Q$3="Cu",IF( AE27="","",AE27/1000),$Q$3="Al",IF(AI26="","",AI26/1000)) | T25: =IF(S25="",0,R25*S25) -> 0 | Y25: =T25+X25 -> 0 | AC25: 750 | AD25: THHN | AE25: 25921 | AG25: 800 | AH25: XHHW
Q26: 1000 KCMIL | R26: =SUMIF($G$5:$G$27,Q26,$F$5:$F$27)+SUMIF($G$33:$G$38,Q26,$F$33:$F$38)+SUMIF($G$44:$G$91,Q26,$F$44:$F$91)+SUMIF($K$5:$K$27,Q26,$J$5:$J$27)+SUMIF($K$44:$K$91,Q26,$J$44:$J$91)+SUMIF($K$33:$K$38,Q26,$J$33:$J$38) -> 0 | S26: =_xlfn.IFS($Q$3="Cu",IF( AE28="","",AE28/1000),$Q$3="Al",IF(AI27="","",AI27/1000)) -> 34.398 | T26: =IF(S26="",0,R26*S26) -> 0 | Y26: =T26+X26 -> 0 | AC26: 800 | AD26: THHN | AG26: 900 | AH26: XHHW | AI26: 7566
Y27: =SUM(Y5:Y26)+SUM(Y33:Y54) -> 236.2401 | AC27: 900 | AD27: THHN | AG27: 1000 | AH27: XHHW | AI27: 6668
C28: Total | E28: =SUM(E5:E27) -> 0 | F28: =SUM(F5:F27) -> 0 | H28: =SUM(H5:H27) -> 0 | J28: =MAX(J5:J27) -> 0 | L28: =SUM(L5:L27) -> 0 | M28: =SUM(M5:M27) -> 0 | AC28: 1000 | AD28: THHN | AE28: 34398
Q29: Manual Entry only
C30: PANEL PLACEMENT AND DISTANCE FROM DISTRIBUTION | S30: DATE | W30: DATE
Q31: Al | S31: 46101 | U31: PVC | W31: 46101 | AC31: 3/20/26 | AE31: 480V | AK31: 208V
C32: Size | D32: Panel | E32: Distance | F32: Wire Length | G32: Wire Size | H32: Conduit Length | I32: Conduit Size | J32: Grounding | K32: Grounding Wire Size | L32: Runs | Q32: Wire | R32: Quantity | S32: Unit Cost | T32: Total | U32: Conduit | V32: Quantity | W32: Unit Cost | X32: Total | Y32: Grand Total | AC32: SN | AD32: Description | AE32: Size | AF32: Cost | AG32: Voltage | AI32: 20 | AJ32: Main | AK32: 350A | AL32: 14500 | AN32: 208V
C33: Pole - TX | D33: 1 | E33: 0 | F33: =(E33*4)*L33 -> 0 | G33: 600 KCMIL | H33: =E33*L33 -> 0 | I33: =_xlfn.IFS(G33=$Q$6,$U$6,G33=$Q$8,$U$7,G33=$Q$9,$U$8,G33=$Q$7,$U$7,G33=$Q$10,$U$8,G33=$Q$11,$U$9,G33=$Q$12,$U$10,G33=$Q$13,$U$10,G33=$Q$14,$U$10,G33=$Q$15,$U$11,G33=$Q$16,$U$11,G33=$Q$17,$U$11,G33=$Q$18,$U$11,G33=$Q$20,$U$12,G33=$Q$21,$U$14,G33=$Q$23,$U$14) -> (4") | J33: =E33*L33*0 -> 0 | K33: 4 AWG | L33: 1 | M33: Cu | Q33: 10 AWG | S33: =_xlfn.IFS($Q$31="Cu",IF( AE6="","",AE6/1000),$Q$31="Al",IF(AI5="","",AI5/1000)) -> 0.28 | T33: =IF(S33="",0,R33*S33) -> 0 | U33: (1/2") | W33: =IF($U$31="PVC",AM6,AL6)/100 -> 0.2445 | X33: =V33*W33 -> 0 | Y33: =T33+X33 -> 0 | AI33: 21 | AJ33: breakers | AK33: 40A | AL33: 180 | AN33: 208V
C34: TX - SG | D34: 2 | E34: 0 | F34: =(E34*4)*L34 -> 0 | G34: 600 KCMIL | H34: =E34*(L34+1) -> 0 | I34: =_xlfn.IFS(G34=$Q$6,$U$6,G34=$Q$8,$U$7,G34=$Q$9,$U$8,G34=$Q$7,$U$7,G34=$Q$10,$U$8,G34=$Q$11,$U$9,G34=$Q$12,$U$10,G34=$Q$13,$U$10,G34=$Q$14,$U$10,G34=$Q$15,$U$11,G34=$Q$16,$U$11,G34=$Q$17,$U$11,G34=$Q$18,$U$11,G34=$Q$20,$U$12,G34=$Q$21,$U$14,G34=$Q$23,$U$14) -> (4") | J34: =E34*L34*0 -> 0 | K34: 4 AWG | L34: 3 | Q34: 8 AWG | S34: =_xlfn.IFS($Q$31="Cu",IF( AE7="","",AE7/1000),$Q$31="Al",IF(AI6="","",AI6/1000)) | T34: =IF(S34="",0,R34*S34) -> 0 | U34: (3/4") | W34: =IF($U$31="PVC",AM7,AL7)/100 -> 0.2912 | X34: =V34*W34 -> 0 | Y34: =T34+X34 -> 0 | AC34: 1 | AD34: Main | AE34: 400A | AF34: 20426.82 | AG34: 480V
Q35: 6 AWG | S35: =_xlfn.IFS($Q$31="Cu",IF( AE8="","",AE8/1000),$Q$31="Al",IF(AI7="","",AI7/1000)) -> 0.30636 | T35: =IF(S35="",0,R35*S35) -> 0 | U35: (1") | W35: =IF($U$31="PVC",AM8,AL8)/100 -> 0.4698 | X35: =V35*W35 -> 0 | Y35: =T35+X35 -> 0 | AC35: 2 | AD35: Main | AE35: 800A | AF35: 31187 | AG35: 480V | AI35: 22 | AJ35: main breakers | AK35: 400A | AL35: 1900 | AN35: 208V
Q36: 4 AWG | S36: =_xlfn.IFS($Q$31="Cu",IF( AE9="","",AE9/1000),$Q$31="Al",IF(AI8="","",AI8/1000)) -> 0.37998 | T36: =IF(S36="",0,R36*S36) -> 0 | U36: (1 1/4") | W36: =IF($U$31="PVC",AM9,AL9)/100 -> 0.6155 | X36: =V36*W36 -> 0 | Y36: =T36+X36 -> 0 | AC36: 3 | AD36: Main | AE36: 1000A | AF36: 36812.5 | AG36: 480V | AI36: 23 | AJ36: main breakers | AK36: 600A | AL36: 3400 | AN36: 208V
Q37: 2 AWG | S37: =_xlfn.IFS($Q$31="Cu",IF( AE10="","",AE10/1000),$Q$31="Al",IF(AI9="","",AI9/1000)) -> 0.36681 | T37: =IF(S37="",0,R37*S37) -> 0 | U37: (1 1/2") | W37: =IF($U$31="PVC",AM10,AL10)/100 -> 0.7129 | X37: =V37*W37 -> 0 | Y37: =T37+X37 -> 0 | AC37: 4 | AD37: Main | AE37: 1200A | AF37: 43292.68 | AG37: 480V
Q38: 1 AWG | S38: =_xlfn.IFS($Q$31="Cu",IF( AE11="","",AE11/1000),$Q$31="Al",IF(AI10="","",AI10/1000)) -> 0.4821 | T38: =IF(S38="",0,R38*S38) -> 0 | U38: (2") | W38: =IF($U$31="PVC",AM11,AL11)/100 -> 0.8897 | X38: =V38*W38 -> 0 | Y38: =T38+X38 -> 0 | AC38: 5 | AD38: Main | AE38: 1600A | AF38: 56750 | AG38: 480V | AI38: 24 | AJ38: Transformer | AK38: 75KVA | AL38: 2970 | AN38: 208V
C39: Total | E39: =SUM(E33:E38) -> 0 | F39: =SUM(F33:F38) -> 0 | H39: =SUM(H33:H37) -> 0 | J39: =SUM(J33:J38) -> 0 | Q39: 1 /0 | S39: =_xlfn.IFS($Q$31="Cu",IF( AE12="","",AE12/1000),$Q$31="Al",IF(AI11="","",AI11/1000)) -> 0.66733 | T39: =IF(S39="",0,R39*S39) -> 0 | U39: (2 1/2") | W39: =IF($U$31="PVC",AM12,AL12)/100 -> 1.396 | X39: =V39*W39 -> 0 | Y39: =T39+X39 -> 0 | AC39: 7 | AD39: Main | AE39: 2000A | AF39: 60000 | AG39: 480V | AI39: 25 | AJ39: Transformer | AK39: 112.5KVA | AL39: 3250 | AN39: 208V
Q40: 2 /0 | S40: =_xlfn.IFS($Q$31="Cu",IF( AE13="","",AE13/1000),$Q$31="Al",IF(AI12="","",AI12/1000)) -> 0.75045 | T40: =IF(S40="",0,R40*S40) -> 0 | U40: (3") | W40: =IF($U$31="PVC",AM13,AL13)/100 -> 1.7033 | X40: =V40*W40 -> 0 | Y40: =T40+X40 -> 0 | AC40: 8 | AD40: Main | AE40: 2500 | AF40: 58540 | AG40: 480V | AI40: 26 | AJ40: Transformer | AK40: 150KVA | AL40: 5298 | AN40: 208V
C41: CHARGER PLACEMENT AND DISTANCE FROM DISTRIBUTION | Q41: 3 /0 | S41: =_xlfn.IFS($Q$31="Cu",IF( AE14="","",AE14/1000),$Q$31="Al",IF(AI13="","",AI13/1000)) -> 0.88701 | T41: =IF(S41="",0,R41*S41) -> 0 | U41: (3 1/2") | W41: =IF($U$31="PVC",AM14,AL14)/100 -> 2.25 | X41: =V41*W41 -> 0 | Y41: =T41+X41 -> 0 | AC41: 9 | AD41: Main | AE41: 3000A | AF41: 65000 | AG41: 480V | AI41: 27 | AJ41: Transformer | AK41: 175KVA | AL41: 6000 | AN41: 208V
Q42: 4 /0 | S42: =_xlfn.IFS($Q$31="Cu",IF( AE15="","",AE15/1000),$Q$31="Al",IF(AI14="","",AI14/1000)) -> 1.09956 | T42: =IF(S42="",0,R42*S42) -> 0 | U42: (4") | W42: =IF($U$31="PVC",AM15,AL15)/100 -> 2.3164 | X42: =V42*W42 -> 0 | Y42: =T42+X42 -> 0 | AC42: 10 | AD42: Main | AE42: 4000A | AF42: 67500 | AG42: 480V | AI42: 28 | AJ42: Transformer | AK42: 225KVA | AL42: 7144 | AN42: 208V
C43: L3 | D43: Charger | E43: Distance | F43: Wire Length | G43: Wire Size | H43: Conduit Length | I43: Conduit Size | J43: Grounding | K43: Grounding Wire Size | L43: CAT 5 Cable | M43: Conduit Length | N43: Conduit Size | Q43: 250 KCMIL | S43: =_xlfn.IFS($Q$31="Cu",IF( AE16="","",AE16/1000),$Q$31="Al",IF(AI15="","",AI15/1000)) -> 1.2278 | T43: =IF(S43="",0,R43*S43) -> 0 | U43: (5") | W43: =IF($U$31="PVC",AM16,AL16)/100 -> 3.3106 | X43: =V43*W43 -> 0 | Y43: =T43+X43 -> 0 | AC43: 11 | AD43: Main | AE43: 5000A | AF43: 70000 | AG43: 480V | AI43: 29 | AJ43: Transformer | AK43: 300KVA | AL43: 10493 | AN43: 208V
C44: 100kW | D44: 0 | E44: 15 | F44: =(E44*3)*IF(OR(C44="50kw",C44="60kw",C44="100kw",C44="120kw",C44="160kw"),1,2) -> 45 | G44: =IF($Q$3="Al",_xlfn.IFS(OR(C44="100kW",C44="120kW"), IF($U$3="PVC",$Q$15, $Q$14),OR(C44="50kW",C44="60kW"), IF($U$3="PVC",$Q$10,$Q$9),C44="160kW", $Q$26,C44="300kw",$Q$17,C44="360kw",$Q$20),_xlfn.IFS(OR(C44="100kW",C44="120kW"), IF($U$3="PVC",$Q$13, $Q$13),OR(C44="50kW",C44="60kW"), IF($U$3="PVC",$Q$10,$Q$10),C44="160kW", $Q$21,C44="300kw",$Q$15,C44="360kw",$Q$17)) -> 3 /0 | H44: =E44*IF(OR(C44="50kw",C44="60kw",C44="100kw",C44="120kw",C44="160kw"),1,2) -> 15 | I44: =_xlfn.IFS(G44=$Q$6,$U$6,G44=$Q$8,$U$7,G44=$Q$9,$U$8,G44=$Q$7,$U$7,G44=$Q$10,$U$9,G44=$Q$11,$U$9,G44=$Q$12,$U$10,G44=$Q$13,$U$10,G44=$Q$14,$U$10,G44=$Q$15,$U$11,G44=$Q$16,$U$11,G44=$Q$17,$U$11,G44=$Q$18,$U$12,G44=$Q$21,$U$12) -> (2") | J44: =H44 -> 15 | K44: =IF($Q$3="Al",_xlfn.IFS(OR(C44="100kW",C44="120kW"),$Q$9,OR(C44="50kW", C44="60kW"), $Q$7,C44="160kW", $Q$10,C44="300kW",$Q$11,C44="360kW",$Q$12),_xlfn.IFS(OR(C44="100kW",C44="120kW"),$Q$7,OR(C44="50kW", C44="60kW"), $Q$6,C44="160kW", $Q$8,C44="300kW",$Q$9,C44="360kW",$Q$10)) -> 6 AWG | L44: =E44 -> 15 | M44: =L44 -> 15 | N44: (3/4") | Q44: 300 KCMIL | S44: =_xlfn.IFS($Q$31="Cu",IF( AE17="","",AE17/1000),$Q$31="Al",IF(AI16="","",AI16/1000)) -> 1.49616 | T44: =IF(S44="",0,R44*S44) -> 0 | Y44: =T44+X44 -> 0 | AI44: 30 | AJ44: Transformer | AK44: 500KVA | AL44: 14500 | AN44: 208V
Q45: 350 KCMIL | S45: =_xlfn.IFS($Q$31="Cu",IF( AE18="","",AE18/1000),$Q$31="Al",IF(AI17="","",AI17/1000)) -> 2.06137 | T45: =IF(S45="",0,R45*S45) -> 0 | Y45: =T45+X45 -> 0 | AC45: 12 | AD45: main breakers | AE45: 110A | AF45: 650 | AG45: 480V
Q46: 400 KCMIL | S46: =_xlfn.IFS($Q$31="Cu",IF( AE19="","",AE19/1000),$Q$31="Al",IF(AI18="","",AI18/1000)) -> 2.10412 | T46: =IF(S46="",0,R46*S46) -> 0 | Y46: =T46+X46 -> 0 | AC46: 13 | AD46: main breakers | AE46: 125A | AF46: 700 | AG46: 480V | AI46: 31 | AJ46: sub-Panel | AK46: 150A | AL46: 1000 | AN46: 208V
Q47: 450 KCMIL | S47: =_xlfn.IFS($Q$31="Cu",IF( AE20="","",AE20/1000),$Q$31="Al",IF(AI21="","",AI21/1000)) -> 2.7204 | T47: =IF(S47="",0,R47*S47) -> 0 | Y47: =T47+X47 -> 0 | AC47: 14 | AD47: main breakers | AE47: 250A | AF47: 1100 | AG47: 480V | AI47: 32 | AJ47: sub-Panel | AK47: 250A | AL47: 1120 | AN47: 208V
Q48: 500 KCMIL | S48: =_xlfn.IFS($Q$31="Cu",IF( AE21="","",AE21/1000),$Q$31="Al",IF(AI21="","",AI21/1000)) -> 2.7204 | T48: =IF(S48="",0,R48*S48) -> 0 | Y48: =T48+X48 -> 0 | AC48: 15 | AD48: main breakers | AE48: 3000A | AF48: 32500 | AG48: 480V | AI48: 33 | AJ48: sub-Panel | AK48: 400A | AL48: 1660 | AN48: 208V
Q49: 600 KCMIL | S49: =_xlfn.IFS($Q$31="Cu",IF( AE22="","",AE22/1000),$Q$31="Al",IF(AI21="","",AI21/1000)) -> 2.7204 | T49: =IF(S49="",0,R49*S49) -> 0 | Y49: =T49+X49 -> 0 | AC49: 16 | AI49: 34 | AJ49: sub-Panel | AK49: 600A | AL49: 5387 | AM49: 20ea 40A | AN49: 208V
Q50: 700 KCMIL | S50: =_xlfn.IFS($Q$31="Cu",IF( AE23="","",AE23/1000),$Q$31="Al",IF(AI22="","",AI22/1000)) -> 3.44354 | T50: =IF(S50="",0,R50*S50) -> 0 | Y50: =T50+X50 -> 0 | AC50: 17 | AD50: breakers | AE50: 100A | AF50: 580 | AG50: 480V | AI50: 35 | AJ50: sub-Panel | AK50: 800A | AL50: 4650 | AN50: 208V
Q51: 750 KCMIL | S51: =_xlfn.IFS($Q$31="Cu",IF( AE24="","",AE24/1000),$Q$31="Al",IF(AI23="","",AI23/1000)) -> 4.809 | T51: =IF(S51="",0,R51*S51) -> 0 | Y51: =T51+X51 -> 0 | AC51: 18 | AD51: breakers | AE51: 200A | AF51: 900 | AG51: 480V
Q52: 800 KCMIL | S52: =_xlfn.IFS($Q$31="Cu",IF( AE25="","",AE25/1000),$Q$31="Al",IF(AI24="","",AI24/1000)) -> 4.859 | T52: =IF(S52="",0,R52*S52) -> 0 | Y52: =T52+X52 -> 0 | AC52: 19 | AD52: breakers | AE52: 300A | AF52: 1450 | AG52: 480V | AI52: 36 | AJ52: Distribution panel | AK52: 1000A | AL52: 30000 | AN52: 208V
Q53: 900 KCMIL | S53: =_xlfn.IFS($Q$31="Cu",IF( AE26="","",AE26/1000),$Q$31="Al",IF(AI25="","",AI25/1000)) | T53: =IF(S53="",0,R53*S53) -> 0 | Y53: =T53+X53 -> 0 | AC53: 20 | AD53: breakers | AE53: 500A | AF53: 3100 | AG53: 480V
Q54: 1000 KCMIL | S54: =_xlfn.IFS($Q$31="Cu",IF( AE27="","",AE27/1000),$Q$31="Al",IF(AI26="","",AI26/1000)) -> 7.566 | T54: =IF(S54="",0,R54*S54) -> 0 | Y54: =T54+X54 -> 0 | AC54: 21 | AD54: breakers | AE54: 600A | AF54: 3700 | AG54: 480V | AI54: 37 | AJ54: Meter socket | AK54: 600A | AL54: 1786 | AN54: 208V
O58: 1
C65: Total | E65: =SUM(E44:E64) -> 15 | F65: =SUM(F44:F64) -> 45 | H65: =SUM(H44:H64) -> 15 | J65: =SUM(J44:J64) -> 15 | L65: =SUM(L44:L64) -> 15 | M65: =SUM(M44:M64) -> 15 | Q65: ELECTRICAL GEAR
C67: PERIPHERALS
R68: Main MSA | S68: Subpanels | T68: Main Breakers | U68: Disconnects | V68: Transfromers | W68: Breakers | X68: Breakers | Y68: D. Panels | Z68: Meter Socket
C69: Type | D69: Nuts | E69: Washers | F69: Screws & Bolts | G69: Elbow | H69: Sweeps | I69: GROUND ROD | J69: Uni Strut | K69: Power Strut | L69: Threaded rod | M69: Hole strap | N69: Drop-in Anchors | Q69: QTY | R69: 1 | S69: 0 | T69: 0 | U69: 0 | V69: 0 | W69: 0 | X69: 0 | Y69: 0 | Z69: 0
C70: QTY | D70: 400 | E70: 400 | F70: 1 | G70: 6 | H70: 4 | I70: =MAX(D44:D64)+MAX(D33:D38) -> 2 | J70: 6 | K70: =(IF(U3="PVC",0,_xlfn.IFS(MAX(D44:D64)=0,(MAX(J5:J27)/5)/(5/(MAX(D5:D27))),MAX(D5:D27)=0,(MAX(J44:J64)/5)/(5/(MAX(D44:D64))),MAX(D44:D64)>0,(MAX(J44:J64)/5)/(5/(MAX(D44:D64)))+(MAX(J5:J27)/5)/(5/(MAX(D5:D27)))))*5) -> 0 | L70: =K70*2 -> 0 | M70: =K70*(MAX(D5:D27)+MAX(D44:D64)) -> 0 | N70: =L70 -> 0 | Q70: Unit Cost | R70: 36813 | S70: 5387 | T70: 1200 | U70: 1700 | V70: 5298 | W70: 800 | X70: 60 | Y70: 30000 | Z70: 2055.31
C71: Unit Cost | D71: 0.109 | E71: 0.099 | F71: 182.73 | G71: 6.929 | H71: 75 | I71: 34.87 | J71: 55 | K71: 5.6 | L71: 1.75 | M71: 0.34 | N71: =115/110 -> 1.0454545 | Q71: Size | R71: 100 | S71: 600 | T71: 300 | U71: 300 | V71: 150 | W71: 300 | X71: 40 | Y71: 1000 | Z71: 300A
C72: Total | D72: =D70*D71 -> 43.6 | E72: =E71*E70 -> 39.6 | F72: =F71*F70 -> 182.73 | G72: =G71*G70 -> 41.574 | H72: =H71*H70 -> 300 | I72: =I71*I70 -> 69.74 | J72: =J71*J70 -> 330 | K72: =K71*K70 -> 0 | L72: =L70*L71 -> 0 | M72: =M70*M71 -> 0 | N72: =N70*N71 -> 0 | Q72: Voltage | R72: 480 | S72: 208 | T72: 208 | U72: 208 | V72: 208 | W72: 480 | X72: 208 | Y72: 208 | Z72: 208
C73: Type | D73: PVC Cement | E73: PVC Bushing | F73: PVC Bushing | G73: PVC Coupling | H73: GPR Scan | I73: Ground Rod Clamp | J73: Combo Lock | K73: Tape/Marking Supplies | L73: Data Box | M73: CAT5 | N73: Charger Anchors | Q73: Total | R73: =R70*R69 -> 36813 | S73: =S70*S69 -> 0 | T73: =T70*T69 -> 0 | U73: =U70*U69 -> 0 | V73: =V70*V69 -> 0 | W73: =W70*W69 -> 0 | X73: =X70*X69 -> 0 | Y73: =Y70*Y69 -> 0 | Z73: =Z70*Z69 -> 0
C74: QTY | D74: =SUM(IF(V5>1,V5/300,0),IF(V6>1,V6/200,0),IF(V7>1,V7/125,0),IF(V8>1,V8/100,0),IF(V9>1,V9/90,0),IF(V10>1,V10/60,0),IF(V11>1,V11/50,0),IF(V12>1,V12/40,0),IF(V13>1,V13/35,0),IF(V14>1,V14/30,0),IF(V15>1,V15/10,0)) -> 0.325 | E74: 1 | F74: 1 | G74: =(H65/10)+H39/10+(H28/10) -> 1.5 | H74: 1 | I74: =I70 -> 2 | J74: 2 | K74: 1 | L74: 0 | M74: =L65+L28 -> 15 | N74: =MAX(D44:D64)*6+(MAX(D5:D27)*4)+(MAX(D33:D38)*4) -> 8
C75: Unit Cost | D75: 18.8 | E75: 7.22 | F75: 11.06 | G75: 1.3 | H75: 2500 | I75: 7.22 | J75: 337.73 | K75: 125.57 | L75: 1500 | M75: =0.1 -> 0.1 | N75: 5 | Y75: =SUM(S73:Z73) -> 0
C76: Total | D76: =D75*D74 -> 6.11 | E76: =E75*E74 -> 7.22 | F76: =F75*F74 -> 11.06 | G76: =G75*G74 -> 1.95 | H76: =H75*H74 -> 2500 | I76: =I75*I74 -> 14.44 | J76: =J75*J74 -> 675.46 | K76: =K75*K74 -> 125.57 | ... M76: =M75*M74 -> 1.5 | N76: =N74*N75 -> 40
C77: Type | D77: Ply wood | E77: 2'x4' | F77: Sono tubes | G77: Christy box | H77: Cutting/Saw Consumables | I77: Misc Electrical Hdw. | J77: Form Stakes | K77: Wire Dobies | L77: Junction Box | M77: Wheel stop | N77: GFI Test (SgA>1000
C78: QTY | D78: 6 | E78: 6 | F78: 22 | G78: 0 | H78: 1 | I78: 1 | J78: 20 | K78: 50 | L78: 4 | M78: =(MAX(D44:D64)+MAX(D5:D27)) -> 0 | N78: 0
C79: Unit Cost | D79: 55 | E79: 10 | F79: 19 | G79: 160 | H79: 535.16 | I79: 217.5 | J79: 8.63 | K79: 1.18 | L79: 177 | M79: 70.58 | N79: 2000
C80: Total | D80: =D79*D78 -> 330 | E80: =E79*E78 -> 60 | F80: =F79*F78 -> 418 | G80: =G79*G78 -> 0 | H80: =H79*H78 -> 535.16 | I80: =I79*I78 -> 217.5 | J80: =J79*J78 -> 172.6 | K80: =K79*K78 -> 59 | ... N80: =N79*N78 -> 0
C81: GRAND TOTAL | D81: =SUM(D72,D76,D80) -> 379.71 | E81: =SUM(E72,E76,E80) -> 106.82 | F81: =SUM(F72,F76,F80) -> 611.79 | G81: =SUM(G72,G76,G80) -> 43.524 | H81: =SUM(H72,H76,H80) -> 3335.16 | I81: =SUM(I72,I76,I80) -> 301.68 | J81: =SUM(J72,J76,J80) -> 1178.06 | K81: =SUM(K76,K80,K72) -> 184.57 | L81: =SUM(L72,L76,L80) -> 708 | M81: =SUM(M72,M76,M80) -> 1.5 | N81: =SUM(N72,N76,N80) -> 40
N82: =SUM(D81:N81) -> 6890.814
L84: Utility Fees | M84: QTY | N84: Costs | O84: Equipment
C85: Description | D85: QTY | E85: Unit Cost | F85: Total | I85: Permits | J85: Equipment | L85: R16 Fees | M85: 0 | N85: 1000 | O85: =M85*N85 -> 0
C86: Signs | D86: =MAX(D5:D27)+MAX(D44:D64) -> 0 | E86: 40 | F86: =D86*E86 -> 0 | I86: 1000 | J86: =SUM(H94:H110) -> 11394.63 | L86: Transformer Pad | M86: 0 | N86: 1663 | O86: =M86*N86 -> 0
C87: Sign posts | D87: =MAX(D5:D27)+(MAX(D44:D64)/2) -> 0 | E87: 56.1 | F87: =D87*E87 -> 0 | L87: Cabel well | M87: 0 | N87: 495 | O87: =M87*N87 -> 0
L88: Utility Vault/Pull Box | M88: 0 | N88: 0 | O88: =M88*N88 -> 0
L89: PGE Sand | M89: 0 | N89: 105 | O89: =M89*N89 -> 0
L90: Contract Fees | O90: =M90*N90 -> 0
C91: Bollards | D91: =MAX(D5:D27)*2+(MAX(D44:D64)*4) -> 0 | E91: 110 | F91: =D91*E91 -> 0
F92: =(D92*E92) -> 0 | G92: =SUM(F86:F92) -> 0 | I92: =SUM(I86:I91) -> 1000 | J92: =SUM(J86:J91) -> 11394.63 | O92: =SUM(O85:O91) -> 0
C94: Description | D94: QTY | E94: Unit Cost | F94: Duration | G94: Delivery fees | H94: Total | L94: Concrete | M94: QTY | N94: Costs | O94: Equipment
C95: Fencing | D95: =(((MAX(E44:E64,E5:E27))*2 )+ 60) -> 90 | E95: 0.3 | F95: 30 | G95: =400 -> 400 | H95: =(D95*E95*F95)+(IF(D95>0,400)) -> 1210 | L95: Concrete yd³ | M95: =IF(U3="PVC",MAX(D44:D64) *1+MAX(D5:D27)*0.5+MAX(D33:D38)*1.5,0)+15 -> 18 | N95: 193.54 | O95: =M95*N95 -> 3483.72
C96: Mini x | D96: 1 | E96: =_xlfn.IFS(F96<7,433,F96>=30,2957/30,F96>=7,1103/7) -> 98.566667 | F96: 30 | G96: =IF(X3="PVC",1,0) -> 0 | H96: =D96*E96*F96 -> 2957 | I96: 0 | J96: 0 | L96: Rebar | M96: =IF(U3="PVC",MAX(D44:D64)*3 +MAX(D5:D27)*2+MAX(D33:D38)*2,0) -> 4 | N96: 25.65 | O96: =M96*N96 -> 102.6
C97: Dump Truck | D97: 0 | E97: 520 | F97: 1 | G97: =IF(X3="PVC",1,0) -> 0 | H97: =D97*E97*F97 -> 0 | I97: Freight/Disposal | J97: 2000 | L97: Steel Mesh Roll | M97: 2 | N97: 169 | O97: =M97*N97 -> 338
C98: Forklift | D98: 0 | E98: =_xlfn.IFS(F98<7,563,F98>=30,4503/30,F98>=7,2146/7) -> 563 | F98: 2 | G98: =IF(X3="PVC",1,0)+400*0 -> 0 | H98: =(D98*E98*F98)+G98 -> 0 | O98: =SUM(O95:O97) -> 3924.32
C99: Trench Plates | D99: 0 | E99: 5.18 | F99: 30 | G99: 0 | H99: =D99*E99*F99 -> 0 | I99: =SUM(I97:I98) -> 0 | J99: =SUM(J97:J98) -> 2000
C100: Storage container | D100: 1 | E100: 185 | F100: 15 | G100: =IF(X3="PVC",1,0)+400*0 -> 0 | H100: =(D100*E100*F100)+G100 -> 2775 | L100: Asphalt and Paving | M100: QTY | N100: Costs | O100: Equipment
C101: Portable restroom | D101: 1 | E101: =267 -> 267 | F101: 1 | G101: 65 | H101: =D101*E101*F101+(IF(D101>0,65)) -> 332 | L101: Apshalt | M101: =IF(U3="PVC",MAX(E44:E64)+MAX(E5:E27)+MAX(E33:E38),0)+20 -> 35 | N101: 40.81 | O101: =M101*N101 -> 1428.35
C102: Low boi | D102: 0 | E102: 1000 | F102: 1 | G102: 0 | H102: =D102*E102*F102+(IF(D102>0,0)) -> 0 | L102: Striping | M102: =((MAX(D5:D27)*2+MAX(D44:D64))/10) -> 0 | N102: =1500 -> 1500 | O102: =M102*N102 -> 0
C103: Saw cutter | D103: 1 | E103: 169 | F103: 1 | G103: 0 | H103: =D103*E103*F103+(IF(D103>0,0)) -> 169 | O103: =M103*N103 -> 0
C104: Jack hammer | D104: 1 | E104: 155 | F104: 1 | G104: 0 | H104: =(D104*E104*F104)+(IF(D104>0,G104,0)) -> 155 | O104: =SUM(O101:O103) -> 1428.35
C105: Compactor | D105: 1 | E105: 175 | F105: 1 | G105: 0 | H105: =(D105*E105*F105)+(IF(D105>0,G105,0)) -> 175
C106: Generator rental | D106: 1 | E106: 220 | F106: 1 | G106: 0 | H106: =(D106*E106*F106)+(IF(D106>0,G106,0)) -> 220 | L106: ADA | M106: QTY | N106: Costs | O106: Equipment
C107: Dump trailer rental | D107: 1 | E107: 796.63 | F107: 1 | G107: 0 | H107: =(D107*E107*F107)+(IF(D107>0,G107,0)) -> 796.63 | L107: 2% Ada Stalls | M107: =IF(U3="PVC",IF(COUNTIF(D44:D64,">=4")>0,2,1)+IF(COUNTIF(D5:D27,">=4")>0,2,1)) -> 2 | N107: 4900 | O107: =M107*N107 -> 9800
C108: Equipment protection | D108: 1 | E108: 45 | F108: 1 | G108: 0 | H108: =(D108*E108*F108)+(IF(D108>0,G108,0)) -> 45 | L108: ADA Ramp | M108: =IF(U3="PVC",IF(COUNTIF(D44:D64,">=1")>0,1)+IF(COUNTIF(D5:D27,">=1")>0,1)) -> 0 | N108: 5200 | O108: =M108*N108 -> 0
C109: Skidsteer rental | D109: 1 | E109: 750 | F109: 1 | G109: 0 | H109: =(D109*E109*F109)+(IF(D109>0,G109,0)) -> 750
C110: Telehandler rental | D110: 1 | E110: 1410 | F110: 1 | G110: 400 | H110: =(D110*E110*F110)+(IF(D110>0,G110,0)) -> 1810 | O110: =SUM(O107:O109) -> 9800
H111: =SUM(H95:H110) -> 11394.63
