Workbook

Sheet Version
A1: DOCUMENT CONTROL
A2: Hardcoded. These values identify which generation of the template a returned file came from — never make them formulas.
A4: Template version | B4: 2.9.0
A5: Released | B5: 2026-08-29
A6: Template name | B6: EVSE Project Intake
A7: Issued by | B7: Zero Impact Energy
A8: Template content hash | B8: 4aecae7d4b5f25a9 | C8: The hash of the BLANK template this file was built from, frozen at its release. It does not change when you fill the sheet in.
A9: Completed by — fill these in
A10: This file version | B10: Rev A | C10: e.g. Rev A, Rev B — increment each time you send it back
A11: Date completed | B11: 46267
A12: Completed by | B12: Test CPM
A13: Project reference | B13: BW-TEST-001
A14: Notes on this revision | B14: Fixture for the importer test | C14: What changed since the last version you sent
A15: File content hash | B15: 4aecae7d4b5f25a9 | C15: A hash of THIS workbook. It changes every time someone edits it, and it is what a model records so you can tell whether the model was built from the file in front of you.
A16: Changelog
A17: Version | B17: Released | C17: What changed
A18: 1.0.0 | B18: 2026-08-26 | C18: Initial release — project, equipment, electrical, construction, commercial, revenue and carbon intake with live consistency checks.
A19: 1.1.0 | B19: 2026-08-26 | C19: Deal structure knobs and the override register. Base case unchanged at zero.
A20: 1.2.0 | B20: 2026-08-26 | C20: PG&E Rule 29 interconnection capture. Electrical materials costed independently of the EVSE price book.
A21: 1.3.0 | B21: 2026-08-26 | C21: Utility rate engine across PG&E, SCE and SDG&E. Market benchmarks. Demand subscription ramps with concurrency.
A22: 1.4.0 | B22: 2026-08-26 | C22: Scope of supply controls — each service line can be provided by us, by others, or not required. Document control added.
A23: 1.5.0 | B23: 2026-08-26 | C23: Mixed-fleet fix — accessories no longer counted as charging units, and the placement check compares against DC cabinets only.
A24: 1.6.0 | B24: 2026-08-26 | C24: Description was not recorded at the time. The change sits between the mixed-fleet fix (1.5.0) and the rip-and-replace capability (1.7.0).
A25: 1.7.0 | B25: 2026-08-26 | C25: Rip-and-replace project type. A new Existing tab captures the existing installation, the retained-versus-replaced register, thirty-six months of usage and billing history, port and connector expansion, and the removal scope. Tabs 3, 4 and 6 respond to what is retained and can now be driven from historical actuals.
A26: 1.8.0 | B26: 2026-08-26 | C26: Utility selection became a dropdown of every California delivery utility — 56 investor-owned, publicly owned, tribal and cooperative entities that set their own retail tariff. New Utilities tab carries the roster and the community choice aggregators separately, because a CCA sets generation only and cannot set an EV tariff. New RateLibrary tab carries 32 researched commercial EV and fallback rates with a STATUS column, plus the utility rebate programmes and their open/closed state.
A27: 1.9.0 | B27: 2026-08-27 | C27: Price book states the included manufacturer warranty per charger class — two years on DC fast charging, one year on Level 2, parts only — and the out-of-warranty service column now reads NOT OFFERED rather than sitting blank, because a blank reads as zero to anything consuming the table. Service is sold only against a warranty in force, included or extended.
A28: 1.10.0 | B28: 2026-08-27 | C28: Capacity-first equipment picker on 2_Equipment. Pick a capacity — 60 kW, 120 kW, 360 kW, Level 2 and so on — and the SKU dropdown narrows to that capacity, five to fourteen SKUs instead of ninety-two. The capacity also supplies the rating kW where the price book records none, which it does for every Level 2, Buy America and V2G row; a Buy America 60 kW cabinet previously counted as zero kW and zero cabinets. A DC-only capacity line is added and the carbon credit repointed at it, because the LCFS credit is paid on DC capacity alone.
... A46: 2.9.0 | B46: 2026-08-29 | C46: The demand subscription is computed. This template declared a subscription policy, supplied every input a ramp needs and left both outputs blank, so on a schedule that sells capacity in blocks the largest operating cost on a high-capacity site was not in the workbook at all. Expected peak concurrency and Subscribed kW are now derived from the day's energy, the peak-to-average factor and the safety margin; the block size and price are read from the rate library; and the annual cost joins the fixed-and-demand line the project model reads. Where the library carries no block for a schedule the cost is zero and the check says UNPRICED with the subscribed capacity in it, because a zero that nobody has priced is an absence and not a saving.

Sheet README
A1: EVSE PROJECT INTAKE
A2: Zero Impact Energy — one form, one project. Fill the blue cells; everything else is derived.
A4: How to use this workbook
A5: • | B5: Fill in every BLUE cell you can. Leave a cell blank rather than guessing — a blank is a question we will ask; a guess becomes a number in a proposal.
A6: • | B6: YELLOW cells are key commercial assumptions. They have sensible defaults, but they drive the return — change them deliberately, not by habit.
A7: • | B7: GREEN cells are live checks. They recalculate as you type. If a green cell turns into a warning, the sheet is telling you two of your inputs disagree.
A8: • | B8: GREY tabs (Lists, PriceBook, RefData) are reference data. Do not edit them unless prices have actually changed.
A9: • | B9: When the form is complete, send the file back. Everything downstream — electrical sizing, materials, labour, revenue, carbon, financing, the proposal — is computed from these inputs alone.
A11: Cell legend
A12: Appearance | B12: Meaning | C12: What to do
A13: Blue fill, blue text | B13: Human input | C13: Fill it in
A14: Yellow fill, blue bold | B14: Key commercial assumption | C14: Review the default, change deliberately
A15: Green fill, green text | B15: Live check / derived | C15: Read it — never type over it
A16: Grey | B16: Reference data | C16: Leave alone
A18: Tabs, in the order you should fill them
A19: 1_Project | B19: Who, where, which utility, and how the site is accessed
A20: 2_Equipment | B20: What is being sold — pick SKUs from the price book
A21: 3_Electrical | B21: Distances, wire, existing service. Drives every electrical cost.
A22: 4_Construction | B22: Site works, labour days, ADA, permits, rentals
A23: 5_Commercial | B23: Discounts, financing terms, service and network term
A24: 6_Revenue | B24: Pricing, utilisation, ramp and growth
A25: 7_Carbon | B25: FCI credit rate, aggregator, eligibility, grants
A27: 8_Deal_Structure | B27: Optional. Knobs for trading price against a share of credits or revenue.
A28: 9_Overrides | B28: Optional. Force any derived value when you have a quote or a measurement.
A30: Version | B30: Template 1.4.0, released 2026-08-26 — see the Version tab
A32: Replacement projects
A33: • | B33: The Existing tab is the difference between a greenfield project and a charger swap. Complete it whenever the site already has charging equipment.
A34: • | B34: Set the project type on the Existing tab section A first — every other check on that tab keys off it.
A35: • | B35: Section B is the register that decides the cost. Marking the service, feeder, switchgear and conduit as RETAIN removes most of the electrical and civil scope; the Electrical and Construction tabs then tell you exactly which lines to zero.
A36: • | B36: Section E is the most valuable page in the whole intake. Twelve months of metered history beats every market assumption on the Revenue tab, and twenty-four months beats twelve. Enter outage months as they happened — do not smooth them.
A37: • | B37: Sections F and G turn the old installation into a projection: availability recovered, ports added, connector coverage widened and power increased, each with its own capture factor you can argue with.
A38: • | B38: Section H is the removal scope. It is zero on a greenfield project and real money on a replacement.
A39: • | B39: Set the revenue basis at the foot of the Revenue tab to "Historical actuals" on any replacement site with twelve or more months of data.
A41: Choosing the utility
A42: • | B42: Pick the DELIVERY utility on the Project tab — the one that owns the wires and sets the tariff. If the site buys generation from a community choice aggregator, still pick the delivery utility; the CCA is a separate field below it.
A43: • | B43: A CCA changes only the generation cents per kWh. Eligibility, time-of-use periods, the demand subscription and every delivery charge stay with the utility. Build the bill from the delivery tariff and substitute one line.
A44: • | B44: Rule 29 exists only at investor-owned utilities. A municipal utility, irrigation district or cooperative has its own line-extension policy and the cost split can be completely different — do not carry a Rule 29 allowance on a POU site.
A45: • | B45: Read the STATUS column on RateLibrary before using any rate. VERIFIED means it was read in the utility's own tariff. NOT PUBLISHED means the utility does not publish it — SCE is the significant case — and those rows are left at zero deliberately rather than filled with a guess.
A46: • | B46: Whether a utility has an EV tariff at all is often worth more than the cents per kWh. A site on a utility with no EV rate pays full demand charges on a general commercial schedule, which at low utilisation dominates the bill.
A48: Returning this workbook
A49: • | B49: Send the whole workbook back, not extracts. The version tab is how we know which generation of questions you answered.
A50: • | B50: If you are returning a file built on an older template, say so in Notes — some fields will have moved.

Sheet Project
A1: 1 · PROJECT AND SITE
A2: Identity, location, utility and access policy.
A4: Client
A5: Client legal name | B5: Best Western Hawthorne | C5: As it will appear on the proposal
A6: Client contact name | B6: Mohammad Noorali
A7: Contact title | B7: General Manager
A8: Contact email | B8: gm@example.com
A9: Contact phone | B9: 310-555-0100
A11: Site
A12: Site name | B12: Best Western Hawthorne
A13: Street address | B13: 15000 Hawthorn Blvd
A14: City / State / ZIP | B14: Hawthorne, CA 90260
A15: County | B15: Los Angeles
A16: Property type | B16: Hotel | C16: Retail, dealership, fleet depot, hotel, grocery…
A17: Project type | B17: =Existing!B5 | C17: Set this on the Existing tab. A replacement site must complete the Existing tab in full; a greenfield site leaves it blank.
A18: Existing chargers on site? | B18: =IF(Existing!B43=0,"None",TEXT(Existing!B43,"0")&" ports across "&TEXT(Existing!B42,"0")&" units — see the Existing tab") | C18: Derived from the equipment schedule on the Existing tab.
A20: Access and operating policy
A21: Public access | B21: Public 24/7 | C21: Public 24/7 / Public during business hours / Restricted
A22: Hours open per day | B22: 24 | C22: CRITICAL: 24 unless access is genuinely gated
A23: Days open per year | B23: 365 | C23: Use 365 unless the site closes seasonally
A25: Utility
A26: Electric utility (delivery) | B26: SCE — Southern California Edison | C26: Pick from the list. This is the utility that DELIVERS power and therefore sets the EV tariff — see the Utilities tab. If the site is served by a community choice aggregator, still pick the delivery utility here.
A27: Current rate schedule | B27: TOU-GS-2 | C27: From a recent bill
A28: Existing service size (A) | B28: 800 | C28: Main service amperage today
A29: Service voltage | B29: 480 | C29: Usually 480V 3-phase for DC fast charging
A30: 12 months of bills obtained? | B30: Yes | C30: Yes / No — needed to validate the energy cost
A32: Commercial
A33: Proposal date | B33: 46266
A34: Proposal validity (days) | B34: 30
A35: Prepared by | B35: Vatsal Patel
A36: RSM / account owner | B36: Account Owner
A39: Utility context — derived from the selection above
A40: These read the Utilities and RateLibrary tabs. They tell you what tariff regime the site sits in before anyone opens a tariff book.
A41: Utility type | B41: =IFERROR(INDEX(Utilities!$K$5:$K$78,MATCH($B$26,Utilities!$J$5:$J$78,0)),"") | C41: IOU utilities are CPUC-regulated and follow Rule 29. POUs and co-ops set their own rules — no Rule 29, no PCIA, their own interconnection process.
A42: Service territory | B42: =IFERROR(INDEX(Utilities!$L$5:$L$78,MATCH($B$26,Utilities!$J$5:$J$78,0)),"")
A43: EV rate status | B43: =IFERROR(INDEX(Utilities!$M$5:$M$78,MATCH($B$26,Utilities!$J$5:$J$78,0)),"") | C43: Whether this utility publishes a commercial EV tariff at all. Where it does not, the site pays full demand charges on a general commercial schedule — usually the single largest difference between two otherwise identical sites.
A44: Rate rows in the library | B44: =COUNTIF(RATE_UTIL,$B$26) | C44: How many schedules the library carries for this utility. Zero means it has not been researched — obtain the tariff.
A45: Best status in the library | B45: =IF(COUNTIF(RATE_UTIL,$B$26)=0,"NOT RESEARCHED — obtain the tariff at site selection",IF(COUNTIFS(RATE_UTIL,$B$26,RATE_STATUS,"VERIFIED")>0,"VERIFIED rates available",IF(COUNTIFS(RATE_UTIL,$B$26,RATE_STATUS,"PARTIAL")>0,"PARTIAL — some fields missing, read the row before pricing","UNVERIFIED — the library carries a rate but nobody has checked it against the filed tariff"))) | C45: Never price a project from a NOT PUBLISHED row. Get the tariff sheet or a written rate quotation.
A46: Community choice aggregator, if any | B46: Clean Power Alliance | C46: A CCA changes ONLY the generation $/kWh. Eligibility, time-of-use periods, the demand subscription and every delivery charge stay with the utility above.
A47: CCA delivery utility check | B47: =IF(OR($B$46="",$B$46="None — bundled utility service"),"n/a — no aggregator",IF(IFERROR(INDEX(Utilities!$N$5:$N$78,MATCH($B$26,Utilities!$J$5:$J$78,0)),"")<>"California","n/a — community choice aggregation is a California mechanism",IFERROR(IF(ISNUMBER(SEARCH(LEFT($B$26,4),INDEX(Utilities!$C$67:$C$93,MATCH($B$46,Utilities!$A$67:$A$93,0)))),"OK — this CCA operates in the selected utility territory","CHECK — this CCA normally rides "&INDEX(Utilities!$C$67:$C$93,MATCH($B$46,Utilities!$A$67:$A$93,0))&" delivery"),"CHECK the pairing"))) | C47: Catches an aggregator paired with the wrong delivery utility. Central Coast Community Energy genuinely spans both PG&E and SCE, so it will flag — settle the host utility by address. Silent where no aggregator is named and outside California, where the mechanism does not exist.
A48: Interconnection regime | B48: =IF($B$26="","pick the delivery utility above",IF(AND(IFERROR(INDEX(Utilities!$N$5:$N$78,MATCH($B$26,Utilities!$J$5:$J$78,0)),"")="California",$B$41="IOU"),"California IOU — Electric Rule 29 and Rules 15/16 apply. Complete the interconnection block on the Electrical tab.","THE SERVING UTILITY'S OWN RULES. Rule 29 does not apply here. Leave the Rule 29 rows on the Electrical tab blank and carry whatever this utility quotes as a pass-through fee.")) | C48: Decides whether the Rule 29 questions on the Electrical tab are worth asking. Outside a California investor-owned utility they are not, and nothing reads them.
A49: INTERCONNECTION IS THE SERVING UTILITY'S ANSWER, NOT OURS. In California, PG&E and SCE publish Electric Rule 29 and the interconnection block on the Electrical tab follows it. Everywhere else there is no equivalent and no general substitute — ask the utility what it requires and what it charges, and carry their figure as a pass-through fee. Do not price an interconnection from this template.

Sheet Existing
A1: 1B · EXISTING INSTALLATION — RIP AND REPLACE
A2: Complete this tab only when the site already has charging equipment. On a greenfield site leave it blank and the model ignores it entirely. On a replacement site this tab is the most valuable page in the intake, because it replaces market assumptions with the site's own operating history.
A4: A · Project type
A5: Project type | B5: Rip and replace — reuse infrastructure | C5: Greenfield builds everything. Rip and replace swaps the chargers and reuses the electrical infrastructure. Replace and expand does both — new chargers plus added capacity.
A6: Age of the existing installation (years) | B6: 7 | C6: Drives whether the existing conductors and gear are worth reusing.
A7: Reason for replacement | B7: End of life and unreliable | C7: End of life, unreliability, obsolete connectors, insufficient power, or a commercial decision.
A8: Who owns the existing equipment? | B8: Client | C8: If a third party owns it, removal and disposal need their agreement.
A10: B · What is retained and what is replaced
A11: This register is the whole commercial difference between a greenfield project and a replacement. Every line marked RETAIN removes cost from the electrical and construction scope. Every line marked REPLACE puts it back. Answer honestly — a conductor that is retained on paper and re-pulled in the field is a change order.
A12: Element | B12: Decision | C12: Basis for the decision
A13: Utility service and meter | B13: RETAIN | C13: Existing service stays. No Rule 29 application, no new meter.
A14: Service feeder to switchgear | B14: RETAIN | C14: Conductor from the point of delivery to the switchboard.
A15: Main distribution switchgear | B15: REPLACE | C15: Switchboard, main breaker and metering section.
A16: Branch conductors to each charger | B16: RETAIN | C16: The feeders from switchgear to cabinet. The single largest reuse saving.
A17: Conduit and trench | B17: RETAIN | C17: Existing conduit reused; no re-trenching if the new cabinets land on the same pads.
A18: Branch breakers | B18: REPLACE | C18: Sized to the new cabinet, not the old one. Usually cheap and always worth replacing.
A19: Concrete pads | B19: REPLACE | C19: New cabinets rarely match the old footprint or anchor pattern.
A20: Bollards and equipment protection | B20: REPLACE | C20: Usually disturbed by pad removal.
A21: Paving and striping | B21: PARTIAL | C21: Reinstatement around the new pads only.
A22: ADA stalls and route | B22: RETAIN | C22: Reused if the layout is unchanged and still compliant.
A23: Signage | B23: REPLACE | C23: Network branding, pricing and connector types all change.
A24: Network and payment hardware | B24: REPLACE | C24: Integrated in the new cabinets.
A26: Elements retained | B26: =COUNTIF($B$13:$B$24,"RETAIN") | C26: Of 12 in the register.
A27: Elements replaced | B27: =COUNTIF($B$13:$B$24,"REPLACE")+COUNTIF($B$13:$B$24,"PARTIAL")
A28: Scope profile | B28: =IF($B$13="RETAIN",IF($B$14="RETAIN","Infrastructure reuse — no new service, no new feeder","Service retained, feeder replaced"),"New or upgraded service — price this as greenfield electrical") | D28: What the retained register implies for the electrical scope on the Electrical tab.
A30: C · Existing equipment being removed
A31: One row per existing cabinet or unit. This drives the demolition, disconnection and disposal scope on the Construction tab, and the port comparison in section F.
A32: Make and model | B32: Rating kW | C32: Ports | D32: Connectors | E32: Qty | F32: Year installed | G32: Working?
A33: ABB Terra 54 | B33: 50 | C33: 2 | D33: CCS1 / CHAdeMO | E33: 2 | F33: 2018 | G33: Working
A34: ChargePoint Express 250 | B34: 62.5 | C34: 1 | D34: CCS1 | E34: 2 | F34: 2019 | G34: Failed
A42: Existing units on site | B42: =SUM($E$33:$E$40) | C42: Cabinets or standalone units to be removed.
A43: Existing ports on site | B43: =SUMPRODUCT($C$33:$C$40,$E$33:$E$40) | C43: Ports the site presents today.
A44: Existing connected load (kW) | B44: =SUMPRODUCT($B$33:$B$40,$E$33:$E$40) | C44: The load the existing service was sized for. Compare against the new load on the Electrical tab.
A45: Units fully working | B45: =SUMIF($G$33:$G$40,"Working",$E$33:$E$40) | C45: Quantity, not row count. The gap against units on site is the availability the new equipment recovers.
A46: Units failed or intermittent | B46: =SUMIF($G$33:$G$40,"Failed",$E$33:$E$40)+SUMIF($G$33:$G$40,"Intermittent",$E$33:$E$40) | C46: What the replacement is actually fixing.
A47: Units of unknown condition | B47: =SUMIF($G$33:$G$40,"Unknown",$E$33:$E$40) | C47: The availability uplift on the revenue projection is built from what was working and what was not. Anything in this row is a projection input nobody has established yet.
A48: D · Existing electrical infrastructure
A49: What is already in the ground. Where a line is being retained, this is what the new design has to work with; where it is being replaced, this is what has to come out.
A50: Existing service size (A) | B50: 800 | C50: From the meter panel or the utility bill.
A51: Existing service voltage | B51: 480 | C51: 480V three-phase for most DC sites.
A52: Spare capacity in the existing gear (A) | B52: 200 | C52: What is available for the new equipment without an upgrade.
A53: Existing switchgear frame (A) | B53: 800 | C53: The main breaker frame size.
A54: Existing branch conductor size | B54: 250 KCMIL Cu | C54: e.g. 250 KCMIL Cu. Determines whether it can carry the new cabinet.
A55: Average branch run length (ft) | B55: 120 | C55: Switchgear to cabinet, per position.
A56: Existing conduit size and type | B56: 2-1/2 in PVC | C56: e.g. 2-1/2 in PVC. Determines whether a larger conductor could be pulled if needed.
A57: Existing rate schedule | B57: TOU-GS-2 | C57: The tariff the site is billed on today.
A58: Separately metered for EV today? | B58: No | C58: If not, a separate EV meter may be needed to reach the EV tariff.
A60: Does the existing service carry the new load? | B60: =IF(LEFT($B$5,10)="Greenfield","n/a — greenfield, there is no existing service",IF(OR(NOT(ISNUMBER($B$50)),NOT(ISNUMBER($B$51)),N(Electrical!$B$38)=0),"enter the existing service size and voltage as NUMBERS, and the new equipment",IF(N(Electrical!$B$38)*1000/($B$51*SQRT(3))*1.25<=$B$50,"OK — the existing service covers the new load at 125%","UPGRADE NEEDED — "&TEXT(N(Electrical!$B$38)*1000/($B$51*SQRT(3))*1.25,"#,##0")&" A required against a "&TEXT($B$50,"#,##0")&" A service"))) | D60: Stands down on a greenfield project, and asks for a NUMBER rather than a non-empty cell — "N/A" typed here used to reach a division and return #VALUE! on a site with no existing service at all.
A61: Does the existing switchgear carry the new load? | B61: =IF(LEFT($B$5,10)="Greenfield","n/a — greenfield, there is no existing gear",IF(OR(NOT(ISNUMBER($B$53)),NOT(ISNUMBER($B$51)),N(Equipment!B23)=0),"enter the existing frame as a NUMBER and the new equipment",IF($B$53>=Equipment!B23*1000/($B$51*SQRT(3))*1.25,"OK — existing frame is adequate","UNDERSIZED — the existing frame does not cover the new load at 125%"))) | D61: Stands down on a greenfield project, and asks for a NUMBER rather than a non-empty cell — "N/A" typed here used to reach a division and return #VALUE! on a site with no existing service at all.
A62: Load change from the existing installation | B62: =IF(OR($B$44=0,N(Equipment!B23)=0),"enter the existing equipment and the new equipment",TEXT(Equipment!B23-$B$44,"+#,##0;-#,##0")&" kW ("&TEXT(Equipment!B23/$B$44-1,"+0%;-0%")&") against the existing "&TEXT($B$44,"#,##0")&" kW") | D62: A replacement that raises connected load is the case where reuse assumptions break.
A64: E · Historical usage and billing
A65: Up to thirty-six months of actuals. This is what replaces the market benchmark on the Revenue tab. Enter what you have and leave the rest blank — the derived baseline below uses only the months that carry data. Where a month was an outage, mark it so it can be excluded from the run rate rather than dragging the average down.
A66: Month (YYYY-MM) | B66: kWh dispensed | C66: Gross revenue | D66: Sessions | E66: Utility cost | F66: Ports working | G66: Note / outage
A67: 2025-09 | B67: 9800 | C67: 5390 | D67: 306 | E67: 2744 | F67: 4
A68: 2025-10 | B68: 10200 | C68: 5610 | D68: 319 | E68: 2856 | F68: 4
A69: 2025-11 | B69: 9900 | C69: 5445 | D69: 309 | E69: 2772 | F69: 3 | G69: Two units down all month
A70: 2025-12 | B70: 11500 | C70: 6325 | D70: 359 | E70: 3220 | F70: 3
A71: 2026-01 | B71: 12000 | C71: 6600 | D71: 375 | E71: 3360 | F71: 3
A72: 2026-02 | B72: 11800 | C72: 6490 | D72: 369 | E72: 3304 | F72: 4
A73: 2026-03 | B73: 12500 | C73: 6875 | D73: 391 | E73: 3500 | F73: 3
A74: 2026-04 | B74: 13100 | C74: 7205 | D74: 409 | E74: 3668 | F74: 3
A75: 2026-05 | B75: 12800 | C75: 7040 | D75: 400 | E75: 3584 | F75: 3
A76: 2026-06 | B76: 13400 | C76: 7370 | D76: 419 | E76: 3752 | F76: 4
A77: 2026-07 | B77: 13900 | C77: 7645 | D77: 434 | E77: 3892 | F77: 4
A78: 2026-08 | B78: 14100 | C78: 7755 | D78: 441 | E78: 3948 | F78: 4
A104: Months with data | B104: =COUNT($B$67:$B$102) | C104: Twelve is the minimum for a credible run rate; twenty-four is better.
A105: Total kWh dispensed | B105: =SUM($B$67:$B$102)
A106: Total gross revenue | B106: =SUM($C$67:$C$102)
A107: Total sessions | B107: =SUM($D$67:$D$102)
A108: Total utility cost | B108: =SUM($E$67:$E$102)
A110: Average kWh per month | B110: =IFERROR(SUM($B$67:$B$102)/COUNT($B$67:$B$102),0)
A111: Average kWh per day | B111: =IFERROR(SUM($B$67:$B$102)/COUNT($B$67:$B$102)*12/365,0) | C111: The historical daily run rate. This is the number the new projection is built from.
A112: Historical kWh per year | B112: =IFERROR(SUM($B$67:$B$102)/COUNT($B$67:$B$102)*12,0)
A113: Historical gross revenue per year | B113: =IFERROR(SUM($C$67:$C$102)/COUNT($C$67:$C$102)*12,0)
A114: Historical utility cost per year | B114: =IFERROR(SUM($E$67:$E$102)/COUNT($E$67:$E$102)*12,0)
A115: Historical net before card fees | B115: =$B$113-$B$114
A116: Implied retail price $/kWh | B116: =IFERROR(SUM($C$67:$C$102)/SUM($B$67:$B$102),0) | C116: What drivers actually paid. Compare against the price proposed on the Revenue tab.
A117: Implied delivered cost $/kWh | B117: =IFERROR(SUM($E$67:$E$102)/SUM($B$67:$B$102),0) | C117: What the utility actually charged, all-in. Far better than any tariff estimate.
A118: Average kWh per session | B118: =IFERROR(SUM($B$67:$B$102)/SUM($D$67:$D$102),0) | C118: Typically 25 to 55 kWh on DC. A low figure suggests failed or abandoned sessions.
A119: Average ports working | B119: =IFERROR(AVERAGE($F$67:$F$102),0) | C119: Against the ports installed. The gap between them is the availability the new equipment recovers.
A120: Historical availability | B120: =IFERROR(AVERAGE($F$67:$F$102)/$B$43,0) | C120: Ports working as a share of ports installed. This is the recovery opportunity, quantified.
A122: OUTAGE MONTHS DRAG THE RUN RATE DOWN, AND THAT IS USUALLY THE POINT. A site that averaged 3.4 of 5 ports working was not meeting demand — it was rationing it. Do not "correct" the history upward. Enter it as it happened and let section F state the recovery separately, where a customer can see it and argue with it.
A124: F · Port expansion and connector coverage
A125: What the new equipment adds over the old. Each uplift below is stated separately so it can be challenged individually rather than hidden inside one optimistic growth rate.
A126: Existing ports | B126: =$B$43
A127: New ports | B127: =N(Equipment!B22) | C127: From the Equipment tab. Dual-port cabinets present two positions each.
A128: Port count multiple | B128: =IF(OR($B$43=0,N(Equipment!B22)=0),1,Equipment!B22/$B$43) | C128: More positions means more simultaneous vehicles, not proportionally more energy — see the capture factor below.
A130: Connector | B130: On the existing equipment | C130: On the new equipment | D130: Share of the California fleet
A131: NACS / Tesla | B131: No | C131: Yes | D131: 0.55
A132: CCS1 | B132: Yes | C132: Yes | D132: 0.4
A133: CHAdeMO | B133: Yes | C133: No | D133: 0.03
A134: J1772 (Level 2) | B134: No | C134: Yes | D134: 0.02
A136: Enter the share of the local fleet each connector reaches. Tesla vehicles are the largest single population in California, so a site that could not serve them natively was turning away a large share of passing demand.
A137: Fleet coverage today | B137: =SUMIF($B$131:$B$134,"Yes",$D$131:$D$134) | C137: Share of the fleet the existing connectors serve natively.
A138: Fleet coverage after replacement | B138: =SUMIF($C$131:$C$134,"Yes",$D$131:$D$134)
A139: Coverage multiple | B139: =IFERROR($B$138/$B$137,1) | C139: Adding NACS to a CCS-only site is the single largest addressable-market change available on a replacement project.
A141: Existing power per position (kW) | B141: =IFERROR(SUMPRODUCT(--($B$33:$B$40>=30),$B$33:$B$40,$E$33:$E$40)/SUMPRODUCT(--($B$33:$B$40>=30),$C$33:$C$40,$E$33:$E$40),0) | C141: DC positions only. Blending Level 2 into this average understates the old power and inflates the uplift.
A142: New power per position (kW) | B142: =IF(N(Equipment!B22)=0,0,Equipment!B23/Equipment!B22)
A143: Power multiple | B143: =IF(OR($B$141=0,$B$142=0),1,MIN(2,$B$142/$B$141)) | C143: Capped at 2.00x. Faster charging frees the stall sooner, but beyond roughly double the constraint stops being how fast the hardware charges and becomes how many vehicles arrive. Raising the cap does not make demand appear.
A145: G · Projected baseline — history plus stated uplifts
...

Sheet Equipment
A1: 2 · EQUIPMENT SCHEDULE
A2: Pick the CAPACITY first, then the SKU. A distributed system is TWO kinds of line: the power cabinet, and each dispenser it feeds.
A4: Enter one row per SKU. Qty is the number of CABINETS, not ports.
A6: Line | B6: Capacity | C6: SKU | D6: Description (auto) | E6: Role (auto) | F6: DC output kW (auto) | G6: AC input kW (auto) | H6: Connectors (auto) | I6: Qty (units) | J6: Discount — set on the Commercial tab | K6: MSRP each (auto) | L6: Dispenser SKU (distributed only) | M6: Max dispensers (auto) | N6: Dispensers per cabinet | O6: Connectors per dispenser (1 or 2) | P6: Dispenser MSRP each (auto)
A7: 1 | B7: 360 kW DC | C7: TP5-360-480-2-300 | D7: =IFERROR(INDEX(PriceBook!$C$2:$C$203,MATCH($C7,PriceBook!$B$2:$B$203,0)),"") | E7: =IF($C7="","",IFERROR(INDEX(ROLE_VAL,MATCH($C7,ROLE_SKU,0)),"all_in_one")) | F7: =IF($C7="",0,IFERROR(INDEX(SPEC_DCKW,MATCH($C7,SPEC_SKU,0)),IF($E7="dispenser",0,IF($E7="accessory",0,IFERROR(IF(N(INDEX(PriceBook!$E$2:$E$203,MATCH($C7,PriceBook!$B$2:$B$203,0)))>0,INDEX(PriceBook!$E$2:$E$203,MATCH($C7,PriceBook!$B$2:$B$203,0)),INDEX(RATED_KW,MATCH($B7,CAPACITY_LIST,0))*IF(INDEX(PER_PORT,MATCH($B7,CAPACITY_LIST,0))=1,MAX(1,N($H7)),1)),0))))) | G7: =IF($C7="",0,IFERROR(INDEX(SPEC_ACKW,MATCH($C7,SPEC_SKU,0)),$F7)) | H7: =IF($C7="",0,IF($E7="power_cabinet",N($N7)*N($O7),IFERROR(INDEX(SPEC_OUTS,MATCH($C7,SPEC_SKU,0)),IFERROR(INDEX(SKU_CONN,MATCH($C7,SKU_ALL,0)),0)))) | I7: 4 | K7: =IFERROR(INDEX(PriceBook!$D$2:$D$203,MATCH($C7,PriceBook!$B$2:$B$203,0)),0) | M7: =IF($E7<>"power_cabinet",0,IFERROR(INDEX(SPEC_MAXDISP,MATCH($C7,SPEC_SKU,0)),0)) | P7: =IF($L7="",0,IFERROR(INDEX(PriceBook!$D$2:$D$203,MATCH($L7,PriceBook!$B$2:$B$203,0)),0))
A8: 2 | B8: Level 2 AC | C8: CTX-C40-240-2 | D8: =IFERROR(INDEX(PriceBook!$C$2:$C$203,MATCH($C8,PriceBook!$B$2:$B$203,0)),"") | E8: =IF($C8="","",IFERROR(INDEX(ROLE_VAL,MATCH($C8,ROLE_SKU,0)),"all_in_one")) | F8: =IF($C8="",0,IFERROR(INDEX(SPEC_DCKW,MATCH($C8,SPEC_SKU,0)),IF($E8="dispenser",0,IF($E8="accessory",0,IFERROR(IF(N(INDEX(PriceBook!$E$2:$E$203,MATCH($C8,PriceBook!$B$2:$B$203,0)))>0,INDEX(PriceBook!$E$2:$E$203,MATCH($C8,PriceBook!$B$2:$B$203,0)),INDEX(RATED_KW,MATCH($B8,CAPACITY_LIST,0))*IF(INDEX(PER_PORT,MATCH($B8,CAPACITY_LIST,0))=1,MAX(1,N($H8)),1)),0))))) | G8: =IF($C8="",0,IFERROR(INDEX(SPEC_ACKW,MATCH($C8,SPEC_SKU,0)),$F8)) | H8: =IF($C8="",0,IF($E8="power_cabinet",N($N8)*N($O8),IFERROR(INDEX(SPEC_OUTS,MATCH($C8,SPEC_SKU,0)),IFERROR(INDEX(SKU_CONN,MATCH($C8,SKU_ALL,0)),0)))) | I8: 2 | K8: =IFERROR(INDEX(PriceBook!$D$2:$D$203,MATCH($C8,PriceBook!$B$2:$B$203,0)),0) | M8: =IF($E8<>"power_cabinet",0,IFERROR(INDEX(SPEC_MAXDISP,MATCH($C8,SPEC_SKU,0)),0)) | P8: =IF($L8="",0,IFERROR(INDEX(PriceBook!$D$2:$D$203,MATCH($L8,PriceBook!$B$2:$B$203,0)),0))
A9: 3 | D9: =IFERROR(INDEX(PriceBook!$C$2:$C$203,MATCH($C9,PriceBook!$B$2:$B$203,0)),"") | E9: =IF($C9="","",IFERROR(INDEX(ROLE_VAL,MATCH($C9,ROLE_SKU,0)),"all_in_one")) | F9: =IF($C9="",0,IFERROR(INDEX(SPEC_DCKW,MATCH($C9,SPEC_SKU,0)),IF($E9="dispenser",0,IF($E9="accessory",0,IFERROR(IF(N(INDEX(PriceBook!$E$2:$E$203,MATCH($C9,PriceBook!$B$2:$B$203,0)))>0,INDEX(PriceBook!$E$2:$E$203,MATCH($C9,PriceBook!$B$2:$B$203,0)),INDEX(RATED_KW,MATCH($B9,CAPACITY_LIST,0))*IF(INDEX(PER_PORT,MATCH($B9,CAPACITY_LIST,0))=1,MAX(1,N($H9)),1)),0))))) | G9: =IF($C9="",0,IFERROR(INDEX(SPEC_ACKW,MATCH($C9,SPEC_SKU,0)),$F9)) | H9: =IF($C9="",0,IF($E9="power_cabinet",N($N9)*N($O9),IFERROR(INDEX(SPEC_OUTS,MATCH($C9,SPEC_SKU,0)),IFERROR(INDEX(SKU_CONN,MATCH($C9,SKU_ALL,0)),0)))) | K9: =IFERROR(INDEX(PriceBook!$D$2:$D$203,MATCH($C9,PriceBook!$B$2:$B$203,0)),0) | M9: =IF($E9<>"power_cabinet",0,IFERROR(INDEX(SPEC_MAXDISP,MATCH($C9,SPEC_SKU,0)),0)) | P9: =IF($L9="",0,IFERROR(INDEX(PriceBook!$D$2:$D$203,MATCH($L9,PriceBook!$B$2:$B$203,0)),0))
A10: 4 | D10: =IFERROR(INDEX(PriceBook!$C$2:$C$203,MATCH($C10,PriceBook!$B$2:$B$203,0)),"") | E10: =IF($C10="","",IFERROR(INDEX(ROLE_VAL,MATCH($C10,ROLE_SKU,0)),"all_in_one")) | F10: =IF($C10="",0,IFERROR(INDEX(SPEC_DCKW,MATCH($C10,SPEC_SKU,0)),IF($E10="dispenser",0,IF($E10="accessory",0,IFERROR(IF(N(INDEX(PriceBook!$E$2:$E$203,MATCH($C10,PriceBook!$B$2:$B$203,0)))>0,INDEX(PriceBook!$E$2:$E$203,MATCH($C10,PriceBook!$B$2:$B$203,0)),INDEX(RATED_KW,MATCH($B10,CAPACITY_LIST,0))*IF(INDEX(PER_PORT,MATCH($B10,CAPACITY_LIST,0))=1,MAX(1,N($H10)),1)),0))))) | G10: =IF($C10="",0,IFERROR(INDEX(SPEC_ACKW,MATCH($C10,SPEC_SKU,0)),$F10)) | H10: =IF($C10="",0,IF($E10="power_cabinet",N($N10)*N($O10),IFERROR(INDEX(SPEC_OUTS,MATCH($C10,SPEC_SKU,0)),IFERROR(INDEX(SKU_CONN,MATCH($C10,SKU_ALL,0)),0)))) | K10: =IFERROR(INDEX(PriceBook!$D$2:$D$203,MATCH($C10,PriceBook!$B$2:$B$203,0)),0) | M10: =IF($E10<>"power_cabinet",0,IFERROR(INDEX(SPEC_MAXDISP,MATCH($C10,SPEC_SKU,0)),0)) | P10: =IF($L10="",0,IFERROR(INDEX(PriceBook!$D$2:$D$203,MATCH($L10,PriceBook!$B$2:$B$203,0)),0))
A11: 5 | D11: =IFERROR(INDEX(PriceBook!$C$2:$C$203,MATCH($C11,PriceBook!$B$2:$B$203,0)),"") | E11: =IF($C11="","",IFERROR(INDEX(ROLE_VAL,MATCH($C11,ROLE_SKU,0)),"all_in_one")) | F11: =IF($C11="",0,IFERROR(INDEX(SPEC_DCKW,MATCH($C11,SPEC_SKU,0)),IF($E11="dispenser",0,IF($E11="accessory",0,IFERROR(IF(N(INDEX(PriceBook!$E$2:$E$203,MATCH($C11,PriceBook!$B$2:$B$203,0)))>0,INDEX(PriceBook!$E$2:$E$203,MATCH($C11,PriceBook!$B$2:$B$203,0)),INDEX(RATED_KW,MATCH($B11,CAPACITY_LIST,0))*IF(INDEX(PER_PORT,MATCH($B11,CAPACITY_LIST,0))=1,MAX(1,N($H11)),1)),0))))) | G11: =IF($C11="",0,IFERROR(INDEX(SPEC_ACKW,MATCH($C11,SPEC_SKU,0)),$F11)) | H11: =IF($C11="",0,IF($E11="power_cabinet",N($N11)*N($O11),IFERROR(INDEX(SPEC_OUTS,MATCH($C11,SPEC_SKU,0)),IFERROR(INDEX(SKU_CONN,MATCH($C11,SKU_ALL,0)),0)))) | K11: =IFERROR(INDEX(PriceBook!$D$2:$D$203,MATCH($C11,PriceBook!$B$2:$B$203,0)),0) | M11: =IF($E11<>"power_cabinet",0,IFERROR(INDEX(SPEC_MAXDISP,MATCH($C11,SPEC_SKU,0)),0)) | P11: =IF($L11="",0,IFERROR(INDEX(PriceBook!$D$2:$D$203,MATCH($L11,PriceBook!$B$2:$B$203,0)),0))
A12: 6 | D12: =IFERROR(INDEX(PriceBook!$C$2:$C$203,MATCH($C12,PriceBook!$B$2:$B$203,0)),"") | E12: =IF($C12="","",IFERROR(INDEX(ROLE_VAL,MATCH($C12,ROLE_SKU,0)),"all_in_one")) | F12: =IF($C12="",0,IFERROR(INDEX(SPEC_DCKW,MATCH($C12,SPEC_SKU,0)),IF($E12="dispenser",0,IF($E12="accessory",0,IFERROR(IF(N(INDEX(PriceBook!$E$2:$E$203,MATCH($C12,PriceBook!$B$2:$B$203,0)))>0,INDEX(PriceBook!$E$2:$E$203,MATCH($C12,PriceBook!$B$2:$B$203,0)),INDEX(RATED_KW,MATCH($B12,CAPACITY_LIST,0))*IF(INDEX(PER_PORT,MATCH($B12,CAPACITY_LIST,0))=1,MAX(1,N($H12)),1)),0))))) | G12: =IF($C12="",0,IFERROR(INDEX(SPEC_ACKW,MATCH($C12,SPEC_SKU,0)),$F12)) | H12: =IF($C12="",0,IF($E12="power_cabinet",N($N12)*N($O12),IFERROR(INDEX(SPEC_OUTS,MATCH($C12,SPEC_SKU,0)),IFERROR(INDEX(SKU_CONN,MATCH($C12,SKU_ALL,0)),0)))) | K12: =IFERROR(INDEX(PriceBook!$D$2:$D$203,MATCH($C12,PriceBook!$B$2:$B$203,0)),0) | M12: =IF($E12<>"power_cabinet",0,IFERROR(INDEX(SPEC_MAXDISP,MATCH($C12,SPEC_SKU,0)),0)) | P12: =IF($L12="",0,IFERROR(INDEX(PriceBook!$D$2:$D$203,MATCH($L12,PriceBook!$B$2:$B$203,0)),0))
A13: 7 | D13: =IFERROR(INDEX(PriceBook!$C$2:$C$203,MATCH($C13,PriceBook!$B$2:$B$203,0)),"") | E13: =IF($C13="","",IFERROR(INDEX(ROLE_VAL,MATCH($C13,ROLE_SKU,0)),"all_in_one")) | F13: =IF($C13="",0,IFERROR(INDEX(SPEC_DCKW,MATCH($C13,SPEC_SKU,0)),IF($E13="dispenser",0,IF($E13="accessory",0,IFERROR(IF(N(INDEX(PriceBook!$E$2:$E$203,MATCH($C13,PriceBook!$B$2:$B$203,0)))>0,INDEX(PriceBook!$E$2:$E$203,MATCH($C13,PriceBook!$B$2:$B$203,0)),INDEX(RATED_KW,MATCH($B13,CAPACITY_LIST,0))*IF(INDEX(PER_PORT,MATCH($B13,CAPACITY_LIST,0))=1,MAX(1,N($H13)),1)),0))))) | G13: =IF($C13="",0,IFERROR(INDEX(SPEC_ACKW,MATCH($C13,SPEC_SKU,0)),$F13)) | H13: =IF($C13="",0,IF($E13="power_cabinet",N($N13)*N($O13),IFERROR(INDEX(SPEC_OUTS,MATCH($C13,SPEC_SKU,0)),IFERROR(INDEX(SKU_CONN,MATCH($C13,SKU_ALL,0)),0)))) | K13: =IFERROR(INDEX(PriceBook!$D$2:$D$203,MATCH($C13,PriceBook!$B$2:$B$203,0)),0) | M13: =IF($E13<>"power_cabinet",0,IFERROR(INDEX(SPEC_MAXDISP,MATCH($C13,SPEC_SKU,0)),0)) | P13: =IF($L13="",0,IFERROR(INDEX(PriceBook!$D$2:$D$203,MATCH($L13,PriceBook!$B$2:$B$203,0)),0))
A14: 8 | D14: =IFERROR(INDEX(PriceBook!$C$2:$C$203,MATCH($C14,PriceBook!$B$2:$B$203,0)),"") | E14: =IF($C14="","",IFERROR(INDEX(ROLE_VAL,MATCH($C14,ROLE_SKU,0)),"all_in_one")) | F14: =IF($C14="",0,IFERROR(INDEX(SPEC_DCKW,MATCH($C14,SPEC_SKU,0)),IF($E14="dispenser",0,IF($E14="accessory",0,IFERROR(IF(N(INDEX(PriceBook!$E$2:$E$203,MATCH($C14,PriceBook!$B$2:$B$203,0)))>0,INDEX(PriceBook!$E$2:$E$203,MATCH($C14,PriceBook!$B$2:$B$203,0)),INDEX(RATED_KW,MATCH($B14,CAPACITY_LIST,0))*IF(INDEX(PER_PORT,MATCH($B14,CAPACITY_LIST,0))=1,MAX(1,N($H14)),1)),0))))) | G14: =IF($C14="",0,IFERROR(INDEX(SPEC_ACKW,MATCH($C14,SPEC_SKU,0)),$F14)) | H14: =IF($C14="",0,IF($E14="power_cabinet",N($N14)*N($O14),IFERROR(INDEX(SPEC_OUTS,MATCH($C14,SPEC_SKU,0)),IFERROR(INDEX(SKU_CONN,MATCH($C14,SKU_ALL,0)),0)))) | K14: =IFERROR(INDEX(PriceBook!$D$2:$D$203,MATCH($C14,PriceBook!$B$2:$B$203,0)),0) | M14: =IF($E14<>"power_cabinet",0,IFERROR(INDEX(SPEC_MAXDISP,MATCH($C14,SPEC_SKU,0)),0)) | P14: =IF($L14="",0,IFERROR(INDEX(PriceBook!$D$2:$D$203,MATCH($L14,PriceBook!$B$2:$B$203,0)),0))
A15: 9 | D15: =IFERROR(INDEX(PriceBook!$C$2:$C$203,MATCH($C15,PriceBook!$B$2:$B$203,0)),"") | E15: =IF($C15="","",IFERROR(INDEX(ROLE_VAL,MATCH($C15,ROLE_SKU,0)),"all_in_one")) | F15: =IF($C15="",0,IFERROR(INDEX(SPEC_DCKW,MATCH($C15,SPEC_SKU,0)),IF($E15="dispenser",0,IF($E15="accessory",0,IFERROR(IF(N(INDEX(PriceBook!$E$2:$E$203,MATCH($C15,PriceBook!$B$2:$B$203,0)))>0,INDEX(PriceBook!$E$2:$E$203,MATCH($C15,PriceBook!$B$2:$B$203,0)),INDEX(RATED_KW,MATCH($B15,CAPACITY_LIST,0))*IF(INDEX(PER_PORT,MATCH($B15,CAPACITY_LIST,0))=1,MAX(1,N($H15)),1)),0))))) | G15: =IF($C15="",0,IFERROR(INDEX(SPEC_ACKW,MATCH($C15,SPEC_SKU,0)),$F15)) | H15: =IF($C15="",0,IF($E15="power_cabinet",N($N15)*N($O15),IFERROR(INDEX(SPEC_OUTS,MATCH($C15,SPEC_SKU,0)),IFERROR(INDEX(SKU_CONN,MATCH($C15,SKU_ALL,0)),0)))) | K15: =IFERROR(INDEX(PriceBook!$D$2:$D$203,MATCH($C15,PriceBook!$B$2:$B$203,0)),0) | M15: =IF($E15<>"power_cabinet",0,IFERROR(INDEX(SPEC_MAXDISP,MATCH($C15,SPEC_SKU,0)),0)) | P15: =IF($L15="",0,IFERROR(INDEX(PriceBook!$D$2:$D$203,MATCH($L15,PriceBook!$B$2:$B$203,0)),0))
A16: 10 | D16: =IFERROR(INDEX(PriceBook!$C$2:$C$203,MATCH($C16,PriceBook!$B$2:$B$203,0)),"") | E16: =IF($C16="","",IFERROR(INDEX(ROLE_VAL,MATCH($C16,ROLE_SKU,0)),"all_in_one")) | F16: =IF($C16="",0,IFERROR(INDEX(SPEC_DCKW,MATCH($C16,SPEC_SKU,0)),IF($E16="dispenser",0,IF($E16="accessory",0,IFERROR(IF(N(INDEX(PriceBook!$E$2:$E$203,MATCH($C16,PriceBook!$B$2:$B$203,0)))>0,INDEX(PriceBook!$E$2:$E$203,MATCH($C16,PriceBook!$B$2:$B$203,0)),INDEX(RATED_KW,MATCH($B16,CAPACITY_LIST,0))*IF(INDEX(PER_PORT,MATCH($B16,CAPACITY_LIST,0))=1,MAX(1,N($H16)),1)),0))))) | G16: =IF($C16="",0,IFERROR(INDEX(SPEC_ACKW,MATCH($C16,SPEC_SKU,0)),$F16)) | H16: =IF($C16="",0,IF($E16="power_cabinet",N($N16)*N($O16),IFERROR(INDEX(SPEC_OUTS,MATCH($C16,SPEC_SKU,0)),IFERROR(INDEX(SKU_CONN,MATCH($C16,SKU_ALL,0)),0)))) | K16: =IFERROR(INDEX(PriceBook!$D$2:$D$203,MATCH($C16,PriceBook!$B$2:$B$203,0)),0) | M16: =IF($E16<>"power_cabinet",0,IFERROR(INDEX(SPEC_MAXDISP,MATCH($C16,SPEC_SKU,0)),0)) | P16: =IF($L16="",0,IFERROR(INDEX(PriceBook!$D$2:$D$203,MATCH($L16,PriceBook!$B$2:$B$203,0)),0))
A17: 11 | D17: =IFERROR(INDEX(PriceBook!$C$2:$C$203,MATCH($C17,PriceBook!$B$2:$B$203,0)),"") | E17: =IF($C17="","",IFERROR(INDEX(ROLE_VAL,MATCH($C17,ROLE_SKU,0)),"all_in_one")) | F17: =IF($C17="",0,IFERROR(INDEX(SPEC_DCKW,MATCH($C17,SPEC_SKU,0)),IF($E17="dispenser",0,IF($E17="accessory",0,IFERROR(IF(N(INDEX(PriceBook!$E$2:$E$203,MATCH($C17,PriceBook!$B$2:$B$203,0)))>0,INDEX(PriceBook!$E$2:$E$203,MATCH($C17,PriceBook!$B$2:$B$203,0)),INDEX(RATED_KW,MATCH($B17,CAPACITY_LIST,0))*IF(INDEX(PER_PORT,MATCH($B17,CAPACITY_LIST,0))=1,MAX(1,N($H17)),1)),0))))) | G17: =IF($C17="",0,IFERROR(INDEX(SPEC_ACKW,MATCH($C17,SPEC_SKU,0)),$F17)) | H17: =IF($C17="",0,IF($E17="power_cabinet",N($N17)*N($O17),IFERROR(INDEX(SPEC_OUTS,MATCH($C17,SPEC_SKU,0)),IFERROR(INDEX(SKU_CONN,MATCH($C17,SKU_ALL,0)),0)))) | K17: =IFERROR(INDEX(PriceBook!$D$2:$D$203,MATCH($C17,PriceBook!$B$2:$B$203,0)),0) | M17: =IF($E17<>"power_cabinet",0,IFERROR(INDEX(SPEC_MAXDISP,MATCH($C17,SPEC_SKU,0)),0)) | P17: =IF($L17="",0,IFERROR(INDEX(PriceBook!$D$2:$D$203,MATCH($L17,PriceBook!$B$2:$B$203,0)),0))
A18: 12 | D18: =IFERROR(INDEX(PriceBook!$C$2:$C$203,MATCH($C18,PriceBook!$B$2:$B$203,0)),"") | E18: =IF($C18="","",IFERROR(INDEX(ROLE_VAL,MATCH($C18,ROLE_SKU,0)),"all_in_one")) | F18: =IF($C18="",0,IFERROR(INDEX(SPEC_DCKW,MATCH($C18,SPEC_SKU,0)),IF($E18="dispenser",0,IF($E18="accessory",0,IFERROR(IF(N(INDEX(PriceBook!$E$2:$E$203,MATCH($C18,PriceBook!$B$2:$B$203,0)))>0,INDEX(PriceBook!$E$2:$E$203,MATCH($C18,PriceBook!$B$2:$B$203,0)),INDEX(RATED_KW,MATCH($B18,CAPACITY_LIST,0))*IF(INDEX(PER_PORT,MATCH($B18,CAPACITY_LIST,0))=1,MAX(1,N($H18)),1)),0))))) | G18: =IF($C18="",0,IFERROR(INDEX(SPEC_ACKW,MATCH($C18,SPEC_SKU,0)),$F18)) | H18: =IF($C18="",0,IF($E18="power_cabinet",N($N18)*N($O18),IFERROR(INDEX(SPEC_OUTS,MATCH($C18,SPEC_SKU,0)),IFERROR(INDEX(SKU_CONN,MATCH($C18,SKU_ALL,0)),0)))) | K18: =IFERROR(INDEX(PriceBook!$D$2:$D$203,MATCH($C18,PriceBook!$B$2:$B$203,0)),0) | M18: =IF($E18<>"power_cabinet",0,IFERROR(INDEX(SPEC_MAXDISP,MATCH($C18,SPEC_SKU,0)),0)) | P18: =IF($L18="",0,IFERROR(INDEX(PriceBook!$D$2:$D$203,MATCH($L18,PriceBook!$B$2:$B$203,0)),0))
A20: Charging units (excludes accessories) | B20: =SUMPRODUCT(--($H$7:$H$18>0),$I$7:$I$18) | C20: Units a driver plugs into — dispensers, all-in-one chargers and Level 2. A power cabinet has no connectors and is not one.
A21: AC-connected units — cabinets and all-in-ones | B21: =SUMPRODUCT(($E$7:$E$18="power_cabinet")+($E$7:$E$18="all_in_one"),$I$7:$I$18) | C21: Each of these needs its own AC run from the switchgear, and a placement distance on the Electrical tab.
A22: Total ports | B22: =SUMPRODUCT($H$7:$H$18,$I$7:$I$18) | C22: Connectors x units. The EVOLV billing basis. Dispensers carry the ports on a distributed system; the cabinet carries none.
A23: Total connected load (kW) | B23: =SUMPRODUCT(($E$7:$E$18="power_cabinet")+($E$7:$E$18="all_in_one")+($E$7:$E$18="level_2"),$G$7:$G$18,$I$7:$I$18) | C23: AC input, which is what the switchgear sees — a 480 kW cabinet draws 524 kW. Dispensers add nothing: their power comes from the cabinet, not the switchgear.
A24: Equipment MSRP total | B24: =SUMPRODUCT($I$7:$I$18,$K$7:$K$18)+SUMPRODUCT($I$7:$I$18,$N$7:$N$18,$P$7:$P$18) | C24: Catalogue SKUs at their price-book price, plus any dispensers priced by hand on the cabinet row.
A25: Equipment after discount | B25: =$B$24*(1-Commercial!$B$5) | C25: Sales tax is computed on THIS, not on MSRP. The discount is the one on the Commercial tab — there is no per-line discount any more.
A26: of which DC fast-charging capacity (kW) | B26: =SUMPRODUCT(($E$7:$E$18="power_cabinet")+($E$7:$E$18="all_in_one"),$F$7:$F$18,$I$7:$I$18) | C26: DC output. The LCFS credit basis. Counted once, at the cabinet — never again at the dispenser.
A27: Scope of work sentence (one line, must match the rows above) | B27: Installation of (4) 360 kW dual-port DC fast chargers and (2) dual Level 2 units — 12 charging positions
B29: Write it from the table, e.g. "Installation of (4) 360 kW dual-port DC fast chargers — 8 charging positions".
A32: Distributed system — do the dispensers fit the cabinets?
A33: Only relevant when a power cabinet is on the schedule. A cabinet feeds a limited number of DC outputs; each dual dispenser consumes two of them. Every dispenser also needs a DC run back to its cabinet — schedule those on the Electrical tab.
A34: Power cabinets on site | B34: =SUMPRODUCT(--($E$7:$E$18="power_cabinet"),$I$7:$I$18)
A35: Dispensers those cabinets can take | B35: =SUMPRODUCT($M$7:$M$18,$I$7:$I$18) | C35: From the architecture table: a 480 kW cabinet takes up to 3 dual dispensers, a 1.28 MW up to 8.
A36: Dispensers on the cabinet rows | B36: =SUMPRODUCT(--($E$7:$E$18="power_cabinet"),$N$7:$N$18,$I$7:$I$18) | C36: Dispensers per cabinet x the number of cabinets. This is now the only way a dispenser is entered.
A37: Dispensers entered on a line of their own | B37: =SUMPRODUCT(--($E$7:$E$18="dispenser"),$I$7:$I$18) | C37: Should always be zero. A dispenser belongs on its cabinet row, not on a line of its own.
A38: Dispensers in total | B38: =$B$36+$B$37
A39: Connectors those dispensers carry | B39: =SUMPRODUCT(--($E$7:$E$18="power_cabinet"),$H$7:$H$18,$I$7:$I$18)
A40: DISTRIBUTED SYSTEM CHECK | B40: =IF(AND($B$34=0,$B$38=0),"n/a — no distributed system on this schedule",IF($B$34=0,"ERROR — DISPENSERS WITHOUT A POWER CABINET. A dispenser has no power of its own.",IF($B$38=0,"ERROR — POWER CABINET WITHOUT DISPENSERS. A cabinet has no connectors and cannot charge a vehicle on its own. Enter the dispensers in the last column of the table.",IF($B$38>$B$35,"ERROR — TOO MANY DISPENSERS. "&TEXT($B$38,"0")&" entered against a limit of "&TEXT($B$35,"0")&" for the cabinets on this schedule.","OK — "&TEXT($B$38,"0")&" dispenser(s) on "&TEXT($B$34,"0")&" cabinet(s), "&TEXT($B$35-$B$38,"0")&" more allowed, "&TEXT($B$39,"0")&" connectors"))))
A41: Dispenser value at list | B41: =SUMPRODUCT($I$7:$I$18,$N$7:$N$18,$P$7:$P$18) | C41: Dispensers x their price-book price. Included in the two equipment totals above.
A42: Is a dispenser SKU picked where dispensers are scheduled? | B42: {=IF(SUMPRODUCT(($E$7:$E$18="power_cabinet")*N($N$7:$N$18))=0,"n/a — no dispensers scheduled",IF(SUMPRODUCT((N($N$7:$N$18)>0)*($L$7:$L$18=""))>0,"ERROR — dispensers are scheduled on a cabinet row with no dispenser SKU picked, so they are costing this project nothing. Pick one from the dropdown.",IF(SUMPRODUCT((N($N$7:$N$18)>0)*(N($O$7:$O$18)=0))>0,"ERROR — dispensers are scheduled with no connectors-per-dispenser picked, so the site shows no charging positions. Pick 1 or 2.","OK — "&TEXT(SUMPRODUCT(N($I$7:$I$18),N($N$7:$N$18)),"0")&" dispenser(s) at their price-book price")))}
A43: Any dispenser on a line of its own? | B43: =IF(AND(SUMPRODUCT(--($E$7:$E$18="dispenser"),$I$7:$I$18)>0,$B$36>0),"ERROR — dispensers are entered BOTH on their own line and as a count on a cabinet row. Pick one route: the totals add them together and double-count ports and price.",IF(SUMPRODUCT(--($E$7:$E$18="dispenser"),$I$7:$I$18)>0,"OK — dispensers are on their own lines, priced from the price book","OK — no dispenser is on a line of its own")) | C43: It used to fire whenever a dispenser was on its own line at all, which is a legitimate entry now the dispenser SKU is in the price book. The thing that is actually wrong is using both routes, because the totals sum them.
A46: ENTRY CHECKS — what a wrong entry looks like
A47: Each of these is a real way to get a wrong answer out of this tab. None of them used to say anything.
A48: Any discount typed on an equipment line? | B48: =IF(COUNTA($J$7:$J$18)>0,"ERROR — A DISCOUNT HAS BEEN TYPED ON A LINE. Discounts are set once, on the Commercial tab. A figure in this column is not applied to anything and will mislead whoever reads the schedule next — clear it, and change the rate on the Commercial tab instead.","OK — the discount is set once, on the Commercial tab: "&TEXT(Commercial!$B$5,"0%"))
A49: Dispensers counted twice? | B49: =IF(AND(SUMPRODUCT(--($E$7:$E$18="power_cabinet"),$N$7:$N$18)>0,SUMPRODUCT(--($E$7:$E$18="dispenser"))>0),"ERROR — DOUBLE COUNTED. Dispensers appear both on a cabinet row and on a line of their own. Delete the separate line; the cabinet row is the only place they belong.","OK — dispensers are entered one way only")
A50: Anything entered below the table? | B50: =IF(COUNTA($B$19:$C$19)>0,"ERROR — SOMETHING IS ENTERED BELOW LINE 12. Every total on this tab covers rows 7 to 18 only, so a line entered underneath is not counted and not priced. Move it into the table.","OK — nothing entered below the table")
A51: Every SKU found in the price book? | B51: =IF(SUMPRODUCT(($C$7:$C$18<>"")*ISNA(MATCH($C$7:$C$18,PriceBook!$B$2:$B$203,0)))>0,"ERROR — A SKU ON THIS SCHEDULE IS NOT IN THE PRICE BOOK. A trailing space is enough. The row still shows a connector count from the default, so it looks alive, but it has no price and no total counts it.",IF(SUMPRODUCT(($L$7:$L$18<>"")*ISNA(MATCH($L$7:$L$18,PriceBook!$B$2:$B$203,0)))>0,"ERROR — A DISPENSER SKU IS NOT IN THE PRICE BOOK. The dispensers are counted and their connectors are counted, but they are priced at nothing.","OK — every SKU and dispenser SKU is in the price book"))
A52: Every line with a SKU has a quantity? | B52: =IF(SUMPRODUCT(($C$7:$C$18<>"")*($I$7:$I$18=0))>0,"ERROR — A LINE HAS A SKU BUT NO QUANTITY. Description, role, connectors and MSRP all populate from the SKU, so the line looks finished; quantity is what every total multiplies by, so it contributes nothing.","OK — every line with a SKU has a quantity")
A53: Every line with a capacity has a SKU? | B53: =IF(SUMPRODUCT(($B$7:$B$18<>"")*($C$7:$C$18=""))>0,"INCOMPLETE — a capacity is picked on a line with no SKU. The line is inert until the SKU is chosen.","OK — every line with a capacity has a SKU")
A54: Every SKU has a connector count? | B54: =IF(COUNTA($C$7:$C$18)=0,"OK — nothing scheduled yet",IF(SUMPRODUCT(--($C$7:$C$18<>""),--($E$7:$E$18<>"accessory"),--($E$7:$E$18<>"power_cabinet"),--(H$7:H$18=0))>0,"A SCHEDULED SKU HAS NO CONNECTOR COUNT — add it to the price book column I; the sheet will not guess","OK — every scheduled SKU carries a connector count")) | C54: Power cabinets are exempt: their connectors are on their dispensers, which are scheduled separately. Accessories are exempt for the same reason — they are not charging positions.
A55: =IF(SUMPRODUCT(--($B$43:$B$54<>""),--(LEFT($B$43:$B$54,2)<>"OK"))>0,"FIX "&TEXT(SUMPRODUCT(--($B$43:$B$54<>""),--(LEFT($B$43:$B$54,2)<>"OK")),"0")&" ITEM(S) ABOVE — the equipment totals on this tab are wrong until you do","ENTRY CHECKS ALL PASS")

Sheet Electrical
A1: 3 · SITE AND ELECTRICAL
A2: Distances and materials. This tab drives the largest single cost in the project.
A4: Materials | E4: Conductor sizing basis
A5: Feeder conductor material | B5: Cu | C5: Cu or Al | E5: Design ambient (C) | F5: 40 | G5: Design ambient for the branch runs, in Celsius. THIS IS SITE DATA — there is no house default and none is offered. Use the ASHRAE 2% design dry-bulb for the location, or the duct-bank design temperature if the run is buried. NEC Table 310.15(B)(1)(1) corrects the ampacity from it, so an ambient carried over from another project silently resizes every conductor on this one.
A6: Conduit type | B6: PVC | C6: PVC or EMT | E6: Conductor insulation rating (C) | F6: 90 | G6: What the wire is rated for. THHN/XHHW-2 is 90 C. Ambient correction is applied to THIS column.
A7: Trench surface | B7: Asphalt | C7: Asphalt / concrete / landscape / mixed | E7: Termination rating (C) | F7: 75 | G7: NEC 110.14(C). The corrected ampacity is capped here. Confirm against the switchgear and the cabinet terminals — 60 C lugs change every size on this tab.
A8: Trench depth (in) | B8: 24 | E8: Allowable voltage drop (%) | F8: 0.03 | G8: NEC treats voltage drop as an informational note, not a requirement. On a 300 ft feeder it is usually what decides the size.
A10: AC runs — switchgear to each charger: all-in-one units and power cabinets alike | C10: One feeder per AC-connected unit. An all-in-one charger and a power cabinet both take a feeder and both belong here; a DISPENSER does not — it takes DC from its cabinet and is scheduled in the DC runs block further down. The "What this run feeds" column below says which is which for every line.
A11: Unit | B11: Equip. line | C11: AC input kW (auto) | D11: Distance from switchgear (ft) | E11: Design current A (auto) | F11: Continuous 125% A (auto) | G11: OCPD A (auto) | H11: Ampacity floor A (auto) | I11: Conductor size | J11: Sets in parallel | K11: Ampacity per set, corrected (auto) | L11: Provided A (auto) | M11: Voltage drop % (auto) | N11: Verdict (auto) | O11: Conduit size | P11: What this run feeds (auto) | Q11: Phase conductor (ft) (auto) | R11: Ground size (auto, 250.122) | S11: Ground (ft) (auto) | T11: Conduit (ft) (auto) | U11: Comms (ft) (auto) | V11: Material cost (auto)
A12: Charger 1 | B12: 1 | C12: =IF(N($B12)=0,"",IFERROR(INDEX(Equipment!$G$7:$G$18,MATCH($B12,Equipment!$A$7:$A$18,0)),"")) | D12: 80 | E12: =IF(N($C12)=0,"",N($C12)*1000/(Project!$B$29*SQRT(3))) | F12: =IF(N($E12)=0,"",N($E12)*1.25) | G12: =IF(N($F12)=0,"",IF(ISNUMBER(MATCH($F12,OCPD_LIST,0)),$F12,IF($F12>MAX(OCPD_LIST),"ABOVE THE LARGEST STANDARD DEVICE",INDEX(OCPD_LIST,MATCH($F12,OCPD_LIST,1)+1)))) | H12: =IF(N($G12)=0,"",IF(N($G12)>800,N($G12),N($F12))) | I12: 300 kcmil | J12: 2 | K12: =IF($I12="","",IFERROR(MIN(N(INDEX(AMP_TBL,MATCH($I12,AMP_SIZE,0),MATCH($B$5&"-"&TEXT($F$6,"0"),AMP_HDR,0)))*N(INDEX(AMB_TBL,IF(ISNUMBER(MATCH($F$5,AMB_MAX,0)),MATCH($F$5,AMB_MAX,0),MATCH($F$5,AMB_MAX,1)+1),MATCH(TEXT($F$6,"0"),AMB_HDR,0))),N(INDEX(AMP_TBL,MATCH($I12,AMP_SIZE,0),MATCH($B$5&"-"&TEXT($F$7,"0"),AMP_HDR,0)))),"")) | L12: =IF(N($K12)=0,"",N($K12)*MAX(1,N($J12))) | M12: =IF(OR($I12="",N($D12)=0,N($E12)=0),"",IFERROR(SQRT(3)*N($E12)/MAX(1,N($J12))*N($D12)*N(INDEX(Z_TBL,MATCH($I12,Z_SIZE,0),IF($B$5="Cu",1,2)))/1000/Project!$B$29,"")) | N12: =IF(N($C12)=0,"",IF($I12="","pick a conductor size",IF($F$5="","SET THE DESIGN AMBIENT for this run — ampacity cannot be corrected without it, and this verdict cannot be trusted until it is set",IF(N($K12)=0,"no ampacity on file for that size — NEC Table 310.16 does not list it",IF(N($J12)=0,"enter the number of parallel sets",IF(N($L12)<N($H12),"UNDERSIZED — "&TEXT(N($L12),"#,##0")&" A provided against a floor of "&TEXT(N($H12),"#,##0")&" A. NEC 240.4(C) applies above 800 A: the conductor carries the device, not the load.",IF(N($M12)>N($F$8),"ampacity OK, but voltage drop "&TEXT(N($M12),"0.00%")&" exceeds the "&TEXT($F$8,"0.0%")&" allowance — ADVISORY, the impedance table is unverified","OK — "&TEXT(N($L12),"#,##0")&" A against a "&TEXT(N($H12),"#,##0")&" A floor; voltage drop "&TEXT(N($M12),"0.00%")&" (ADVISORY)"))))))) | O12: 3" | P12: =IF($B12="","",IFERROR(IF(INDEX(Equipment!$E$7:$E$18,MATCH($B12,Equipment!$A$7:$A$18,0))="power_cabinet","power cabinet — dispensers run on from it",IF(INDEX(Equipment!$E$7:$E$18,MATCH($B12,Equipment!$A$7:$A$18,0))="dispenser","DISPENSER — this belongs in the DC runs block, not here",IF(INDEX(Equipment!$B$7:$B$18,MATCH($B12,Equipment!$A$7:$A$18,0))="Level 2 AC","Level 2 — use the Level 2 branch circuits block","all-in-one charger"))),"equipment line not found")) | Q12: =IF(N($D12)=0,0,N($D12)*MAX(1,N($J12))*3) | R12: =IF(N($G12)=0,"",IFERROR(INDEX(IF($B$5="Cu",EGC_CU,EGC_AL),MATCH($G12,EGC_OCPD,1)+IF(ISNUMBER(MATCH($G12,EGC_OCPD,0)),0,1)),"")) | S12: =IF(N($D12)=0,0,N($D12)*MAX(1,N($J12))) | T12: =IF(N($D12)=0,0,N($D12)*MAX(1,N($J12))) | U12: =IF(N($D12)=0,0,N($D12)) | V12: =IFERROR(N($Q12)*INDEX(IF($B$5="Cu",WIRE_CU,WIRE_AL),MATCH($I12,WIRE_SIZE,0)),0)+IFERROR(N($S12)*INDEX(IF($B$5="Cu",WIRE_CU,WIRE_AL),MATCH($R12,WIRE_SIZE,0)),0)+IFERROR(N($T12)*INDEX(PVC_RATE,MATCH($O12,PVC_SIZE,0)),0)+IFERROR(N($U12)*INDEX(PVC_RATE,MATCH("(3/4"")",PVC_SIZE,0)),0)
A13: Charger 2 | B13: 1 | C13: =IF(N($B13)=0,"",IFERROR(INDEX(Equipment!$G$7:$G$18,MATCH($B13,Equipment!$A$7:$A$18,0)),"")) | D13: 95 | E13: =IF(N($C13)=0,"",N($C13)*1000/(Project!$B$29*SQRT(3))) | F13: =IF(N($E13)=0,"",N($E13)*1.25) | G13: =IF(N($F13)=0,"",IF(ISNUMBER(MATCH($F13,OCPD_LIST,0)),$F13,IF($F13>MAX(OCPD_LIST),"ABOVE THE LARGEST STANDARD DEVICE",INDEX(OCPD_LIST,MATCH($F13,OCPD_LIST,1)+1)))) | H13: =IF(N($G13)=0,"",IF(N($G13)>800,N($G13),N($F13))) | I13: 300 kcmil | J13: 2 | K13: =IF($I13="","",IFERROR(MIN(N(INDEX(AMP_TBL,MATCH($I13,AMP_SIZE,0),MATCH($B$5&"-"&TEXT($F$6,"0"),AMP_HDR,0)))*N(INDEX(AMB_TBL,IF(ISNUMBER(MATCH($F$5,AMB_MAX,0)),MATCH($F$5,AMB_MAX,0),MATCH($F$5,AMB_MAX,1)+1),MATCH(TEXT($F$6,"0"),AMB_HDR,0))),N(INDEX(AMP_TBL,MATCH($I13,AMP_SIZE,0),MATCH($B$5&"-"&TEXT($F$7,"0"),AMP_HDR,0)))),"")) | L13: =IF(N($K13)=0,"",N($K13)*MAX(1,N($J13))) | M13: =IF(OR($I13="",N($D13)=0,N($E13)=0),"",IFERROR(SQRT(3)*N($E13)/MAX(1,N($J13))*N($D13)*N(INDEX(Z_TBL,MATCH($I13,Z_SIZE,0),IF($B$5="Cu",1,2)))/1000/Project!$B$29,"")) | N13: =IF(N($C13)=0,"",IF($I13="","pick a conductor size",IF($F$5="","SET THE DESIGN AMBIENT for this run — ampacity cannot be corrected without it, and this verdict cannot be trusted until it is set",IF(N($K13)=0,"no ampacity on file for that size — NEC Table 310.16 does not list it",IF(N($J13)=0,"enter the number of parallel sets",IF(N($L13)<N($H13),"UNDERSIZED — "&TEXT(N($L13),"#,##0")&" A provided against a floor of "&TEXT(N($H13),"#,##0")&" A. NEC 240.4(C) applies above 800 A: the conductor carries the device, not the load.",IF(N($M13)>N($F$8),"ampacity OK, but voltage drop "&TEXT(N($M13),"0.00%")&" exceeds the "&TEXT($F$8,"0.0%")&" allowance — ADVISORY, the impedance table is unverified","OK — "&TEXT(N($L13),"#,##0")&" A against a "&TEXT(N($H13),"#,##0")&" A floor; voltage drop "&TEXT(N($M13),"0.00%")&" (ADVISORY)"))))))) | O13: 3" | P13: =IF($B13="","",IFERROR(IF(INDEX(Equipment!$E$7:$E$18,MATCH($B13,Equipment!$A$7:$A$18,0))="power_cabinet","power cabinet — dispensers run on from it",IF(INDEX(Equipment!$E$7:$E$18,MATCH($B13,Equipment!$A$7:$A$18,0))="dispenser","DISPENSER — this belongs in the DC runs block, not here",IF(INDEX(Equipment!$B$7:$B$18,MATCH($B13,Equipment!$A$7:$A$18,0))="Level 2 AC","Level 2 — use the Level 2 branch circuits block","all-in-one charger"))),"equipment line not found")) | Q13: =IF(N($D13)=0,0,N($D13)*MAX(1,N($J13))*3) | R13: =IF(N($G13)=0,"",IFERROR(INDEX(IF($B$5="Cu",EGC_CU,EGC_AL),MATCH($G13,EGC_OCPD,1)+IF(ISNUMBER(MATCH($G13,EGC_OCPD,0)),0,1)),"")) | S13: =IF(N($D13)=0,0,N($D13)*MAX(1,N($J13))) | T13: =IF(N($D13)=0,0,N($D13)*MAX(1,N($J13))) | U13: =IF(N($D13)=0,0,N($D13)) | V13: =IFERROR(N($Q13)*INDEX(IF($B$5="Cu",WIRE_CU,WIRE_AL),MATCH($I13,WIRE_SIZE,0)),0)+IFERROR(N($S13)*INDEX(IF($B$5="Cu",WIRE_CU,WIRE_AL),MATCH($R13,WIRE_SIZE,0)),0)+IFERROR(N($T13)*INDEX(PVC_RATE,MATCH($O13,PVC_SIZE,0)),0)+IFERROR(N($U13)*INDEX(PVC_RATE,MATCH("(3/4"")",PVC_SIZE,0)),0)
A14: Charger 3 | B14: 1 | C14: =IF(N($B14)=0,"",IFERROR(INDEX(Equipment!$G$7:$G$18,MATCH($B14,Equipment!$A$7:$A$18,0)),"")) | D14: 110 | E14: =IF(N($C14)=0,"",N($C14)*1000/(Project!$B$29*SQRT(3))) | F14: =IF(N($E14)=0,"",N($E14)*1.25) | G14: =IF(N($F14)=0,"",IF(ISNUMBER(MATCH($F14,OCPD_LIST,0)),$F14,IF($F14>MAX(OCPD_LIST),"ABOVE THE LARGEST STANDARD DEVICE",INDEX(OCPD_LIST,MATCH($F14,OCPD_LIST,1)+1)))) | H14: =IF(N($G14)=0,"",IF(N($G14)>800,N($G14),N($F14))) | I14: 300 kcmil | J14: 2 | K14: =IF($I14="","",IFERROR(MIN(N(INDEX(AMP_TBL,MATCH($I14,AMP_SIZE,0),MATCH($B$5&"-"&TEXT($F$6,"0"),AMP_HDR,0)))*N(INDEX(AMB_TBL,IF(ISNUMBER(MATCH($F$5,AMB_MAX,0)),MATCH($F$5,AMB_MAX,0),MATCH($F$5,AMB_MAX,1)+1),MATCH(TEXT($F$6,"0"),AMB_HDR,0))),N(INDEX(AMP_TBL,MATCH($I14,AMP_SIZE,0),MATCH($B$5&"-"&TEXT($F$7,"0"),AMP_HDR,0)))),"")) | L14: =IF(N($K14)=0,"",N($K14)*MAX(1,N($J14))) | M14: =IF(OR($I14="",N($D14)=0,N($E14)=0),"",IFERROR(SQRT(3)*N($E14)/MAX(1,N($J14))*N($D14)*N(INDEX(Z_TBL,MATCH($I14,Z_SIZE,0),IF($B$5="Cu",1,2)))/1000/Project!$B$29,"")) | N14: =IF(N($C14)=0,"",IF($I14="","pick a conductor size",IF($F$5="","SET THE DESIGN AMBIENT for this run — ampacity cannot be corrected without it, and this verdict cannot be trusted until it is set",IF(N($K14)=0,"no ampacity on file for that size — NEC Table 310.16 does not list it",IF(N($J14)=0,"enter the number of parallel sets",IF(N($L14)<N($H14),"UNDERSIZED — "&TEXT(N($L14),"#,##0")&" A provided against a floor of "&TEXT(N($H14),"#,##0")&" A. NEC 240.4(C) applies above 800 A: the conductor carries the device, not the load.",IF(N($M14)>N($F$8),"ampacity OK, but voltage drop "&TEXT(N($M14),"0.00%")&" exceeds the "&TEXT($F$8,"0.0%")&" allowance — ADVISORY, the impedance table is unverified","OK — "&TEXT(N($L14),"#,##0")&" A against a "&TEXT(N($H14),"#,##0")&" A floor; voltage drop "&TEXT(N($M14),"0.00%")&" (ADVISORY)"))))))) | O14: 3" | P14: =IF($B14="","",IFERROR(IF(INDEX(Equipment!$E$7:$E$18,MATCH($B14,Equipment!$A$7:$A$18,0))="power_cabinet","power cabinet — dispensers run on from it",IF(INDEX(Equipment!$E$7:$E$18,MATCH($B14,Equipment!$A$7:$A$18,0))="dispenser","DISPENSER — this belongs in the DC runs block, not here",IF(INDEX(Equipment!$B$7:$B$18,MATCH($B14,Equipment!$A$7:$A$18,0))="Level 2 AC","Level 2 — use the Level 2 branch circuits block","all-in-one charger"))),"equipment line not found")) | Q14: =IF(N($D14)=0,0,N($D14)*MAX(1,N($J14))*3) | R14: =IF(N($G14)=0,"",IFERROR(INDEX(IF($B$5="Cu",EGC_CU,EGC_AL),MATCH($G14,EGC_OCPD,1)+IF(ISNUMBER(MATCH($G14,EGC_OCPD,0)),0,1)),"")) | S14: =IF(N($D14)=0,0,N($D14)*MAX(1,N($J14))) | T14: =IF(N($D14)=0,0,N($D14)*MAX(1,N($J14))) | U14: =IF(N($D14)=0,0,N($D14)) | V14: =IFERROR(N($Q14)*INDEX(IF($B$5="Cu",WIRE_CU,WIRE_AL),MATCH($I14,WIRE_SIZE,0)),0)+IFERROR(N($S14)*INDEX(IF($B$5="Cu",WIRE_CU,WIRE_AL),MATCH($R14,WIRE_SIZE,0)),0)+IFERROR(N($T14)*INDEX(PVC_RATE,MATCH($O14,PVC_SIZE,0)),0)+IFERROR(N($U14)*INDEX(PVC_RATE,MATCH("(3/4"")",PVC_SIZE,0)),0)
A15: Charger 4 | B15: 1 | C15: =IF(N($B15)=0,"",IFERROR(INDEX(Equipment!$G$7:$G$18,MATCH($B15,Equipment!$A$7:$A$18,0)),"")) | D15: 125 | E15: =IF(N($C15)=0,"",N($C15)*1000/(Project!$B$29*SQRT(3))) | F15: =IF(N($E15)=0,"",N($E15)*1.25) | G15: =IF(N($F15)=0,"",IF(ISNUMBER(MATCH($F15,OCPD_LIST,0)),$F15,IF($F15>MAX(OCPD_LIST),"ABOVE THE LARGEST STANDARD DEVICE",INDEX(OCPD_LIST,MATCH($F15,OCPD_LIST,1)+1)))) | H15: =IF(N($G15)=0,"",IF(N($G15)>800,N($G15),N($F15))) | I15: 300 kcmil | J15: 2 | K15: =IF($I15="","",IFERROR(MIN(N(INDEX(AMP_TBL,MATCH($I15,AMP_SIZE,0),MATCH($B$5&"-"&TEXT($F$6,"0"),AMP_HDR,0)))*N(INDEX(AMB_TBL,IF(ISNUMBER(MATCH($F$5,AMB_MAX,0)),MATCH($F$5,AMB_MAX,0),MATCH($F$5,AMB_MAX,1)+1),MATCH(TEXT($F$6,"0"),AMB_HDR,0))),N(INDEX(AMP_TBL,MATCH($I15,AMP_SIZE,0),MATCH($B$5&"-"&TEXT($F$7,"0"),AMP_HDR,0)))),"")) | L15: =IF(N($K15)=0,"",N($K15)*MAX(1,N($J15))) | M15: =IF(OR($I15="",N($D15)=0,N($E15)=0),"",IFERROR(SQRT(3)*N($E15)/MAX(1,N($J15))*N($D15)*N(INDEX(Z_TBL,MATCH($I15,Z_SIZE,0),IF($B$5="Cu",1,2)))/1000/Project!$B$29,"")) | N15: =IF(N($C15)=0,"",IF($I15="","pick a conductor size",IF($F$5="","SET THE DESIGN AMBIENT for this run — ampacity cannot be corrected without it, and this verdict cannot be trusted until it is set",IF(N($K15)=0,"no ampacity on file for that size — NEC Table 310.16 does not list it",IF(N($J15)=0,"enter the number of parallel sets",IF(N($L15)<N($H15),"UNDERSIZED — "&TEXT(N($L15),"#,##0")&" A provided against a floor of "&TEXT(N($H15),"#,##0")&" A. NEC 240.4(C) applies above 800 A: the conductor carries the device, not the load.",IF(N($M15)>N($F$8),"ampacity OK, but voltage drop "&TEXT(N($M15),"0.00%")&" exceeds the "&TEXT($F$8,"0.0%")&" allowance — ADVISORY, the impedance table is unverified","OK — "&TEXT(N($L15),"#,##0")&" A against a "&TEXT(N($H15),"#,##0")&" A floor; voltage drop "&TEXT(N($M15),"0.00%")&" (ADVISORY)"))))))) | O15: 3" | P15: =IF($B15="","",IFERROR(IF(INDEX(Equipment!$E$7:$E$18,MATCH($B15,Equipment!$A$7:$A$18,0))="power_cabinet","power cabinet — dispensers run on from it",IF(INDEX(Equipment!$E$7:$E$18,MATCH($B15,Equipment!$A$7:$A$18,0))="dispenser","DISPENSER — this belongs in the DC runs block, not here",IF(INDEX(Equipment!$B$7:$B$18,MATCH($B15,Equipment!$A$7:$A$18,0))="Level 2 AC","Level 2 — use the Level 2 branch circuits block","all-in-one charger"))),"equipment line not found")) | Q15: =IF(N($D15)=0,0,N($D15)*MAX(1,N($J15))*3) | R15: =IF(N($G15)=0,"",IFERROR(INDEX(IF($B$5="Cu",EGC_CU,EGC_AL),MATCH($G15,EGC_OCPD,1)+IF(ISNUMBER(MATCH($G15,EGC_OCPD,0)),0,1)),"")) | S15: =IF(N($D15)=0,0,N($D15)*MAX(1,N($J15))) | T15: =IF(N($D15)=0,0,N($D15)*MAX(1,N($J15))) | U15: =IF(N($D15)=0,0,N($D15)) | V15: =IFERROR(N($Q15)*INDEX(IF($B$5="Cu",WIRE_CU,WIRE_AL),MATCH($I15,WIRE_SIZE,0)),0)+IFERROR(N($S15)*INDEX(IF($B$5="Cu",WIRE_CU,WIRE_AL),MATCH($R15,WIRE_SIZE,0)),0)+IFERROR(N($T15)*INDEX(PVC_RATE,MATCH($O15,PVC_SIZE,0)),0)+IFERROR(N($U15)*INDEX(PVC_RATE,MATCH("(3/4"")",PVC_SIZE,0)),0)
A16: Charger 5 | C16: =IF(N($B16)=0,"",IFERROR(INDEX(Equipment!$G$7:$G$18,MATCH($B16,Equipment!$A$7:$A$18,0)),"")) | E16: =IF(N($C16)=0,"",N($C16)*1000/(Project!$B$29*SQRT(3))) | F16: =IF(N($E16)=0,"",N($E16)*1.25) | G16: =IF(N($F16)=0,"",IF(ISNUMBER(MATCH($F16,OCPD_LIST,0)),$F16,IF($F16>MAX(OCPD_LIST),"ABOVE THE LARGEST STANDARD DEVICE",INDEX(OCPD_LIST,MATCH($F16,OCPD_LIST,1)+1)))) | H16: =IF(N($G16)=0,"",IF(N($G16)>800,N($G16),N($F16))) | K16: =IF($I16="","",IFERROR(MIN(N(INDEX(AMP_TBL,MATCH($I16,AMP_SIZE,0),MATCH($B$5&"-"&TEXT($F$6,"0"),AMP_HDR,0)))*N(INDEX(AMB_TBL,IF(ISNUMBER(MATCH($F$5,AMB_MAX,0)),MATCH($F$5,AMB_MAX,0),MATCH($F$5,AMB_MAX,1)+1),MATCH(TEXT($F$6,"0"),AMB_HDR,0))),N(INDEX(AMP_TBL,MATCH($I16,AMP_SIZE,0),MATCH($B$5&"-"&TEXT($F$7,"0"),AMP_HDR,0)))),"")) | L16: =IF(N($K16)=0,"",N($K16)*MAX(1,N($J16))) | M16: =IF(OR($I16="",N($D16)=0,N($E16)=0),"",IFERROR(SQRT(3)*N($E16)/MAX(1,N($J16))*N($D16)*N(INDEX(Z_TBL,MATCH($I16,Z_SIZE,0),IF($B$5="Cu",1,2)))/1000/Project!$B$29,"")) | N16: =IF(N($C16)=0,"",IF($I16="","pick a conductor size",IF($F$5="","SET THE DESIGN AMBIENT for this run — ampacity cannot be corrected without it, and this verdict cannot be trusted until it is set",IF(N($K16)=0,"no ampacity on file for that size — NEC Table 310.16 does not list it",IF(N($J16)=0,"enter the number of parallel sets",IF(N($L16)<N($H16),"UNDERSIZED — "&TEXT(N($L16),"#,##0")&" A provided against a floor of "&TEXT(N($H16),"#,##0")&" A. NEC 240.4(C) applies above 800 A: the conductor carries the device, not the load.",IF(N($M16)>N($F$8),"ampacity OK, but voltage drop "&TEXT(N($M16),"0.00%")&" exceeds the "&TEXT($F$8,"0.0%")&" allowance — ADVISORY, the impedance table is unverified","OK — "&TEXT(N($L16),"#,##0")&" A against a "&TEXT(N($H16),"#,##0")&" A floor; voltage drop "&TEXT(N($M16),"0.00%")&" (ADVISORY)"))))))) | P16: =IF($B16="","",IFERROR(IF(INDEX(Equipment!$E$7:$E$18,MATCH($B16,Equipment!$A$7:$A$18,0))="power_cabinet","power cabinet — dispensers run on from it",IF(INDEX(Equipment!$E$7:$E$18,MATCH($B16,Equipment!$A$7:$A$18,0))="dispenser","DISPENSER — this belongs in the DC runs block, not here",IF(INDEX(Equipment!$B$7:$B$18,MATCH($B16,Equipment!$A$7:$A$18,0))="Level 2 AC","Level 2 — use the Level 2 branch circuits block","all-in-one charger"))),"equipment line not found")) | Q16: =IF(N($D16)=0,0,N($D16)*MAX(1,N($J16))*3) | R16: =IF(N($G16)=0,"",IFERROR(INDEX(IF($B$5="Cu",EGC_CU,EGC_AL),MATCH($G16,EGC_OCPD,1)+IF(ISNUMBER(MATCH($G16,EGC_OCPD,0)),0,1)),"")) | S16: =IF(N($D16)=0,0,N($D16)*MAX(1,N($J16))) | T16: =IF(N($D16)=0,0,N($D16)*MAX(1,N($J16))) | U16: =IF(N($D16)=0,0,N($D16)) | V16: =IFERROR(N($Q16)*INDEX(IF($B$5="Cu",WIRE_CU,WIRE_AL),MATCH($I16,WIRE_SIZE,0)),0)+IFERROR(N($S16)*INDEX(IF($B$5="Cu",WIRE_CU,WIRE_AL),MATCH($R16,WIRE_SIZE,0)),0)+IFERROR(N($T16)*INDEX(PVC_RATE,MATCH($O16,PVC_SIZE,0)),0)+IFERROR(N($U16)*INDEX(PVC_RATE,MATCH("(3/4"")",PVC_SIZE,0)),0)
A17: Charger 6 | C17: =IF(N($B17)=0,"",IFERROR(INDEX(Equipment!$G$7:$G$18,MATCH($B17,Equipment!$A$7:$A$18,0)),"")) | E17: =IF(N($C17)=0,"",N($C17)*1000/(Project!$B$29*SQRT(3))) | F17: =IF(N($E17)=0,"",N($E17)*1.25) | G17: =IF(N($F17)=0,"",IF(ISNUMBER(MATCH($F17,OCPD_LIST,0)),$F17,IF($F17>MAX(OCPD_LIST),"ABOVE THE LARGEST STANDARD DEVICE",INDEX(OCPD_LIST,MATCH($F17,OCPD_LIST,1)+1)))) | H17: =IF(N($G17)=0,"",IF(N($G17)>800,N($G17),N($F17))) | K17: =IF($I17="","",IFERROR(MIN(N(INDEX(AMP_TBL,MATCH($I17,AMP_SIZE,0),MATCH($B$5&"-"&TEXT($F$6,"0"),AMP_HDR,0)))*N(INDEX(AMB_TBL,IF(ISNUMBER(MATCH($F$5,AMB_MAX,0)),MATCH($F$5,AMB_MAX,0),MATCH($F$5,AMB_MAX,1)+1),MATCH(TEXT($F$6,"0"),AMB_HDR,0))),N(INDEX(AMP_TBL,MATCH($I17,AMP_SIZE,0),MATCH($B$5&"-"&TEXT($F$7,"0"),AMP_HDR,0)))),"")) | L17: =IF(N($K17)=0,"",N($K17)*MAX(1,N($J17))) | M17: =IF(OR($I17="",N($D17)=0,N($E17)=0),"",IFERROR(SQRT(3)*N($E17)/MAX(1,N($J17))*N($D17)*N(INDEX(Z_TBL,MATCH($I17,Z_SIZE,0),IF($B$5="Cu",1,2)))/1000/Project!$B$29,"")) | N17: =IF(N($C17)=0,"",IF($I17="","pick a conductor size",IF($F$5="","SET THE DESIGN AMBIENT for this run — ampacity cannot be corrected without it, and this verdict cannot be trusted until it is set",IF(N($K17)=0,"no ampacity on file for that size — NEC Table 310.16 does not list it",IF(N($J17)=0,"enter the number of parallel sets",IF(N($L17)<N($H17),"UNDERSIZED — "&TEXT(N($L17),"#,##0")&" A provided against a floor of "&TEXT(N($H17),"#,##0")&" A. NEC 240.4(C) applies above 800 A: the conductor carries the device, not the load.",IF(N($M17)>N($F$8),"ampacity OK, but voltage drop "&TEXT(N($M17),"0.00%")&" exceeds the "&TEXT($F$8,"0.0%")&" allowance — ADVISORY, the impedance table is unverified","OK — "&TEXT(N($L17),"#,##0")&" A against a "&TEXT(N($H17),"#,##0")&" A floor; voltage drop "&TEXT(N($M17),"0.00%")&" (ADVISORY)"))))))) | P17: =IF($B17="","",IFERROR(IF(INDEX(Equipment!$E$7:$E$18,MATCH($B17,Equipment!$A$7:$A$18,0))="power_cabinet","power cabinet — dispensers run on from it",IF(INDEX(Equipment!$E$7:$E$18,MATCH($B17,Equipment!$A$7:$A$18,0))="dispenser","DISPENSER — this belongs in the DC runs block, not here",IF(INDEX(Equipment!$B$7:$B$18,MATCH($B17,Equipment!$A$7:$A$18,0))="Level 2 AC","Level 2 — use the Level 2 branch circuits block","all-in-one charger"))),"equipment line not found")) | Q17: =IF(N($D17)=0,0,N($D17)*MAX(1,N($J17))*3) | R17: =IF(N($G17)=0,"",IFERROR(INDEX(IF($B$5="Cu",EGC_CU,EGC_AL),MATCH($G17,EGC_OCPD,1)+IF(ISNUMBER(MATCH($G17,EGC_OCPD,0)),0,1)),"")) | S17: =IF(N($D17)=0,0,N($D17)*MAX(1,N($J17))) | T17: =IF(N($D17)=0,0,N($D17)*MAX(1,N($J17))) | U17: =IF(N($D17)=0,0,N($D17)) | V17: =IFERROR(N($Q17)*INDEX(IF($B$5="Cu",WIRE_CU,WIRE_AL),MATCH($I17,WIRE_SIZE,0)),0)+IFERROR(N($S17)*INDEX(IF($B$5="Cu",WIRE_CU,WIRE_AL),MATCH($R17,WIRE_SIZE,0)),0)+IFERROR(N($T17)*INDEX(PVC_RATE,MATCH($O17,PVC_SIZE,0)),0)+IFERROR(N($U17)*INDEX(PVC_RATE,MATCH("(3/4"")",PVC_SIZE,0)),0)
A18: Charger 7 | C18: =IF(N($B18)=0,"",IFERROR(INDEX(Equipment!$G$7:$G$18,MATCH($B18,Equipment!$A$7:$A$18,0)),"")) | E18: =IF(N($C18)=0,"",N($C18)*1000/(Project!$B$29*SQRT(3))) | F18: =IF(N($E18)=0,"",N($E18)*1.25) | G18: =IF(N($F18)=0,"",IF(ISNUMBER(MATCH($F18,OCPD_LIST,0)),$F18,IF($F18>MAX(OCPD_LIST),"ABOVE THE LARGEST STANDARD DEVICE",INDEX(OCPD_LIST,MATCH($F18,OCPD_LIST,1)+1)))) | H18: =IF(N($G18)=0,"",IF(N($G18)>800,N($G18),N($F18))) | K18: =IF($I18="","",IFERROR(MIN(N(INDEX(AMP_TBL,MATCH($I18,AMP_SIZE,0),MATCH($B$5&"-"&TEXT($F$6,"0"),AMP_HDR,0)))*N(INDEX(AMB_TBL,IF(ISNUMBER(MATCH($F$5,AMB_MAX,0)),MATCH($F$5,AMB_MAX,0),MATCH($F$5,AMB_MAX,1)+1),MATCH(TEXT($F$6,"0"),AMB_HDR,0))),N(INDEX(AMP_TBL,MATCH($I18,AMP_SIZE,0),MATCH($B$5&"-"&TEXT($F$7,"0"),AMP_HDR,0)))),"")) | L18: =IF(N($K18)=0,"",N($K18)*MAX(1,N($J18))) | M18: =IF(OR($I18="",N($D18)=0,N($E18)=0),"",IFERROR(SQRT(3)*N($E18)/MAX(1,N($J18))*N($D18)*N(INDEX(Z_TBL,MATCH($I18,Z_SIZE,0),IF($B$5="Cu",1,2)))/1000/Project!$B$29,"")) | N18: =IF(N($C18)=0,"",IF($I18="","pick a conductor size",IF($F$5="","SET THE DESIGN AMBIENT for this run — ampacity cannot be corrected without it, and this verdict cannot be trusted until it is set",IF(N($K18)=0,"no ampacity on file for that size — NEC Table 310.16 does not list it",IF(N($J18)=0,"enter the number of parallel sets",IF(N($L18)<N($H18),"UNDERSIZED — "&TEXT(N($L18),"#,##0")&" A provided against a floor of "&TEXT(N($H18),"#,##0")&" A. NEC 240.4(C) applies above 800 A: the conductor carries the device, not the load.",IF(N($M18)>N($F$8),"ampacity OK, but voltage drop "&TEXT(N($M18),"0.00%")&" exceeds the "&TEXT($F$8,"0.0%")&" allowance — ADVISORY, the impedance table is unverified","OK — "&TEXT(N($L18),"#,##0")&" A against a "&TEXT(N($H18),"#,##0")&" A floor; voltage drop "&TEXT(N($M18),"0.00%")&" (ADVISORY)"))))))) | P18: =IF($B18="","",IFERROR(IF(INDEX(Equipment!$E$7:$E$18,MATCH($B18,Equipment!$A$7:$A$18,0))="power_cabinet","power cabinet — dispensers run on from it",IF(INDEX(Equipment!$E$7:$E$18,MATCH($B18,Equipment!$A$7:$A$18,0))="dispenser","DISPENSER — this belongs in the DC runs block, not here",IF(INDEX(Equipment!$B$7:$B$18,MATCH($B18,Equipment!$A$7:$A$18,0))="Level 2 AC","Level 2 — use the Level 2 branch circuits block","all-in-one charger"))),"equipment line not found")) | Q18: =IF(N($D18)=0,0,N($D18)*MAX(1,N($J18))*3) | R18: =IF(N($G18)=0,"",IFERROR(INDEX(IF($B$5="Cu",EGC_CU,EGC_AL),MATCH($G18,EGC_OCPD,1)+IF(ISNUMBER(MATCH($G18,EGC_OCPD,0)),0,1)),"")) | S18: =IF(N($D18)=0,0,N($D18)*MAX(1,N($J18))) | T18: =IF(N($D18)=0,0,N($D18)*MAX(1,N($J18))) | U18: =IF(N($D18)=0,0,N($D18)) | V18: =IFERROR(N($Q18)*INDEX(IF($B$5="Cu",WIRE_CU,WIRE_AL),MATCH($I18,WIRE_SIZE,0)),0)+IFERROR(N($S18)*INDEX(IF($B$5="Cu",WIRE_CU,WIRE_AL),MATCH($R18,WIRE_SIZE,0)),0)+IFERROR(N($T18)*INDEX(PVC_RATE,MATCH($O18,PVC_SIZE,0)),0)+IFERROR(N($U18)*INDEX(PVC_RATE,MATCH("(3/4"")",PVC_SIZE,0)),0)
A19: Charger 8 | C19: =IF(N($B19)=0,"",IFERROR(INDEX(Equipment!$G$7:$G$18,MATCH($B19,Equipment!$A$7:$A$18,0)),"")) | E19: =IF(N($C19)=0,"",N($C19)*1000/(Project!$B$29*SQRT(3))) | F19: =IF(N($E19)=0,"",N($E19)*1.25) | G19: =IF(N($F19)=0,"",IF(ISNUMBER(MATCH($F19,OCPD_LIST,0)),$F19,IF($F19>MAX(OCPD_LIST),"ABOVE THE LARGEST STANDARD DEVICE",INDEX(OCPD_LIST,MATCH($F19,OCPD_LIST,1)+1)))) | H19: =IF(N($G19)=0,"",IF(N($G19)>800,N($G19),N($F19))) | K19: =IF($I19="","",IFERROR(MIN(N(INDEX(AMP_TBL,MATCH($I19,AMP_SIZE,0),MATCH($B$5&"-"&TEXT($F$6,"0"),AMP_HDR,0)))*N(INDEX(AMB_TBL,IF(ISNUMBER(MATCH($F$5,AMB_MAX,0)),MATCH($F$5,AMB_MAX,0),MATCH($F$5,AMB_MAX,1)+1),MATCH(TEXT($F$6,"0"),AMB_HDR,0))),N(INDEX(AMP_TBL,MATCH($I19,AMP_SIZE,0),MATCH($B$5&"-"&TEXT($F$7,"0"),AMP_HDR,0)))),"")) | L19: =IF(N($K19)=0,"",N($K19)*MAX(1,N($J19))) | M19: =IF(OR($I19="",N($D19)=0,N($E19)=0),"",IFERROR(SQRT(3)*N($E19)/MAX(1,N($J19))*N($D19)*N(INDEX(Z_TBL,MATCH($I19,Z_SIZE,0),IF($B$5="Cu",1,2)))/1000/Project!$B$29,"")) | N19: =IF(N($C19)=0,"",IF($I19="","pick a conductor size",IF($F$5="","SET THE DESIGN AMBIENT for this run — ampacity cannot be corrected without it, and this verdict cannot be trusted until it is set",IF(N($K19)=0,"no ampacity on file for that size — NEC Table 310.16 does not list it",IF(N($J19)=0,"enter the number of parallel sets",IF(N($L19)<N($H19),"UNDERSIZED — "&TEXT(N($L19),"#,##0")&" A provided against a floor of "&TEXT(N($H19),"#,##0")&" A. NEC 240.4(C) applies above 800 A: the conductor carries the device, not the load.",IF(N($M19)>N($F$8),"ampacity OK, but voltage drop "&TEXT(N($M19),"0.00%")&" exceeds the "&TEXT($F$8,"0.0%")&" allowance — ADVISORY, the impedance table is unverified","OK — "&TEXT(N($L19),"#,##0")&" A against a "&TEXT(N($H19),"#,##0")&" A floor; voltage drop "&TEXT(N($M19),"0.00%")&" (ADVISORY)"))))))) | P19: =IF($B19="","",IFERROR(IF(INDEX(Equipment!$E$7:$E$18,MATCH($B19,Equipment!$A$7:$A$18,0))="power_cabinet","power cabinet — dispensers run on from it",IF(INDEX(Equipment!$E$7:$E$18,MATCH($B19,Equipment!$A$7:$A$18,0))="dispenser","DISPENSER — this belongs in the DC runs block, not here",IF(INDEX(Equipment!$B$7:$B$18,MATCH($B19,Equipment!$A$7:$A$18,0))="Level 2 AC","Level 2 — use the Level 2 branch circuits block","all-in-one charger"))),"equipment line not found")) | Q19: =IF(N($D19)=0,0,N($D19)*MAX(1,N($J19))*3) | R19: =IF(N($G19)=0,"",IFERROR(INDEX(IF($B$5="Cu",EGC_CU,EGC_AL),MATCH($G19,EGC_OCPD,1)+IF(ISNUMBER(MATCH($G19,EGC_OCPD,0)),0,1)),"")) | S19: =IF(N($D19)=0,0,N($D19)*MAX(1,N($J19))) | T19: =IF(N($D19)=0,0,N($D19)*MAX(1,N($J19))) | U19: =IF(N($D19)=0,0,N($D19)) | V19: =IFERROR(N($Q19)*INDEX(IF($B$5="Cu",WIRE_CU,WIRE_AL),MATCH($I19,WIRE_SIZE,0)),0)+IFERROR(N($S19)*INDEX(IF($B$5="Cu",WIRE_CU,WIRE_AL),MATCH($R19,WIRE_SIZE,0)),0)+IFERROR(N($T19)*INDEX(PVC_RATE,MATCH($O19,PVC_SIZE,0)),0)+IFERROR(N($U19)*INDEX(PVC_RATE,MATCH("(3/4"")",PVC_SIZE,0)),0)
A20: Charger 9 | C20: =IF(N($B20)=0,"",IFERROR(INDEX(Equipment!$G$7:$G$18,MATCH($B20,Equipment!$A$7:$A$18,0)),"")) | E20: =IF(N($C20)=0,"",N($C20)*1000/(Project!$B$29*SQRT(3))) | F20: =IF(N($E20)=0,"",N($E20)*1.25) | G20: =IF(N($F20)=0,"",IF(ISNUMBER(MATCH($F20,OCPD_LIST,0)),$F20,IF($F20>MAX(OCPD_LIST),"ABOVE THE LARGEST STANDARD DEVICE",INDEX(OCPD_LIST,MATCH($F20,OCPD_LIST,1)+1)))) | H20: =IF(N($G20)=0,"",IF(N($G20)>800,N($G20),N($F20))) | K20: =IF($I20="","",IFERROR(MIN(N(INDEX(AMP_TBL,MATCH($I20,AMP_SIZE,0),MATCH($B$5&"-"&TEXT($F$6,"0"),AMP_HDR,0)))*N(INDEX(AMB_TBL,IF(ISNUMBER(MATCH($F$5,AMB_MAX,0)),MATCH($F$5,AMB_MAX,0),MATCH($F$5,AMB_MAX,1)+1),MATCH(TEXT($F$6,"0"),AMB_HDR,0))),N(INDEX(AMP_TBL,MATCH($I20,AMP_SIZE,0),MATCH($B$5&"-"&TEXT($F$7,"0"),AMP_HDR,0)))),"")) | L20: =IF(N($K20)=0,"",N($K20)*MAX(1,N($J20))) | M20: =IF(OR($I20="",N($D20)=0,N($E20)=0),"",IFERROR(SQRT(3)*N($E20)/MAX(1,N($J20))*N($D20)*N(INDEX(Z_TBL,MATCH($I20,Z_SIZE,0),IF($B$5="Cu",1,2)))/1000/Project!$B$29,"")) | N20: =IF(N($C20)=0,"",IF($I20="","pick a conductor size",IF($F$5="","SET THE DESIGN AMBIENT for this run — ampacity cannot be corrected without it, and this verdict cannot be trusted until it is set",IF(N($K20)=0,"no ampacity on file for that size — NEC Table 310.16 does not list it",IF(N($J20)=0,"enter the number of parallel sets",IF(N($L20)<N($H20),"UNDERSIZED — "&TEXT(N($L20),"#,##0")&" A provided against a floor of "&TEXT(N($H20),"#,##0")&" A. NEC 240.4(C) applies above 800 A: the conductor carries the device, not the load.",IF(N($M20)>N($F$8),"ampacity OK, but voltage drop "&TEXT(N($M20),"0.00%")&" exceeds the "&TEXT($F$8,"0.0%")&" allowance — ADVISORY, the impedance table is unverified","OK — "&TEXT(N($L20),"#,##0")&" A against a "&TEXT(N($H20),"#,##0")&" A floor; voltage drop "&TEXT(N($M20),"0.00%")&" (ADVISORY)"))))))) | P20: =IF($B20="","",IFERROR(IF(INDEX(Equipment!$E$7:$E$18,MATCH($B20,Equipment!$A$7:$A$18,0))="power_cabinet","power cabinet — dispensers run on from it",IF(INDEX(Equipment!$E$7:$E$18,MATCH($B20,Equipment!$A$7:$A$18,0))="dispenser","DISPENSER — this belongs in the DC runs block, not here",IF(INDEX(Equipment!$B$7:$B$18,MATCH($B20,Equipment!$A$7:$A$18,0))="Level 2 AC","Level 2 — use the Level 2 branch circuits block","all-in-one charger"))),"equipment line not found")) | Q20: =IF(N($D20)=0,0,N($D20)*MAX(1,N($J20))*3) | R20: =IF(N($G20)=0,"",IFERROR(INDEX(IF($B$5="Cu",EGC_CU,EGC_AL),MATCH($G20,EGC_OCPD,1)+IF(ISNUMBER(MATCH($G20,EGC_OCPD,0)),0,1)),"")) | S20: =IF(N($D20)=0,0,N($D20)*MAX(1,N($J20))) | T20: =IF(N($D20)=0,0,N($D20)*MAX(1,N($J20))) | U20: =IF(N($D20)=0,0,N($D20)) | V20: =IFERROR(N($Q20)*INDEX(IF($B$5="Cu",WIRE_CU,WIRE_AL),MATCH($I20,WIRE_SIZE,0)),0)+IFERROR(N($S20)*INDEX(IF($B$5="Cu",WIRE_CU,WIRE_AL),MATCH($R20,WIRE_SIZE,0)),0)+IFERROR(N($T20)*INDEX(PVC_RATE,MATCH($O20,PVC_SIZE,0)),0)+IFERROR(N($U20)*INDEX(PVC_RATE,MATCH("(3/4"")",PVC_SIZE,0)),0)
A21: Charger 10 | C21: =IF(N($B21)=0,"",IFERROR(INDEX(Equipment!$G$7:$G$18,MATCH($B21,Equipment!$A$7:$A$18,0)),"")) | E21: =IF(N($C21)=0,"",N($C21)*1000/(Project!$B$29*SQRT(3))) | F21: =IF(N($E21)=0,"",N($E21)*1.25) | G21: =IF(N($F21)=0,"",IF(ISNUMBER(MATCH($F21,OCPD_LIST,0)),$F21,IF($F21>MAX(OCPD_LIST),"ABOVE THE LARGEST STANDARD DEVICE",INDEX(OCPD_LIST,MATCH($F21,OCPD_LIST,1)+1)))) | H21: =IF(N($G21)=0,"",IF(N($G21)>800,N($G21),N($F21))) | K21: =IF($I21="","",IFERROR(MIN(N(INDEX(AMP_TBL,MATCH($I21,AMP_SIZE,0),MATCH($B$5&"-"&TEXT($F$6,"0"),AMP_HDR,0)))*N(INDEX(AMB_TBL,IF(ISNUMBER(MATCH($F$5,AMB_MAX,0)),MATCH($F$5,AMB_MAX,0),MATCH($F$5,AMB_MAX,1)+1),MATCH(TEXT($F$6,"0"),AMB_HDR,0))),N(INDEX(AMP_TBL,MATCH($I21,AMP_SIZE,0),MATCH($B$5&"-"&TEXT($F$7,"0"),AMP_HDR,0)))),"")) | L21: =IF(N($K21)=0,"",N($K21)*MAX(1,N($J21))) | M21: =IF(OR($I21="",N($D21)=0,N($E21)=0),"",IFERROR(SQRT(3)*N($E21)/MAX(1,N($J21))*N($D21)*N(INDEX(Z_TBL,MATCH($I21,Z_SIZE,0),IF($B$5="Cu",1,2)))/1000/Project!$B$29,"")) | N21: =IF(N($C21)=0,"",IF($I21="","pick a conductor size",IF($F$5="","SET THE DESIGN AMBIENT for this run — ampacity cannot be corrected without it, and this verdict cannot be trusted until it is set",IF(N($K21)=0,"no ampacity on file for that size — NEC Table 310.16 does not list it",IF(N($J21)=0,"enter the number of parallel sets",IF(N($L21)<N($H21),"UNDERSIZED — "&TEXT(N($L21),"#,##0")&" A provided against a floor of "&TEXT(N($H21),"#,##0")&" A. NEC 240.4(C) applies above 800 A: the conductor carries the device, not the load.",IF(N($M21)>N($F$8),"ampacity OK, but voltage drop "&TEXT(N($M21),"0.00%")&" exceeds the "&TEXT($F$8,"0.0%")&" allowance — ADVISORY, the impedance table is unverified","OK — "&TEXT(N($L21),"#,##0")&" A against a "&TEXT(N($H21),"#,##0")&" A floor; voltage drop "&TEXT(N($M21),"0.00%")&" (ADVISORY)"))))))) | P21: =IF($B21="","",IFERROR(IF(INDEX(Equipment!$E$7:$E$18,MATCH($B21,Equipment!$A$7:$A$18,0))="power_cabinet","power cabinet — dispensers run on from it",IF(INDEX(Equipment!$E$7:$E$18,MATCH($B21,Equipment!$A$7:$A$18,0))="dispenser","DISPENSER — this belongs in the DC runs block, not here",IF(INDEX(Equipment!$B$7:$B$18,MATCH($B21,Equipment!$A$7:$A$18,0))="Level 2 AC","Level 2 — use the Level 2 branch circuits block","all-in-one charger"))),"equipment line not found")) | Q21: =IF(N($D21)=0,0,N($D21)*MAX(1,N($J21))*3) | R21: =IF(N($G21)=0,"",IFERROR(INDEX(IF($B$5="Cu",EGC_CU,EGC_AL),MATCH($G21,EGC_OCPD,1)+IF(ISNUMBER(MATCH($G21,EGC_OCPD,0)),0,1)),"")) | S21: =IF(N($D21)=0,0,N($D21)*MAX(1,N($J21))) | T21: =IF(N($D21)=0,0,N($D21)*MAX(1,N($J21))) | U21: =IF(N($D21)=0,0,N($D21)) | V21: =IFERROR(N($Q21)*INDEX(IF($B$5="Cu",WIRE_CU,WIRE_AL),MATCH($I21,WIRE_SIZE,0)),0)+IFERROR(N($S21)*INDEX(IF($B$5="Cu",WIRE_CU,WIRE_AL),MATCH($R21,WIRE_SIZE,0)),0)+IFERROR(N($T21)*INDEX(PVC_RATE,MATCH($O21,PVC_SIZE,0)),0)+IFERROR(N($U21)*INDEX(PVC_RATE,MATCH("(3/4"")",PVC_SIZE,0)),0)
A22: Charger 11 | C22: =IF(N($B22)=0,"",IFERROR(INDEX(Equipment!$G$7:$G$18,MATCH($B22,Equipment!$A$7:$A$18,0)),"")) | E22: =IF(N($C22)=0,"",N($C22)*1000/(Project!$B$29*SQRT(3))) | F22: =IF(N($E22)=0,"",N($E22)*1.25) | G22: =IF(N($F22)=0,"",IF(ISNUMBER(MATCH($F22,OCPD_LIST,0)),$F22,IF($F22>MAX(OCPD_LIST),"ABOVE THE LARGEST STANDARD DEVICE",INDEX(OCPD_LIST,MATCH($F22,OCPD_LIST,1)+1)))) | H22: =IF(N($G22)=0,"",IF(N($G22)>800,N($G22),N($F22))) | K22: =IF($I22="","",IFERROR(MIN(N(INDEX(AMP_TBL,MATCH($I22,AMP_SIZE,0),MATCH($B$5&"-"&TEXT($F$6,"0"),AMP_HDR,0)))*N(INDEX(AMB_TBL,IF(ISNUMBER(MATCH($F$5,AMB_MAX,0)),MATCH($F$5,AMB_MAX,0),MATCH($F$5,AMB_MAX,1)+1),MATCH(TEXT($F$6,"0"),AMB_HDR,0))),N(INDEX(AMP_TBL,MATCH($I22,AMP_SIZE,0),MATCH($B$5&"-"&TEXT($F$7,"0"),AMP_HDR,0)))),"")) | L22: =IF(N($K22)=0,"",N($K22)*MAX(1,N($J22))) | M22: =IF(OR($I22="",N($D22)=0,N($E22)=0),"",IFERROR(SQRT(3)*N($E22)/MAX(1,N($J22))*N($D22)*N(INDEX(Z_TBL,MATCH($I22,Z_SIZE,0),IF($B$5="Cu",1,2)))/1000/Project!$B$29,"")) | N22: =IF(N($C22)=0,"",IF($I22="","pick a conductor size",IF($F$5="","SET THE DESIGN AMBIENT for this run — ampacity cannot be corrected without it, and this verdict cannot be trusted until it is set",IF(N($K22)=0,"no ampacity on file for that size — NEC Table 310.16 does not list it",IF(N($J22)=0,"enter the number of parallel sets",IF(N($L22)<N($H22),"UNDERSIZED — "&TEXT(N($L22),"#,##0")&" A provided against a floor of "&TEXT(N($H22),"#,##0")&" A. NEC 240.4(C) applies above 800 A: the conductor carries the device, not the load.",IF(N($M22)>N($F$8),"ampacity OK, but voltage drop "&TEXT(N($M22),"0.00%")&" exceeds the "&TEXT($F$8,"0.0%")&" allowance — ADVISORY, the impedance table is unverified","OK — "&TEXT(N($L22),"#,##0")&" A against a "&TEXT(N($H22),"#,##0")&" A floor; voltage drop "&TEXT(N($M22),"0.00%")&" (ADVISORY)"))))))) | P22: =IF($B22="","",IFERROR(IF(INDEX(Equipment!$E$7:$E$18,MATCH($B22,Equipment!$A$7:$A$18,0))="power_cabinet","power cabinet — dispensers run on from it",IF(INDEX(Equipment!$E$7:$E$18,MATCH($B22,Equipment!$A$7:$A$18,0))="dispenser","DISPENSER — this belongs in the DC runs block, not here",IF(INDEX(Equipment!$B$7:$B$18,MATCH($B22,Equipment!$A$7:$A$18,0))="Level 2 AC","Level 2 — use the Level 2 branch circuits block","all-in-one charger"))),"equipment line not found")) | Q22: =IF(N($D22)=0,0,N($D22)*MAX(1,N($J22))*3) | R22: =IF(N($G22)=0,"",IFERROR(INDEX(IF($B$5="Cu",EGC_CU,EGC_AL),MATCH($G22,EGC_OCPD,1)+IF(ISNUMBER(MATCH($G22,EGC_OCPD,0)),0,1)),"")) | S22: =IF(N($D22)=0,0,N($D22)*MAX(1,N($J22))) | T22: =IF(N($D22)=0,0,N($D22)*MAX(1,N($J22))) | U22: =IF(N($D22)=0,0,N($D22)) | V22: =IFERROR(N($Q22)*INDEX(IF($B$5="Cu",WIRE_CU,WIRE_AL),MATCH($I22,WIRE_SIZE,0)),0)+IFERROR(N($S22)*INDEX(IF($B$5="Cu",WIRE_CU,WIRE_AL),MATCH($R22,WIRE_SIZE,0)),0)+IFERROR(N($T22)*INDEX(PVC_RATE,MATCH($O22,PVC_SIZE,0)),0)+IFERROR(N($U22)*INDEX(PVC_RATE,MATCH("(3/4"")",PVC_SIZE,0)),0)
A23: Charger 12 | C23: =IF(N($B23)=0,"",IFERROR(INDEX(Equipment!$G$7:$G$18,MATCH($B23,Equipment!$A$7:$A$18,0)),"")) | E23: =IF(N($C23)=0,"",N($C23)*1000/(Project!$B$29*SQRT(3))) | F23: =IF(N($E23)=0,"",N($E23)*1.25) | G23: =IF(N($F23)=0,"",IF(ISNUMBER(MATCH($F23,OCPD_LIST,0)),$F23,IF($F23>MAX(OCPD_LIST),"ABOVE THE LARGEST STANDARD DEVICE",INDEX(OCPD_LIST,MATCH($F23,OCPD_LIST,1)+1)))) | H23: =IF(N($G23)=0,"",IF(N($G23)>800,N($G23),N($F23))) | K23: =IF($I23="","",IFERROR(MIN(N(INDEX(AMP_TBL,MATCH($I23,AMP_SIZE,0),MATCH($B$5&"-"&TEXT($F$6,"0"),AMP_HDR,0)))*N(INDEX(AMB_TBL,IF(ISNUMBER(MATCH($F$5,AMB_MAX,0)),MATCH($F$5,AMB_MAX,0),MATCH($F$5,AMB_MAX,1)+1),MATCH(TEXT($F$6,"0"),AMB_HDR,0))),N(INDEX(AMP_TBL,MATCH($I23,AMP_SIZE,0),MATCH($B$5&"-"&TEXT($F$7,"0"),AMP_HDR,0)))),"")) | L23: =IF(N($K23)=0,"",N($K23)*MAX(1,N($J23))) | M23: =IF(OR($I23="",N($D23)=0,N($E23)=0),"",IFERROR(SQRT(3)*N($E23)/MAX(1,N($J23))*N($D23)*N(INDEX(Z_TBL,MATCH($I23,Z_SIZE,0),IF($B$5="Cu",1,2)))/1000/Project!$B$29,"")) | N23: =IF(N($C23)=0,"",IF($I23="","pick a conductor size",IF($F$5="","SET THE DESIGN AMBIENT for this run — ampacity cannot be corrected without it, and this verdict cannot be trusted until it is set",IF(N($K23)=0,"no ampacity on file for that size — NEC Table 310.16 does not list it",IF(N($J23)=0,"enter the number of parallel sets",IF(N($L23)<N($H23),"UNDERSIZED — "&TEXT(N($L23),"#,##0")&" A provided against a floor of "&TEXT(N($H23),"#,##0")&" A. NEC 240.4(C) applies above 800 A: the conductor carries the device, not the load.",IF(N($M23)>N($F$8),"ampacity OK, but voltage drop "&TEXT(N($M23),"0.00%")&" exceeds the "&TEXT($F$8,"0.0%")&" allowance — ADVISORY, the impedance table is unverified","OK — "&TEXT(N($L23),"#,##0")&" A against a "&TEXT(N($H23),"#,##0")&" A floor; voltage drop "&TEXT(N($M23),"0.00%")&" (ADVISORY)"))))))) | P23: =IF($B23="","",IFERROR(IF(INDEX(Equipment!$E$7:$E$18,MATCH($B23,Equipment!$A$7:$A$18,0))="power_cabinet","power cabinet — dispensers run on from it",IF(INDEX(Equipment!$E$7:$E$18,MATCH($B23,Equipment!$A$7:$A$18,0))="dispenser","DISPENSER — this belongs in the DC runs block, not here",IF(INDEX(Equipment!$B$7:$B$18,MATCH($B23,Equipment!$A$7:$A$18,0))="Level 2 AC","Level 2 — use the Level 2 branch circuits block","all-in-one charger"))),"equipment line not found")) | Q23: =IF(N($D23)=0,0,N($D23)*MAX(1,N($J23))*3) | R23: =IF(N($G23)=0,"",IFERROR(INDEX(IF($B$5="Cu",EGC_CU,EGC_AL),MATCH($G23,EGC_OCPD,1)+IF(ISNUMBER(MATCH($G23,EGC_OCPD,0)),0,1)),"")) | S23: =IF(N($D23)=0,0,N($D23)*MAX(1,N($J23))) | T23: =IF(N($D23)=0,0,N($D23)*MAX(1,N($J23))) | U23: =IF(N($D23)=0,0,N($D23)) | V23: =IFERROR(N($Q23)*INDEX(IF($B$5="Cu",WIRE_CU,WIRE_AL),MATCH($I23,WIRE_SIZE,0)),0)+IFERROR(N($S23)*INDEX(IF($B$5="Cu",WIRE_CU,WIRE_AL),MATCH($R23,WIRE_SIZE,0)),0)+IFERROR(N($T23)*INDEX(PVC_RATE,MATCH($O23,PVC_SIZE,0)),0)+IFERROR(N($U23)*INDEX(PVC_RATE,MATCH("(3/4"")",PVC_SIZE,0)),0)
A24: AC branch material cost ($) | B24: =SUM($V$12:$V$23) | C24: Phase conductor, equipment ground, conduit and a comms run for every AC branch, at RefData rates. This used to be computed in the project model instead, so a conductor size could be changed here and the cost only moved two artefacts later. The model now reads this figure.
A25: Total AC branch distance (ft) | B25: =SUM($D$12:$D$23) | C25: Switchgear to the cabinets only. The transformer-to-switchgear run is separate and is sized in its own block at the foot of this tab.
A26: AC-connected units placed | B26: =SUMPRODUCT(ISNUMBER($D$12:$D$23)*($D$12:$D$23>0)) | C26: Must equal Total cabinets on 2_Equipment
A27: Placement matches equipment? | B27: =IF(COUNT(C12:C23)=Equipment!$B$21,"OK — a distance for every AC-connected unit","MISMATCH — "&TEXT(Equipment!$B$21,"0")&" cabinets or all-in-one chargers but "&TEXT(COUNT(C12:C23),"0")&" distances") | C27: Counts power cabinets and all-in-one chargers. Dispensers are not counted here.
A28: Every AC run costed? | B28: =IF(COUNT($D$12:$D$23)=0,"OK — no AC runs entered yet",IF(SUMPRODUCT(--($D$12:$D$23>0),--($V$12:$V$23=0))>0,"A RUN HAS A DISTANCE BUT NO MATERIAL COST — check the conductor size, the conduit size and the sets in parallel on that line. A run costing zero is a run nobody priced.","OK — every AC run with a distance carries a material cost"))
A29: Service and switchgear
A30: Point of connection | B30: Existing MSB | C30: Existing MSB / new service / pole transformer
A31: Distance, transformer to switchgear (ft) | B31: 40 | C31: Customer-side feeder, our scope. Sized in the service feeder block at the foot of this tab, which has its own material and its own ambient.
A32: Distance, switchgear to pole (ft) | B32: 120
A33: Spare capacity in existing gear (A) | B33: 200 | C33: 0 if a new service is required
A34: Load management proposed? | B34: No | C34: Yes caps site draw below full nameplate
A35: Capped site draw (kW) if load managed | C35: Leave blank if not load managed
A36: Service boards in the lineup | B36: 1 | C36: One unless the service is split. Above roughly 4,000 A it usually is: NEC 230.71 allows up to six service disconnects in separate enclosures, and the frame below is sized PER BOARD. A site needing 6,303 A has no single frame RefData can price; two boards at 3,151 A each have one.
A37: Live electrical check — derived from 2_Equipment
A38: Connected load (kW) | B38: =IF($B$34="Yes",IF(N($B$35)=0,Equipment!B23,MIN(Equipment!B23,N($B$35))),Equipment!B23) | C38: Full nameplate from the equipment schedule, or the managed cap when load management is proposed and a cap is entered. Sizing to a managed maximum needs an energy management system under NEC 750 and the engineer's sign-off — the sheet applies the cap you enter, it does not certify it.
A39: Design current at service voltage (A) | B39: =IF(N($B$38)=0,"",$B$38*1000/(Project!$B$29*SQRT(3))) | C39: kW x 1000 / (V x sqrt 3)
A40: Required OCPD at 125% (A) | B40: =IF(N($B$39)=0,"",N($B$39)*1.25) | C40: NEC continuous-load rule
A41: Standard frame required per board (A) | B41: =IF(N($B$40)=0,"",IFERROR(INDEX(RefData!$B$4:$B$15,MATCH(N($B$40)/MAX(1,N($B$36)),RefData!$A$4:$A$15,1)),"check the frame table")) | C41: The required overcurrent device divided across the boards in the lineup, then rounded up to the next standard frame.
A42: Switchgear size being priced (A) | B42: 3200 | C42: Type what you are actually quoting
A43: Switchgear adequate? | B43: =IF(N($B$38)=0,"no connected load on the equipment tab",IF(N($B$41)=0,"CANNOT TELL — there is a connected load but no required frame behind it",IF(N($B$42)=0,"enter the frame being priced",IF(N($B$42)<N($B$41),"UNDERSIZED — "&TEXT($B$42,"#,##0")&" A per board against "&TEXT($B$41,"#,##0")&" A required on each of "&TEXT(MAX(1,N($B$36)),"0")&" board(s)",IF(ISNA(MATCH(TEXT($B$42,"0")&"A",RefData!$B$20:$B$29,0)),"OK on size, BUT RefData carries no price for a "&TEXT($B$42,"#,##0")&" A frame — it needs a switchboard quote","OK — "&TEXT(MAX(1,N($B$36)),"0")&" x "&TEXT($B$42,"#,##0")&" A against "&TEXT($B$41,"#,##0")&" A required per board"))))) | C43: Checks the per-board size AND whether the workbook can price that frame.
A44: Load management stated and capped? | B44: =IF($B$34<>"Yes","n/a — not load managed, so the site is sized on full nameplate",IF(N($B$35)=0,"LOAD MANAGED WITH NO CAP ENTERED — the sheet has fallen back to full nameplate and the frame below is sized for an unmanaged site","Sized on a managed cap of "&TEXT($B$35,"#,##0")&" kW against "&TEXT(N(Equipment!$B$23),"#,##0")&" kW of nameplate. The energy management system that enforces it is scope, and the AHJ will ask to see it."))
A48: Utility interconnection — governed by the serving utility
A49: The rows marked CA ONLY are written around PG&E Electric Rule 29 and Rules 15/16. They apply only where the Project tab's interconnection regime says they do. Anywhere else leave them blank: what the utility requires and charges to connect this site is their answer for this site, and it belongs in their quote and then in the fee block on the Construction tab as a pass-through.
A51: Service type | B51: Added load to existing service | C51: New service / added load to existing service
A52: Overhead or underground service | B52: Underground
A53: Distance to PG&E point of interconnection (ft) | B53: 150 | C53: CA ONLY — Drives whether distribution work is likely
A54: Rule 29 application submitted? | B54: No | C54: CA ONLY — Yes / No — with date
A55: PG&E project or design number | C55: CA ONLY — Once issued
A56: Utility interconnection design and application fee | B56: 3500 | C56: What the serving utility charges to design and connect the service. Leave blank until they say. There is no default: the $3,500 that used to sit here was PG&E's typical Rule 29 figure and it followed a Michigan project into its cost build-up.
A57: Rule 15 distribution extension indicated? | B57: Unknown — design not yet submitted | C57: CA ONLY — Unknown until the utility design is returned
A58: Rule 15 allowance calculated by PG&E | C58: CA ONLY — Leave blank until the design comes back
A59: Customer contribution above the allowance | C59: CA ONLY — Leave blank until the design comes back
A60: Rule 16 component? | B60: Unknown | C60: CA ONLY — Temporary or speculative service only
A61: ITCC gross-up applies? | B61: Only if Rule 15/16 contribution arises | C61: CA ONLY — Tax on any contribution to utility-owned plant
A62: Transformer pad location agreed with client? | B62: Yes | C62: Client must provide the space
A63: Proof of commitment to purchase provided? | B63: Yes | C63: CA ONLY — Rule 29 requires a PO, budget approval or grant agreement
A64: Client accepts the 5-year operate-and-maintain obligation? | B64: Yes | C64: CA ONLY — Rule 29 condition
A65: Client accepts 30-business-day activation after energization? | B65: Yes | C65: CA ONLY — Rule 29 condition, 180 days maximum
A66: Utility design submitted (date)
A67: Utility design returned (date)
A69: Retained infrastructure — replacement sites only
A70: Mirrors the register on the Existing tab section B. Where an element is retained, the corresponding material take-off should be entered as zero rather than left at the standard build quantity. These checks say plainly which lines to zero. ON A GREENFIELD PROJECT THIS WHOLE BLOCK IS INERT and says so — the register can hold whatever it likes and none of it reaches the take-off.
A71: Project type | B71: =Existing!$B$5 | C71: From the Existing tab.
A73: Electrical element | B73: Decision | C73: What it means for the take-off
A74: Utility service and meter | B74: =IF(Existing!$B$5="Greenfield — new service","n/a — greenfield",Existing!$B$13) | C74: =IF($B$74="n/a — greenfield","Greenfield — there is nothing to retain, so this line has no bearing on the take-off. The full electrical scope is priced.",IF($B$74="RETAIN","No Rule 29 application, no new service, no interconnection allowance. Zero the utility lines below.",IF($B$74="NOT PRESENT","Not present on this site.","Price the new service and the Rule 29 scope in full.")))
A75: Service feeder | B75: =IF(Existing!$B$5="Greenfield — new service","n/a — greenfield",Existing!$B$14) | C75: =IF($B$75="n/a — greenfield","Greenfield — there is nothing to retain, so this line has no bearing on the take-off. The full electrical scope is priced.",IF($B$75="RETAIN","Zero the service feeder conductor. Verify ampacity against the new load first.",IF($B$75="NOT PRESENT","Not present on this site.","Price the service feeder at the distances entered above.")))
A76: Switchgear | B76: =IF(Existing!$B$5="Greenfield — new service","n/a — greenfield",Existing!$B$15) | C76: =IF($B$76="n/a — greenfield","Greenfield — there is nothing to retain, so this line has no bearing on the take-off. The full electrical scope is priced.",IF($B$76="RETAIN","Zero the switchgear line. Confirm the frame carries the new load — see the check on the Existing tab.",IF($B$76="NOT PRESENT","Not present on this site.","Price a new switchboard sized to the new load.")))
A77: Branch conductors | B77: =IF(Existing!$B$5="Greenfield — new service","n/a — greenfield",Existing!$B$16) | C77: =IF($B$77="n/a — greenfield","Greenfield — there is nothing to retain, so this line has no bearing on the take-off. The full electrical scope is priced.",IF($B$77="RETAIN","Zero the feeder conductor and equipment ground. The largest single saving on a replacement.",IF($B$77="NOT PRESENT","Not present on this site.","Price branch conductors at the placement distances entered above.")))
A78: Conduit and trench | B78: =IF(Existing!$B$5="Greenfield — new service","n/a — greenfield",Existing!$B$17) | C78: =IF($B$78="n/a — greenfield","Greenfield — there is nothing to retain, so this line has no bearing on the take-off. The full electrical scope is priced.",IF($B$78="RETAIN","Zero conduit, trenching, paving reinstatement and GPR. No ground is opened.",IF($B$78="NOT PRESENT","Not present on this site.","Price conduit and trenching in full.")))
A79: Branch breakers | B79: =IF(Existing!$B$5="Greenfield — new service","n/a — greenfield",Existing!$B$18) | C79: =IF($B$79="n/a — greenfield","Greenfield — there is nothing to retain, so this line has no bearing on the take-off. The full electrical scope is priced.",IF($B$79="RETAIN","Rare. Breakers are normally replaced to match the new cabinet.",IF($B$79="NOT PRESENT","Not present on this site.","Price one breaker per new cabinet at the size on the Equipment tab.")))
A81: Electrical scope profile | B81: =IF(Existing!$B$5="Greenfield — new service","GREENFIELD — price the full electrical scope",IF(AND(Existing!$B$13="RETAIN",Existing!$B$16="RETAIN",Existing!$B$17="RETAIN"),"CHARGER SWAP — electrical scope is breakers, terminations and commissioning only","PARTIAL REUSE — price only the elements marked REPLACE above")) | D81: The one-line summary of what the electrical estimate should contain.
A82: Reuse feasibility | B82: =IF(Existing!$B$5="Greenfield — new service","n/a",IF(OR(Existing!$B$50="",Equipment!B23=""),"enter the existing service size and the new equipment",IF(Equipment!B23*1000/(Project!B29*SQRT(3))*1.25<=Existing!$B$50,"OK — reuse is feasible on capacity grounds","REUSE NOT FEASIBLE — the new load exceeds the existing service. This is a service upgrade, not a swap."))) | D82: Repeats the Existing tab capacity test here, where the electrical estimate is actually built.
A85: DC runs — moved to the foot of this tab
A86: MOVED. The dispenser run schedule is now at row 171 of this tab, where it has 32 rows instead of 12 and totals bound to the table. It moved because a site with three 1.28 MW cabinets needs 24 rows, and the twelve-row table was extended by hand while the totals underneath went on summing the first twelve.
A116: SERVICE FEEDER — TRANSFORMER TO SWITCHGEAR
A117: One feeder carrying the whole site, so the load is the equipment tab's total rather than any single unit. The columns line up with the AC branch table above — load, distance, current, device, floor, size, sets, verdict all sit in the same columns — so the two tables can be read against each other. The distance is read from the Service and switchgear block above; do not retype it here.
A118: Governing rule | B118: Service conductor — NEC 230.42 | C118: A conductor from the utility transformer to the service disconnect is a SERVICE conductor. Its overcurrent device sits at the far end, in the switchgear, so NEC 240.4(C) — which sizes a conductor to the device feeding it — does not apply. 230.42(A) asks for 125% of the continuous load, which is the same figure the branch runs start from but without the step up to the next standard device. Switch to Feeder if the run is protected at its supply end.
A119: Who provides this run? | B119: Utility — EV infrastructure rule | C119: Under the California IOUs' EV infrastructure rules — PG&E Electric Rule 29, SDG&E Rule 45 and their equivalents — the utility designs, builds and owns the service from its transformer to the customer's service equipment. On those projects this run is NOT ours to price, and the bid excludes it by name rather than carrying it silently. It is still sized here, because we have to coordinate with what the utility installs and check it carries the load. Switch to Zero Impact Energy where the service point sits at the transformer secondary and the conductors are genuinely customer-side.
A120: Design ambient for this run (C) | C120: Site data for THIS run. A buried duct bank and a run on a south wall are different numbers, and neither is a house default.
A122: Run | B122: Conductor material | C122: Site load kW (auto) | D122: Distance to switchgear (ft) | E122: Design current A (auto) | F122: Continuous 125% A (auto) | G122: OCPD A (auto) | H122: Ampacity floor A (auto) | I122: Conductor size | J122: Sets in parallel | K122: Ampacity per set, corrected (auto) | L122: Provided A (auto) | M122: Voltage drop % (auto) | N122: Verdict (auto) | O122: Per lateral. A two-board service has two of these runs, and asking one conductor to carry 6,303 A was a question with no answer.
A123: Transformer to switchgear | C123: =Equipment!$B$23 | D123: =$B$31 | E123: =IF(N($C123)=0,"",N($C123)*1000/(Project!$B$29*SQRT(3))/MAX(1,N($B$36))) | F123: =IF(N($E123)=0,"",N($E123)*1.25) | G123: =IF(N($F$123)=0,"",IF(ISNUMBER(MATCH($F$123,OCPD_LIST,0)),$F$123,IF($F$123>MAX(OCPD_LIST),"ABOVE THE LARGEST STANDARD DEVICE — "&TEXT($F$123,"#,##0")&" A is past the end of the standard frame list. This is a switchboard quote and probably a medium-voltage service, not a catalogue item.",INDEX(OCPD_LIST,MATCH($F$123,OCPD_LIST,1)+1)))) | H123: =IF(N($F$123)=0,"",IF(LEFT($B$118,7)="Service",N($F$123),IF(N($G$123)>800,N($G$123),N($F$123)))) | K123: =IF($I$123="","",IFERROR(MIN(N(INDEX(AMP_TBL,MATCH($I$123,AMP_SIZE,0),MATCH($B$123&"-"&TEXT($F$6,"0"),AMP_HDR,0)))*N(INDEX(AMB_TBL,IF(ISNUMBER(MATCH($B$120,AMB_MAX,0)),MATCH($B$120,AMB_MAX,0),MATCH($B$120,AMB_MAX,1)+1),MATCH(TEXT($F$6,"0"),AMB_HDR,0))),N(INDEX(AMP_TBL,MATCH($I$123,AMP_SIZE,0),MATCH($B$123&"-"&TEXT($F$7,"0"),AMP_HDR,0)))),"")) | L123: =IF(N($K$123)=0,"",N($K$123)*MAX(1,N($J$123))) | M123: =IF(OR($I$123="",N($D$123)=0,N($E$123)=0),"",IFERROR(SQRT(3)*N($E$123)/MAX(1,N($J$123))*N($D$123)*N(INDEX(Z_TBL,MATCH($I$123,Z_SIZE,0),IF($B$123="Cu",1,2)))/1000/Project!$B$29,"")) | N123: =IF(LEFT($B$119,7)="Utility","n/a — the serving utility provides this run under its EV infrastructure rule, so it is not sized or costed here",IF(N($C$123)=0,"no connected load on the equipment tab",IF($I$123="","pick a conductor size",IF(N($K$123)=0,"no ampacity on file for that size and material — NEC Table 310.16 does not list the combination",IF(N($J$123)=0,"enter the number of parallel sets",IF(N($L$123)<N($H$123),"UNDERSIZED — "&TEXT(N($L$123),"#,##0")&" A provided against a floor of "&TEXT(N($H$123),"#,##0")&" A, set by "&$B$118,IF(N($M$123)>N($F$8),"ampacity OK, but voltage drop "&TEXT(N($M$123),"0.00%")&" exceeds the "&TEXT($F$8,"0.0%")&" allowance — ADVISORY, the impedance table is unverified","OK — "&TEXT(N($L$123),"#,##0")&" A against a "&TEXT(N($H$123),"#,##0")&" A floor ("&$B$118&"); voltage drop "&TEXT(N($M$123),"0.00%")&" (ADVISORY). "&IF(LEFT($B$119,7)="Utility","UTILITY SCOPE — sized for coordination, NOT priced in the bid.","Priced in the bid as customer-side scope.")))))))) | O123: Stands down when the utility provides the run. It used to say "pick a conductor size" about a conductor that is not in our scope.
A125: The branch runs above take their conductor material from the Materials block and their ambient from the sizing basis beside it. This run takes both from the two blue cells at the top of this block, because a long buried aluminium service feeding short copper branches is an ordinary design and the sheet should let you say so. Whatever is picked here is what the bid prices — the model no longer chooses.
A127: DISTRIBUTION EQUIPMENT SCHEDULE
A128: Every board, panel, disconnect and transformer between the point of connection and the chargers. Until this block existed the workbook modelled one switchboard and nothing else, so a two-voltage site had nowhere to put its subpanels and they arrived as one lump in the Overrides register. Price each line or say who does: an unpriced row in a schedule reads as free.
A129: Item | B129: Type | C129: Qty | D129: Volts | E129: Phases | F129: Rating (A) | G129: Fed from | H129: What it feeds | I129: Location | J129: Who provides | K129: Cost basis | L129: Quoted cost ($)
A130: EVSE disconnects | B130: EVSE disconnect | C130: 4 | D130: 480 | E130: 3 | F130: 600 | G130: MSB | H130: TP5 cabinets | I130: Pad | J130: Zero Impact Energy | K130: Vendor quote | L130: 12000
A142: Items scheduled | B142: =SUMPRODUCT(--($A$130:$A$141<>""),--($C$130:$C$141>0))*0+SUM($C$130:$C$141)
A143: Distribution equipment cost ($) | B143: =SUM($L$130:$L$141) | C143: Carried into the cost build-up as distribution equipment, at the materials markup. Enter it in the Overrides register if a single vendor quote covers the whole schedule.
A144: Every item priced? | B144: =IF(COUNTA($A$130:$A$141)=0,"OK — nothing scheduled yet",IF(SUMPRODUCT(--($A$130:$A$141<>""),--($L$130:$L$141=0),--($K$130:$K$141<>"By others"),--($K$130:$K$141<>"Priced elsewhere in this workbook"))>0,"UNPRICED — a scheduled item carries no cost. Read the Cost basis column: an allowance nobody has set is still a hole, and every cost in this workbook is short by it.","OK — every scheduled item carries a cost or is provided by others"))
A145: Every item fed from something? | B145: =IF(COUNTA($A$130:$A$141)=0,"OK — nothing scheduled yet",IF(SUMPRODUCT(--($A$130:$A$141<>""),--($G$130:$G$141=""))>0,"INCOMPLETE — an item has no source named. A panel nobody feeds is a panel nobody costed a feeder to.","OK — every item names what feeds it"))
A146: EVSE disconnects — NEC 625.43 | B146: =IF(COUNTA($A$130:$A$141)=0,"OK — nothing scheduled yet","ADVISORY — "&TEXT(SUMIF($B$130:$B$141,"EVSE disconnect",$C$130:$C$141),"0")&" EVSE disconnect(s) scheduled against "&TEXT(N(Equipment!$B$20),"0")&" charging unit(s). Under the 2025 CEC (NEC 2023) 625.43 a disconnect is required for EVSE over 60 A OR over 150 V to ground, lockable open per 110.25 — a 60 kW unit at 480 V is 72 A at 277 V to ground and needs one; a 32 A Level 2 at 208 V is 120 V "&"to ground and does not. The 2026 NEC removes both thresholds. The engineer and the AHJ settle it.")
A148: LEVEL 2 BRANCH CIRCUITS
A149: Level 2 units are single-phase branch circuits off a panelboard, not three-phase feeders off a switchboard, and the AC runs table above cannot express them — it also holds only twelve rows, which a site with four DC units and ten Level 2 exceeds. Ampacity is read from the same RefData table and corrected at the same design ambient.
A150: Circuit | B150: Equip. line | C150: Units on circuit | D150: Volts | E150: Amps per unit | F150: Continuous 125% A (auto) | G150: Breaker (A) | H150: Distance (ft) | I150: Conductor size | J150: Ampacity (auto) | K150: Verdict (auto)
A151: L2-01 | B151: 2 | C151: 1 | D151: 208 | E151: 40 | F151: =IF(N($E151)=0,"",N($E151)*1.25) | G151: =IF(N($F151)=0,"",IFERROR(INDEX(OCPD_LIST,MATCH($F151,OCPD_LIST,1)+IF(ISNUMBER(MATCH($F151,OCPD_LIST,0)),0,1)),"")) | H151: 60 | I151: 8 AWG | J151: =IF($I151="","",IFERROR(MIN(N(INDEX(AMP_TBL,MATCH($I151,AMP_SIZE,0),MATCH($B$5&"-"&TEXT($F$6,"0"),AMP_HDR,0)))*N(INDEX(AMB_TBL,IF(ISNUMBER(MATCH($F5,AMB_MAX,0)),MATCH($F5,AMB_MAX,0),MATCH($F5,AMB_MAX,1)+1),MATCH(TEXT($F$6,"0"),AMB_HDR,0))),N(INDEX(AMP_TBL,MATCH($I151,AMP_SIZE,0),MATCH($B$5&"-"&TEXT($F$7,"0"),AMP_HDR,0)))),"")) | K151: =IF(N($E151)=0,"",IF($I151="","pick a conductor size",IF($F5="","SET THE DESIGN AMBIENT for this run — ampacity cannot be corrected without it, and this verdict cannot be trusted until it is set",IF(N($J151)=0,"no ampacity on file for that size",IF(N($J151)<N($G151),"UNDERSIZED — "&TEXT(N($J151),"#,##0")&" A against a "&TEXT(N($G151),"#,##0")&" A breaker","OK — "&TEXT(N($J151),"#,##0")&" A against a "&TEXT(N($G151),"#,##0")&" A breaker")))))
A152: L2-02 | B152: 2 | C152: 1 | D152: 208 | E152: 40 | F152: =IF(N($E152)=0,"",N($E152)*1.25) | G152: =IF(N($F152)=0,"",IFERROR(INDEX(OCPD_LIST,MATCH($F152,OCPD_LIST,1)+IF(ISNUMBER(MATCH($F152,OCPD_LIST,0)),0,1)),"")) | H152: 75 | I152: 8 AWG | J152: =IF($I152="","",IFERROR(MIN(N(INDEX(AMP_TBL,MATCH($I152,AMP_SIZE,0),MATCH($B$5&"-"&TEXT($F$6,"0"),AMP_HDR,0)))*N(INDEX(AMB_TBL,IF(ISNUMBER(MATCH($F5,AMB_MAX,0)),MATCH($F5,AMB_MAX,0),MATCH($F5,AMB_MAX,1)+1),MATCH(TEXT($F$6,"0"),AMB_HDR,0))),N(INDEX(AMP_TBL,MATCH($I152,AMP_SIZE,0),MATCH($B$5&"-"&TEXT($F$7,"0"),AMP_HDR,0)))),"")) | K152: =IF(N($E152)=0,"",IF($I152="","pick a conductor size",IF($F5="","SET THE DESIGN AMBIENT for this run — ampacity cannot be corrected without it, and this verdict cannot be trusted until it is set",IF(N($J152)=0,"no ampacity on file for that size",IF(N($J152)<N($G152),"UNDERSIZED — "&TEXT(N($J152),"#,##0")&" A against a "&TEXT(N($G152),"#,##0")&" A breaker","OK — "&TEXT(N($J152),"#,##0")&" A against a "&TEXT(N($G152),"#,##0")&" A breaker")))))
A153: L2-03 | F153: =IF(N($E153)=0,"",N($E153)*1.25) | G153: =IF(N($F153)=0,"",IFERROR(INDEX(OCPD_LIST,MATCH($F153,OCPD_LIST,1)+IF(ISNUMBER(MATCH($F153,OCPD_LIST,0)),0,1)),"")) | J153: =IF($I153="","",IFERROR(MIN(N(INDEX(AMP_TBL,MATCH($I153,AMP_SIZE,0),MATCH($B$5&"-"&TEXT($F$6,"0"),AMP_HDR,0)))*N(INDEX(AMB_TBL,IF(ISNUMBER(MATCH($F5,AMB_MAX,0)),MATCH($F5,AMB_MAX,0),MATCH($F5,AMB_MAX,1)+1),MATCH(TEXT($F$6,"0"),AMB_HDR,0))),N(INDEX(AMP_TBL,MATCH($I153,AMP_SIZE,0),MATCH($B$5&"-"&TEXT($F$7,"0"),AMP_HDR,0)))),"")) | K153: =IF(N($E153)=0,"",IF($I153="","pick a conductor size",IF($F5="","SET THE DESIGN AMBIENT for this run — ampacity cannot be corrected without it, and this verdict cannot be trusted until it is set",IF(N($J153)=0,"no ampacity on file for that size",IF(N($J153)<N($G153),"UNDERSIZED — "&TEXT(N($J153),"#,##0")&" A against a "&TEXT(N($G153),"#,##0")&" A breaker","OK — "&TEXT(N($J153),"#,##0")&" A against a "&TEXT(N($G153),"#,##0")&" A breaker")))))
A154: L2-04 | F154: =IF(N($E154)=0,"",N($E154)*1.25) | G154: =IF(N($F154)=0,"",IFERROR(INDEX(OCPD_LIST,MATCH($F154,OCPD_LIST,1)+IF(ISNUMBER(MATCH($F154,OCPD_LIST,0)),0,1)),"")) | J154: =IF($I154="","",IFERROR(MIN(N(INDEX(AMP_TBL,MATCH($I154,AMP_SIZE,0),MATCH($B$5&"-"&TEXT($F$6,"0"),AMP_HDR,0)))*N(INDEX(AMB_TBL,IF(ISNUMBER(MATCH($F5,AMB_MAX,0)),MATCH($F5,AMB_MAX,0),MATCH($F5,AMB_MAX,1)+1),MATCH(TEXT($F$6,"0"),AMB_HDR,0))),N(INDEX(AMP_TBL,MATCH($I154,AMP_SIZE,0),MATCH($B$5&"-"&TEXT($F$7,"0"),AMP_HDR,0)))),"")) | K154: =IF(N($E154)=0,"",IF($I154="","pick a conductor size",IF($F5="","SET THE DESIGN AMBIENT for this run — ampacity cannot be corrected without it, and this verdict cannot be trusted until it is set",IF(N($J154)=0,"no ampacity on file for that size",IF(N($J154)<N($G154),"UNDERSIZED — "&TEXT(N($J154),"#,##0")&" A against a "&TEXT(N($G154),"#,##0")&" A breaker","OK — "&TEXT(N($J154),"#,##0")&" A against a "&TEXT(N($G154),"#,##0")&" A breaker")))))
A155: L2-05 | F155: =IF(N($E155)=0,"",N($E155)*1.25) | G155: =IF(N($F155)=0,"",IFERROR(INDEX(OCPD_LIST,MATCH($F155,OCPD_LIST,1)+IF(ISNUMBER(MATCH($F155,OCPD_LIST,0)),0,1)),"")) | J155: =IF($I155="","",IFERROR(MIN(N(INDEX(AMP_TBL,MATCH($I155,AMP_SIZE,0),MATCH($B$5&"-"&TEXT($F$6,"0"),AMP_HDR,0)))*N(INDEX(AMB_TBL,IF(ISNUMBER(MATCH($F5,AMB_MAX,0)),MATCH($F5,AMB_MAX,0),MATCH($F5,AMB_MAX,1)+1),MATCH(TEXT($F$6,"0"),AMB_HDR,0))),N(INDEX(AMP_TBL,MATCH($I155,AMP_SIZE,0),MATCH($B$5&"-"&TEXT($F$7,"0"),AMP_HDR,0)))),"")) | K155: =IF(N($E155)=0,"",IF($I155="","pick a conductor size",IF($F5="","SET THE DESIGN AMBIENT for this run — ampacity cannot be corrected without it, and this verdict cannot be trusted until it is set",IF(N($J155)=0,"no ampacity on file for that size",IF(N($J155)<N($G155),"UNDERSIZED — "&TEXT(N($J155),"#,##0")&" A against a "&TEXT(N($G155),"#,##0")&" A breaker","OK — "&TEXT(N($J155),"#,##0")&" A against a "&TEXT(N($G155),"#,##0")&" A breaker")))))
...

Sheet Construction
A1: 4 · CONSTRUCTION SCOPE
A2: Site works and labour. Defaults come from the standard build; override where the site differs.
A4: Labour
A5: Crew days on site | B5: 34 | C5: Must match the construction schedule you publish
A6: Crew day rate | B6: 2750 | C6: Fully burdened
A7: Contingency on labour | B7: 0.1
A8: Markup on labour | B8: 0.2 | C8: House standing decision: 20%, applied after contingency. Change it per project on purpose, not by inheriting the last one.
A9: Labour total | B9: =B5*B6*(1+B7)*(1+B8) | C9: Days x rate x (1 + contingency) x (1 + markup)
A10: Construction PM as % of labour | B10: 0.15
A12: Site works — enter quantities, leave blank to use the standard build
A13: Item | B13: Quantity | C13: Unit basis | D13: Unit cost | E13: Include?
A14: Concrete (yd3) | B14: 6 | C14: Pads per cabinet | D14: 193.54 | E14: Y
A15: Rebar (ea) | C15: 3 per cabinet | D15: 25.65 | E15: Y
A16: Steel mesh roll (ea) | D16: 169 | E16: Y
A17: Asphalt / paving (sq ft) | B17: 400 | C17: Trench restoration — $15/sq ft set by ZIE, 28 Aug 2026 | D17: 15 | E17: Y
A18: Striping (lot) | D18: 1500 | E18: Y
A19: ADA stalls (ea) | B19: 2 | C19: 2% of stalls, min 1 | D19: 4900 | E19: Y
A20: ADA ramp (ea) | B20: 1 | D20: 5200 | E20: Y
A21: Bollards (ea) | B21: 12 | C21: 4 per DC cabinet / 2 + 6 | D21: 110 | E21: Y
A22: Signs (ea) | C22: 2 per DC cabinet | D22: 40 | E22: Y
A23: Sign posts (ea) | D23: 56.1 | E23: Y
A24: Switchgear sign (ea) | D24: 150 | E24: Y
A25: GPR scan (ea) | B25: 1 | C25: Underground utility locate | D25: 2500 | E25: Y
A26: GFI test (ea) | B26: 1 | C26: Required above 1000 sq ft gear area | D26: 3500 | E26: Y
A27: Dump / disposal (lot) | B27: 1 | C27: Freight and disposal | D27: 5000 | E27: Y
A31: Design and engineering
A32: AutoCAD design — drawing sets | B32: 3 | C32: One issued drawing package: site plan, equipment layout, civil details. | D32: 3412.5
A33: Electrical engineering — drawing sets | B33: 3 | C33: One stamped electrical package: single-line, panel schedule, load calculation. | D33: 2080
A34: Project management — hours | B34: 35 | C34: Billed hourly across design, permitting and construction. | D34: 358
A35: Design and engineering total | B35: =SUMPRODUCT($B$32:$B$34,$D$32:$D$34) | C35: Quantity in column B times the rate in column D. These are ZIE billing rates for work performed in house — change the rate here, not in a formula.
A37: Equipment rentals — standard build, override durations if the job differs
A38: Rental | B38: Qty | C38: Unit cost | D38: Days | E38: Include?
A39: Fencing | C39: 0.3 | E39: Y
A40: Mini x | B40: 1 | C40: 98.566667 | D40: 30 | E40: Y
A41: Dump Truck | B41: 1 | C41: 520 | D41: 4 | E41: Y
A42: Forklift | C42: 563 | E42: Y
A43: Trench Plates | C43: 5.18 | E43: Y
A44: Storage container | C44: 185 | E44: Y
A45: Portable restroom | C45: 267 | E45: Y
A46: Low boi | C46: 1000 | E46: Y
A47: Saw cutter | C47: 169 | E47: Y
A48: Jack hammer | C48: 155 | E48: Y
A49: Compactor | C49: 175 | E49: Y
A50: Generator rental | B50: 1 | C50: 220 | D50: 10 | E50: Y
A51: Dump trailer rental | C51: 796.63 | E51: Y
A52: Equipment protection | C52: 45 | E52: Y
A54: Removal and demolition — replacement sites only
A55: Zero on a greenfield site. On a replacement site these quantities come from the Existing tab section H and are priced like any other construction line.
A56: Item | B56: Quantity | C56: Source
A57: Cabinets to disconnect and remove (ea) | B57: =IF(Existing!$B$5="Greenfield — new service",0,Existing!$B$174) | C57: The Existing tab section H
A58: Concrete pads to break out (ea) | B58: =IF(Existing!$B$5="Greenfield — new service",0,Existing!$B$175) | C58: The Existing tab section H
A59: Bollards to remove (ea) | B59: =IF(Existing!$B$5="Greenfield — new service",0,Existing!$B$176) | C59: The Existing tab section H
A60: Signage to remove (ea) | B60: =IF(Existing!$B$5="Greenfield — new service",0,Existing!$B$177) | C60: The Existing tab section H
A61: Disposal loads (ea) | B61: =IF(Existing!$B$5="Greenfield — new service",0,Existing!$B$178) | C61: The Existing tab section H
A62: Site protection and traffic control (days) | B62: =IF(Existing!$B$5="Greenfield — new service",0,Existing!$B$182) | C62: The Existing tab section H
A64: Removal crew days — add to the crew days above | B64: =IF(Existing!$B$5="Greenfield — new service",0,ROUND(N(Existing!$B$174)*0.5+N(Existing!$B$175)*0.75,0)) | C64: Indicative only. A cabinet takes roughly half a crew day to disconnect and remove; a pad roughly three quarters of a day to break out and dispose of.
A66: Construction scope profile | B66: =IF(Existing!$B$5="Greenfield — new service","GREENFIELD — full site works",IF(Existing!$B$17="RETAIN","PAD-AND-CHARGER SWAP — demolition, new pads, reinstatement and protection. No trenching, no paving beyond the pads.","PARTIAL — trenching required for the elements marked REPLACE"))
A67: Does the site stay live during the works? | B67: =IF(Existing!$B$181="Yes","PHASED PROGRAMME REQUIRED — temporary charging is not in the standard scope and must be priced separately",IF(Existing!$B$181="No","OK — the site can go dark during the works","not yet answered"))
A68: Removal scope on a greenfield project? | B68: =IF(AND(Existing!$B$5="Greenfield — new service",N(Existing!$B$174)+N(Existing!$B$175)+N(Existing!$B$176)+N(Existing!$B$177)+N(Existing!$B$178)>0),"ERROR — REMOVAL QUANTITIES ARE ENTERED ON A GREENFIELD PROJECT. Greenfield means there is nothing on the site to take out, so these quantities are not being priced. Either the project type is wrong or the removal section is. Fix one of them on purpose.",IF(Existing!$B$5="Greenfield — new service","OK — greenfield, and no removal scope has been entered","OK — replacement project, removal scope is priced"))
A69: A CHARGER SWAP IS NOT A SMALL GREENFIELD PROJECT. Demolition, disposal, working around a live customer lot and phasing to keep the site trading are real costs that a greenfield estimate does not contain. Enter them rather than assuming the reuse saving covers them.
A71: MARKUPS — WHAT TURNS COST INTO PRICE
A72: Markup on materials | B72: 0.2 | C72: Applies to switchgear, conductor, conduit, site works and construction rentals — everything priced from a rate rather than from a crew day. Set at 20%, matching the house markup on labour cost.
A73: Markup on labour | B73: =$B$8 | C73: Shown here for comparison only — the labour markup is still entered in the Labour block at the top of this tab. One input, one place.
A75: Every materials rate in this workbook is a COST rate — the RefData switchgear table is headed "Cost", and the site-works unit costs are what the item costs to buy and place. Nothing turns them into a price. The note beside the labour markup at the top of this tab already says materials are marked up "the same way"; until this cell carries a figure, that is not true and the discount on the Commercial tab comes straight out of margin.
A77: UTILITY AND THIRD-PARTY FEES — PASS-THROUGH
A78: These are charges levied by someone else: the AHJ, the utility, the fire district. ZIE pays them and bills them on at exactly what they cost. They carry NO markup and NO discount, and they are shown as their own line on the bid — a fee schedule is a public document and a marked-up permit is the fastest way to lose an argument you should never have been having.
A80: Fee | B80: Quantity | C80: Basis | D80: Unit cost | E80: Include?
A81: Permit and plan-check fees | B81: 1 | C81: AHJ — verify locally | D81: 4000 | E81: Y
A82: Utility contract fees | B82: 1 | C82: Application and contract | D82: 3500 | E82: Y
A83: Utility interconnection design and application fee | B83: 1 | C83: Entered on the Electrical tab — this row reads it. Pass-through at cost. | D83: =Electrical!$B$56 | E83: Y
A84: Utility line-extension contribution, if any | B84: 0 | C84: Whatever the serving utility charges the customer toward extending distribution or service. Zero until they say otherwise. | D84: =Electrical!$B$59 | E84: Y
A85: Fire department plan review | B85: 1 | C85: Fire district — common on DCFC sites | D85: 850 | E85: Y
A86: Encroachment / street-opening permit | B86: 0 | C86: Municipal, when trenching leaves the property | D86: 0 | E86: Y
A87: Electrical inspection fees | B87: 0 | C87: AHJ inspection, separate from plan check | D87: 0 | E87: Y
A88: Meter and service connection fee | B88: 0 | C88: Utility, if charged separately from Rule 29 | D88: 0 | E88: Y
A89: Utility and third-party fees total | B89: =SUMPRODUCT($B$81:$B$88,$D$81:$D$88) | C89: Billed to the client at exactly this figure. No markup, no discount, its own line on the bid.
A91: Any fee left in the site-works table? | B91: =IF(SUMPRODUCT(--ISNUMBER(SEARCH("fee",$A$14:$A$29)))+SUMPRODUCT(--ISNUMBER(SEARCH("permit",$A$14:$A$29)))>0,"ERROR — A FEE IS SITTING IN THE SITE-WORKS TABLE. Everything in that table takes the materials markup and then the discount, so a fee entered there is marked up 20% and then discounted. Move it into the fee block below.","OK — the site-works table holds no fees")

Sheet Commercial
A1: 5 · COMMERCIAL TERMS
A2: Discounts, financing and the service and network term.
A4: Discounts applied to customer price
A5: Charger hardware discount | B5: 0.07
A6: Service and warranty discount | B6: 0.07
A7: EVOLV and commissioning discount | B7: 0
A8: Labour and in-house services discount | B8: 0.07 | C8: Applies ONLY to work ZIE performs: construction labour, construction project management, and design and engineering. It may never be applied to materials, to equipment rentals, or to any third-party or utility fee.
A9: Sales tax rate | B9: 0.0725 | C9: Applied to the DISCOUNTED equipment price
A11: Service, warranty and network
A12: Contract length (years) | B12: 5 | C12: Years of service included in the price
A13: In-warranty years | B13: 2 | C13: Years billed at the in-warranty rate
A14: EVOLV network fee per port per month | B14: 39.99
A15: EVOLV annual cost | B15: =Equipment!B22*B14*12 | C15: Ports x rate x 12 — ports, never cabinets
A16: EVOLV cost across contract | B16: =B15*B12
A18: Financing
A19: Financing offered? | B19: Yes
A20: Lender | B20: De Lage Landen
A21: Annual interest rate | B21: 0.0839
A22: Term (years) | B22: 5
A23: Payments per year | B23: 12
A24: Down payment | B24: 0
A25: Financing start date | B25: 46296
A27: Analysis horizon
A28: Model horizon (years) | B28: 10 | C28: Use 10 — the carbon credit runs ten years
A29: Discount rate for NPV | B29: 0.0839 | C29: Default: the financing rate

Sheet Revenue
A1: 6 · REVENUE ASSUMPTIONS
A2: Every one of these will be challenged by the customer. Set them where you can defend them.
A4: Pricing
A5: Retail price to driver ($/kWh) | B5: 0.65
A6: Delivered energy cost — leave blank, now derived | B6: =IF(N($B$91)=0,"",$B$91) | C6: Derived from the tariff block at the foot of this tab. Set the figures there.
A7: Utility subscription — leave blank, now derived | B7: =IF(N($B$95)=0,"",$B$95) | C7: Customer charge plus demand charge, annualised, from the tariff block at the foot of this tab. On a demand schedule this is the largest number on the page.
A8: Card processing fee (% of gross) | B8: 0.03
A9: Idle fee revenue included? | B9: No | C9: Keep this No unless it is contracted
A11: Utilisation — steady state
A12: Hours per day the site is chargeable | B12: =Project!B22 | C12: From 1_Project
A13: Stall occupancy (share of stalls used per day) | B13: 0.2
A14: Charging hours per occupied stall, as share of open hours | B14: 0.25
A15: Nameplate de-rate factor | B15: 0.98 | C15: Cabinet output vs label
A16: Average delivered power, share of port rating | B16: 0.7 | C16: CHARGING-CURVE TAPER
A18: Ramp and growth
A19: Year 1 share of steady state | B19: 0.5 | C19: Greenfield sites take time to fill
A20: Year 2 share of steady state | B20: 0.75
A21: Year 3 share of steady state | B21: 1
A22: Annual growth after ramp | B22: 0.06 | C22: Justify as a level, not a rate
A24: Historical actuals — replacement sites only, leave blank for greenfield
A25: Months of history available
A26: Historical kWh dispensed per day
A27: Historical gross revenue per year
A28: Historical net profit per year
A29: Ports in service on an average day
A30: Share of sessions under 1 kWh | C30: Failed-session rate
A32: Utility rate selection — drives the delivered energy cost
A33: Pick the utility and schedule and the model derives $/kWh and the subscription from the tariff. No blended guess required.
A35: Utility | B35: =IF(Project!$B$26="","",Project!$B$26) | C35: Reads the utility named on the Project tab. Set it there.
A36: Rate schedule | B36: TOU-EV-9 | C36: Pick the schedule this site will actually take. The list is on the Utilities tab under RATE SCHEDULE PICKER; add the schedule there first if it is not on it.
A37: Service voltage level | B37: Secondary | C37: Secondary or primary. On schedules that price them differently this changes the rate.
A38: Share of energy dispensed on-peak | B38: 0.3 | C38: Only if the schedule has time-of-use periods, and then from ITS periods — not from a remembered 4-9 pm peak. Leave all three blank on a flat schedule.
A39: Share off-peak | B39: 0.55
A40: Share super off-peak | B40: 0.15 | C40: The three shares must sum to 100% where they are used at all.
A41: Expected peak concurrency (ports drawing at once) | B41: =IF(OR(N($B$77)=0,N($B$75)=0,N($B$52)=0),"",ROUNDUP($B$77/(24*$B$75)*$B$52,0)) | C41: DERIVED, not typed. Average concurrent ports is the day's energy over twenty-four hours of average delivered power; the peak-to-average factor above turns that into a peak. Rounded up, because you cannot subscribe to a fraction of a port.
A42: Subscribed kW | B42: =IF(N($B$41)=0,"",IF($B$51="Subscribe at full nameplate",Equipment!$B$23,$B$41*IF($B$54="Yes",$B$74,$B$75)*(1+N($B$53)))) | C42: Peak concurrent ports at the sizing basis above, plus the safety margin. This follows the Subscription policy row: set it to "Subscribe at full nameplate" and this becomes the whole connected load instead. A site is built for its peak and paid for its average, and on a schedule that sells capacity in blocks the difference between the two is the largest operating number in the project.
A44: Market benchmarking
A45: State for benchmarking | B45: California | C45: REQUIRED. Pick the market this projection should be tested against — the list is on RefData under MARKET BENCHMARKS. There is no default: this used to say California on every project regardless of where the site was.
A46: Expected site factor (% of the state average port) | C46: Leave blank and the model derives it from your utilisation inputs
A48: Demand subscription — how it should ramp
A49: Demand charges are set by simultaneous draw, not annual energy. A site that fills gradually should not carry a full-nameplate subscription from day one.
A51: Subscription policy | B51: Ramped to projected demand
A52: Peak-to-average concurrency factor | B52: 4 | C52: Ratio of peak simultaneous draw to the daily average
A53: Safety margin on subscribed kW | B53: 0.2 | C53: Headroom above projected peak before overage bites
A54: Size demand on full port rating? | B54: Yes | C54: A vehicle at the start of a session draws full power
A55: Interval data available from the utility? | C55: Lets the subscription be trued up after two quarters
A57: Revenue basis — greenfield benchmark or historical actuals
A58: On a greenfield site the projection is built from market benchmarks, because there is nothing else. On a replacement site the projection should be built from the site's own history plus the uplifts stated on the Existing tab. Pick one. The model uses whichever is selected here.
A59: Revenue basis | B59: Historical actuals — replacement site | C59: Switch to historical actuals on any site with twelve or more months of usable data.
A61: Months of history available | B61: =Existing!$B$104 | C61: From the Existing tab section E.
A62: Historical kWh per year | B62: =Existing!$B$112
A63: Combined uplift multiple | B63: =Existing!$B$155
A64: Projected kWh per year — replacement basis | B64: =Existing!$B$156 | C64: History times the stated uplifts. This is what the model uses when the basis above is set to historical actuals.
A66: Which basis is in force? | B66: =IF(LEFT($B$59,10)="Historical",IF(Existing!$B$104>=12,"HISTORICAL — "&TEXT(Existing!$B$104,"0")&" months of data, projecting "&TEXT($B$64,"#,##0")&" kWh a year","HISTORICAL SELECTED BUT THIN — fewer than 12 months of data. Either add history or revert to the benchmark."),"MARKET BENCHMARK — greenfield method, using the site factor above") | D66: A replacement site running on market benchmarks is throwing away its best evidence.
A67: Historical price against the proposed price | B67: =IF(Existing!$B$116=0,"no history entered","History "&TEXT(Existing!$B$116,"$0.000")&" vs proposed "&TEXT($B$5,"$0.000")&" — "&TEXT(IF(Existing!$B$116=0,0,$B$5/Existing!$B$116-1),"+0.0%;-0.0%")) | D67: A large price increase on a site with a settled driver base is a demand risk, not a revenue gain.
A68: Historical delivered cost against the tariff estimate | B68: =IF(Existing!$B$117=0,"no history entered","Twelve months of billing says "&TEXT(Existing!$B$117,"$0.0000")&" all-in. Use it in preference to any tariff estimate.") | D68: Actual billing beats a tariff lookup every time. This is the number to carry into the model.
A70: ON A REPLACEMENT SITE, THREE INPUTS ABOVE STOP BEING ASSUMPTIONS. Stall occupancy, the chargeable-hours share and the site factor are all greenfield estimating devices. Where twelve months of metered history exists they are superseded by it — leave them at default and let the historical basis drive the projection.
A72: STEADY-STATE PROJECTION — the greenfield basis, computed here
A73: The model used to compute this downstream, which meant nothing on this sheet could test it. It is computed here so the market cross-check on the Existing tab has something to read on a site with no history.
A74: Power per position (kW) | B74: =IF(N(Equipment!$B$22)=0,0,Equipment!$B$26/Equipment!$B$22)
A75: Average delivered power (kW) | B75: =$B$74*$B$15*$B$16 | C75: De-rated, then tapered
A76: Charging stall-hours per day | B76: =Equipment!$B$22*$B$13*$B$12*$B$14
A77: Steady-state kWh per day | B77: =$B$76*$B$75
A78: Steady-state kWh per year | B78: =$B$77*365
A80: Tariff provenance and rate-entry checks
A81: Every revenue figure in the model rests on the rate figures above. This block records how much weight they can carry, and the proposal prints it at the point of use rather than in a risk register nobody reads.
A82: Source of the rate figures | B82: SCE TOU-EV rate fact sheet, July 2025 | C82: Where each $/kWh and fixed charge came from — a filed tariff sheet, a rate insert, a bill, or a phone call. Name it. The proposal prints this.
A83: Verified against the filed tariff sheets? | B83: No | C83: Yes / No. "No" is a perfectly good answer and the proposal will say so at the point of use; what is not acceptable is nobody knowing.
A84: Verified by / date | B84: VP · 2026-09-01 | C84: Who checked it, and when.
A85: Demand-schedule eligibility threshold | C85: If this utility moves a customer onto a demand schedule above some monthly consumption, record the threshold and its units here. Leave blank if unknown — blank prints as unconfirmed, which is honest. A figure typed from memory is not.
A86: Would this site cross that threshold? | C86: Against the steady-state projection at the foot of this tab. If yes, the tariff behind every revenue figure in the model is the wrong one.
A87: Time-of-use shares entered? | B87: =IF(COUNT($B$38:$B$40)=0,"none entered — correct on a flat schedule",IF(ROUND(SUM($B$38:$B$40),4)<>1,"THE THREE SHARES DO NOT SUM TO 100%","ok")) | C87: Blank on a flat schedule is the right answer. A split that does not sum to 100% is not.
A89: Tariff figures — the bill, decomposed
A90: One row per component of the bill, so a demand charge cannot hide inside a blended cents-per-kWh figure. Take them from the schedule row in the RateLibrary tab.
A91: Volumetric energy cost ($/kWh) | B91: 0.28 | C91: The per-kWh charge on the chosen schedule, before fixed and demand charges.
A92: Customer charge ($/month) | B92: 701.42 | C92: The fixed monthly meter charge.
A93: Demand charge ($/kW-month) | B93: 0 | C93: Zero on a schedule with no demand charge. This is the figure that decides whether a fast charging site works: at low load factor a demand charge can cost more than all the energy.
A94: Billing demand assumed (kW) | C94: What the meter will see as the monthly maximum. Full nameplate unless load management caps it. Every kW here costs the demand charge above, twelve times a year.
A95: Annual fixed and demand cost ($/yr) | B95: =12*(N($B$92)+N($B$93)*N($B$94))+N($B$102) | C95: Customer charge plus any demand charge, annualised, PLUS the subscription. The Revenue tab's utility subscription line reads this row and the project model reads that. Until 2.9.0 the subscription was not in it at all, so a schedule that sells capacity in blocks was costing nothing.
A97: DEMAND SUBSCRIPTION — WHAT THE RAMP ABOVE COSTS
A98: A schedule that sells capacity in blocks charges for what you subscribe to, not what you draw. The subscribed figure comes from the ramp above; the block size and price come from the rate library. If the library has no block for this schedule the cost is zero and the check at the foot of this block says so rather than letting the zero pass for an answer.
A99: Subscription block size (kW) | B99: =IFERROR(SUMIFS(RateLibrary!$J$5:$J$74,RateLibrary!$A$5:$A$74,$B$7,RateLibrary!$B$5:$B$74,$B$36),0) | C99: From the rate library row for this utility and schedule. Zero means the library has no block size for it — not that the schedule has no blocks.
A100: Subscription block price ($/block/month) | B100: =IFERROR(SUMIFS(RateLibrary!$K$5:$K$74,RateLibrary!$A$5:$A$74,$B$7,RateLibrary!$B$5:$B$74,$B$36),0) | C100: From the same library row.
A101: Blocks subscribed | B101: =IF(OR(N($B$99)=0,N($B$42)=0),0,ROUNDUP($B$42/$B$99,0)) | C101: Subscribed kW over the block size, rounded up.
A102: Subscription cost ($/yr) | B102: =N($B$101)*N($B$100)*12 | C102: Blocks times the block price times twelve. This is the line that decides whether a high-capacity, low-utilisation site works.
A103: Subscription cost basis | B103: =IF(N($B$42)=0,"n/a — no subscribed capacity derived yet",IF(N($B$99)=0,"UNPRICED — "&TEXT($B$42,"#,##0")&" kW subscribed and the rate library carries no block size or block price for this schedule, so the subscription is costing this model NOTHING. On a site built to "&TEXT(Equipment!$B$23,"#,##0")&" kW that is the largest unpriced item here. Two numbers from the utility settle it.","OK — "&TEXT($B$101,"#,##0")&" block(s) of "&TEXT($B$99,"#,##0")&" kW, "&TEXT($B$102,"$#,##0")&" a year, against "&TEXT(Equipment!$B$23,"#,##0")&" kW of connected load")) | C103: A zero here is an absence, not a saving. The whole point of the ramp above is that it makes the subscription affordable; it cannot do that while nobody has asked what a block costs.

Sheet Carbon
A1: 7 · CARBON CREDITS AND INCENTIVES
A2: The FCI capacity credit is usually the most reliable revenue in the model. Treat its inputs accordingly.
A4: LCFS / FCI capacity credit
A5: Site qualifies for FCI capacity credits? | B5: Yes | C5: Yes / No / Pending
A6: Permit clears the 1 Jan 2022 test? | B6: Yes | C6: Yes / No
A7: Application filed? | B7: No | C7: Yes / No — with date
A8: Registered aggregator | B8: Registered aggregator LLC
A9: Aggregator share of credit value | B9: 0.05 | C9: Third-party administrator. Not our scope — a deduction from proceeds, disclosed as a cost.
A10: FCI credit rate ($/kW/yr) | B10: 71.6667 | C10: Confirm with the aggregator in writing
A11: Crediting period (years) | B11: 10
A12: Gross capacity credit per year | B12: =Equipment!$B$26*B10 | C12: DC fast-charging capacity only — the FCI credit does not pay on Level 2.
A13: Net of aggregator share, per year | B13: =B12*(1-B9)
A14: Gross across crediting period | B14: =B12*B11
A16: Consumption credits (Level 2)
A17: L2 consumption credit ($/kWh) | B17: 0.0045
A18: Site-total L2 kWh per day | C18: SITE total, not per port
A20: Cap test
A21: Cap multiple of net capex | B21: 1.5 | C21: FCI revenue stops at this multiple
A22: Grants or rebates awarded | B22: 0 | C22: Reduces net capex and therefore the cap
A24: Federal and state incentives
A25: Federal ITC claimed? | B25: No | C25: Sec 30C ended for property in service after 30 Jun 2026
A26: State programme evaluated | B26: Fast Charge California | C26: e.g. Fast Charge California — name it even if it does not qualify
A27: State programme outcome | B27: Does not qualify | C27: Qualifies / Does not qualify / Applied — with the reason

Sheet Deal_Structure
A1: 8 · DEAL STRUCTURE (OPTIONAL)
A2: Leave every knob at zero for a straight sale. Fill them in only when we are trading price for a share of the upside.
A4: • | B4: This tab is optional. Zero everywhere means a conventional sale and the model runs exactly as it does today.
A5: • | B5: Use it when we want to lower the client's price in return for keeping part of the carbon credit or the charging revenue.
A6: • | B6: The model reports both sides — what the client nets and what we net on the capital we put in — so a structure can be judged before it is offered.
A8: What we keep
A9: Structure name | B9: Carbon share test | C9: A label so a reader knows which structure this is
A10: Our share of the net carbon credit | B10: 0.5 | C10: 0% = client keeps all of it
A11: Our share of charging revenue | B11: 0.1 | C11: 0% = client keeps all of it
A12: Revenue share is taken on | B12: Net charging profit | C12: Net charging profit / Gross revenue
A13: Share runs for (years) | B13: 10 | C13: Cannot exceed the model horizon
A15: What we give in return
A16: Extra discount on charger hardware | B16: 0.05 | C16: On top of the discount already in the base price
A17: Extra discount on electrical and construction | B17: 0
A18: Extra discount on service, warranty and network | B18: 0
A19: Direct capital contribution | B19: 100000 | C19: Cash or hardware we fund outright
A21: Guard rails — the model will report against these
A22: Minimum acceptable client NPV | B22: 0 | C22: Below this the structure is not worth offering
A23: Minimum acceptable return on our capital | B23: 2 | C23: Multiple of what we contribute
A24: Maximum capital we will contribute | B24: 150000 | C24: Hard ceiling on our exposure
A26: Scope of supply — which lines do we provide?
A27: Default is all of them, which is the base case. Mark a line "By others" when a third party supplies it — it leaves our contract but stays in the client's project.
A29: Service line | B29: Who provides it | C29: Third party name | D29: Notes
A30: Charger hardware — procurement and sale | B30: We provide
A31: Extended warranty and O&M service | B31: We provide
A32: EVOLV platform and commissioning | B32: We provide
A33: Sales tax on chargers | B33: We provide
A34: Design and engineering | B34: By others
A35: Construction — all-inclusive (materials, equipment, labour) | B35: We provide
A36: Utility interconnection management | B36: We provide
A37: Carbon credit administration is NOT one of our lines — a third-party aggregator takes a share of proceeds. See 7_Carbon.
B38: Handing a line to a third party removes its price and its margin. The model shows what each one is worth before you offer it.
A40: Financing basis
A41: Client finances | B41: Whole project | C41: Whether the facility covers third-party scope too

Sheet Overrides
A1: 9 · OVERRIDE REGISTER
A2: The escape hatch. Force any derived value here when you know better than the engine — a quote, a fee schedule, a field measurement.
A4: • | B4: Leave a row blank and the engine uses its own computed number. Fill it in and the engine uses yours, everywhere.
A5: • | B5: Every override is reported on the model summary, so a reviewer can always see that the model was touched and exactly where.
A6: • | B6: Put the reason in the last column. An override with no reason is indistinguishable from a typo six months later.
A8: Value | B8: Override | C8: Units | D8: Why — quote, fee schedule, measurement
A9: Wires, conduits and peripherals (before uplift) | C9: $
A10: Switchgear and distribution (before uplift) | B10: 150000 | C10: $ | D10: Vendor quote for the switchboard
A11: Site works (before uplift) | C11: $
A12: Dump, waste and freight (before uplift) | C12: $
A13: Permits and plan check (before uplift) | C13: $
A14: Utility application and contract fees (before uplift) | C14: $
A15: Construction equipment rentals (before uplift) | C15: $
A16: Design and engineering | C16: $
A17: Rule 15/16 customer contribution (if triggered) | C17: $ | D17: Leave blank and it is excluded by name in the proposal. Fill it in only when PG&E returns a design that requires it.
A18: Additional or unforeseen scope | C18: $
A19: Standard frame (A) | B19: 3200 | C19: amps | D19: Engineer's single line
A20: Branch breaker per cabinet (A) | C20: amps
A21: Crew days on site | C21: days
A22: Steady-state kWh per day | B22: 1400 | C22: kWh | D22: Traffic study, Aug 2026
A23: Gross capacity credit per year | C23: $
A24: Monthly loan payment | C24: $
A25: Hardware MSRP each | C25: $
A26: Retail price to driver | B26: 0.62 | C26: $/kWh | D26: Pricing committee
A27: Delivered energy cost | C27: $/kWh
A28: Utility demand / subscription | C28: $/yr

Sheet PriceBook
A1: Category | I1: CONNECTORS | J1: HOW THE COUNT WAS DECIDED | K1: SKU INDEX — built from the categories above; the capacity dropdown on 2_Equipment resolves against these columns
A2: _L2 | B2: CTX-R40-240-1 | C2: 40A Single Home Charger | D2: 605 | I2: 1 | J2: description says Single | K2: Level 2 AC | L2: 30 kW DC | M2: 60 kW DC | N2: 120 kW DC | O2: 160 kW DC | P2: 180 kW DC | Q2: 240 kW DC | R2: 360 kW DC | S2: V2G | T2: Distributed system | U2: Accessory | W2: CAPACITY | X2: RATED kW | Y2: PER PORT | AD2: ROLE BY SKU | AE2: ROLE | AG2: DISPENSERS
A3: _L2 | B3: CTX-R48-240-1 | C3: 48A Single Home Charger | D3: 605 | I3: 1 | J3: description says Single | K3: CTX-R40-240-1 | L3: TP5-30-480-1 | M3: TP5-60-480-1 | N3: TP5-120-480-1 | O3: TP5-160-480-1 | P3: TP5-180-480-1 | Q3: TP5-240-480-2-300 | R3: TP5-360-480-1-300 | S3: CTX-V2G-20-480-1 | T3: CTX-DSPB-360 | U3: CTX-FLUXPED | W3: Level 2 AC | X3: 7.2 | Y3: 1 | AD3: CTX-R40-240-1 | AE3: level_2 | AG3: CTX-DST-2-300
A4: _L2 | B4: CTX-C32-240-1 | C4: 32A Single Commercial L2 Charger | D4: 1402.5 | I4: 1 | J4: description says Single | K4: CTX-R48-240-1 | L4: TP5-30-480-3 | M4: TP5-60-480-2 | N4: TP5-120-480-2 | O4: TP5-160-480-2 | P4: TP5-180-480-2 | Q4: TP5-240-480-2-400 | R4: TP5-360-480-2-300 | S4: CTX-V2G-30-480-1 | T4: CTX-DSPB-480 | U4: CTX-FLUXWAL-CMS-1 | W4: 30 kW DC | X4: 30 | Y4: 0 | AD4: CTX-R48-240-1 | AE4: level_2 | AG4: CTX-DST-HPC-2-500/300
A5: _L2 | B5: CTX-C48-240-1 | C5: 48A Single Commercial L2 Charger (18' Cable with Modem) | D5: 1402.5 | I5: 1 | J5: description says Single | K5: CTX-C32-240-1 | M5: TP5-60-480-3 | N5: TP5-120-480-2-300 | O5: TP5-160-480-3 | P5: TP5-180-480-2-300 | Q5: HPC-240-480-1 | R5: TP5-360-480-3-300 | S5: CTX-V2G-40-480-1 | T5: CTX-DSPB-1280 | U5: CTX-FLUXPED-CMS-1 | W5: 60 kW DC | X5: 60 | Y5: 0 | AD5: CTX-C32-240-1 | AE5: level_2
A6: _L2 | B6: CTX-C80-240-1 | C6: 80A Single Commercial L2 Charger (18' Cable with Modem) | D6: 1650 | I6: 1 | J6: description says Single | K6: CTX-C48-240-1 | M6: TP5-60-480-4 | N6: TP5-120-480-3-300 | O6: TP5-160-480-2-300 | P6: TP5-180-480-3-300 | Q6: HPC-240-480-2 | R6: TP5-360-480-4-300 | S6: CTX-V2G-60-480-1 | T6: CTX-DST-2-300 | U6: CTX-FLUXPED-CMS-2 | W6: 120 kW DC | X6: 120 | Y6: 0 | AD6: CTX-C48-240-1 | AE6: level_2
A7: _L2 | B7: CTX-C40-240-2 | C7: 40A Dual Commercial L2 Charger (18' Cable with Modem) | D7: 1952.5 | I7: 2 | J7: description says Dual | K7: CTX-C80-240-1 | M7: CTX-AiO-60-2-200 | N7: CTX-AiO-120-2-350 | O7: HPC-160-480-1 | P7: TP5-180-480-2-300-CL20 | Q7: CTX-AiO-240-2-300 | R7: HPC-360-480-1 | T7: CTX-DST-HPC-2-500/300 | U7: CTX-FLUXPED-SBS | W7: 160 kW DC | X7: 160 | Y7: 0 | AD7: CTX-C80-240-1 | AE7: level_2
A8: _L2 | B8: CTX-C80-240-2 | C8: 80A Dual Commercial L2 Charger (18' Cable with Modem) | D8: 2194.5 | I8: 2 | J8: description says Dual | K8: CTX-C40-240-2 | M8: CTX-AiO-60-3-200 | N8: CTX-AiO-120-3-350 | O8: HPC-160-480-2 | P8: TP5-180-480-2-BAA | Q8: CTX-AiO-240-3-300 | R8: HPC-360-480-2 | W8: 180 kW DC | X8: 180 | Y8: 0 | AD8: CTX-C40-240-2 | AE8: level_2
A9: _L2 | B9: CTX-C80-240-1-ISO | C9: 80A Single Commercial L2 Charger (18' Cable with Modem) | D9: 2255 | I9: 1 | J9: description says Single | K9: CTX-C80-240-2 | M9: CTX-AiO-60-4-200 | N9: CTX-AiO-120-4-350 | O9: CTX-AiO-160-2-350 | P9: TP5-180-480-3-BAA | Q9: CTX-AiO-240-4-300 | R9: HPC-360-480-3 | W9: 240 kW DC | X9: 240 | Y9: 0 | AD9: CTX-C80-240-2 | AE9: level_2
A10: _L2 | B10: CTX-C40-240-2-ISO | C10: 40A Dual Commercial L2 Charger (18' Cable with Modem) | D10: 2530 | I10: 2 | J10: description says Dual | K10: CTX-C80-240-1-ISO | M10: TP5-60-480-2-BAA | N10: CTX-AiO-120-5-350 | O10: CTX-AiO-160-3-350 | P10: TP5-180-480-4-BAA | Q10: CTX-AiO-240-5-300 | R10: HPC-360-480-4 | W10: 360 kW DC | X10: 360 | Y10: 0 | AD10: CTX-C80-240-1-ISO | AE10: level_2
A11: _L2 | B11: CTX-C80-240-2-ISO | C11: 80A Dual Commercial L2 Charger (18' Cable with Modem) | D11: 2805 | I11: 2 | J11: description says Dual | K11: CTX-C40-240-2-ISO | M11: TP5-60-480-3-BAA | N11: CTX-AiO-120-6-350 | O11: CTX-AiO-160-4-350 | P11: HPC-180-480-2-BAA | R11: TP5-360-480-2-BAA | W11: V2G | X11: 0 | Y11: 0 | AD11: CTX-C40-240-2-ISO | AE11: level_2
A12: _kW30 | B12: TP5-30-480-1 | C12: Gen2 30kW DCFC Wall Mount - 100 Amps / 1000VDC with CCS1 (~16ft) | D12: 13750 | E12: 30 | I12: 1 | J12: connectors named in the description | K12: CTX-C80-240-2-ISO | M12: TP5-60-480-4-BAA | N12: TP5-120-480-2-300-BAA | O12: CTX-AiO-160-5-350 | P12: HPC-180-480-3-BAA | R12: TP5-360-480-3-BAA | W12: Distributed system | X12: 0 | Y12: 0 | AD12: CTX-C80-240-2-ISO | AE12: level_2
A13: _kW30 | B13: TP5-30-480-3 | C13: Gen 2Gen 30kW DCFC Wall Mount - 200 Amps / 1000VDC with NACS (~16ft) | D13: 13750 | E13: 30 | I13: 1 | J13: connectors named in the description | N13: TP5-120-480-3-300-BAA | O13: CTX-AiO-160-6-350 | P13: HPC-180-480-4-BAA | R13: TP5-360-480-4-BAA | W13: Accessory | X13: 0 | Y13: 0 | AD13: TP5-30-480-1 | AE13: all_in_one
A14: _kW60 | B14: TP5-60-480-1 | C14: 60kW DCFC - 200 Amps / 1000VDC with CCS1 & NACS(~16ft) ; 4G Modem | D14: 28500 | E14: 60 | I14: 2 | J14: connectors named in the description | N14: TP5-120-480-4-300-BAA | R14: HPC-360-480-2-BAA | AD14: TP5-30-480-3 | AE14: all_in_one
A15: _kW60 | B15: TP5-60-480-2 | C15: 60kW DCFC - 200 Amps / 1000VDC with CCS1 & CCS1(~16ft) ; 4G Modem | D15: 28500 | E15: 60 | I15: 2 | J15: connectors named in the description | R15: HPC-360-480-3-BAA | AD15: TP5-60-480-1 | AE15: all_in_one
A16: _kW60 | B16: TP5-60-480-3 | C16: 60kW DCFC - 200 Amps / 1000VDC with CCS1 & NACS(~16ft) ; 4G Modem | D16: 28500 | E16: 60 | I16: 2 | J16: connectors named in the description | R16: HPC-360-480-4-BAA | AD16: TP5-60-480-2 | AE16: all_in_one
A17: _kW60 | B17: TP5-60-480-4 | C17: 60kW DCFC - 200 Amps / 1000VDC with NACS & NACS(~16ft) ; 4G Modem | D17: 28500 | E17: 60 | I17: 2 | J17: connectors named in the description | AD17: TP5-60-480-3 | AE17: all_in_one
A18: _kW60 | B18: CTX-AiO-60-2-200 | C18: Gen 2 60kW DCFC - 200 Amps / 1000VDC with CCS1 & CCS1(~16ft) ; 4G Modem | D18: 31350 | E18: 60 | I18: 2 | J18: connectors named in the description | AD18: TP5-60-480-4 | AE18: all_in_one
A19: _kW60 | B19: CTX-AiO-60-3-200 | C19: Gen 2 60kW DCFC - 200 Amps / 1000VDC with CCS1 & NACS(~16ft) ; 4G Modem | D19: 31350 | E19: 60 | I19: 2 | J19: connectors named in the description | AD19: CTX-AiO-60-2-200 | AE19: all_in_one
A20: _kW60 | B20: CTX-AiO-60-4-200 | C20: Gen 2 60kW DCFC - 200 Amps / 1000VDC with NACS & NACS(~16ft) ; 4G Modem | D20: 31350 | E20: 60 | I20: 2 | J20: connectors named in the description | AD20: CTX-AiO-60-3-200 | AE20: all_in_one
A21: _kW120 | B21: TP5-120-480-1 | C21: 120kW DCFC All In One Charger - 200 Amps / 1000VDC with CCS1 & NACS(~16ft) ; Can charge 2 cars simultaneously with 60kW each ; 4G Modem | D21: 54000 | E21: 120 | I21: 2 | J21: connectors named in the description | AD21: CTX-AiO-60-4-200 | AE21: all_in_one
A22: _kW120 | B22: TP5-120-480-2 | C22: 120kW DCFC All In One Charger - 200 Amps / 1000VDC with CCS1 & CCS1(~16ft); Can charge 2 cars simultaneously with 60kW each ; 4G Modem | D22: 54000 | E22: 120 | I22: 2 | J22: connectors named in the description | AD22: TP5-120-480-1 | AE22: all_in_one
A23: _kW120 | B23: TP5-120-480-2-300 | C23: 120kW DCFC All In One Charger - 350A Cable / 1000VDC with CCS1 & CCS1(~16ft); Can charge 2 cars simultaneously with 60kW each ; 4G Modem | D23: 54000 | E23: 120 | I23: 2 | J23: connectors named in the description | AD23: TP5-120-480-2 | AE23: all_in_one
A24: _kW120 | B24: TP5-120-480-3-300 | C24: 120kW DCFC All In One Charger - 1000VDC, Cables: 350A CCS1 & 400A NACS (~16ft); Can charge 2 cars simultaneously with 60kW each ; 4G Modem | D24: 54000 | E24: 120 | I24: 2 | J24: manual — description does not state the count | AD24: TP5-120-480-2-300 | AE24: all_in_one
A25: _kW120 | B25: CTX-AiO-120-2-350 | C25: Gen3 120kW CCS1 350A + CCS1 350A ; Cable Management + CC | D25: 59400 | E25: 120 | I25: 2 | J25: connectors named in the description | AD25: TP5-120-480-3-300 | AE25: all_in_one
A26: _kW120 | B26: CTX-AiO-120-3-350 | C26: Gen3 120kW CCS1 350A + NACS 350A ; Cable Management + CC | D26: 59400 | E26: 120 | I26: 2 | J26: connectors named in the description | AD26: CTX-AiO-120-2-350 | AE26: all_in_one
A27: _kW120 | B27: CTX-AiO-120-4-350 | C27: Gen3 120kW NACS 350A + NACS 350A ; Cable Management + CC | D27: 59400 | E27: 120 | I27: 2 | J27: connectors named in the description | AD27: CTX-AiO-120-3-350 | AE27: all_in_one
A28: _kW120 | B28: CTX-AiO-120-5-350 | C28: Gen3 120kW Single CCS1 350A ; Cable Management + CC | D28: 59400 | E28: 120 | I28: 1 | J28: description says Single | AD28: CTX-AiO-120-4-350 | AE28: all_in_one
... A61: _kW360 | B61: HPC-360-480-4 | C61: 360kW HPC All In One Charger - 500 Amps / 1000VDC with Liquid Cooled Connector for NACS / NACS ; Can deliver 500A on CCS coonnector. Can charge 2 cars simultaneously; 4G | D61: 110000 | E61: 360 | I61: 2 | J61: connectors named in the description | AD61: HPC-360-480-3 | AE61: all_in_one
A62: _Distributed_System | B62: CTX-DSPB-360 | C62: 360kW Tower | D62: 81400 | E62: 360 | J62: distributed system — the architecture table holds this | AD62: HPC-360-480-4 | AE62: all_in_one
A63: _Distributed_System | B63: CTX-DSPB-480 | C63: 480kW Tower | D63: 90200 | E63: 480 | J63: distributed system — the architecture table holds this | AD63: CTX-DSPB-360 | AE63: power_cabinet
A64: _Distributed_System | B64: CTX-DSPB-1280 | C64: 1,280kW Tower | D64: 225000 | E64: 1280 | J64: distributed system — the architecture table holds this | AD64: CTX-DSPB-480 | AE64: power_cabinet
A65: _Distributed_System | B65: CTX-DST-2-300 | C65: Dispenser 300/300 | D65: 35200 | J65: distributed system — the architecture table holds this | AD65: CTX-DSPB-1280 | AE65: power_cabinet
A66: _Distributed_System | B66: CTX-DST-HPC-2-500/300 | C66: Dispenser 500/300 | D66: 49500 | J66: distributed system — the architecture table holds this | AD66: CTX-DST-2-300 | AE66: dispenser
A67: _Buy_America | B67: TP5-60-480-2-BAA | C67: Buy America NEVI Compliant, Assembled in CA, USA 60kW DCFC - 140 Amps / 1000VDC with CCS1 & CCS1(~16ft) ; 4G Modem | D67: 68200 | I67: 2 | J67: connectors named in the description | AD67: CTX-DST-HPC-2-500/300 | AE67: dispenser
A68: _Buy_America | B68: TP5-60-480-3-BAA | C68: Buy America NEVI Compliant, Assembled in CA, USA 60kW DCFC - 140 Amps / 1000VDC with CCS1 & NACS ; 4G Modem | D68: 68200 | I68: 2 | J68: connectors named in the description | AD68: TP5-60-480-2-BAA | AE68: all_in_one
A69: _Buy_America | B69: TP5-60-480-4-BAA | C69: Buy America NEVI Compliant, Assembled in CA, USA 60kW DCFC - 140 Amps / 1000VDC with NACS & NACS ; 4G Modem | D69: 68200 | I69: 2 | J69: connectors named in the description | AD69: TP5-60-480-3-BAA | AE69: all_in_one
A70: _Buy_America | B70: TP5-120-480-2-300-BAA | C70: Buy America NEVI Compliant, Assembled in CA, USA 120kW DCFC All In One Charger - 350A Cable / 1000VDC with CCS1 & CCS1(~16ft); Can charge 2 cars simultaneously with 60kW | D70: 75900 | I70: 2 | J70: connectors named in the description | AD70: TP5-60-480-4-BAA | AE70: all_in_one
A71: _Buy_America | B71: TP5-120-480-3-300-BAA | C71: Buy America NEVI Compliant, Assembled in CA, USA 120kW DCFC All In One Charger - 350A Cable / 1000VDC with CCS1 & NACS; Can charge 2 cars simultaneously with 60kW each ; | D71: 75900 | I71: 2 | J71: connectors named in the description | AD71: TP5-120-480-2-300-BAA | AE71: all_in_one
A72: _Buy_America | B72: TP5-120-480-4-300-BAA | C72: Buy America NEVI Compliant, Assembled in CA, USA 120kW DCFC All In One Charger - 350A Cable / 1000VDC with NACS & NACS(~16ft); Can charge 2 cars simultaneously with 60kW | D72: 75900 | I72: 2 | J72: connectors named in the description | AD72: TP5-120-480-3-300-BAA | AE72: all_in_one
A73: _Buy_America | B73: TP5-180-480-2-BAA | C73: Buy America NEVI Compliant, Assembled in CA, USA 180kW Air Cooled 350A Cable (BAA) CCS1 / CCS1 1000VDC Connector for Dual CCS1; Can deliver 350A on one CCS conector. Set | D73: 82500 | I73: 2 | J73: description says Dual | AD73: TP5-120-480-4-300-BAA | AE73: all_in_one
A74: _Buy_America | B74: TP5-180-480-3-BAA | C74: Buy America NEVI Compliant, Assembled in CA, USA 180kW Air Cooled 350A Cable (BAA) CCS1 / NACS 1000VDC Connector for Dual CCS1; Can deliver 350A on one CCS conector. Set | D74: 82500 | I74: 2 | J74: description says Dual | AD74: TP5-180-480-2-BAA | AE74: all_in_one
A75: _Buy_America | B75: TP5-180-480-4-BAA | C75: Buy America NEVI Compliant, Assembled in CA, USA 180kW Air Cooled 350A Cable (BAA) NACS / NACS 1000VDC Connector for Dual CCS1; Can deliver 350A on one CCS conector. Set | D75: 82500 | I75: 2 | J75: description says Dual | AD75: TP5-180-480-3-BAA | AE75: all_in_one
A76: _Buy_America | B76: HPC-180-480-2-BAA | C76: Buy America NEVI Compliant, Assembled in CA, USA 180kW Liquid Cooled (BAA) Dual CCS1 500 Amps / 1000VDC with Liquid Cooled Connector for Dual CCS1 ; Can deliver 450A on o | D76: 82500 | I76: 2 | J76: description says Dual | AD76: TP5-180-480-4-BAA | AE76: all_in_one
A77: _Buy_America | B77: HPC-180-480-3-BAA | C77: Buy America NEVI Compliant, Assembled in CA, USA 180kW Liquid Cooled (BAA) CCS1 / NACS 1000VDC with Liquid Cooled Connector for Dual CCS1 ; Can deliver 450A on one CCS co | D77: 82500 | I77: 2 | J77: description says Dual | AD77: HPC-180-480-2-BAA | AE77: all_in_one
A78: _Buy_America | B78: HPC-180-480-4-BAA | C78: Buy America NEVI Compliant, Assembled in CA, USA 180kW Liquid Cooled (BAA) NACS /NACS 1000VDC with Liquid Cooled Connector for Dual CCS1 ; Can deliver 450A on one CCS con | D78: 82500 | I78: 2 | J78: description says Dual | AD78: HPC-180-480-3-BAA | AE78: all_in_one
... A93: _L2_Accessories | B93: CTX-FLUXPED-SBS | C93: Side By Side Bracket | D93: 137.5 | I93: 0 | J93: accessory — not a charging position | AD93: CTX-FLUXPED-CMS-2 | AE93: accessory
AD94: CTX-FLUXPED-SBS | AE94: accessory
A95: SERVICE AND WARRANTY RATES PER CABINET PER YEAR
A96: Class | C96: Yearly warranty | D96: In-warranty service | E96: Warranty + service, year 3+ | F96: Out-of-warranty service | G96: Included manufacturer warranty
A97: AC Charger - 7.2 kW UP80J-PMP Single | C97: 416 | D97: 320.11 | E97: 736.11 | F97: NOT OFFERED | G97: 1 year, parts only
A98: AC Charger - 2 x 7.2 kW UP160J-PMP Dual | C98: 416 | D98: 320.11 | E98: 736.11 | F98: NOT OFFERED | G98: 1 year, parts only
A99: AC Charger - 7.2 kW UP80J-WMP Single | C99: 416 | D99: 320.11 | E99: 736.11 | F99: NOT OFFERED | G99: 1 year, parts only
A100: AC Charger - 2 x 7.2 kW UP160J-WMP Dual | C100: 416 | D100: 320.11 | E100: 736.11 | F100: NOT OFFERED | G100: 1 year, parts only
A101: DC-60kW CCS1 + NACS | C101: 962.84 | D101: 1476.36 | E101: 2439.2 | F101: NOT OFFERED | G101: 2 years, parts only
A102: DC-120kW CCS1 + NACS | C102: 1196.91 | D102: 1616.76 | E102: 2813.67 | F102: NOT OFFERED | G102: 2 years, parts only
A103: DC-160kW CCS1 + NACS | C103: 1428.57 | D103: 1879.2 | E103: 3307.77 | F103: NOT OFFERED | G103: 2 years, parts only
A104: DC-180KW | C104: 1856.844 | D104: 2708.64 | E104: 4565.484 | F104: NOT OFFERED | G104: 2 years, parts only
A105: DC-240KW | C105: 2708.64 | D105: 6478.754 | E105: 9187.394 | F105: NOT OFFERED | G105: 2 years, parts only
A106: DC-360kW CCS1 + CCS1 | C106: 4051.08 | D106: 4898.88 | E106: 8949.96 | F106: NOT OFFERED | G106: 2 years, parts only
A107: CTX-DSPB-360 | C107: =C106+(C106*25%) | D107: =D106+(D106*25%) | E107: =D107+C107 | F107: NOT OFFERED | G107: 2 years, parts only
A108: CTX-DSPB-480 | C108: =C107+(C107*30%) | D108: =D107+(D107*25%) | E108: =D108+C108 | F108: NOT OFFERED | G108: 2 years, parts only
A109: CTX-DSPB-1280 | C109: =C108+(C108*50%) | D109: =D108+(D108*25%) | E109: =D109+C109 | F109: NOT OFFERED | G109: 2 years, parts only
A110: CTX-DST-2-300/CTX-DST-HPC-2-500/300 | C110: 962.84 | D110: 1476.36 | E110: =D110+C110
A111: Service is sold only against a warranty in force — the included manufacturer term or a paid extension of it. Zero Impact Energy does not normally service equipment carrying no warranty, which is why the rate is called in-warranty service. The out-of-warranty column is deliberately "NOT OFFERED" rather than blank: a blank reads as zero to anything that consumes this table.
A112: The year-3+ rate is the yearly warranty plus the in-warranty service rate. Extending the warranty does not change what service costs; it adds back the warranty the manufacturer previously gave.
A115: EQUIPMENT ARCHITECTURE — what each SKU is, not just what it costs
A116: A power cabinet takes AC and produces DC and has no connectors. A dispenser has the connectors and no power of its own. An all-in-one is both in one enclosure. The role decides whether a row adds load, ports, both or neither — see 2_Equipment.
A117: SKU | B117: Role | C117: DC output kW | D117: AC input kW | E117: AC input circuits | F117: AC FLA total | G117: DC outputs / connectors | H117: Max dual dispensers | I117: Source and confidence
A118: CTX-DSPB-360 | B118: Power cabinet — no connectors | C118: 360 | D118: 393 | E118: 2 | F118: 472.7 | G118: 6 | H118: 3 | I118: DERIVED — AC input, circuit count and the 3-dispenser limit extrapolated from the published 480 kW cabinet. Confirm all three with Chargetronix before sizing service.
A119: CTX-DSPB-480 | B119: Power cabinet — no connectors | C119: 480 | D119: 524 | E119: 2 | F119: 630.3 | G119: 6 | H119: 3 | I119: PUBLISHED — 480 VAC +/-10%, 3P+PE, 2 input circuits at 315 A each, input power 524 kW, output 480 kW, 200-1000 VDC, 500 A per channel, 1,600 A system, up to 6 DC outputs, dynamic power sharing in 40 kW increments. Takes UP TO 3 DUAL DISPENSERS (6 connectors).
A120: CTX-DSPB-1280 | B120: Power cabinet — no connectors | C120: 1280 | D120: 1397.3 | E120: 6 | F120: 1680.7 | G120: 16 | H120: 8 | I120: PART PUBLISHED — 1,280 kW output, 480 VAC, 200-1000 VDC, 500 A per output, 4,267 A total, 16 connectors max — so UP TO 8 DUAL DISPENSERS. AC input power and circuit count are DERIVED; confirm with Chargetronix before sizing service.
A121: CTX-DST-2-300 | B121: Dispenser — connectors only | C121: 0 | D121: 0 | E121: 0 | F121: 0 | G121: 2 | H121: 0 | I121: PUBLISHED — 2 connectors CCS1/NACS, 200-1000 V, up to 2 input circuits per dispenser, load sharing across 2 EVs, 5 m cable, 15 in touchscreen, 241 kg.
A122: CTX-DST-HPC-2-500/300 | B122: Dispenser — connectors only | C122: 0 | D122: 0 | E122: 0 | F122: 0 | G122: 2 | H122: 0 | I122: PUBLISHED — liquid-cooled connector rated 500 A, air-cooled 200/350 A boost to 400 A.
A124: MISSING FROM THE PRICE BOOK — Nexus Fleet Dispenser | C124: single connector, CCS1/NACS air cooled 200/350 A, 50 kg, 5 m or 7 m cable, no user interface — in the published range but absent from the price book, so it cannot be quoted.

Sheet RefData
A1: REFERENCE DATA
A2: Lookup tables used by the electrical checks and the costing engine.
A3: Amps required | B3: Standard frame | D3: Charger kW | E3: Design amps | F3: Breaker A
A4: 0 | B4: 400 | D4: 30 | E4: 40 | F4: 50
A5: 400 | B5: 600 | D5: 50 | E5: 72 | F5: 100
A6: 600 | B6: 800 | D6: 60 | E6: 80 | F6: 100
A7: 800 | B7: 1000 | D7: 100 | E7: 130 | F7: 200
A8: 1000 | B8: 1200 | D8: 120 | E8: 160 | F8: 200
A9: 1200 | B9: 1600 | D9: 160 | E9: 215 | F9: 300
A10: 1600 | B10: 2000 | D10: 180 | E10: 240 | F10: 300
A11: 2000 | B11: 3200 | D11: 200 | E11: 265 | F11: 335
A12: 3200 | B12: 4000 | D12: 240 | E12: 320 | F12: 400
A13: 4000 | B13: 5000 | D13: 275 | E13: 385 | F13: 500
A14: 5000 | B14: 6000 | D14: 300 | E14: 400 | F14: 500
A15: 6000 | B15: 10000 | D15: 360 | E15: 480 | F15: 600
A18: 480V SWITCHGEAR AND BREAKER PRICES
A19: Item | B19: Size | C19: Cost
A20: Main | B20: 400A | C20: 20426.82
A21: Main | B21: 800A | C21: 31187
A22: Main | B22: 1000A | C22: 36812.5
A23: Main | B23: 1200A | C23: 43292.68
A24: Main | B24: 1600A | C24: 56750
A25: Main | B25: 2000A | C25: 60000
A26: Main | B26: 2500.0 | C26: 58540
A27: Main | B27: 3000A | C27: 65000
A28: Main | B28: 4000A | C28: 67500
A29: Main | B29: 5000A | C29: 70000
A30: main breakers | B30: 110A | C30: 650
A31: main breakers | B31: 125A | C31: 700
... A39: disconnects | B39: 500A | C39: 4000
A40: CONDUCTOR AND CONDUIT — $ PER FOOT
A41: Wire size | B41: Copper $/ft | C41: Aluminium $/ft | D41: Conduit size | E41: PVC $/ft
A42: 10 AWG | B42: 0.30329 | C42: 0.28 | D42: (1/2") | E42: 0.2445
A43: 8 AWG | B43: 0.56613 | D43: (3/4") | E43: 0.2912
A44: 6 AWG | B44: 0.87104 | C44: 0.30636 | D44: (1") | E44: 0.4698
A45: 4 AWG | B45: 1.33293 | C45: 0.37998 | D45: (1 1/4") | E45: 0.6155
A46: 2 AWG | B46: 2.1044 | C46: 0.36681 | D46: (1 1/2") | E46: 0.7129
A47: 1 AWG | B47: 2.39833 | C47: 0.4821 | D47: (2") | E47: 0.8897
A48: 1 /0 | B48: 2.95304 | C48: 0.66733 | D48: (2 1/2") | E48: 1.396
A49: 2 /0 | B49: 3.63758 | C49: 0.75045 | D49: (3") | E49: 1.7033
A50: 3 /0 | B50: 4.5658 | C50: 0.88701 | D50: (3 1/2") | E50: 2.25
A51: 4 /0 | B51: 5.73045 | C51: 1.09956 | D51: (4") | E51: 2.3164
A52: 250 KCMIL | B52: 6.64016 | C52: 1.2278 | D52: (5") | E52: 3.3106
A53: 300 KCMIL | B53: 7.9632 | C53: 1.49616
A54: 350 KCMIL | B54: 9.32416 | C54: 2.06137
A55: 400 KCMIL | B55: 10.60671 | C55: 2.10412
A56: 450 KCMIL | B56: 11.334 | C56: 2.7204
A57: 500 KCMIL | B57: 13.30059 | C57: 2.7204
A58: 600 KCMIL | B58: 16.57382 | C58: 2.7204
A59: 750 KCMIL | B59: 25.921 | C59: 4.809
A60: 1000 KCMIL | B60: 34.398 | C60: 7.566
A63: CONDUCTOR AMPACITY — NEC Table 310.16
A64: Ampacity at 30 C ambient, not more than three current-carrying conductors in a raceway. Correct for ambient using the table below, then cap the result at the TERMINATION rating per 110.14(C). 450 KCMIL is in this workbook's size list but is not a size Table 310.16 carries, so it is deliberately blank.
A65: Size | B65: Cu-60 | C65: Cu-75 | D65: Cu-90 | E65: Al-60 | F65: Al-75 | G65: Al-90
A66: 10 AWG | B66: 30 | C66: 35 | D66: 40 | E66: 25 | F66: 30 | G66: 35
A67: 8 AWG | B67: 40 | C67: 50 | D67: 55 | E67: 35 | F67: 40 | G67: 45
A68: 6 AWG | B68: 55 | C68: 65 | D68: 75 | E68: 40 | F68: 50 | G68: 55
A69: 4 AWG | B69: 70 | C69: 85 | D69: 95 | E69: 55 | F69: 65 | G69: 75
A70: 2 AWG | B70: 95 | C70: 115 | D70: 130 | E70: 75 | F70: 90 | G70: 100
A71: 1 AWG | B71: 110 | C71: 130 | D71: 145 | E71: 85 | F71: 100 | G71: 115
A72: 1 /0 | B72: 125 | C72: 150 | D72: 170 | E72: 100 | F72: 120 | G72: 135
A73: 2 /0 | B73: 145 | C73: 175 | D73: 195 | E73: 115 | F73: 135 | G73: 150
A74: 3 /0 | B74: 165 | C74: 200 | D74: 225 | E74: 130 | F74: 155 | G74: 175
A75: 4 /0 | B75: 195 | C75: 230 | D75: 260 | E75: 150 | F75: 180 | G75: 205
A76: 250 KCMIL | B76: 215 | C76: 255 | D76: 290 | E76: 170 | F76: 205 | G76: 230
A77: 300 KCMIL | B77: 240 | C77: 285 | D77: 320 | E77: 195 | F77: 230 | G77: 260
... A79: 400 KCMIL | B79: 280 | C79: 335 | D79: 380 | E79: 225 | F79: 270 | G79: 305
A80: 450 KCMIL
A81: 500 KCMIL | B81: 320 | C81: 380 | D81: 430 | E81: 260 | F81: 310 | G81: 350
A82: 600 KCMIL | B82: 350 | C82: 420 | D82: 475 | E82: 285 | F82: 340 | G82: 385
A83: 750 KCMIL | B83: 400 | C83: 475 | D83: 535 | E83: 320 | F83: 385 | G83: 435
A84: 1000 KCMIL | B84: 455 | C84: 545 | D84: 615 | E84: 375 | F84: 445 | G84: 500
A87: AMBIENT TEMPERATURE CORRECTION — NEC Table 310.15(B)(1)(1)
A88: Multiplier on the ampacity above, based on 30 C. "Up to C" is the top of each band; a design ambient is matched to the first band it does not exceed. A blank means that ambient is not permitted for that insulation rating.
A89: Up to C | B89: 60 | C89: 75 | D89: 90
A90: 10 | B90: 1.29 | C90: 1.2 | D90: 1.15
A91: 15 | B91: 1.22 | C91: 1.15 | D91: 1.12
A92: 20 | B92: 1.15 | C92: 1.11 | D92: 1.08
A93: 25 | B93: 1.08 | C93: 1.05 | D93: 1.04
A94: 30 | B94: 1 | C94: 1 | D94: 1
A95: 35 | B95: 0.91 | C95: 0.94 | D95: 0.96
A96: 40 | B96: 0.82 | C96: 0.88 | D96: 0.91
A97: 45 | B97: 0.71 | C97: 0.82 | D97: 0.87
A98: 50 | B98: 0.58 | C98: 0.75 | D98: 0.82
A99: 55 | B99: 0.41 | C99: 0.67 | D99: 0.76
A100: 60 | C100: 0.58 | D100: 0.71
A101: 65 | C101: 0.47 | D101: 0.65
A102: 70 | C102: 0.33 | D102: 0.58
A103: 75 | D103: 0.5
A104: 80 | D104: 0.41
A107: CONDUCTOR IMPEDANCE — NEC Chapter 9 Table 9
A108: VERIFY BEFORE RELYING ON THE VOLTAGE DROP. Effective Z at 0.85 power factor, ohms per 1,000 ft, PVC conduit. These figures were typed from memory of the printed table and have NOT been checked against it. The ampacity and correction tables above are trusted; this one is not, and the voltage-drop verdict on the Electrical tab says ADVISORY until an engineer has corrected these rows.
A109: Size | B109: Cu ohm/1000ft | C109: Al ohm/1000ft
A110: 10 AWG | B110: 1.2
A111: 8 AWG | B111: 0.78
A112: 6 AWG | B112: 0.49 | C112: 0.71
A113: 4 AWG | B113: 0.31 | C113: 0.45
A114: 2 AWG | B114: 0.19 | C114: 0.29
A115: 1 AWG | B115: 0.15 | C115: 0.23
A116: 1 /0 | B116: 0.12 | C116: 0.19
...

Sheet Utilities
A1: CALIFORNIA ELECTRIC UTILITIES — DELIVERY
A2: Every entity that sets its own retail DELIVERY tariff in California, and therefore its own EV rate. Community choice aggregators are NOT here: a CCA sets the generation component only and cannot set an EV tariff — the delivery utility's tariff still governs in full. CCAs are listed separately below.
A4: Utility | B4: Type | C4: Service territory | D4: EV rate status | F4: DELIVERY UTILITY PICKER — what the Project tab offers | H4: RATE SCHEDULE PICKER — what the Revenue tab offers | J4: Utility (resolved) | K4: Type | L4: Service territory | M4: EV rate status | N4: State
A5: PG&E — Pacific Gas and Electric | B5: IOU | C5: Northern & central CA, 47 counties | D5: EV rate: BEV-1 / BEV-2-S / BEV-2-P | F5: PG&E — Pacific Gas and Electric | H5: BEV-1 | J5: PG&E — Pacific Gas and Electric | K5: IOU | L5: Northern & central CA, 47 counties | M5: EV rate: BEV-1 / BEV-2-S / BEV-2-P | N5: California
A6: SCE — Southern California Edison | B6: IOU | C6: Central & southern CA, 15 counties | D6: EV rate: TOU-EV-7 / 8 / 9 | F6: SCE — Southern California Edison | H6: BEV-2-S | J6: SCE — Southern California Edison | K6: IOU | L6: Central & southern CA, 15 counties | M6: EV rate: TOU-EV-7 / 8 / 9 | N6: California
A7: SDG&E — San Diego Gas & Electric | B7: IOU | C7: San Diego Co. + southern Orange Co. | D7: EV rate: EV-HP | F7: SDG&E — San Diego Gas & Electric | H7: BEV-2-P | J7: SDG&E — San Diego Gas & Electric | K7: IOU | L7: San Diego Co. + southern Orange Co. | M7: EV rate: EV-HP | N7: California
A8: Liberty Utilities (CalPeco Electric) | B8: IOU | C8: North Lake Tahoe & eastern Sierra | D8: EV rate: TOU A-1/A-2/A-3 EV | F8: Liberty Utilities (CalPeco Electric) | H8: TOU-EV-7 | J8: Liberty Utilities (CalPeco Electric) | K8: IOU | L8: North Lake Tahoe & eastern Sierra | M8: EV rate: TOU A-1/A-2/A-3 EV | N8: California
A9: Pacific Power (PacifiCorp) | B9: IOU | C9: Siskiyou, Modoc, Shasta, Del Norte | D9: NO commercial EV rate | F9: Pacific Power (PacifiCorp) | H9: TOU-EV-8 | J9: Pacific Power (PacifiCorp) | K9: IOU | L9: Siskiyou, Modoc, Shasta, Del Norte | M9: NO commercial EV rate | N9: California
A10: Bear Valley Electric Service (BVES) | B10: IOU | C10: Big Bear Lake, San Bernardino Co. | D10: EV rate: TOU-EV-2 / TOU-EV-3 (max 500 kW) | F10: Bear Valley Electric Service (BVES) | H10: TOU-EV-9 | J10: Bear Valley Electric Service (BVES) | K10: IOU | L10: Big Bear Lake, San Bernardino Co. | M10: EV rate: TOU-EV-2 / TOU-EV-3 (max 500 kW) | N10: California
A11: LADWP — Los Angeles Dept of Water & Power | B11: POU | C11: City of Los Angeles + Owens Valley | D11: EV rate: EVA1 / EVA2 / EVA3 (pilot) | F11: LADWP — Los Angeles Dept of Water & Power | H11: EV-HP >150kW | J11: LADWP — Los Angeles Dept of Water & Power | K11: POU | L11: City of Los Angeles + Owens Valley | M11: EV rate: EVA1 / EVA2 / EVA3 (pilot) | N11: California
A12: SMUD — Sacramento Municipal Utility District | B12: POU | C12: Sacramento Co. + part of Placer Co. | D12: EV rate: EV_SR subscription | F12: SMUD — Sacramento Municipal Utility District | H12: EV-HP <150kW | J12: SMUD — Sacramento Municipal Utility District | K12: POU | L12: Sacramento Co. + part of Placer Co. | M12: EV rate: EV_SR subscription | N12: California
A13: IID — Imperial Irrigation District | B13: POU | C13: Imperial Co. + eastern Coachella Valley | D13: NO EV rate | F13: IID — Imperial Irrigation District | H13: UMERC Cg1 — General Secondary, three-phase | J13: IID — Imperial Irrigation District | K13: POU | L13: Imperial Co. + eastern Coachella Valley | M13: NO EV rate | N13: California
A14: MID — Modesto Irrigation District | B14: POU | C14: Modesto & Stanislaus Co. | D14: NO commercial EV rate | F14: MID — Modesto Irrigation District | H14: UMERC Cg5 — General Secondary Time-of-Use | J14: MID — Modesto Irrigation District | K14: POU | L14: Modesto & Stanislaus Co. | M14: NO commercial EV rate | N14: California
A15: Anaheim Public Utilities | B15: POU | C15: City of Anaheim, Orange Co. | D15: EV rate D-EV-2 CLOSED to new customers | F15: Anaheim Public Utilities | H15: UMERC Cg3 — General Secondary Demand TOU | J15: Anaheim Public Utilities | K15: POU | L15: City of Anaheim, Orange Co. | M15: EV rate D-EV-2 CLOSED to new customers | N15: California
... A18: Glendale Water and Power | B18: POU | C18: City of Glendale, LA Co. | D18: NO commercial EV rate | F18: Glendale Water and Power | H18: REU E7/E8 — Large Commercial (demand) | J18: Glendale Water and Power | K18: POU | L18: City of Glendale, LA Co. | M18: NO commercial EV rate | N18: California
A19: Roseville Electric Utility | B19: POU | C19: City of Roseville, Placer Co. | D19: NO commercial EV rate | F19: Roseville Electric Utility | J19: Roseville Electric Utility | K19: POU | L19: City of Roseville, Placer Co. | M19: NO commercial EV rate | N19: California
A20: Pasadena Water and Power | B20: POU | C20: City of Pasadena, LA Co. | D20: NO commercial EV rate | F20: Pasadena Water and Power | J20: Pasadena Water and Power | K20: POU | L20: City of Pasadena, LA Co. | M20: NO commercial EV rate | N20: California
A21: Silicon Valley Power (Santa Clara) | B21: POU | C21: City of Santa Clara | D21: NO EV rate — by policy | F21: Silicon Valley Power (Santa Clara) | J21: Silicon Valley Power (Santa Clara) | K21: POU | L21: City of Santa Clara | M21: NO EV rate — by policy | N21: California
A22: Burbank Water and Power | B22: POU | C22: City of Burbank, LA Co. | D22: NO commercial EV rate | F22: Burbank Water and Power | J22: Burbank Water and Power | K22: POU | L22: City of Burbank, LA Co. | M22: NO commercial EV rate | N22: California
A23: Redding Electric Utility | B23: POU | C23: City of Redding, Shasta Co. | D23: Not researched | F23: Redding Electric Utility | J23: Redding Electric Utility | K23: POU | L23: City of Redding, Shasta Co. | M23: Not researched | N23: California
A24: Alameda Municipal Power | B24: POU | C24: City of Alameda | D24: NO commercial EV rate | F24: Alameda Municipal Power | J24: Alameda Municipal Power | K24: POU | L24: City of Alameda | M24: NO commercial EV rate | N24: California
A25: City of Palo Alto Utilities | B25: POU | C25: City of Palo Alto | D25: NO commercial EV rate | F25: City of Palo Alto Utilities | J25: City of Palo Alto Utilities | K25: POU | L25: City of Palo Alto | M25: NO commercial EV rate | N25: California
A26: Lodi Electric Utility | B26: POU | C26: City of Lodi, San Joaquin Co. | D26: Not researched | F26: Lodi Electric Utility | J26: Lodi Electric Utility | K26: POU | L26: City of Lodi, San Joaquin Co. | M26: Not researched | N26: California
A27: Colton Public Utilities | B27: POU | C27: City of Colton, San Bernardino Co. | D27: EV rate page exists — obtain tariff | F27: Colton Public Utilities | J27: Colton Public Utilities | K27: POU | L27: City of Colton, San Bernardino Co. | M27: EV rate page exists — obtain tariff | N27: California
A28: Azusa Light & Water | B28: POU | C28: City of Azusa, LA Co. | D28: NO commercial EV rate | F28: Azusa Light & Water | J28: Azusa Light & Water | K28: POU | L28: City of Azusa, LA Co. | M28: NO commercial EV rate | N28: California
A29: Lompoc Electric Division | B29: POU | C29: City of Lompoc, Santa Barbara Co. | D29: Not researched | F29: Lompoc Electric Division | J29: Lompoc Electric Division | K29: POU | L29: City of Lompoc, Santa Barbara Co. | M29: Not researched | N29: California
A30: Truckee Donner PUD | B30: POU | C30: Truckee & Donner, Nevada/Placer Co. | D30: Not researched | F30: Truckee Donner PUD | J30: Truckee Donner PUD | K30: POU | L30: Truckee & Donner, Nevada/Placer Co. | M30: Not researched | N30: California
... A59: Valley Electric Association | B59: Co-op | C59: Sliver of eastern Inyo Co. (44 customers) | D59: Not researched | F59: Valley Electric Association | J59: Valley Electric Association | K59: Co-op | L59: Sliver of eastern Inyo Co. (44 customers) | M59: Not researched | N59: California
A60: Other / not listed — enter manually | B60: Other | D60: Enter the tariff manually on 9_Overrides | F60: DTE Electric Company | J60: DTE Electric Company | K60: IOU | L60: Southeast Michigan — Detroit, Ann Arbor, Port Huron | M60: Not researched here | N60: Michigan
F61: Consumers Energy | J61: Consumers Energy | K61: IOU | L61: Most of the Lower Peninsula outside DTE | M61: Not researched here | N61: Michigan
F62: Indiana Michigan Power (AEP) | J62: Indiana Michigan Power (AEP) | K62: IOU | L62: Southwest MI — Berrien, Cass, St Joseph | M62: Not researched here | N62: Michigan
A63: COMMUNITY CHOICE AGGREGATORS — generation only | F63: UMERC — Upper Michigan Energy Resources (We Energies) | J63: UMERC — Upper Michigan Energy Resources (We Energies) | K63: IOU | L63: Upper Peninsula — Marquette, Menominee | M63: Not researched here | N63: Michigan
A64: A CCA replaces ONLY the generation $/kWh line. Rate eligibility, time-of-use periods, the demand subscription, facilities charges, Rule 29 treatment and every other charge stay with the delivery utility. Build the bill from the delivery tariff, then substitute the generation line and add PCIA plus the franchise fee surcharge. CCA rebates and make-ready grants are separate cash flows, never a tariff change. | F64: UPPCO — Upper Peninsula Power Company | J64: UPPCO — Upper Peninsula Power Company | K64: IOU | L64: Upper Peninsula | M64: Not researched here | N64: Michigan
F65: Northern States Power — Xcel | J65: Northern States Power — Xcel | K65: IOU | L65: Western Upper Peninsula | M65: Not researched here | N65: Michigan
A66: Community choice aggregator | C66: Delivery utility | F66: Alpena Power Company | J66: Alpena Power Company | K66: IOU | L66: Alpena and surrounding townships | M66: Not researched here | N66: Michigan
A67: None — bundled utility service | C67: — | F67: Lansing Board of Water & Light | J67: Lansing Board of Water & Light | K67: POU | L67: Lansing and East Lansing | M67: Not researched here | N67: Michigan
A68: Ava Community Energy (fmr East Bay CE) | C68: PG&E | F68: Holland Board of Public Works | J68: Holland Board of Public Works | K68: POU | L68: City of Holland | M68: Not researched here | N68: Michigan
A69: Clean Power Alliance | C69: SCE | F69: Traverse City Light & Power | J69: Traverse City Light & Power | K69: POU | L69: City of Traverse City | M69: Not researched here | N69: Michigan
A70: Central Coast Community Energy (3CE) | C70: PG&E and SCE — depends on address | F70: Coldwater Board of Public Utilities | J70: Coldwater Board of Public Utilities | K70: POU | L70: City of Coldwater | M70: Not researched here | N70: Michigan
A71: MCE | C71: PG&E | F71: Wyandotte Municipal Services | J71: Wyandotte Municipal Services | K71: POU | L71: City of Wyandotte | M71: Not researched here | N71: Michigan
A72: San Diego Community Power | C72: SDG&E | F72: Cloverland Electric Cooperative | J72: Cloverland Electric Cooperative | K72: Co-op | L72: Eastern Upper Peninsula | M72: Not researched here | N72: Michigan
A73: CleanPowerSF | C73: PG&E | F73: Great Lakes Energy | J73: Great Lakes Energy | K73: Co-op | L73: Northwest Lower Peninsula | M73: Not researched here | N73: Michigan
A74: WestLight Energy (fmr Peninsula Clean Energy) | C74: PG&E | F74: Presque Isle Electric & Gas Co-op | J74: Presque Isle Electric & Gas Co-op | K74: Co-op | L74: Northeast Lower Peninsula | M74: Not researched here | N74: Michigan
A75: San José Clean Energy | C75: PG&E | F75: HomeWorks Tri-County Electric | J75: HomeWorks Tri-County Electric | K75: Co-op | L75: Central Lower Peninsula | M75: Not researched here | N75: Michigan
A76: Silicon Valley Clean Energy | C76: PG&E | F76: Midwest Energy & Communications | J76: Midwest Energy & Communications | K76: Co-op | L76: Southwest Lower Peninsula | M76: Not researched here | N76: Michigan
A77: Clean Energy Alliance | C77: SDG&E | F77: Thumb Electric Cooperative | J77: Thumb Electric Cooperative | K77: Co-op | L77: The Thumb — Huron, Sanilac, Tuscola | M77: Not researched here | N77: Michigan
A78: Sonoma Clean Power | C78: PG&E | F78: Other / not listed — enter manually | J78: Other / not listed — enter manually | K78: Other | M78: Enter the tariff manually
A79: Orange County Power Authority | C79: SCE
A80: Pioneer Community Energy | C80: PG&E
A81: Redwood Coast Energy Authority | C81: PG&E
A82: Valley Clean Energy | C82: PG&E
A83: Lancaster Energy | C83: SCE
A84: Desert Community Energy | C84: SCE
A85: Rancho Mirage Energy Authority | C85: SCE
A86: Apple Valley Choice Energy | C86: SCE
A87: Energy for Palmdale's Independent Choice | C87: SCE
A88: King City Community Power | C88: PG&E
A89: Pico Rivera Innovative Municipal Energy | C89: SCE
A90: Pomona Choice Energy | C90: SCE
... A93: Direct Access ESP (Calpine, Constellation, Shell…) | C93: Host IOU
A96: MICHIGAN ELECTRIC UTILITIES — DELIVERY
A97: Service territory in Michigan does not follow a mailing address in any obvious way. Confirm the serving utility against the site address before pricing anything that depends on it.
A99: Utility | B99: Type | C99: Service territory
A100: DTE Electric Company | B100: IOU | C100: Southeast Michigan — Detroit, Ann Arbor, Port Huron
A101: Consumers Energy | B101: IOU | C101: Most of the Lower Peninsula outside DTE
A102: Indiana Michigan Power (AEP) | B102: IOU | C102: Southwest MI — Berrien, Cass, St Joseph
A103: UMERC — Upper Michigan Energy Resources (We Energies) | B103: IOU | C103: Upper Peninsula — Marquette, Menominee
A104: UPPCO — Upper Peninsula Power Company | B104: IOU | C104: Upper Peninsula
A105: Northern States Power — Xcel | B105: IOU | C105: Western Upper Peninsula
A106: Alpena Power Company | B106: IOU | C106: Alpena and surrounding townships
A107: Lansing Board of Water & Light | B107: POU | C107: Lansing and East Lansing
A108: Holland Board of Public Works | B108: POU | C108: City of Holland
A109: Traverse City Light & Power | B109: POU | C109: City of Traverse City
A110: Coldwater Board of Public Utilities | B110: POU | C110: City of Coldwater
... A117: Thumb Electric Cooperative | B117: Co-op | C117: The Thumb — Huron, Sanilac, Tuscola

Sheet RateLibrary
A1: CALIFORNIA EVSE RATE LIBRARY
A2: Commercial EV and fallback general-service rates, researched 26 August 2026. Read the STATUS column before using any row. VERIFIED means the figure was read in the utility's own published tariff. NOT PUBLISHED means the utility does not publish it — SCE is the significant case, and those rows are deliberately left at zero rather than filled with an estimate. Rates move: re-verify before pricing a project.
A4: Utility | B4: Schedule | C4: From kW | D4: To kW | E4: Voltage | F4: Peak $/kWh | G4: Off-peak $/kWh | H4: Super off $/kWh | I4: Demand $/kW-mo | J4: Block kW | K4: Block $/mo | L4: Overage $/kW | M4: Customer $/mo | N4: Seasons | O4: Time-of-use periods | P4: STATUS | Q4: Effective | R4: Source
A5: PG&E — Pacific Gas and Electric | B5: BEV-1 | C5: 0 | D5: 100 | E5: Secondary | F5: 0.35711 | G5: 0.1651 | H5: 0.13844 | I5: 0 | J5: 10 | K5: 12.41 | L5: 2.48 | M5: 0 | N5: None — no seasonal variation | O5: Peak 4-9pm daily; Off 9pm-9am & 2-4pm; Super off 9am-2pm — ALL YEAR | P5: VERIFIED | Q5: 2026-03-01 | R5: https://www.pge.com/tariffs/assets/pdf/tariffbook/ELEC_SCHEDS_BEV.pdf
A6: PG&E — Pacific Gas and Electric | B6: BEV-2-S | C6: 100 | D6: 99999 | E6: Secondary | F6: 0.36977 | G6: 0.15654 | H6: 0.13327 | I6: 0 | J6: 50 | K6: 95.56 | L6: 3.82 | M6: 0 | N6: None — no seasonal variation | O6: Peak 4-9pm daily; Off 9pm-9am & 2-4pm; Super off 9am-2pm — ALL YEAR | P6: VERIFIED | Q6: 2026-03-01 | R6: https://www.pge.com/tariffs/assets/pdf/tariffbook/ELEC_SCHEDS_BEV.pdf
A7: PG&E — Pacific Gas and Electric | B7: BEV-2-P | C7: 100 | D7: 99999 | E7: Primary | F7: 0.36003 | G7: 0.15115 | H7: 0.12849 | I7: 0 | J7: 50 | K7: 85.98 | L7: 3.44 | M7: 0 | N7: None — no seasonal variation | O7: Peak 4-9pm daily; Off 9pm-9am & 2-4pm; Super off 9am-2pm — ALL YEAR | P7: VERIFIED | Q7: 2026-03-01 | R7: https://www.pge.com/tariffs/assets/pdf/tariffbook/ELEC_SCHEDS_BEV.pdf
A8: PG&E — Pacific Gas and Electric | B8: B-20 (non-EV alternative) | C8: 1000 | D8: 99999 | E8: Secondary | F8: 0.17702 | G8: 0.11482 | H8: 0.05872 | I8: 80.43 | J8: 0 | K8: 0 | L8: 0 | M8: 3265 | N8: Summer Jun-Sep / Winter Oct-May | O8: Peak 4-9pm; Super off 9am-2pm MARCH-MAY ONLY | P8: PARTIAL | Q8: 2026-03-01 | R8: https://www.pge.com/tariffs/assets/pdf/tariffbook/ELEC_SCHEDS_B-20.pdf
A9: SCE — Southern California Edison | B9: TOU-EV-7 | C9: 0 | D9: 20 | E9: Secondary | F9: 0 | G9: 0 | H9: 0 | I9: 0 | J9: 0 | K9: 0 | L9: 0 | M9: 0 | N9: Summer Jun-Sep / Winter Oct-May | O9: On-peak 4-9pm summer weekdays | P9: NOT PUBLISHED | R9: https://www.sce.com/sites/default/files/custom-files/PDF_Files/TOU-EV-7_8_9_Rate_Fact_Sheet_072025_Accessible.pdf
A10: SCE — Southern California Edison | B10: TOU-EV-8 | C10: 20 | D10: 500 | E10: Secondary | F10: 0 | G10: 0 | H10: 0 | I10: 0 | J10: 0 | K10: 0 | L10: 0 | M10: 0 | N10: Summer Jun-Sep / Winter Oct-May | O10: On-peak 4-9pm summer weekdays | P10: NOT PUBLISHED | R10: https://www.sce.com/sites/default/files/custom-files/PDF_Files/TOU-EV-7_8_9_Rate_Fact_Sheet_072025_Accessible.pdf
A11: SCE — Southern California Edison | B11: TOU-EV-9 | C11: 500 | D11: 99999 | E11: Tiered by voltage | F11: 0 | G11: 0 | H11: 0 | I11: 0 | J11: 0 | K11: 0 | L11: 0 | M11: 0 | N11: Summer Jun-Sep / Winter Oct-May | O11: On-peak 4-9pm summer weekdays | P11: NOT PUBLISHED | R11: https://www.sce.com/sites/default/files/custom-files/PDF_Files/TOU-EV-7_8_9_Rate_Fact_Sheet_072025_Accessible.pdf
A12: SDG&E — San Diego Gas & Electric | B12: EV-HP (<=150 kW) | C12: 20 | D12: 150 | E12: Secondary | F12: 0.32882 | G12: 0.16295 | H12: 0.15307 | I12: 9.43 | J12: 10 | K12: 50.76 | L12: 0 | M12: 151.26 | N12: Summer Jun 1-Oct 31 / Winter Nov 1-May 31 | O12: NOT PUBLISHED — obtain from the tariff sheet | P12: PARTIAL | Q12: 2026-08-01 | R12: https://www.sdge.com/sites/default/files/regulatory/Summary%20Table%20for%20Medium%20Comm%208-1-26.pdf
A13: SDG&E — San Diego Gas & Electric | B13: EV-HP (>150 kW) | C13: 150 | D13: 99999 | E13: Secondary | F13: 0.32882 | G13: 0.16295 | H13: 0.15307 | I13: 9.43 | J13: 25 | K13: 126.89 | L13: 0 | M13: 151.26 | N13: Summer Jun 1-Oct 31 / Winter Nov 1-May 31 | O13: NOT PUBLISHED — obtain from the tariff sheet | P13: PARTIAL | Q13: 2026-08-01 | R13: https://www.sdge.com/sites/default/files/regulatory/Summary%20Table%20for%20Medium%20Comm%208-1-26.pdf
A14: SDG&E — San Diego Gas & Electric | B14: EV-HP Primary (>150 kW) | C14: 150 | D14: 99999 | E14: Primary | F14: 0.3055 | G14: 0.16257 | H14: 0.15283 | I14: 9.39 | J14: 25 | K14: 126.24 | L14: 0 | M14: 66.15 | N14: Summer Jun 1-Oct 31 / Winter Nov 1-May 31 | O14: NOT PUBLISHED — obtain from the tariff sheet | P14: PARTIAL | Q14: 2026-08-01 | R14: https://www.sdge.com/sites/default/files/regulatory/Summary%20Table%20for%20Large%20Comm%208-1-26.pdf
A15: Liberty Utilities (CalPeco Electric) | B15: TOU A-3 EV | C15: 200 | D15: 99999 | E15: All | F15: 0.52239 | G15: 0.30281 | H15: 0 | I15: 0 | J15: 0 | K15: 0 | L15: 0 | M15: 850.81 | N15: Summer / Winter — months NOT PUBLISHED | O15: NOT PUBLISHED — cross-referenced to Special Conditions | P15: PARTIAL | Q15: 2026-06-01 | R15: https://california.libertyutilities.com/uploads/CalPeco%20Tariffs/Schedule%20No.%20A-3%20TOU%20EV%20Large%20General%20Service.pdf
A16: Liberty Utilities (CalPeco Electric) | B16: TOU A-2 EV | C16: 0 | D16: 200 | E16: All | F16: 0 | G16: 0 | H16: 0 | I16: 0 | J16: 0 | K16: 0 | L16: 0 | M16: 201.85 | N16: Summer / Winter — months NOT PUBLISHED | O16: NOT PUBLISHED | P16: PARTIAL | Q16: 2026-06-01 | R16: https://california.libertyutilities.com/uploads/CalPeco%20Tariffs/Schedule%20No%20A-2%20TOU%20EV.pdf
A17: Pacific Power (PacifiCorp) | B17: AT-48 Large General TOU | C17: 500 | D17: 99999 | E17: Secondary | F17: 0.14448 | G17: 0.13419 | H17: 0 | I17: 13.45 | J17: 0 | K17: 0 | L17: 0 | M17: 842.62 | N17: None | O17: On-peak adder +0.858c; off-peak credit -0.171c | P17: VERIFIED | Q17: 2026-07-10 | R17: https://www.pacificpower.net/content/dam/pcorp/documents/en/pacificpower/rates-regulation/california/CA_Price_Summary.pdf
A18: Pacific Power (PacifiCorp) | B18: A-32 General Service | C18: 20 | D18: 500 | E18: Secondary | F18: 0.20212 | G18: 0.20212 | H18: 0.20212 | I18: 8.5 | J18: 0 | K18: 0 | L18: 0 | M18: 30.54 | N18: None | O18: NO time-of-use differentiation at all | P18: VERIFIED | Q18: 2026-06-08 | R18: https://www.pacificpower.net/content/dam/pcorp/documents/en/pacificpower/rates-regulation/california/CA_Price_Summary.pdf
A19: Bear Valley Electric Service (BVES) | B19: TOU-EV-3 | C19: 20 | D19: 500 | E19: All | F19: 0.46315 | G19: 0.37417 | H19: 0.26005 | I19: 9.5 | J19: 0 | K19: 0 | L19: 0 | M19: 0 | N19: Summer / Winter — months NOT PUBLISHED | O19: NOT PUBLISHED | P19: PARTIAL | Q19: 2026-09-01 | R19: https://www.bvesinc.com/assets/documents/rates/8-24-26-549-e/schedule-no-tou-ev-3.pdf
A20: SMUD — Sacramento Municipal Utility District | B20: EV_SR tier EV3 (>20% util) | C20: 20 | D20: 99999 | E20: Secondary | F20: 0.2151 | G20: 0.089 | H20: 0.0638 | I20: 0 | J20: 25 | K20: 333 | L20: 0 | M20: 0 | N20: Summer Jun 1-Sep 30 / Non-summer Oct 1-May 31 | O20: Peak 4-9pm weekdays; off-peak saver 9am-4pm non-summer | P20: VERIFIED | Q20: 2026-01-01 | R20: https://www.smud.org/-/media/Documents/Rate-Information/Rates/EV-Pilot-Tariff.ashx
A21: SMUD — Sacramento Municipal Utility District | B21: EV_SR tier EV2 (10-20% util) | C21: 20 | D21: 99999 | E21: Secondary | F21: 0.2669 | G21: 0.1088 | H21: 0.0658 | I21: 0 | J21: 25 | K21: 264 | L21: 0 | M21: 0 | N21: Summer Jun 1-Sep 30 / Non-summer Oct 1-May 31 | O21: Peak 4-9pm weekdays; off-peak saver 9am-4pm non-summer | P21: VERIFIED | Q21: 2026-01-01 | R21: https://www.smud.org/-/media/Documents/Rate-Information/Rates/EV-Pilot-Tariff.ashx
A22: SMUD — Sacramento Municipal Utility District | B22: EV_SR tier EV1 (<10% util) | C22: 20 | D22: 99999 | E22: Secondary | F22: 0.5198 | G22: 0.2051 | H22: 0.115 | I22: 0 | J22: 25 | K22: 120 | L22: 0 | M22: 0 | N22: Summer Jun 1-Sep 30 / Non-summer Oct 1-May 31 | O22: Peak 4-9pm weekdays; off-peak saver 9am-4pm non-summer | P22: VERIFIED | Q22: 2026-01-01 | R22: https://www.smud.org/-/media/Documents/Rate-Information/Rates/EV-Pilot-Tariff.ashx
A23: SMUD — Sacramento Municipal Utility District | B23: CI-TOD4 (non-EV alternative) | C23: 1000 | D23: 99999 | E23: Secondary | F23: 0.2438 | G23: 0.1186 | H23: 0.0788 | I23: 17.66 | J23: 0 | K23: 0 | L23: 0 | M23: 4014.3 | N23: Summer Jun 1-Sep 30 / Non-summer Oct 1-May 31 | O23: Peak 4-9pm weekdays | P23: VERIFIED | Q23: 2026-01-01 | R23: https://www.smud.org/-/media/Documents/Rate-Information/Rates/CI-TOD4.ashx
... A41: Redding Electric Utility | B41: E7/E8 — Large Commercial (demand) | C41: 25 | D41: 99999 | E41: Secondary | F41: 0.1086 | G41: 0.1086 | H41: 0.1086 | I41: 21.5 | J41: 0 | K41: 0 | L41: 0 | M41: 95 | N41: None — flat all year | O41: None — no time-of-use. Demand is set by the highest 15-minute interval in the month | P41: UNVERIFIED — third-party summary | Q41: 2025-01-01 | R41: Third-party tariff summary (nectarclimate.com/rates/redding-electric-utility). REU publishes its Rate Book as a PDF that could not be read directly. VERIFY against the City of Redding Rate Book, Section A, and a recent bill. REU proposed 4.5%/yr increases effective 1 Apr 2026 and adoption is unconfirmed.
A60: UTILITY EV CHARGING REBATE AND MAKE-READY PROGRAMMES
A61: Incentives are separate cash flows, not tariff changes. Never model one as a rate reduction, and never bank one that is closed or waitlisted.
A62: Utility | B62: Programme | C62: Status | D62: Amounts
A63: LADWP | B63: Commercial EV Charger Rebate | C63: CLOSED — reopening Oct 2026 | D63: DCFC $20k (50-149kW) / $55k (150-274kW) / $100k (275kW+); +25% in DACs; $2m cap per premises
A64: SMUD | B64: Commercial EV Program | C64: OPEN — first come first served | D64: DCFC $7.5k/handle <50kW; $15k 50-149.9kW; $30k >=150kW. Make-ready: panel $1k, transformer $5k, storage $100/kWh
A65: Riverside Public Utilities | B65: Electrify Riverside | C65: OPEN — first come first served | D65: Up to $10k per DC fast charger; infrastructure 50% of cost up to $50k
A66: Glendale Water and Power | B66: Commercial EV charger rebate | C66: OPEN | D66: Lesser of $50k or 50%; up to $75k/75% for DCFC >=50kW, DACs, public access
A67: Burbank Water and Power | B67: Commercial EV charging rebate | C67: Status not stated | D67: DCFC $5k-$10k/port; $10k-$20k for DAC/public/MFH. Cap $200k or 40 ports
A68: Pasadena Water and Power | B68: Commercial charger rebate | C68: 'Limited time' — status not stated | D68: $4,000 per L2; DCFC double, up to $8,000 per charger
A69: Roseville Electric Utility | B69: Charge Ahead | C69: OPEN — but DCFC is non-profit & multifamily ONLY | D69: DCFC $20k/unit (not available to commercial); transformer $5k, panel $1k
A70: Silicon Valley Power | B70: MFH & Commercial EV incentive | C70: CLOSED — fully subscribed | D70: Up to $150k/site but LEVEL 2 ONLY, no DCFC. Refers DCFC to CALeVIP
A71: City of Palo Alto Utilities | B71: EV charger programme | C71: Non-residential reservations CLOSED | D71: Level 2 only, no DCFC. MFH up to $8k/EVSE, $80k site cap
A72: IID | B72: (none found for commercial) | C72: — | D72: Residential Level 2 only, up to $500
A73: SCE | B73: Charge Ready | C73: CLOSED — agreements had to be signed by 31 Dec 2026 | D73: Level 1 and 2 only; DCFC was never available
A74: Redding Electric Utility | B74: DC Fast Charger Rebate | C74: OPEN — verify funding before relying on it | D74: Up to $6,000 per DC fast charging station, maximum 4 stations per customer. Stations must be separately metered. THE CUSTOMER MUST ASSIGN LCFS CREDITS TO REU — which forecloses the FCI capacity credit on the Carbon tab. The two cannot both be taken.
